Workbook
Name CU?: 'JV Waterfall'!$A$5
Name Equity_Share_GP: 'JV Waterfall'!$C$8
Name Equity_Share_LP: 'JV Waterfall'!$C$9
Name Preferred_Return: 'JV Waterfall'!$E$14
Name SF: Budget!$E$5
Name Total_Equity: 'JV Waterfall'!$D$10

Sheet Budget
B2: =D2 -> 1500 Boston Post Road, Darien | D2: 1500 Boston Post Road, Darien | H2: Sources & Uses Summary | P2: =D2 -> 1500 Boston Post Road, Darien | T2: Leasing Commission Calculation
B3: Development Budget Notes | D3: Acquisition Budget | E3: Current Cost | F3: Cost/SF | H3: Total Capitalization (Sources) | I3: Amount | J3: $ PSF | L3: Total Project Cost (Uses) | M3: Amount | N3: $ PSF | P3: Project Capitalization | U3: =1 -> 1 | V3: =U3+1 -> 2 | W3: =V3+1 -> 3 | X3: =W3+1 -> 4 | Y3: =X3+1 -> 5 | Z3: =Y3+1 -> 6 | AA3: =Z3+1 -> 7 | AB3: =AA3+1 -> 8 | AC3: =AB3+1 -> 9 | ... AL3: =AK3+1 -> 18
B5: Per Offering Memorandum | D5: Building Sq. ft. | E5: 18754 | H5: =H23 -> Permanent Loan @ 64.25% LTC | I5: =I23 -> 6550000 | J5: =+I5/SF -> 349.25882 | L5: =D8 -> Occupied Building | M5: =E8 -> 9700000 | N5: =+M5/SF -> 517.22299 | P5: Total Capitalization | Q5: =E31 -> 10395210 | R5: =Q5/SF -> 554.29296 | T5: Year Ending | U5: 45107 | V5: =EOMONTH(U5,12) -> 45473 | W5: =EOMONTH(V5,12) -> 45838 | X5: =EOMONTH(W5,12) -> 46203 | Y5: =EOMONTH(X5,12) -> 46568 | Z5: =EOMONTH(Y5,12) -> 46934 | AA5: =EOMONTH(Z5,12) -> 47299 | AB5: =EOMONTH(AA5,12) -> 47664 | AC5: =EOMONTH(AB5,12) -> 48029 | ... AL5: =EOMONTH(AK5,12) -> 51317
H6: =H24 -> Equity Contribution @ 35.75% LTC | I6: =I24 -> 3551440.2 | J6: =+I6/SF -> 189.36975 | L6: =D9 -> Acquisition & Development Fee | M6: =E9 -> 200000 | N6: =+M6/SF -> 10.664392 | P6: =P24 -> Permanent Loan @ 64.25% LTC | Q6: =Q24 -> 6550000 | R6: =+Q6/$E$5 -> 349.25882
D7: Site Acquisition Costs | H7: Addition Equity Contribution | I7: =Q26+Q38 -> 293770 | J7: =+I7/SF -> 15.664392 | L7: =D26 -> Tenant Capital Reimbursement | M7: =E26 -> 93770 | N7: =+M7/SF -> 5 | P7: =P25 -> Equity Contribution @ 35.75% LTC | Q7: =Q25 -> 3551440.2 | R7: =+Q7/$E$5 -> 189.36975 | T7: Rental Rate | U7: =F33 -> 35.436907 | V7: =U7 -> 35.436907 | W7: =V7*1.02 -> 36.145645 | X7: =W7*1.02 -> 36.868558 | Y7: =X7*1.02 -> 37.605929 | Z7: =Y7*1.02 -> 38.358048 | AA7: =Z7*1.02 -> 39.125209 | AB7: =AA7*1.02 -> 39.907713 | AC7: =AB7*1.02 -> 40.705867 | AD7: =AC7*1.02 -> 41.519985 | ... AL7: =AK7*1.02 -> 48.64728
B8: Per Letter of Intent Dated 2.28.23 | D8: Occupied Building | E8: 9700000 | F8: =E8/$E$5 -> 517.22299 | G8: =E33/E8 -> 0.06851379 | L8: =D10 -> Lender Rent Escrow | M8: =E10 -> 68000 | N8: =+M8/SF -> 3.6258931 | P8: Additional Equity Contribution | Q8: =Q26 -> 93770 | R8: =+Q8/$E$5 -> 5 | T8: Existing Lease Obligations | U8: =F33 -> 35.436907 | V8: =U8 -> 35.436907 | W8: =V8 -> 35.436907 | X8: =W8 -> 35.436907 | Y8: =X8 -> 35.436907 | Z8: =Y8 -> 35.436907 | AA8: =Z8*1.1 -> 38.980598 | AB8: =AA8 -> 38.980598 | AC8: 0 | AD8: 0 | AE8: 0 | AF8: 0 | AG8: 0 | AH8: 0 | AI8: 0 | AJ8: 0 | AK8: 0 | AL8: 0
B9: Aspect Health Standard Acquisition Fee | D9: Acquisition & Development Fee | E9: 200000 | F9: =E9/$E$5 -> 10.664392 | L9: =D11 -> Closing Costs - Buyer | M9: =E11 -> 80897.21 | N9: =+M9/SF -> 4.3135976 | P9: Total | Q9: =SUM(Q6:Q8) -> 10195210 | R9: =SUM(R6:R8) -> 543.62857 | T9: LC % | U9: 0 | V9: 0 | W9: 0 | X9: 0 | Y9: 0 | Z9: 0 | AA9: 0 | AB9: 0 | AC9: 0.025 | AD9: 0.025 | AE9: 0.025 | AF9: 0.025 | AG9: 0.025 | AH9: 0.0125 | AI9: 0.0125 | AJ9: 0.0125 | AK9: 0.0125 | AL9: 0.0125
B10: Calculated; Required Per Lender Term Sheet Dated 5.02.23 | D10: Lender Rent Escrow | E10: 68000 | F10: =E10/$E$5 -> 3.6258931 | L10: =D12 -> Closing Costs - Lender - Permanent Loan | M10: =E12 -> 16412 | N10: =+M10/SF -> 0.87511997 | T10: LC/RSF | U10: =(U7-U8)*U9 -> 0 | V10: =(V7-V8)*V9 -> 0 | W10: =(W7-W8)*W9 -> 0 | X10: =(X7-X8)*X9 -> 0 | Y10: =(Y7-Y8)*Y9 -> 0 | Z10: =(Z7-Z8)*Z9 -> 0 | AA10: =(AA7-AA8)*AA9 -> 0 | AB10: =(AB7-AB8)*AB9 -> 0 | ... AL10: =(AL7-AL8)*AL9 -> 0.608091
B11: Estimated Based on Hospital Ave/Stratford | D11: Closing Costs - Buyer | E11: ='Closing Costs '!E32+'Closing Costs '!E21 -> 80897.21 | F11: =E11/$E$5 -> 4.3135976 | L11: =D21 -> Lender Origination Fee - Permanent Loan | M11: =E21 -> 32750 | N11: =+M11/SF -> 1.7462941 | P11: =P37 -> Construction Loan @ 0.00% LTC | Q11: =Q37 -> 0 | R11: =+Q11/$E$5 -> 0 | T11: Total LC/RSF
B12: Estimated Based on Hospital Ave/Stratford | D12: Closing Costs - Lender - Permanent Loan | E12: ='Closing Costs '!E10 -> 16412 | F12: =E12/$E$5 -> 0.87511997 | L12: =D13 -> Closing Costs - Lender - Construction Loan | M12: =E13 -> 0 | N12: =+M12/SF -> 0 | P12: =P38 -> Equity Contribution @ 100.00% LTC | Q12: =Q38 -> 200000 | R12: =+Q12/$E$5 -> 10.664392
B13: Estimated Based on Hospital Ave/Stratford | D13: Closing Costs - Lender - Construction Loan | E13: 0 | F13: =E13/$E$5 -> 0 | L13: =D22 -> Lender Origination Fee - Construction Loan | M13: =E22 -> 0 | N13: =+M13/SF -> 0 | P13: Total | Q13: =SUM(Q11:Q12) -> 200000 | R13: =SUM(R11:R12) -> 10.664392 | T13: RSF | U13: =SF -> 18754 | V13: =U13 -> 18754 | W13: =V13 -> 18754 | X13: =W13 -> 18754 | Y13: =X13 -> 18754 | Z13: =Y13 -> 18754 | AA13: =Z13 -> 18754 | AB13: =AA13 -> 18754 | AC13: =AB13 -> 18754 | ... AL13: =AK13 -> 18754
D14: Site Acquisition Costs Subtotal | E14: =SUM(E8:E13) -> 10065309 | F14: =E14/$E$5 -> 536.70199 | L14: =D17 -> Construction Costs | M14: =E17 -> 200000 | N14: =+M14/SF -> 10.664392 | T14: LC's per Year | U14: =U10*U13 -> 0 | V14: =V10*V13 -> 0 | W14: =W10*W13 -> 0 | X14: =X10*X13 -> 0 | Y14: =Y10*Y13 -> 0 | Z14: =Z10*Z13 -> 0 | AA14: =AA13*AA10 -> 0 | AB14: =AB13*AB10 -> 0 | AC14: =AC13*AC10 -> 19084.946 | AD14: =AD13*AD10 -> 19466.645 | AE14: =AE13*AE10 -> 19855.978 | AF14: =AF13*AF10 -> 20253.097 | AG14: =AG13*AG10 -> 20658.159 | AH14: =AH13*AH10 -> 10535.661 | ... AL14: =AL13*AL10 -> 11404.139
L15: =D27 -> Leasing Legal | M15: =E27 -> 3381 | N15: =+M15/SF -> 0.18028154
D16: Construction Costs | L16: =D28 -> Broker Fee | M16: =E28 -> 0 | N16: =+M16/SF -> 0 | T16: Total LC's | AL16: =SUM(U14:AL14) -> 154146.83
B17: Pre-Disposition Renovation Costs | D17: Construction Costs | E17: ='Property CF'!AO27 -> 200000 | F17: =E17/$E$5 -> 10.664392
D18: Construction Costs Subtotal | E18: =E17 -> 200000 | F18: =F17 -> 10.664392 | H18: Project Capitalization | I18: =+SUBTOTAL(9,I5:I17) -> 10395210 | J18: =+I18/SF -> 554.29296 | L18: Total Project Cost | M18: =SUM(M5:M17) -> 10395210 | N18: =+M18/SF -> 554.29296 | T18: Leasing Commission Calculation
U19: =1 -> 1 | V19: =U19+1 -> 2 | W19: =V19+1 -> 3 | X19: =W19+1 -> 4 | Y19: =X19+1 -> 5 | Z19: =Y19+1 -> 6 | AA19: =Z19+1 -> 7 | AB19: =AA19+1 -> 8 | AC19: =AB19+1 -> 9 | ... AL19: =AK19+1 -> 18
D20: Development Financing | H20: Sources & Uses Summary - Permanent Loan | P20: =P2 -> 1500 Boston Post Road, Darien
B21: 0.50% of Loan Amount | D21: Lender Origination Fee - Permanent Loan | E21: =Q28 -> 32750 | F21: =E21/$E$5 -> 1.7462941 | H21: Total Capitalization (Sources) | I21: Amount | J21: $ PSF | L21: Total Project Cost (Uses) | M21: Amount | N21: $ PSF | P21: Project Capitalization | T21: Year Ending | U21: 45657 | V21: =EOMONTH(U21,12) -> 46022 | W21: =EOMONTH(V21,12) -> 46387 | X21: =EOMONTH(W21,12) -> 46752 | Y21: =EOMONTH(X21,12) -> 47118 | Z21: =EOMONTH(Y21,12) -> 47483 | AA21: =EOMONTH(Z21,12) -> 47848 | AB21: =EOMONTH(AA21,12) -> 48213
B22: 1.00% of Loan Amount | D22: Lender Origination Fee - Construction Loan | E22: 0 | F22: =E22/$E$5 -> 0
D23: Development Financing Subtotal | E23: =SUM(E21:E22) -> 32750 | F23: =SUM(F21:F22) -> 1.7462941 | H23: =P24 -> Permanent Loan @ 64.25% LTC | I23: =Q24 -> 6550000 | J23: =+I23/SF -> 349.25882 | L23: =L5 -> Occupied Building | M23: =M5 -> 9700000 | N23: =+M23/SF -> 517.22299 | P23: Total Capitalization | Q23: =SUM(E8:E12)+E21+E26+E27 -> 10195210 | R23: =Q23/SF -> 543.62857 | T23: Rental Rate | U23: =29.07*1.1 -> 31.977 | V23: =U23 -> 31.977 | W23: =V23 -> 31.977 | X23: =W23 -> 31.977 | Y23: =X23 -> 31.977 | Z23: =Y23*1.1 -> 35.1747 | AA23: =Z23 -> 35.1747 | AB23: =AA23 -> 35.1747
H24: =P25 -> Equity Contribution @ 35.75% LTC | I24: =Q25 -> 3551440.2 | J24: =+I24/SF -> 189.36975 | L24: =L6 -> Acquisition & Development Fee | M24: =M6 -> 200000 | N24: =+M24/SF -> 10.664392 | P24: =+"Permanent Loan @ "&(TEXT(S24,"0.00% LTC")) -> Permanent Loan @ 64.25% LTC | Q24: 6550000 | R24: =+Q24/$E$5 -> 349.25882 | S24: =Q24/Q23 -> 0.64245855 | T24: Operating Expenses | U24: 15 | V24: =U24*1.02 -> 15.3 | W24: =V24*1.02 -> 15.606 | X24: =W24*1.02 -> 15.91812 | Y24: =X24*1.02 -> 16.236482 | Z24: =Y24*1.02 -> 16.561212 | AA24: =Z24*1.02 -> 16.892436 | AB24: =AA24*1.02 -> 17.230285
D25: Tenant Fit-Out | H25: Addition Equity Contribution | I25: =Q26 -> 93770 | J25: =+I25/SF -> 5 | L25: =L7 -> Tenant Capital Reimbursement | M25: =M7 -> 93770 | N25: =+M25/SF -> 5 | P25: =+"Equity Contribution @ "&(TEXT(S25,"0.00% LTC")) -> Equity Contribution @ 35.75% LTC | Q25: =Q23-Q24-Q26 -> 3551440.2 | R25: =+Q25/$E$5 -> 189.36975 | S25: =1-S24 -> 0.35754145 | T25: LC % | U25: 0.025 | V25: 0.025 | W25: 0.025 | X25: 0.025 | Y25: 0.025 | Z25: 0.0125 | AA25: 0.0125 | AB25: 0.0125
B26: Per Fifth Amendment to Lease Agreement | D26: Tenant Capital Reimbursement | E26: 93770 | F26: =E26/$E$5 -> 5 | L26: =L8 -> Lender Rent Escrow | M26: =M8 -> 68000 | N26: =+M26/SF -> 3.6258931 | P26: Additional Equity Contribution | Q26: =E26 -> 93770 | R26: =+Q26/$E$5 -> 5 | T26: LC/RSF | U26: =(U23+U24)*U25 -> 1.174425 | V26: =(V23+V24)*V25 -> 1.181925 | W26: =(W23+W24)*W25 -> 1.189575 | X26: =(X23+X24)*X25 -> 1.197378 | Y26: =(Y23+Y24)*Y25 -> 1.2053371 | Z26: =(Z23+Z24)*Z25 -> 0.6466989 | AA26: =(AA23+AA24)*AA25 -> 0.6508392 | AB26: =(AB23+AB24)*AB25 -> 0.65506231
B27: Per McGuire Woods Invoice | D27: Leasing Legal | E27: 3381 | F27: =E27/$E$5 -> 0.18028154 | L27: =L9 -> Closing Costs - Buyer | M27: =M9 -> 80897.21 | N27: =+M27/SF -> 4.3135976 | T27: Total LC/RSF
B28: Based on Leasing Commission Sheet, 5.00% Year 1-5, 2.50% Year 6-10, 1.00% Year 11-15 | D28: Broker Fee | E28: 0 | F28: =E28/$E$5 -> 0 | L28: =L10 -> Closing Costs - Lender - Permanent Loan | M28: =M10 -> 16412 | N28: =+M28/SF -> 0.87511997 | P28: Origination Fee | Q28: =+Q24*S28 -> 32750 | R28: =+Q28/$E$5 -> 1.7462941 | S28: 0.005
D29: Development Financing Subtotal | E29: =SUM(E26:E28) -> 97151 | F29: =SUM(F26:F28) -> 5.1802815 | L29: =L11 -> Lender Origination Fee - Permanent Loan | M29: =M11 -> 32750 | N29: =+M29/SF -> 1.7462941 | T29: RSF | U29: =SF -> 18754 | V29: =U29 -> 18754 | W29: =V29 -> 18754 | X29: =W29 -> 18754 | Y29: =X29 -> 18754 | Z29: =Y29 -> 18754 | AA29: =Z29 -> 18754 | AB29: =AA29/3 -> 6251.3333
L30: =L15 -> Leasing Legal | M30: =M15 -> 3381 | N30: =+M30/SF -> 0.18028154 | T30: LC's per Year | U30: =U26*U29 -> 22025.166 | V30: =V26*V29 -> 22165.821 | W30: =W26*W29 -> 22309.29 | X30: =X26*X29 -> 22455.627 | Y30: =Y26*Y29 -> 22604.891 | Z30: =Z26*Z29 -> 12128.191 | AA30: =AA29*AA26 -> 12205.838 | AB30: =AB29*AB26 -> 4095.0129
D31: Total Development Cost | E31: =E14+E18+E23+E29 -> 10395210 | F31: =+E31/$E$5 -> 554.29296 | G31: =E33/E31 -> 0.063931729
H32: Project Capitalization | I32: =+SUBTOTAL(9,I23:I31) -> 10195210 | J32: =+I32/SF -> 543.62857 | L32: Total Project Cost | M32: =SUM(M23:M31) -> 10195210 | N32: =+M32/SF -> 543.62857 | T32: Total LC's | AL32: =SUM(U30:AL30) -> 139989.84
D33: Existing Base Rental Rate | E33: ='Offering Memorandum'!BA14 -> 664583.76 | F33: =E33/SF -> 35.436907 | G33: =E33/E31 -> 0.063931729 | P33: =P20 -> 1500 Boston Post Road, Darien
H34: Sources & Uses Summary - Additional Equity | P34: Project Capitalization
H35: Total Capitalization (Sources) | I35: Amount | J35: $ PSF | L35: Total Project Cost (Uses) | M35: Amount | N35: $ PSF
P36: Total Capitalization | Q36: =E17+E13+E22 -> 200000 | R36: =Q36/SF -> 10.664392
H37: =P37 -> Construction Loan @ 0.00% LTC | I37: =Q37 -> 0 | J37: =+I37/SF -> 0 | L37: =L14 -> Construction Costs | M37: =M14 -> 200000 | N37: =+M37/SF -> 10.664392 | P37: =+"Construction Loan @ "&(TEXT(S37,"0.00% LTC")) -> Construction Loan @ 0.00% LTC | Q37: =Q36*S37 -> 0 | R37: =+Q37/$E$5 -> 0 | S37: 0
H38: =P38 -> Equity Contribution @ 100.00% LTC | I38: =Q38 -> 200000 | J38: =+I38/SF -> 10.664392 | L38: =L16 -> Broker Fee | M38: =M16 -> 0 | N38: =+M38/SF -> 0 | P38: =+"Equity Contribution @ "&(TEXT(S38,"0.00% LTC")) -> Equity Contribution @ 100.00% LTC | Q38: =Q36-Q37 -> 200000 | R38: =+Q38/$E$5 -> 10.664392 | S38: =1-S37 -> 1
L39: =L12 -> Closing Costs - Lender - Construction Loan | M39: =M12 -> 0 | N39: =+M39/SF -> 0 | P39: Additional Equity Contribution | Q39: =Q36-SUM(Q37:Q38) -> 0 | R39: =+Q39/$E$5 -> 0
L40: =L13 -> Lender Origination Fee - Construction Loan | M40: =M13 -> 0 | N40: =+M40/SF -> 0
P41: Origination Fee | Q41: =+Q37*S41 -> 0 | R41: =+Q41/$E$5 -> 0 | S41: 0.01
H43: Project Capitalization | I43: =+SUBTOTAL(9,I37:I42) -> 200000 | J43: =+I43/SF -> 10.664392 | L43: Total Project Cost | M43: =SUM(M37:M41) -> 200000 | N43: =+M43/SF -> 10.664392

Sheet Property CF
B4: Acquisition Assumptions | E4: Project Development Schedule | AR4: Welltower JV Assumptions | AU4: CASH FLOW | BI4: Levered Development Returns to Equity | BM4: Levered Deal Returns to Equity - Year 5 | BQ4: Aspect Health, Inc. Fee Schedule - Year 5 Sale
B5: Property | F5: Start | G5: Term | H5: =0 -> 0 | I5: =H5+1 -> 1 | J5: =I5+1 -> 2 | K5: =J5+1 -> 3 | L5: =K5+1 -> 4 | M5: =L5+1 -> 5 | N5: =M5+1 -> 6 | O5: =N5+1 -> 7 | P5: =O5+1 -> 8 | ... AN5: =AM5+1 -> 32 | AO5: Total | AP5: PSF | AR5: Property | AU5: =Budget!D2 -> 1500 Boston Post Road, Darien | BI5: Project-Level | BJ5: Amount | BK5: $PSF | BM5: Project-Level Returns | BN5: Amount | BO5: $ PSF | BQ5: Self-Perform + Welltower JV
B6: Total Acquisition Cost | C6: =Budget!E31 -> 10395210 | AR6: Property Size (RSF) | AS6: =SF -> 18754 | BI6: Total Proceeds | BJ6: =SUMIF(H144:AN145,">0") -> 4696380.2 | BK6: =BJ6/SF -> 250.42019 | BM6: Total Proceeds | BN6: =SUM(BB81:BB85) -> 6423201.1 | BO6: =BN6/$AS$6 -> 342.49766
E7: Month Ending | H7: 45120 | I7: =EOMONTH(H7,0) -> 45138 | J7: =EOMONTH(I7,1) -> 45169 | K7: =EOMONTH(J7,1) -> 45199 | L7: =EOMONTH(K7,1) -> 45230 | M7: =EOMONTH(L7,1) -> 45260 | N7: =EOMONTH(M7,1) -> 45291 | O7: =EOMONTH(N7,1) -> 45322 | P7: =EOMONTH(O7,1) -> 45351 | Q7: =EOMONTH(P7,1) -> 45382 | ... AN7: =EOMONTH(AM7,1) -> 46081 | AR7: Starting Rent (RSF) | AS7: =AW12/AS6 -> 36.930006 | AV7: 0 | AW7: =AV7+1 -> 1 | AY7: =AW7+1 -> 2 | AZ7: =AY7+1 -> 3 | BA7: =AZ7+1 -> 4 | BB7: =BA7+1 -> 5 | BC7: =BB7+1 -> 6 | BD7: =BC7+1 -> 7 | BE7: =BD7+1 -> 8 | BF7: =BE7+1 -> 9 | BG7: =BF7+1 -> 10 | BI7: Capital Contribution | BJ7: =SUMIF(H144:AN145,"<0") -> -3895347.3 | BK7: =-BJ7/SF -> 207.70754 | BM7: Capital Contribution | BN7: =AV44 -> -4154538.5 | BO7: =BN7/-$AS$6 -> 221.52812 | BR7: =0 -> 0 | BS7: =BR7+1 -> 1 | BT7: =BS7+1 -> 2 | BU7: =BT7+1 -> 3 | BV7: =BU7+1 -> 4 | BW7: =BV7+1 -> 5
B8: Debt | AR8: Total Valuation - All-In Gross Sale Price Welltower | AS8: =AS71 -> 11870110 | AU8: Year Ending | AV8: =AL7 -> 46022 | AW8: =EOMONTH(AV8,12) -> 46387 | AY8: =EOMONTH(AW8,12) -> 46752 | AZ8: =EOMONTH(AY8,12) -> 47118 | BA8: =EOMONTH(AZ8,12) -> 47483 | BB8: =EOMONTH(BA8,12) -> 47848 | BC8: =EOMONTH(BB8,12) -> 48213 | BD8: =EOMONTH(BC8,12) -> 48579 | BE8: =EOMONTH(BD8,12) -> 48944 | BF8: =EOMONTH(BE8,12) -> 49309 | BG8: =EOMONTH(BF8,12) -> 49674 | BI8: Net Profit | BJ8: =BJ6+BJ7 -> 801032.86 | BK8: =BJ8/SF -> 42.712641 | BM8: Net Profit | BN8: =BN6+BN7 -> 2268662.6 | BO8: =BN8/$AS$6 -> 120.96953 | BQ8: Year Ending | BR8: =AN7 -> 46081 | BS8: =EOMONTH(BR8,12) -> 46446 | BT8: =EOMONTH(BS8,12) -> 46812 | BU8: =EOMONTH(BT8,12) -> 47177 | BV8: =EOMONTH(BU8,12) -> 47542 | BW8: =EOMONTH(BV8,12) -> 47907
B9: Permanent LTC | C9: =Budget!S24 -> 0.64245855 | AR9: Total Valuation per RSF | AS9: =AS8/AS6 -> 632.9375
B10: Permanent Interest Rate Spread | C10: ='Offering Memorandum'!BG4+'Offering Memorandum'!BH4+'Offering Memorandum'!BI4+'Offering Memorandum'!BJ4 -> 0.0226 | E10: Effective Gross Rent | I10: =I12+I11 -> 52850.495 | J10: =J12+J11 -> 70436.913 | K10: =K12+K11 -> 70436.913 | L10: =L12+L11 -> 70436.913 | M10: =M12+M11 -> 70436.913 | N10: =N12+N11 -> 25005.333 | O10: =O12+O11 -> 25005.333 | P10: =P12+P11 -> 80387.313 | ... AL10: =AL12+AL11 -> 26015.549 | AM10: 0 | AN10: 0 | AO10: =SUM(H10:AN10) -> 2145989.5 | AP10: =+AO10/SF -> 114.42836 | AR10: Term (Yrs) | AS10: 15.25 | AU10: Effective Gross Rent | AW10: =AW12+AW11 -> 992649.33 | AY10: =AY12+AY11 -> 1012502.3 | AZ10: =AZ12+AZ11 -> 1032752.4 | BA10: =BA12+BA11 -> 1053407.4 | BB10: =BB12+BB11 -> 1074475.6 | BC10: =BC12+BC11 -> 1095965.1 | BD10: =BD12+BD11 -> 1117884.4 | BE10: =BE12+BE11 -> 1140242.1 | BF10: =BF12+BF11 -> 1163046.9 | BG10: =BG12+BG11 -> 1186307.8 | BI10: IRR | BJ10: =F61 -> 0.089599493 | BM10: IRR | BN10: =BB49 -> 0.10594725 | BQ10: Acquisition & Development Fee | BR10: =BR24 -> 200000
B11: Loan Index Rate | C11: ='Offering Memorandum'!BM4 -> 0.0411 | E11: Operating Expenses | I11: =AS19*SF/12 -> 25005.333 | J11: =I11 -> 25005.333 | K11: =J11 -> 25005.333 | L11: =K11 -> 25005.333 | M11: =L11 -> 25005.333 | N11: =M11 -> 25005.333 | O11: =N11 -> 25005.333 | P11: =O11 -> 25005.333 | Q11: =P11 -> 25005.333 | ... U11: =T11 -> 25005.333 | V11: =J11*1.02 -> 25505.44 | W11: =K11*1.02 -> 25505.44 | X11: =L11*1.02 -> 25505.44 | Y11: =M11*1.02 -> 25505.44 | Z11: =N11*1.02 -> 25505.44 | AA11: =O11*1.02 -> 25505.44 | AB11: =P11*1.02 -> 25505.44 | AC11: =Q11*1.02 -> 25505.44 | ... AL11: =Z11*1.02 -> 26015.549 | AM11: 0 | AN11: 0 | AO11: =SUM(H11:AN11) -> 761212.36 | AP11: =+AO11/SF -> 40.589333 | AR11: Asset Management Fee % (Equity) | AS11: 0.0025 | AU11: Operating Expenses | AW11: =AS19*AS6 -> 300064 | AY11: =AW11*(1+$AS$20) -> 306065.28 | AZ11: =AY11*(1+$AS$20) -> 312186.59 | BA11: =AZ11*(1+$AS$20) -> 318430.32 | BB11: =BA11*(1+$AS$20) -> 324798.92 | BC11: =BB11*(1+$AS$20) -> 331294.9 | BD11: =BC11*(1+$AS$20) -> 337920.8 | BE11: =BD11*(1+$AS$20) -> 344679.22 | BF11: =BE11*(1+$AS$20) -> 351572.8 | BG11: =BF11*(1+$AS$20) -> 358604.26 | BI11: Equity Multiple | BJ11: =BJ8/-BJ7+1 -> 1.2056384 | BM11: Equity Multiple | BN11: =BN8/-BN7+1 -> 1.5460685 | BQ11: Inside Fee | BR11: ='Property CF'!$AS$8*$BR$25 -> 237402.2 | BS11: 0 | BT11: 0 | BU11: 0 | BV11: 0 | BW11: 0
B12: All-In Interest Rate | C12: =C10+C11 -> 0.0637 | E12: NOI | I12: ='Offering Memorandum'!BA5/12*(((_xlfn.DAYS(I7,H7-1))/_xlfn.DAYS(I7,EOMONTH(I7,-1)))) -> 27845.162 | J12: ='Offering Memorandum'!BA5/12 -> 45431.58 | K12: =J12 -> 45431.58 | L12: =K12 -> 45431.58 | M12: =L12 -> 45431.58 | N12: 0 | O12: =N12 -> 0 | P12: =Budget!E33/12 -> 55381.98 | Q12: =P12 -> 55381.98 | R12: =Q12 -> 55381.98 | S12: =R12 -> 55381.98 | T12: =S12 -> 55381.98 | U12: =T12 -> 55381.98 | V12: =U12 -> 55381.98 | W12: =V12 -> 55381.98 | X12: =W12 -> 55381.98 | Y12: =X12 -> 55381.98 | Z12: 0 | AA12: =(Y12)*(1+$AS$13) -> 56489.619 | AB12: =AA12 -> 56489.619 | AC12: =AB12 -> 56489.619 | AD12: =AC12 -> 56489.619 | AE12: =AD12 -> 56489.619 | AF12: =AE12 -> 56489.619 | AG12: =AF12 -> 56489.619 | AH12: =AG12 -> 56489.619 | AI12: =AH12 -> 56489.619 | ... AK12: =AJ12 -> 56489.619 | AL12: 0 | AM12: 0 | AN12: 0 | AO12: =SUM(H12:AN12) -> 1384777.1 | AP12: =+AO12/SF -> 73.839026 | AR12: Capital Reserves (RSF) | AS12: 0 | AU12: Net Operating Income | AW12: =(SUM(AA12:AL12)*(1+$AS$13))+(AK12*(1+$AS$13))*(1+$AS$13) -> 692585.33 | AY12: =AW12*(1+$AS$13) -> 706437.04 | AZ12: =AY12*(1+$AS$13) -> 720565.78 | BA12: =AZ12*(1+$AS$13) -> 734977.09 | BB12: =BA12*(1+$AS$13) -> 749676.64 | BC12: =BB12*(1+$AS$13) -> 764670.17 | BD12: =BC12*(1+$AS$13) -> 779963.57 | BE12: =BD12*(1+$AS$13) -> 795562.84 | BF12: =BE12*(1+$AS$13) -> 811474.1 | BG12: =BF12*(1+$AS$13) -> 827703.58 | BM12: Avg. Cash-on-Cash | BN12: =BB47 -> 0.095691193 | BQ12: Management Fee | BR12: 0 | BS12: ='Property CF'!AW10*$BR$26 -> 0 | BT12: ='Property CF'!AY10*$BR$26 -> 0 | BU12: ='Property CF'!AZ10*$BR$26 -> 0 | BV12: ='Property CF'!BA10*$BR$26 -> 0 | BW12: ='Property CF'!BB10*$BR$26 -> 0
B13: Loan Amount | C13: =Budget!Q24 -> 6550000 | E13: Asset Management Fee | F13: Accrue? | G13: Yes | I13: =I10*$BR$27 -> 1057.0099 | J13: =J10*$BR$27 -> 1408.7383 | K13: =K10*$BR$27 -> 1408.7383 | L13: =L10*$BR$27 -> 1408.7383 | M13: =M10*$BR$27 -> 1408.7383 | N13: =N10*$BR$27 -> 500.10667 | O13: =O10*$BR$27 -> 500.10667 | P13: =P10*$BR$27 -> 1607.7463 | ... AL13: =AL10*$BR$27 -> 520.31098 | AM13: 0 | AN13: 0 | AO13: =SUM(H13:AN13) -> 42919.789 | AP13: =+AO13/SF -> 2.2885672 | AR13: Rent Escalator % | AS13: 0.02 | AU13: Rental Rate per RSF | AW13: =AW12/SF -> 36.930006 | AY13: =AY12/SF -> 37.668606 | AZ13: =AZ12/SF -> 38.421978 | BA13: =BA12/SF -> 39.190418 | BB13: =BB12/SF -> 39.974226 | BC13: =BC12/SF -> 40.773711 | BD13: =BD12/SF -> 41.589185 | BE13: =BE12/SF -> 42.420968 | BF13: =BF12/SF -> 43.269388 | BG13: =BG12/SF -> 44.134776 | BI13: Levered Development Returns to Equity | BQ13: Asset Management Fee | BR13: =SUM(AO13) -> 42919.789 | BS13: =-'Property CF'!AW43 -> 10386.346 | BT13: =-'Property CF'!AY43 -> 10386.346 | BU13: =-'Property CF'!AZ43 -> 10386.346 | BV13: =-'Property CF'!BA43 -> 10386.346 | BW13: =-'Property CF'!BB43 -> 10386.346
E14: Lender Escrow/Additional Return | G14: Yes | I14: 0 | J14: 0 | K14: 0 | L14: 0 | M14: 0 | N14: =H19 -> 68000 | O14: 0 | P14: 0 | Q14: 0 | R14: 0 | S14: 0 | T14: 0 | U14: 0 | V14: 0 | W14: 0 | X14: 0 | Y14: 0 | Z14: 0 | AA14: 0 | AB14: 0 | AC14: 0 | AD14: 0 | AE14: 0 | AF14: 0 | AG14: 0 | AH14: 0 | AI14: 0 | AJ14: 0 | AK14: 0 | AL14: 0 | AM14: 0 | AN14: 0 | AO14: =SUM(H14:AN14) -> 68000 | AP14: =+AO14/SF -> 3.6258931 | AR14: Year 1 Going-In Cap Rate | AS14: 0.0595 | AU14: Capital Reserves | AW14: =AS12*AS6 -> 0 | AY14: =AW14 -> 0 | AZ14: =AY14 -> 0 | BA14: =AZ14 -> 0 | BB14: =BA14 -> 0 | BC14: =BB14 -> 0 | BD14: =BC14 -> 0 | BE14: =BD14 -> 0 | BF14: =BE14 -> 0 | BG14: =BF14 -> 0 | BI14: Doctors Interest | BJ14: Amount | BK14: $PSF | BM14: Levered Deal Returns to Equity - Year 5
B15: Equity | G15: No | AR15: Year 2 Exit Cap Rate | AS15: 0.0585 | AU15: Tenant Improvement Allowance | AW15: 0 | AY15: 0 | AZ15: 0 | BA15: 0 | BB15: 0 | BC15: 0 | BD15: 0 | BE15: 0 | BF15: 0 | BG15: 0 | BI15: Total Proceeds | BJ15: =SUM(I105:AN105) -> 0 | BK15: =BJ15/SF -> 0 | BM15: Aspect Health Inc. Returns | BN15: Amount | BO15: $ PSF | BQ15: Yearly Total | BR15: =SUM(BR10:BR13) -> 480321.99 | BS15: =SUM(BS10:BS13) -> 10386.346 | BT15: =SUM(BT10:BT13) -> 10386.346 | BU15: =SUM(BU10:BU13) -> 10386.346 | BV15: =SUM(BV10:BV13) -> 10386.346 | BW15: =SUM(BW10:BW13) -> 10386.346
B16: Required Initial Common Capital Contributions | C16: =Budget!Q25 -> 3551440.2 | E16: =Budget!D7 -> Site Acquisition Costs | AR16: Year 3-10 Exit Cap Rate Adjustment per Year | AS16: 0.0005 | AU16: Net Cash Flow Before Debt Service | AW16: =AW12-SUM(AW14:AW15) -> 692585.33 | AY16: =AY12-SUM(AY14:AY15) -> 706437.04 | AZ16: =AZ12-SUM(AZ14:AZ15) -> 720565.78 | BA16: =BA12-SUM(BA14:BA15) -> 734977.09 | BB16: =BB12-SUM(BB14:BB15) -> 749676.64 | BC16: =BC12-SUM(BC14:BC15) -> 764670.17 | BD16: =BD12-SUM(BD14:BD15) -> 779963.57 | BE16: =BE12-SUM(BE14:BE15) -> 795562.84 | BF16: =BF12-SUM(BF14:BF15) -> 811474.1 | BG16: =BG12-SUM(BG14:BG15) -> 827703.58 | BI16: Capital Contribution | BJ16: =H105 -> 0 | BK16: =-BJ16/SF -> 0 | BM16: Total Proceeds | BN16: ='JV Waterfall'!T36 -> 642320.11 | BO16: =BN16/$AS$6 -> 34.249766
B17: Tenant Capital Reimbursement Equity Contribution | C17: =Budget!Q8 -> 93770 | E17: =Budget!D8 -> Occupied Building | F17: 0 | G17: 0 | H17: =IF(AND(H$5>=$F17,H$5<=$G17),$AO17/($G17-$F17+1),0) -> 9700000 | I17: =IF(AND(I$5>=$F17,I$5<=$G17),$AO17/($G17-$F17+1),0) -> 0 | J17: =IF(AND(J$5>=$F17,J$5<=$G17),$AO17/($G17-$F17+1),0) -> 0 | K17: =IF(AND(K$5>=$F17,K$5<=$G17),$AO17/($G17-$F17+1),0) -> 0 | L17: =IF(AND(L$5>=$F17,L$5<=$G17),$AO17/($G17-$F17+1),0) -> 0 | M17: =IF(AND(M$5>=$F17,M$5<=$G17),$AO17/($G17-$F17+1),0) -> 0 | N17: =IF(AND(N$5>=$F17,N$5<=$G17),$AO17/($G17-$F17+1),0) -> 0 | O17: =IF(AND(O$5>=$F17,O$5<=$G17),$AO17/($G17-$F17+1),0) -> 0 | ... AN17: =IF(AND(AN$5>=$F17,AN$5<=$G17),$AO17/($G17-$F17+1),0) -> 0 | AO17: =Budget!E8 -> 9700000 | AP17: =+AO17/SF -> 517.22299 | AR17: Tenant Improvement Allowance (RSF) | AS17: 15 | AU17: Unlevered Cash Flow | AV17: =-AS8 -> -11870110 | AW17: =AW16 -> 692585.33 | AY17: =AY16 -> 706437.04 | AZ17: =AZ16 -> 720565.78 | BA17: =BA16 -> 734977.09 | BB17: =BB16 -> 749676.64 | BC17: =BC16 -> 764670.17 | BD17: =BD16 -> 779963.57 | BE17: =BE16 -> 795562.84 | BF17: =BF16 -> 811474.1 | BG17: =BG16 -> 827703.58 | BI17: Net Profit | BJ17: =BJ15+BJ16 -> 0 | BK17: =BJ17/SF -> 0 | BM17: Total Asset Management Fee's | BN17: ='JV Waterfall'!T37 -> 51931.731 | BO17: =BN17/$AS$6 -> 2.7691016 | BQ17: Hold Period Total | BR17: =SUM(BR15:BW15) -> 532253.72
B18: Construction Cost Equity Contribution | C18: =Budget!Q38 -> 200000 | E18: =Budget!D9 -> Acquisition & Development Fee | F18: 0 | G18: 0 | H18: =IF(AND(H$5>=$F18,H$5<=$G18),$AO18/($G18-$F18+1),0) -> 200000 | I18: =IF(AND(I$5>=$F18,I$5<=$G18),$AO18/($G18-$F18+1),0) -> 0 | J18: =IF(AND(J$5>=$F18,J$5<=$G18),$AO18/($G18-$F18+1),0) -> 0 | K18: =IF(AND(K$5>=$F18,K$5<=$G18),$AO18/($G18-$F18+1),0) -> 0 | L18: =IF(AND(L$5>=$F18,L$5<=$G18),$AO18/($G18-$F18+1),0) -> 0 | M18: =IF(AND(M$5>=$F18,M$5<=$G18),$AO18/($G18-$F18+1),0) -> 0 | N18: =IF(AND(N$5>=$F18,N$5<=$G18),$AO18/($G18-$F18+1),0) -> 0 | O18: =IF(AND(O$5>=$F18,O$5<=$G18),$AO18/($G18-$F18+1),0) -> 0 | ... AN18: =IF(AND(AN$5>=$F18,AN$5<=$G18),$AO18/($G18-$F18+1),0) -> 0 | AO18: =Budget!E9 -> 200000 | AP18: =+AO18/SF -> 10.664392 | AR18: Renewal Term (Yrs) | AS18: 5 | BM18: Capital Contribution | BN18: =BN47 -> -415453.85 | BO18: =BN18/-$AS$6 -> 22.152812
B19: Required Final Common Capital Contributions | C19: =C16+C17+C18 -> 3845210.2 | E19: =Budget!D10 -> Lender Rent Escrow | F19: 0 | G19: 0 | H19: =IF(AND(H$5>=$F19,H$5<=$G19),$AO19/($G19-$F19+1),0) -> 68000 | I19: =IF(AND(I$5>=$F19,I$5<=$G19),$AO19/($G19-$F19+1),0) -> 0 | J19: =IF(AND(J$5>=$F19,J$5<=$G19),$AO19/($G19-$F19+1),0) -> 0 | K19: =IF(AND(K$5>=$F19,K$5<=$G19),$AO19/($G19-$F19+1),0) -> 0 | L19: =IF(AND(L$5>=$F19,L$5<=$G19),$AO19/($G19-$F19+1),0) -> 0 | M19: =IF(AND(M$5>=$F19,M$5<=$G19),$AO19/($G19-$F19+1),0) -> 0 | N19: =IF(AND(N$5>=$F19,N$5<=$G19),$AO19/($G19-$F19+1),0) -> 0 | O19: =IF(AND(O$5>=$F19,O$5<=$G19),$AO19/($G19-$F19+1),0) -> 0 | ... AN19: =IF(AND(AN$5>=$F19,AN$5<=$G19),$AO19/($G19-$F19+1),0) -> 0 | AO19: =Budget!E10 -> 68000 | AP19: =+AO19/SF -> 3.6258931 | AR19: Operating Expenses (RSF) | AS19: 16 | AU19: WALT | AW19: =$AS$10-AW7 -> 14.25 | AY19: =$AS$10-AY7 -> 13.25 | AZ19: =$AS$10-AZ7 -> 12.25 | BA19: =$AS$10-BA7 -> 11.25 | BB19: =$AS$10-BB7 -> 10.25 | BC19: =$AS$10-BC7 -> 9.25 | BD19: =$AS$10-BD7 -> 8.25 | BE19: =$AS$10-BE7 -> 7.25 | BF19: =$AS$10-BF7 -> 6.25 | BG19: =$AS$10-BG7 -> 5.25 | BI19: IRR | BJ19: =IFERROR(F105,0) -> 0 | BM19: Net Profit | BN19: =BN16+BN17+BN18 -> 278797.99 | BO19: =BN19/$AS$6 -> 14.866055 | BQ19: Total Project Profit | BR19: =BN66 -> 226866.26
E20: =Budget!D11 -> Closing Costs - Buyer | F20: 0 | G20: 0 | H20: =IF(AND(H$5>=$F20,H$5<=$G20),$AO20/($G20-$F20+1),0) -> 80897.21 | I20: =IF(AND(I$5>=$F20,I$5<=$G20),$AO20/($G20-$F20+1),0) -> 0 | J20: =IF(AND(J$5>=$F20,J$5<=$G20),$AO20/($G20-$F20+1),0) -> 0 | K20: =IF(AND(K$5>=$F20,K$5<=$G20),$AO20/($G20-$F20+1),0) -> 0 | L20: =IF(AND(L$5>=$F20,L$5<=$G20),$AO20/($G20-$F20+1),0) -> 0 | M20: =IF(AND(M$5>=$F20,M$5<=$G20),$AO20/($G20-$F20+1),0) -> 0 | N20: =IF(AND(N$5>=$F20,N$5<=$G20),$AO20/($G20-$F20+1),0) -> 0 | O20: =IF(AND(O$5>=$F20,O$5<=$G20),$AO20/($G20-$F20+1),0) -> 0 | ... AN20: =IF(AND(AN$5>=$F20,AN$5<=$G20),$AO20/($G20-$F20+1),0) -> 0 | AO20: =Budget!E11 -> 80897.21 | AP20: =+AO20/SF -> 4.3135976 | AR20: Operating Expense Inflation % | AS20: 0.02 | BI20: Equity Multiple | BJ20: =IFERROR(BJ17/-BJ16,0) -> 0 | BQ20: Total Project + Fee Profit | BR20: =BR17+BR19 -> 759119.98
B21: Aspect Equity Interest % | C21: 1 | E21: =Budget!D12 -> Closing Costs - Lender - Permanent Loan | F21: 0 | G21: 0 | H21: =IF(AND(H$5>=$F21,H$5<=$G21),$AO21/($G21-$F21+1),0) -> 16412 | I21: =IF(AND(I$5>=$F21,I$5<=$G21),$AO21/($G21-$F21+1),0) -> 0 | J21: =IF(AND(J$5>=$F21,J$5<=$G21),$AO21/($G21-$F21+1),0) -> 0 | K21: =IF(AND(K$5>=$F21,K$5<=$G21),$AO21/($G21-$F21+1),0) -> 0 | L21: =IF(AND(L$5>=$F21,L$5<=$G21),$AO21/($G21-$F21+1),0) -> 0 | M21: =IF(AND(M$5>=$F21,M$5<=$G21),$AO21/($G21-$F21+1),0) -> 0 | N21: =IF(AND(N$5>=$F21,N$5<=$G21),$AO21/($G21-$F21+1),0) -> 0 | O21: =IF(AND(O$5>=$F21,O$5<=$G21),$AO21/($G21-$F21+1),0) -> 0 | ... AN21: =IF(AND(AN$5>=$F21,AN$5<=$G21),$AO21/($G21-$F21+1),0) -> 0 | AO21: =Budget!E12 -> 16412 | AP21: =+AO21/SF -> 0.87511997 | AU21: Cap Rate at Sale | AW21: =IF(AW7<=$AY$7,$AS$15,$AS$15+((AW7-$AY$7)*$AS$16)) -> 0.0585 | AY21: =IF(AY7<=$AY$7,$AS$15,$AS$15+((AY7-$AY$7)*$AS$16)) -> 0.0585 | AZ21: =IF(AZ7<=$AY$7,$AS$15,$AS$15+((AZ7-$AY$7)*$AS$16)) -> 0.059 | BA21: =IF(BA7<=$AY$7,$AS$15,$AS$15+((BA7-$AY$7)*$AS$16)) -> 0.0595 | BB21: =IF(BB7<=$AY$7,$AS$15,$AS$15+((BB7-$AY$7)*$AS$16)) -> 0.06 | BC21: =IF(BC7<=$AY$7,$AS$15,$AS$15+((BC7-$AY$7)*$AS$16)) -> 0.0605 | BD21: =IF(BD7<=$AY$7,$AS$15,$AS$15+((BD7-$AY$7)*$AS$16)) -> 0.061 | BE21: =IF(BE7<=$AY$7,$AS$15,$AS$15+((BE7-$AY$7)*$AS$16)) -> 0.0615 | BF21: =IF(BF7<=$AY$7,$AS$15,$AS$15+((BF7-$AY$7)*$AS$16)) -> 0.062 | BG21: =IF(BG7<=$AY$7,$AS$15,$AS$15+((BG7-$AY$7)*$AS$16)) -> 0.0625 | BM21: IRR | BN21: ='JV Waterfall'!T40 -> 0.13028361
B22: Doctor's Equity Interest % | C22: =1-C21 -> 0 | E22: =Budget!D13 -> Closing Costs - Lender - Construction Loan | F22: 9 | G22: 9 | H22: =IF(AND(H$5>=$F22,H$5<=$G22),$AO22/($G22-$F22+1),0) -> 0 | I22: =IF(AND(I$5>=$F22,I$5<=$G22),$AO22/($G22-$F22+1),0) -> 0 | J22: =IF(AND(J$5>=$F22,J$5<=$G22),$AO22/($G22-$F22+1),0) -> 0 | K22: =IF(AND(K$5>=$F22,K$5<=$G22),$AO22/($G22-$F22+1),0) -> 0 | L22: =IF(AND(L$5>=$F22,L$5<=$G22),$AO22/($G22-$F22+1),0) -> 0 | M22: =IF(AND(M$5>=$F22,M$5<=$G22),$AO22/($G22-$F22+1),0) -> 0 | N22: =IF(AND(N$5>=$F22,N$5<=$G22),$AO22/($G22-$F22+1),0) -> 0 | O22: =IF(AND(O$5>=$F22,O$5<=$G22),$AO22/($G22-$F22+1),0) -> 0 | ... AN22: =IF(AND(AN$5>=$F22,AN$5<=$G22),$AO22/($G22-$F22+1),0) -> 0 | AO22: =Budget!E13 -> 0 | AP22: =+AO22/SF -> 0 | AR22: Fee's, Taxes, and Closing Cost's | AU22: Implied Exit Cap Rate | AW22: =(AW12/$AW$26)*(1-$AS$34) -> 0.05689125 | AY22: =(AY12/$AW$26)*(1-$AS$34) -> 0.058029075 | AZ22: =(AZ12/$AW$26)*(1-$AS$34) -> 0.059189656 | BA22: =(BA12/$AW$26)*(1-$AS$34) -> 0.06037345 | BB22: =(BB12/$AW$26)*(1-$AS$34) -> 0.061580919 | BC22: =(BC12/$AW$26)*(1-$AS$34) -> 0.062812537 | BD22: =(BD12/$AW$26)*(1-$AS$34) -> 0.064068788 | BE22: =(BE12/$AW$26)*(1-$AS$34) -> 0.065350163 | BF22: =(BF12/$AW$26)*(1-$AS$34) -> 0.066657167 | BG22: =(BG12/$AW$26)*(1-$AS$34) -> 0.06799031 | BI22: Levered Development Returns to Equity | BM22: Equity Multiple | BN22: ='JV Waterfall'!T41 -> 1.5460685 | BQ22: Assumptions:
AR23: Cost of Sale - Buyer - Going-In Year | AS23: =AS25+AS24 -> 0.02 | AU23: Accretive (Dilutive) Cap Spread | AW23: =AW22-AW21 -> -0.00160875 | AY23: =AY22-AY21 -> -0.000470925 | AZ23: =AZ22-AZ21 -> 0.0001896565 | BA23: =BA22-BA21 -> 0.00087344963 | BB23: =BB22-BB21 -> 0.0015809186 | BC23: =BC22-BC21 -> 0.002312537 | BD23: =BD22-BD21 -> 0.0030687877 | BE23: =BE22-BE21 -> 0.0038501635 | BF23: =BF22-BF21 -> 0.0046571668 | BG23: =BG22-BG21 -> 0.0054903101 | BI23: Preferred Equity Investors | BJ23: Amount | BK23: $PSF | BQ23: Self-Perform + Welltower JV
B24: Aspect Equity Interest | C24: =C16*C21 -> 3551440.2 | E24: Site Acquisition Costs | H24: =+SUBTOTAL(9,H16:H22) -> 10065309 | I24: =+SUBTOTAL(9,I16:I22) -> 0 | J24: =+SUBTOTAL(9,J16:J22) -> 0 | K24: =+SUBTOTAL(9,K16:K22) -> 0 | L24: =+SUBTOTAL(9,L16:L22) -> 0 | M24: =+SUBTOTAL(9,M16:M22) -> 0 | N24: =+SUBTOTAL(9,N16:N22) -> 0 | O24: =+SUBTOTAL(9,O16:O22) -> 0 | ... AO24: =+SUBTOTAL(9,AO16:AO22) -> 10065309 | AP24: =+AO24/SF -> 536.70199 | AR24: Newmark Venture Transaction Fee | AS24: 0.015 | AU24: REIT GAAP Accounting Cap Rate Average | AW24: =AVERAGE($AW$22:AW22) -> 0.05689125 | AY24: =AVERAGE($AW$22:AY22) -> 0.057460162 | AZ24: =AVERAGE($AW$22:AZ22) -> 0.05803666 | BA24: =AVERAGE($AW$22:BA22) -> 0.058620858 | BB24: =AVERAGE($AW$22:BB22) -> 0.05921287 | BC24: =AVERAGE($AW$22:BC22) -> 0.059812814 | BD24: =AVERAGE($AW$22:BD22) -> 0.060420811 | BE24: =AVERAGE($AW$22:BE22) -> 0.06103698 | BF24: =AVERAGE($AW$22:BF22) -> 0.061661445 | BG24: =AVERAGE($AW$22:BG22) -> 0.062294331 | BI24: Total Proceeds | BJ24: =SUMIF(H144:AN144,">0") -> 4696380.2 | BK24: =BJ24/SF -> 250.42019 | BM24: Unlevered Deal Returns - Year 5 | BQ24: Development Fee | BR24: =Budget!E9 -> 200000
B25: Doctor's Equity Interest | C25: =C16*C22 -> 0 | AR25: JV Closing Cost's | AS25: 0.005 | BI25: Capital Contribution | BJ25: =SUMIF(H144:AN144,"<0") -> -3895347.3 | BK25: =-BJ25/SF -> 207.70754 | BM25: Welltower Returns | BN25: Amount | BO25: $ PSF | BQ25: Inside Fee | BR25: =AS29 -> 0.02
B26: Total Equity Interest | C26: =SUM(C24:C25) -> 3551440.2 | E26: Construction Costs | AR26: Cost of Sale - Seller - Exit Year | AS26: =AS29+ AS28+AS27 -> 0.05 | AU26: Gross Sale Price | AW26: =AW12/AW21 -> 11839065 | AY26: =AY12/AY21 -> 12075847 | AZ26: =AZ12/AZ21 -> 12212979 | BA26: =BA12/BA21 -> 12352556 | BB26: =BB12/BB21 -> 12494611 | BC26: =BC12/BC21 -> 12639176 | BD26: =BD12/BD21 -> 12786288 | BE26: =BE12/BE21 -> 12935981 | BF26: =BF12/BF21 -> 13088292 | BG26: =BG12/BG21 -> 13243257 | BI26: Net Profit | BJ26: =BJ24+BJ25 -> 801032.86 | BK26: =BJ26/SF -> 42.712641 | BM26: Total Proceeds | BN26: =SUM(BB55:BB64) -> 15060999 | BO26: =BN26/$AS$6 -> 803.08195 | BQ26: Property Management Fee | BR26: 0
E27: =Budget!D17 -> Construction Costs | H27: 0 | I27: 0 | J27: 0 | K27: 0 | L27: 0 | M27: 0 | N27: 0 | O27: 0 | P27: 0 | Q27: 0 | R27: 0 | S27: 0 | T27: 0 | U27: 0 | V27: 0 | W27: 0 | X27: 0 | Y27: 0 | Z27: 0 | AA27: 0 | AB27: 0 | AC27: 0 | AD27: 0 | AE27: 0 | AF27: 0 | AG27: 0 | AH27: 0 | AI27: 0 | AJ27: 0 | AK27: 200000 | AL27: 0 | AM27: 0 | AN27: 0 | AO27: =SUM(H27:AN27) -> 200000 | AP27: =+AO27/SF -> 10.664392 | AR27: Connecticut State & Municipal Transfer Tax | AS27: 0.015 | AU27: Gross Sale Price PSF | AW27: =AW26/$AS$6 -> 631.28215 | AY27: =AY26/$AS$6 -> 643.90779 | AZ27: =AZ26/$AS$6 -> 651.21997 | BA27: =BA26/$AS$6 -> 658.66248 | BB27: =BB26/$AS$6 -> 666.2371 | BC27: =BC26/$AS$6 -> 673.94563 | BD27: =BD26/$AS$6 -> 681.78991 | BE27: =BE26/$AS$6 -> 689.77184 | BF27: =BF26/$AS$6 -> 697.89335 | BG27: =BG26/$AS$6 -> 706.15641 | BM27: Capital Contribution | BN27: =BN56 -> -11454656 | BO27: =BN27/-$AS$6 -> 610.78469 | BQ27: Asset Management Fee | BR27: 0.02
B28: Preferred Return % | C28: 0.11 | AR28: Broker (Outside) Fee | AS28: 0.015 | BI28: IRR | BJ28: =F144 -> 0.089599493 | BM28: Net Profit | BN28: =BN26+BN27 -> 3606342.8 | BO28: =BN28/$AS$6 -> 192.29726 | BQ28: Asset Management Fee | BR28: =AS11 -> 0.0025
B29: Preferred Return % of Total Equity Contribution | C29: =C28*C21 -> 0.11 | E29: Construction Costs | H29: =+SUBTOTAL(9,H27) -> 0 | I29: =+SUBTOTAL(9,I27) -> 0 | J29: =+SUBTOTAL(9,J27) -> 0 | K29: =+SUBTOTAL(9,K27) -> 0 | L29: =+SUBTOTAL(9,L27) -> 0 | M29: =+SUBTOTAL(9,M27) -> 0 | N29: =+SUBTOTAL(9,N27) -> 0 | O29: =+SUBTOTAL(9,O27) -> 0 | ... AO29: =+SUBTOTAL(9,AO27) -> 200000 | AP29: =+AO29/SF -> 10.664392 | AR29: Aspect Health (Inside) Fee | AS29: 0.02 | AU29: Net Sale Price | AW29: =AW26*(1-($AS$34)) -> 11513491 | AY29: =AY26*(1-($AS$34)) -> 11743761 | AZ29: =AZ26*(1-($AS$34)) -> 11877122 | BA29: =BA26*(1-($AS$34)) -> 12012861 | BB29: =BB26*(1-($AS$34)) -> 12151009 | BC29: =BC26*(1-($AS$34)) -> 12291599 | BD29: =BD26*(1-($AS$34)) -> 12434665 | BE29: =BE26*(1-($AS$34)) -> 12580242 | BF29: =BF26*(1-($AS$34)) -> 12728364 | BG29: =BG26*(1-($AS$34)) -> 12879068 | BI29: Average Cash-on-Cash | BJ29: =AL163 -> 0
B30: Equity Kicker % | C30: 0.2 | AR30: Accrued Asset Management Fees | AS30: =IF($G$13="Yes",SUM(I13:AL13),0) -> 42919.789 | AU30: Net Sale Price PSF | AW30: =AW29/$AS$6 -> 613.92189 | AY30: =AY29/$AS$6 -> 626.20033 | AZ30: =AZ29/$AS$6 -> 633.31142 | BA30: =BA29/$AS$6 -> 640.54926 | BB30: =BB29/$AS$6 -> 647.91558 | BC30: =BC29/$AS$6 -> 655.41212 | BD30: =BD29/$AS$6 -> 663.04069 | BE30: =BE29/$AS$6 -> 670.80312 | BF30: =BF29/$AS$6 -> 678.70128 | BG30: =BG29/$AS$6 -> 686.73711 | BI30: Equity Multiple | BJ30: =BJ26/-BJ25+1 -> 1.2056384 | BM30: IRR | BN30: =BB53 -> 0.062315052
E31: Tenant Leasing Cost | AR31: Swap Breakage Fees - Permanent Loan | AS31: ='Offering Memorandum'!BQ43 -> 28807.114 | BM31: Equity Multiple | BN31: =BN26/-BN27 -> 1.3148364
B32: Capital Stack | D32: ON | E32: =Budget!D26 -> Tenant Capital Reimbursement | F32: 29 | G32: 29 | H32: =IF(AND(H$5>=$F32,H$5<=$G32),$AO32/($G32-$F32+1),0) -> 0 | I32: =IF(AND(I$5>=$F32,I$5<=$G32),$AO32/($G32-$F32+1),0) -> 0 | J32: =IF(AND(J$5>=$F32,J$5<=$G32),$AO32/($G32-$F32+1),0) -> 0 | K32: =IF(AND(K$5>=$F32,K$5<=$G32),$AO32/($G32-$F32+1),0) -> 0 | L32: =IF(AND(L$5>=$F32,L$5<=$G32),$AO32/($G32-$F32+1),0) -> 0 | M32: =IF(AND(M$5>=$F32,M$5<=$G32),$AO32/($G32-$F32+1),0) -> 0 | N32: =IF(AND(N$5>=$F32,N$5<=$G32),$AO32/($G32-$F32+1),0) -> 0 | O32: =IF(AND(O$5>=$F32,O$5<=$G32),$AO32/($G32-$F32+1),0) -> 0 | ... AN32: =IF(AND(AN$5>=$F32,AN$5<=$G32),$AO32/($G32-$F32+1),0) -> 0 | AO32: =Budget!E26 -> 93770 | AP32: =+AO32/SF -> 5 | AR32: Outstanding Rent/TIA Obligations | AS32: =SUM('Offering Memorandum'!EJ14:EL14) -> 179865.22 | AU32: Unlevered IRR | AW32: =AW66 -> 0.028303582 | AY32: =AY66 -> 0.053732307 | AZ32: =AZ66 -> 0.059661846 | BA32: =BA66 -> 0.062768195 | BB32: =BB66 -> 0.064735984 | BC32: =BC66 -> 0.066129806 | BD32: =BD66 -> 0.067192383 | BE32: =BE66 -> 0.068045333 | BF32: =BF66 -> 0.068756329 | BG32: =BG66 -> 0.069366031 | BI32: Levered Development Returns to Equity
B33: Debt | C33: =H79*C9 -> 0.041763574 | D33: OFF | E33: =Budget!D27 -> Leasing Legal | F33: 0 | G33: 0 | H33: =IF(AND(H$5>=$F33,H$5<=$G33),$AO33/($G33-$F33+1),0) -> 3381 | I33: =IF(AND(I$5>=$F33,I$5<=$G33),$AO33/($G33-$F33+1),0) -> 0 | J33: =IF(AND(J$5>=$F33,J$5<=$G33),$AO33/($G33-$F33+1),0) -> 0 | K33: =IF(AND(K$5>=$F33,K$5<=$G33),$AO33/($G33-$F33+1),0) -> 0 | L33: =IF(AND(L$5>=$F33,L$5<=$G33),$AO33/($G33-$F33+1),0) -> 0 | M33: =IF(AND(M$5>=$F33,M$5<=$G33),$AO33/($G33-$F33+1),0) -> 0 | N33: =IF(AND(N$5>=$F33,N$5<=$G33),$AO33/($G33-$F33+1),0) -> 0 | O33: =IF(AND(O$5>=$F33,O$5<=$G33),$AO33/($G33-$F33+1),0) -> 0 | ... AN33: =IF(AND(AN$5>=$F33,AN$5<=$G33),$AO33/($G33-$F33+1),0) -> 0 | AO33: =Budget!E27 -> 3381 | AP33: =+AO33/SF -> 0.18028154 | AR33: Loan Prepayment Fee - Construction Loan | AS33: =Budget!Q41 -> 0 | AU33: Unlevered Equity Multiple | AW33: =(SUM($AW$16:AW16)+AW29)/-AW67 -> 1.0283036 | AY33: =(SUM($AW$16:AY16)+AY29)/-AY67 -> 1.1072167 | AZ33: =(SUM($AW$16:AZ16)+AZ29)/-AZ67 -> 1.1791559 | BA33: =(SUM($AW$16:BA16)+BA29)/-BA67 -> 1.2525096 | BB33: =(SUM($AW$16:BB16)+BB29)/-BB67 -> 1.3273045 | BC33: =(SUM($AW$16:BC16)+BC29)/-BC67 -> 1.4035684 | BD33: =(SUM($AW$16:BD16)+BD29)/-BD67 -> 1.4813292 | BE33: =(SUM($AW$16:BE16)+BE29)/-BE67 -> 1.5606157 | BF33: =(SUM($AW$16:BF16)+BF29)/-BF67 -> 1.6414571 | BG33: =(SUM($AW$16:BG16)+BG29)/-BG67 -> 1.7238833 | BI33: Aspect Health, Inc. House | BJ33: Amount | BK33: $PSF | BM33: Levered Deal Returns to Equity - Year 10
B34: Equity | C34: =(1-C9)*C29 -> 0.039329559 | E34: =Budget!D28 -> Broker Fee | F34: 7 | G34: 7 | H34: =IF(AND(H$5>=$F34,H$5<=$G34),$AO34/($G34-$F34+1),0) -> 0 | I34: =IF(AND(I$5>=$F34,I$5<=$G34),$AO34/($G34-$F34+1),0) -> 0 | J34: =IF(AND(J$5>=$F34,J$5<=$G34),$AO34/($G34-$F34+1),0) -> 0 | K34: =IF(AND(K$5>=$F34,K$5<=$G34),$AO34/($G34-$F34+1),0) -> 0 | L34: =IF(AND(L$5>=$F34,L$5<=$G34),$AO34/($G34-$F34+1),0) -> 0 | M34: =IF(AND(M$5>=$F34,M$5<=$G34),$AO34/($G34-$F34+1),0) -> 0 | N34: =IF(AND(N$5>=$F34,N$5<=$G34),$AO34/($G34-$F34+1),0) -> 0 | O34: =IF(AND(O$5>=$F34,O$5<=$G34),$AO34/($G34-$F34+1),0) -> 0 | ... AN34: =IF(AND(AN$5>=$F34,AN$5<=$G34),$AO34/($G34-$F34+1),0) -> 0 | AO34: =Budget!E28 -> 0 | AP34: =+AO34/SF -> 0 | AR34: Cost of Sale - Exit Year | AS34: =AS35+AS36+AS37 -> 0.0275 | BI34: Total Proceeds | BJ34: =SUMIF(H145:AN145,">0") -> 0 | BK34: =BJ34/SF -> 0 | BM34: Project-Level Returns | BN34: Amount | BO34: $ PSF
B35: Total Capital Stack | C35: =SUM(C33:C34) -> 0.081093133 | AR35: Connecticut State & Municipal Transfer Tax | AS35: 0.015 | AU35: Loan Balance | AW35: =AS42 -> 7715571.4 | AY35: =AW35 -> 7715571.4 | AZ35: =AY35 -> 7715571.4 | BA35: =AZ35 -> 7715571.4 | BB35: =BA35 -> 7715571.4 | BC35: =BB35 -> 7715571.4 | BD35: =BC35 -> 7715571.4 | BE35: =BD35 -> 7715571.4 | BF35: =BE35 -> 7715571.4 | BG35: =BF35 -> 7715571.4 | BI35: Capital Contribution | BJ35: 0 | BK35: =-BJ35/SF -> 0 | BM35: Total Proceeds | BN35: =SUM(BG81:BG90) -> 9524542.5 | BO35: =BN35/$AS$6 -> 507.86725
E36: Tenant Leasing Cost | H36: =+SUBTOTAL(9,H32:H34) -> 3381 | I36: =+SUBTOTAL(9,I32:I34) -> 0 | J36: =+SUBTOTAL(9,J32:J34) -> 0 | K36: =+SUBTOTAL(9,K32:K34) -> 0 | L36: =+SUBTOTAL(9,L32:L34) -> 0 | M36: =+SUBTOTAL(9,M32:M34) -> 0 | N36: =+SUBTOTAL(9,N32:N34) -> 0 | O36: =+SUBTOTAL(9,O32:O34) -> 0 | ... AO36: =+SUBTOTAL(9,AO32:AO34) -> 97151 | AP36: =+AO36/SF -> 5.1802815 | AR36: Broker (Outside) Fee | AS36: 0.01 | AU36: Debt Service | AW36: =AS43 -> 312909.29 | AY36: =AW36 -> 312909.29 | AZ36: =AW36 -> 312909.29 | BA36: =AY36 -> 312909.29 | BB36: =AZ36 -> 312909.29 | BC36: =BA36 -> 312909.29 | BD36: =BB36 -> 312909.29 | BE36: =BC36 -> 312909.29 | BF36: =BD36 -> 312909.29 | BG36: =BE36 -> 312909.29 | BI36: Net Profit | BJ36: =BJ34+BJ35 -> 0 | BK36: =BJ36/SF -> 0 | BM36: Capital Contribution | BN36: =AV44 -> -4154538.5 | BO36: =BN36/-$AS$6 -> 221.52812
AR37: JV Closing Cost's | AS37: 0.0025 | AU37: Debt Coverage Ratio | AW37: =AW12/AW36 -> 2.2133742 | AY37: =AY12/AY36 -> 2.2576417 | AZ37: =AZ12/AZ36 -> 2.3027945 | BA37: =BA12/BA36 -> 2.3488504 | BB37: =BB12/BB36 -> 2.3958274 | BC37: =BC12/BC36 -> 2.4437439 | BD37: =BD12/BD36 -> 2.4926188 | BE37: =BE12/BE36 -> 2.5424712 | BF37: =BF12/BF36 -> 2.5933206 | BG37: =BG12/BG36 -> 2.645187 | BM37: Net Profit | BN37: =BN35+BN36 -> 5370004 | BO37: =BN37/$AS$6 -> 286.33913
E38: Development Financing
E39: =Budget!D21 -> Lender Origination Fee - Permanent Loan | F39: 0 | G39: 0 | H39: =IF(AND(H$5>=$F39,H$5<=$G39),$AO39/($G39-$F39+1),0) -> 32750 | I39: =IF(AND(I$5>=$F39,I$5<=$G39),$AO39/($G39-$F39+1),0) -> 0 | J39: =IF(AND(J$5>=$F39,J$5<=$G39),$AO39/($G39-$F39+1),0) -> 0 | K39: =IF(AND(K$5>=$F39,K$5<=$G39),$AO39/($G39-$F39+1),0) -> 0 | L39: =IF(AND(L$5>=$F39,L$5<=$G39),$AO39/($G39-$F39+1),0) -> 0 | M39: =IF(AND(M$5>=$F39,M$5<=$G39),$AO39/($G39-$F39+1),0) -> 0 | N39: =IF(AND(N$5>=$F39,N$5<=$G39),$AO39/($G39-$F39+1),0) -> 0 | O39: =IF(AND(O$5>=$F39,O$5<=$G39),$AO39/($G39-$F39+1),0) -> 0 | ... AN39: =IF(AND(AN$5>=$F39,AN$5<=$G39),$AO39/($G39-$F39+1),0) -> 0 | AO39: =Budget!E21 -> 32750 | AP39: =+AO39/SF -> 1.7462941 | AR39: Debt | AU39: Net Cash on Sale | AW39: =AW29-AW35 -> 3797919.8 | AY39: =AY29-AY35 -> 4028189.6 | AZ39: =AZ29-AZ35 -> 4161550.9 | BA39: =BA29-BA35 -> 4297289.5 | BB39: =BB29-BB35 -> 4435437.4 | BC39: =BC29-BC35 -> 4576027.6 | BD39: =BD29-BD35 -> 4719093.7 | BE39: =BE29-BE35 -> 4864670.3 | BF39: =BF29-BF35 -> 5012792.5 | BG39: =BG29-BG35 -> 5163496.3 | BM39: IRR | BN39: =BG49 -> 0.11579856
E40: =Budget!D22 -> Lender Origination Fee - Construction Loan | F40: 9 | G40: 9 | H40: =IF(AND(H$5>=$F40,H$5<=$G40),$AO40/($G40-$F40+1),0) -> 0 | I40: =IF(AND(I$5>=$F40,I$5<=$G40),$AO40/($G40-$F40+1),0) -> 0 | J40: =IF(AND(J$5>=$F40,J$5<=$G40),$AO40/($G40-$F40+1),0) -> 0 | K40: =IF(AND(K$5>=$F40,K$5<=$G40),$AO40/($G40-$F40+1),0) -> 0 | L40: =IF(AND(L$5>=$F40,L$5<=$G40),$AO40/($G40-$F40+1),0) -> 0 | M40: =IF(AND(M$5>=$F40,M$5<=$G40),$AO40/($G40-$F40+1),0) -> 0 | N40: =IF(AND(N$5>=$F40,N$5<=$G40),$AO40/($G40-$F40+1),0) -> 0 | O40: =IF(AND(O$5>=$F40,O$5<=$G40),$AO40/($G40-$F40+1),0) -> 0 | ... AN40: =IF(AND(AN$5>=$F40,AN$5<=$G40),$AO40/($G40-$F40+1),0) -> 0 | AO40: =Budget!E22 -> 0 | AP40: =+AO40/SF -> 0 | AR40: LTV | AS40: 0.65 | AU40: Net Gain | AW40: =AW39+$AV$44 -> -356618.7 | AY40: =AY39+$AV$44 -> -126348.88 | AZ40: =AZ39+$AV$44 -> 7012.4786 | BA40: =BA39+$AV$44 -> 142751.02 | BB40: =BB39+$AV$44 -> 280898.92 | BC40: =BC39+$AV$44 -> 421489.1 | BD40: =BD39+$AV$44 -> 564555.26 | BE40: =BE39+$AV$44 -> 710131.82 | BF40: =BF39+$AV$44 -> 858254.02 | BG40: =BG39+$AV$44 -> 1008957.9 | BM40: Equity Multiple | BN40: =BN37/-BN36+1 -> 2.2925633
AR41: Interest Rate | AS41: =(4%/360)*365 -> 0.040555556 | BM41: Avg. Cash-on-Cash | BN41: =BG47 -> 0.10472065
E42: Tenant Leasing Cost | H42: =+SUBTOTAL(9,H39:H40) -> 32750 | I42: =+SUBTOTAL(9,I39:I40) -> 0 | J42: =+SUBTOTAL(9,J39:J40) -> 0 | K42: =+SUBTOTAL(9,K39:K40) -> 0 | L42: =+SUBTOTAL(9,L39:L40) -> 0 | M42: =+SUBTOTAL(9,M39:M40) -> 0 | N42: =+SUBTOTAL(9,N39:N40) -> 0 | O42: =+SUBTOTAL(9,O39:O40) -> 0 | ... AO42: =+SUBTOTAL(9,AO39:AO40) -> 32750 | AP42: =+AO42/SF -> 1.7462941 | AR42: Loan Amount | AS42: =AS8*AS40 -> 7715571.4 | AU42: Net Cash Flow after Debt Service | AW42: =AW16-AW36 -> 379676.05 | AY42: =AY16-AY36 -> 393527.75 | AZ42: =AZ16-AZ36 -> 407656.49 | BA42: =BA16-BA36 -> 422067.81 | BB42: =BB16-BB36 -> 436767.35 | BC42: =BC16-BC36 -> 451760.88 | BD42: =BD16-BD36 -> 467054.29 | BE42: =BE16-BE36 -> 482653.56 | BF42: =BF16-BF36 -> 498564.81 | BG42: =BG16-BG36 -> 514794.3
AR43: Annual Debt Service | AS43: =AS42*AS41 -> 312909.29 | AU43: Asset Management Fees | AW43: =AV44*AS11 -> -10386.346 | AY43: =AW43 -> -10386.346 | AZ43: =AY43 -> -10386.346 | BA43: =AZ43 -> -10386.346 | BB43: =BA43 -> -10386.346 | BC43: =BB43 -> -10386.346 | BD43: =BC43 -> -10386.346 | BE43: =BD43 -> -10386.346 | BF43: =BE43 -> -10386.346 | BG43: =BF43 -> -10386.346 | BM43: Levered Deal Returns to Equity - Year 10
B44: ` | E44: Total Project Development Cost | H44: =H24+H29+H36+H42 -> 10101440 | I44: =I24+I29+I36+I42 -> 0 | J44: =J24+J29+J36+J42 -> 0 | K44: =K24+K29+K36+K42 -> 0 | L44: =L24+L29+L36+L42 -> 0 | M44: =M24+M29+M36+M42 -> 0 | N44: =N24+N29+N36+N42 -> 0 | O44: =O24+O29+O36+O42 -> 0 | ... AO44: =AO24+AO29+AO36+AO42 -> 10395210 | AP44: =+AO44/Budget!E5 -> 554.29296 | AU44: Levered Cash Flow | AV44: =-AS46 -> -4154538.5 | AW44: =AW42+AW43 -> 369289.7 | AY44: =AY42+AY43 -> 383141.41 | AZ44: =AZ42+AZ43 -> 397270.15 | BA44: =BA42+BA43 -> 411681.46 | BB44: =BB42+BB43 -> 426381 | BC44: =BC42+BC43 -> 441374.54 | BD44: =BD42+BD43 -> 456667.94 | BE44: =BE42+BE43 -> 472267.21 | BF44: =BF42+BF43 -> 488178.47 | BG44: =BG42+BG43 -> 504407.95 | BM44: Aspect Health Inc. Returns | BN44: Amount | BO44: $ PSF
AR45: Equity | BM45: Total Proceeds | BN45: ='JV Waterfall'!D36 -> 951415.61 | BO45: =BN45/$AS$6 -> 50.731343
E46: Disposition | AR46: Required Initial Common Capital Contributions | AS46: =AS8-AS42 -> 4154538.5 | AU46: Cash on Cash Return | AW46: =(AW16-AW36+AW43)/-$AV$44 -> 0.088888261 | AY46: =(AY16-AY36+AY43)/-$AV$44 -> 0.092222376 | AZ46: =(AZ16-AZ36+AZ43)/-$AV$44 -> 0.095623172 | BA46: =(BA16-BA36+BA43)/-$AV$44 -> 0.099091985 | BB46: =(BB16-BB36+BB43)/-$AV$44 -> 0.10263017 | BC46: =(BC16-BC36+BC43)/-$AV$44 -> 0.10623913 | BD46: =(BD16-BD36+BD43)/-$AV$44 -> 0.10992026 | BE46: =(BE16-BE36+BE43)/-$AV$44 -> 0.11367501 | BF46: =(BF16-BF36+BF43)/-$AV$44 -> 0.11750486 | BG46: =(BG16-BG36+BG43)/-$AV$44 -> 0.12141131 | BM46: Total Asset Management Fee's | BN46: ='JV Waterfall'!D37 -> 103863.46 | BO46: =BN46/$AS$6 -> 5.5382031
E47: =+"Net Sale Price @ "&(TEXT(AS14,"0.00% Cap")) -> Net Sale Price @ 5.95% Cap | H47: =IF(H5=(MAX($I5:$AN5)),$AW$12/$AS14,0) -> 0 | I47: =IF(I5=(MAX($I5:$AN5)),$AW$12/$AS14,0) -> 0 | J47: =IF(J5=(MAX($I5:$AN5)),$AW$12/$AS14,0) -> 0 | K47: =IF(K5=(MAX($I5:$AN5)),$AW$12/$AS14,0) -> 0 | L47: =IF(L5=(MAX($I5:$AN5)),$AW$12/$AS14,0) -> 0 | M47: =IF(M5=(MAX($I5:$AN5)),$AW$12/$AS14,0) -> 0 | N47: =IF(N5=(MAX($I5:$AN5)),$AW$12/$AS14,0) -> 0 | O47: =IF(O5=(MAX($I5:$AN5)),$AW$12/$AS14,0) -> 0 | ... AK47: =IF(AK5=(MAX($I5:$AN5)),$AW$12/$AS14,0) -> 0 | AL47: =IF(AL5=(MAX($I5:$AL5)),$AW$12/$AS14,0) -> 11640090 | AM47: =IF(AM5=(MAX($I5:$AL5)),$AW$12/$AS14,0) -> 0 | AN47: =IF(AN5=(MAX($I5:$AL5)),$AW$12/$AS14,0) -> 0 | AO47: =SUM(H47:AN47) -> 11640090 | AP47: =+AO47/SF -> 620.67237 | AR47: Aspect Equity Interest % | AS47: 0.1 | AU47: Average Cash on Cash | AW47: =AVERAGE($AW$46:AW46) -> 0.088888261 | AY47: =AVERAGE($AW$46:AY46) -> 0.090555318 | AZ47: =AVERAGE($AW$46:AZ46) -> 0.092244603 | BA47: =AVERAGE($AW$46:BA46) -> 0.093956448 | BB47: =AVERAGE($AW$46:BB46) -> 0.095691193 | BC47: =AVERAGE($AW$46:BC46) -> 0.097449182 | BD47: =AVERAGE($AW$46:BD46) -> 0.099230765 | BE47: =AVERAGE($AW$46:BE46) -> 0.1010363 | BF47: =AVERAGE($AW$46:BF46) -> 0.10286614 | BG47: =AVERAGE($AW$46:BG46) -> 0.10472065 | BM47: Capital Contribution | BN47: =-AS50 -> -415453.85 | BO47: =BN47/-$AS$6 -> 22.152812
E48: =+"Closing Costs & Fees @ "&(TEXT(AS26,"0.00% ")) -> Closing Costs & Fees @ 5.00% | H48: =IF(H47>0,$AF$47*$AS$26,0) -> 0 | I48: =IF(I47>0,I47*$AS$26,0) -> 0 | J48: =IF(J47>0,J47*$AS$26,0) -> 0 | K48: =IF(K47>0,K47*$AS$26,0) -> 0 | L48: =IF(L47>0,L47*$AS$26,0) -> 0 | M48: =IF(M47>0,M47*$AS$26,0) -> 0 | N48: =IF(N47>0,N47*$AS$26,0) -> 0 | O48: =IF(O47>0,O47*$AS$26,0) -> 0 | P48: =IF(P47>0,P47*$AS$26,0) -> 0 | ... AK48: =IF(AK47>0,AK47*$AS$26,0) -> 0 | AL48: =IF(AL47>0,AL47*$AS$26,0)+$AS$30+$AS$31+$AS$33+$AS$32 -> 833596.6 | AM48: =IF(AM47>0,AM47*$AS$26,0) -> 0 | AN48: =IF(AN47>0,AN47*$AS$26,0) -> 0 | AO48: =SUM(H48:AN48) -> 833596.6 | AP48: =+AO48/SF -> 44.449003 | AR48: Welltower Equity Interest % | AS48: =1-AS47 -> 0.9 | BM48: Net Profit | BN48: =BN45+BN46+BN47 -> 639825.23 | BO48: =BN48/$AS$6 -> 34.116734
E49: Disposition | H49: =H47-H48 -> 0 | I49: =I47-I48 -> 0 | J49: =J47-J48 -> 0 | K49: =K47-K48 -> 0 | L49: =L47-L48 -> 0 | M49: =M47-M48 -> 0 | N49: =N47-N48 -> 0 | O49: =O47-O48 -> 0 | ... AN49: =AN47-AN48 -> 0 | AO49: =SUM(H49:AN49) -> 10806493 | AP49: =+AO49/SF -> 576.22336 | AU49: Levered IRR | AW49: =AW79 -> 0.0030499177 | AY49: =AY79 -> 0.075843861 | AZ49: =AZ79 -> 0.092559787 | BA49: =BA79 -> 0.1009422 | BB49: =BB79 -> 0.10594725 | BC49: =BC79 -> 0.10925328 | BD49: =BD79 -> 0.11158595 | BE49: =BE79 -> 0.11331011 | BF49: =BF79 -> 0.1146292 | BG49: =BG79 -> 0.11579856
AR50: Aspect Equity Interest | AS50: =AS46*AS47 -> 415453.85 | AU50: Levered Equity Multiple | AW50: =((SUM($AW$44:AW44)+(AW39))/-AW80) -> 1.0030499 | AY50: =((SUM($AW$44:AY44)+(AY39))/-AY80) -> 1.1506984 | AZ50: =((SUM($AW$44:AZ44)+(AZ39))/-AZ80) -> 1.2784217 | BA50: =((SUM($AW$44:BA44)+(BA39))/-BA80) -> 1.4101861 | BB50: =((SUM($AW$44:BB44)+(BB39))/-BB80) -> 1.5460685 | BC50: =((SUM($AW$44:BC44)+(BC39))/-BC80) -> 1.6861478 | BD50: =((SUM($AW$44:BD44)+(BD39))/-BD80) -> 1.8305042 | BE50: =((SUM($AW$44:BE44)+(BE39))/-BE80) -> 1.9792195 | BF50: =((SUM($AW$44:BF44)+(BF39))/-BF80) -> 2.1323775 | BG50: =((SUM($AW$44:BG44)+(BG39))/-BG80) -> 2.2900633 | BM50: IRR | BN50: ='JV Waterfall'!D40 -> 0.13861658
E51: =+"Unleveraged Cash Flow ("&IFERROR(TEXT(F51,"0.00%)"),"0%)") -> Unleveraged Cash Flow (7.57%) | F51: =XIRR(H51:AN51,H7:AN7) -> 0.075689134 | H51: =-H44+H49+H12 -> -10101440 | I51: =-I44+I49+I12-IF($G$13="No",I13,0)+I14 -> 27845.162 | J51: =-J44+J49+J12-IF($G$13="No",J13,0)+J14 -> 45431.58 | K51: =-K44+K49+K12-IF($G$13="No",K13,0)+K14 -> 45431.58 | L51: =-L44+L49+L12-IF($G$13="No",L13,0)+L14 -> 45431.58 | M51: =-M44+M49+M12-IF($G$13="No",M13,0)+M14 -> 45431.58 | N51: =-N44+N49+N12-IF($G$13="No",N13,0)+N14 -> 68000 | O51: =-O44+O49+O12-IF($G$13="No",O13,0)+O14 -> 0 | P51: =-P44+P49+P12-IF($G$13="No",P13,0)+P14 -> 55381.98 | ... AN51: =-AN44+AN49+AN12-IF($G$13="No",AN13,0)+AN14 -> 0 | AO51: =SUM(H51:AN51) -> 1864059.9 | AP51: =+AO51/SF -> 99.395322 | AR51: Welltower Equity Interest | AS51: =AS46*AS48 -> 3739084.6 | BM51: Equity Multiple | BN51: ='JV Waterfall'!D41 -> 2.2900633
AR52: Total Equity Interest | AS52: =AS50+AS51 -> 4154538.5 | AU52: Year | AV52: =AV65 -> 0 | AW52: =AW65 -> 1 | AY52: =AY65 -> 2 | AZ52: =AZ65 -> 3 | BA52: =BA65 -> 4 | BB52: =BB65 -> 5 | BC52: =BC65 -> 6 | BD52: =BD65 -> 7 | BE52: =BE65 -> 8 | BF52: =BF65 -> 9 | BG52: =BG65 -> 10
E53: Financing | AU53: Welltower IRR | AV53: -- | AW53: =IRR(AW54:AW64) -> 0.028312783 | AY53: =IRR(AY54:AY64) -> 0.052025111 | AZ53: =IRR(AZ54:AZ64) -> 0.057560641 | BA53: =IRR(BA54:BA64) -> 0.06046767 | BB53: =IRR(BB54:BB64) -> 0.062315052 | BC53: =IRR(BC54:BC64) -> 0.063628375 | BD53: =IRR(BD54:BD64) -> 0.064633533 | BE53: =IRR(BE54:BE64) -> 0.065443689 | BF53: =IRR(BF54:BF64) -> 0.066121795 | BG53: =IRR(BG54:BG64) -> 0.066705669 | BM53: Unlevered Deal Returns - Year 10
E54: Interest Payment | H54: =H83 -> 0 | I54: =I83+I104 -> 24243.55 | J54: =J83+J104 -> 40712.09 | K54: =K83+K104 -> 39462 | L54: =L83+L104 -> 40692.3 | M54: =M83+M104 -> 34769.583 | N54: =N83+N104 -> 35928.569 | O54: =O83+O104 -> 35928.569 | P54: =P83+P104 -> 33610.597 | ... AN54: =AN83+AN104 -> 0 | AO54: =SUM(H54:AN54) -> 1063026.9 | AP54: =+AO54/SF -> 56.682678 | AR54: Preferred Return | AS54: 0.08 | AU54: 0 | AV54: =AW54 -> -11454656 | AW54: =-AS42-AS51 -> -11454656 | AY54: =AW54 -> -11454656 | AZ54: =AY54 -> -11454656 | BA54: =AZ54 -> -11454656 | BB54: =BA54 -> -11454656 | BC54: =BB54 -> -11454656 | BD54: =BC54 -> -11454656 | BE54: =BD54 -> -11454656 | BF54: =BE54 -> -11454656 | BG54: =BF54 -> -11454656 | BM54: Welltower Returns | BN54: Amount | BO54: $ PSF
E55: Principal Payment | H55: 0 | I55: 0 | J55: 0 | K55: 0 | L55: 0 | M55: 0 | N55: 0 | O55: 0 | P55: 0 | Q55: 0 | R55: 0 | S55: 0 | T55: 0 | U55: 0 | V55: 0 | W55: 0 | X55: 0 | Y55: 0 | Z55: 0 | AA55: 0 | AB55: 0 | AC55: 0 | AD55: 0 | AE55: 0 | AF55: 0 | AG55: 0 | AH55: 0 | AI55: 0 | AJ55: 0 | AK55: 0 | AL55: 0 | AM55: 0 | AN55: 0 | AO55: =SUM(H55:AN55) -> 0 | AP55: =+AO55/SF -> 0 | AU55: =AU54+1 -> 1 | AW55: =AW36+(AW44*$AS$48)+AW35+(AW39*$AS$48) -> 11778969 | AY55: =AW$36+(AW$44*$AS$48) -> 645270.01 | AZ55: =AY55 -> 645270.01 | BA55: =AZ55 -> 645270.01 | BB55: =BA55 -> 645270.01 | BC55: =BB55 -> 645270.01 | BD55: =BC55 -> 645270.01 | BE55: =BD55 -> 645270.01 | BF55: =BE55 -> 645270.01 | BG55: =BF55 -> 645270.01 | BM55: Total Proceeds | BN55: =SUM(BG55:BG64) -> 19407405 | BO55: =BN55/$AS$6 -> 1034.8408
E56: Origination Fee | H56: 0 | I56: 0 | J56: 0 | K56: 0 | L56: 0 | M56: 0 | N56: 0 | O56: 0 | P56: 0 | Q56: 0 | R56: 0 | S56: 0 | T56: 0 | U56: 0 | V56: 0 | W56: 0 | X56: 0 | Y56: 0 | Z56: 0 | AA56: 0 | AB56: 0 | AC56: 0 | AD56: 0 | AE56: 0 | AF56: 0 | AG56: 0 | AH56: 0 | AI56: 0 | AJ56: 0 | AK56: 0 | AL56: 0 | AM56: 0 | AN56: 0 | AO56: =SUM(H56:AN56) -> 0 | AP56: =+AO56/SF -> 0 | AR56: JV Ownership Interest | AU56: =AU55+1 -> 2 | AY56: =AY36+(AY44*$AS$48)+AY35+(AY39*$AS$48) -> 11998679 | AZ56: =AY$36+(AY$44*$AS$48) -> 657736.55 | BA56: =AZ56 -> 657736.55 | BB56: =BA56 -> 657736.55 | BC56: =BB56 -> 657736.55 | BD56: =BC56 -> 657736.55 | BE56: =BD56 -> 657736.55 | BF56: =BE56 -> 657736.55 | BG56: =BF56 -> 657736.55 | BM56: Capital Contribution | BN56: =BG54 -> -11454656 | BO56: =-BN56/$AS$6 -> 610.78469
E57: Loan Funding | H57: =-H71-H92 -> -6550000 | I57: =-I71-I92 -> 0 | J57: =-J71-J92 -> 0 | K57: =-K71-K92 -> 0 | L57: =-L71-L92 -> 0 | M57: =-M71-M92 -> 0 | N57: =-N71-N92 -> 0 | O57: =-O71-O92 -> 0 | ... AO57: =-AO71-AO92 -> -6550000 | AP57: =-+AO57/SF -> 349.25882 | AR57: Aspect Total Interest | AS57: =(AS50)/AS8 -> 0.035 | AU57: =AU56+1 -> 3 | AZ57: =AZ36+(AZ44*$AS$48)+AZ35+(AZ39*$AS$48) -> 12131420 | BA57: =AZ$36+(AZ$44*$AS$48) -> 670452.42 | BB57: =BA57 -> 670452.42 | BC57: =BB57 -> 670452.42 | BD57: =BC57 -> 670452.42 | BE57: =BD57 -> 670452.42 | BF57: =BE57 -> 670452.42 | BG57: =BF57 -> 670452.42 | BM57: Net Profit | BN57: =BN55+BN56 -> 7952748.8 | BO57: =BN57/$AS$6 -> 424.05614
E58: Loan Payoff | H58: =H72 -> 0 | I58: =I72 -> 0 | J58: =J72 -> 0 | K58: =K72 -> 0 | L58: =L72 -> 0 | M58: =M72 -> 0 | N58: =N72 -> 0 | O58: =O72 -> 0 | ... Y58: =Y72 -> 0 | Z58: =-Z72 -> 0 | AA58: =-AA72 -> 0 | AB58: =-AB72 -> 0 | AC58: =-AC72 -> 0 | AD58: =-AD72 -> 0 | AE58: =-AE72 -> 0 | AF58: =-AF72 -> 0 | AG58: =-AG72 -> 0 | ... AM58: =-AM72 -> 0 | AN58: =-AN72-AN93 -> 0 | AO58: =SUM(H58:AN58) -> 6550000 | AP58: =+AO58/SF -> 349.25882 | AR58: Welltower Total Interest | AS58: =1-AS57 -> 0.965 | AU58: =AU57+1 -> 4 | BA58: =BA36+(BA44*$AS$48)+BA35+(BA39*$AS$48) -> 12266555 | BB58: =BA$36+(BA$44*$AS$48) -> 683422.6 | BC58: =BB58 -> 683422.6 | BD58: =BC58 -> 683422.6 | BE58: =BD58 -> 683422.6 | BF58: =BE58 -> 683422.6 | BG58: =BF58 -> 683422.6
E59: Financing | H59: =SUM(H54:H58) -> -6550000 | I59: =SUM(I54:I58) -> 24243.55 | J59: =SUM(J54:J58) -> 40712.09 | K59: =SUM(K54:K58) -> 39462 | L59: =SUM(L54:L58) -> 40692.3 | M59: =SUM(M54:M58) -> 34769.583 | N59: =SUM(N54:N58) -> 35928.569 | O59: =SUM(O54:O58) -> 35928.569 | ... AN59: =SUM(AN54:AN58) -> 0 | AO59: =SUM(H59:AN59) -> 1063026.9 | AP59: =+AO59/SF -> 56.682678 | AU59: =AU58+1 -> 5 | BB59: =BB36+(BB44*$AS$48)+BB35+(BB39*$AS$48) -> 12404117 | BC59: =BB$36+(BB$44*$AS$48) -> 696652.19 | BD59: =BC59 -> 696652.19 | BE59: =BD59 -> 696652.19 | BF59: =BE59 -> 696652.19 | BG59: =BF59 -> 696652.19 | BM59: IRR | BN59: =BG53 -> 0.066705669
AR60: Capital Stack | AU60: =AU59+1 -> 6 | BC60: =BC36+(BC44*$AS$48)+BC35+(BC39*$AS$48) -> 12544143 | BD60: =BC$36+(BC$44*$AS$48) -> 710146.37 | BE60: =BD60 -> 710146.37 | BF60: =BE60 -> 710146.37 | BG60: =BF60 -> 710146.37 | BM60: Equity Multiple | BN60: =BN55/-BN56 -> 1.6942809
E61: =+"Leveraged Cash Flow ("&IFERROR(TEXT(F61,"0.00%)"),"0%)") -> Leveraged Cash Flow (8.96%) | F61: =XIRR(H61:AN61,H7:AN7) -> 0.089599493 | H61: =H51-H59 -> -3551440.2 | I61: =ROUNDDOWN(I51-I59,2) -> 3601.61 | J61: =ROUNDDOWN(J51-J59,2) -> 4719.49 | K61: =ROUNDDOWN(K51-K59,2) -> 5969.57 | L61: =ROUNDDOWN(L51-L59,2) -> 4739.27 | M61: =ROUNDDOWN(M51-M59,2) -> 10661.99 | N61: =ROUNDDOWN(N51-N59,2) -> 32071.43 | O61: =ROUNDDOWN(O51-O59,2) -> -35928.56 | P61: =ROUNDDOWN(P51-P59,2) -> 21771.38 | ... AN61: =ROUNDDOWN(AN51-AN59,2) -> 0 | AO61: =SUM(H61:AN61) -> 801032.86 | AP61: =+AO61/SF -> 42.712641 | AR61: Debt | AS61: =AS40*AS41 -> 0.026361111 | AU61: =AU60+1 -> 7 | BD61: =BD36+(BD44*$AS$48)+BD35+(BD39*$AS$48) -> 12686666 | BE61: =BD$36+(BD$44*$AS$48) -> 723910.43 | BF61: =BE61 -> 723910.43 | BG61: =BF61 -> 723910.43
AR62: Equity | AS62: =(1-AS40)*AS54 -> 0.028 | AU62: =AU61+1 -> 8 | BE62: =BE36+(BE44*$AS$48)+BE35+(BE39*$AS$48) -> 12831724 | BF62: =BE$36+(BE$44*$AS$48) -> 737949.78 | BG62: =BF62 -> 737949.78 | BM62: Total Proiect Profit - Year 5
AR63: Total Capital Stack | AS63: =SUM(AS61:AS62) -> 0.054361111 | AU63: =AU62+1 -> 9 | BF63: =BF36+(BF44*$AS$48)+BF35+(BF39*$AS$48) -> 12979355 | BG63: =BF$36+(BF$44*$AS$48) -> 752269.91 | BM63: Aspect Health Inc. Returns | BN63: Amount | BO63: $ PSF
E64: Permanent Financing Schedule | AU64: =AU63+1 -> 10 | BG64: =BG36+(BG44*$AS$48)+BG35+(BG39*$AS$48) -> 13129595 | BM64: Deal Profit | BN64: =BN19-BN17 -> 226866.26 | BO64: =BN64/SF -> 12.096953
H65: =0 -> 0 | I65: =H65+1 -> 1 | J65: =I65+1 -> 2 | K65: =J65+1 -> 3 | L65: =K65+1 -> 4 | M65: =L65+1 -> 5 | N65: =M65+1 -> 6 | O65: =N65+1 -> 7 | P65: =O65+1 -> 8 | ... AN65: =AM65+1 -> 32 | AO65: Total | AP65: PSF | AU65: Year | AV65: =AV7 -> 0 | AW65: =AW7 -> 1 | AY65: =AY7 -> 2 | AZ65: =AZ7 -> 3 | BA65: =BA7 -> 4 | BB65: =BB7 -> 5 | BC65: =BC7 -> 6 | BD65: =BD7 -> 7 | BE65: =BE7 -> 8 | BF65: =BF7 -> 9 | BG65: =BG7 -> 10 | BM65: Developer Profit | BN65: =BJ34 -> 0 | BO65: =BN65/SF -> 0
AR66: Acquisition Cost | AU66: Unlevered IRR | AV66: -- | AW66: =IRR(AW67:AW77) -> 0.028303582 | AY66: =IRR(AY67:AY77) -> 0.053732307 | AZ66: =IRR(AZ67:AZ77) -> 0.059661846 | BA66: =IRR(BA67:BA77) -> 0.062768195 | BB66: =IRR(BB67:BB77) -> 0.064735984 | BC66: =IRR(BC67:BC77) -> 0.066129806 | BD66: =IRR(BD67:BD77) -> 0.067192383 | BE66: =IRR(BE67:BE77) -> 0.068045333 | BF66: =IRR(BF67:BF77) -> 0.068756329 | BG66: =IRR(BG67:BG77) -> 0.069366031 | BM66: Total Profit | BN66: =BN64+BN65 -> 226866.26 | BO66: =BN66/SF -> 12.096953
E67: Month Ending | H67: =H7 -> 45120 | I67: =EOMONTH(J67,-1) -> 45138 | J67: =EOMONTH(K67,-1) -> 45169 | K67: =EOMONTH(L67,-1) -> 45199 | L67: =EOMONTH(M67,-1) -> 45230 | M67: =EOMONTH(N67,-1) -> 45260 | N67: =EOMONTH(O67,-1) -> 45291 | O67: =EOMONTH(P67,-1) -> 45322 | P67: =EOMONTH(Q67,-1) -> 45351 | ... Y67: =EOMONTH(Z67,-1) -> 45626 | Z67: =Z7 -> 45657 | AA67: =AA7 -> 45688 | AB67: =AB7 -> 45716 | AC67: =AC7 -> 45747 | AD67: =AD7 -> 45777 | AE67: =AE7 -> 45808 | AF67: =AF7 -> 45838 | AG67: =AG7 -> 45869 | ... AN67: =AN7 -> 46081 | AR67: All-In Purchase Price | AU67: 0 | AV67: =AW67 -> -11870110 | AW67: =AV17 -> -11870110 | AY67: =AW67 -> -11870110 | AZ67: =AY67 -> -11870110 | BA67: =AZ67 -> -11870110 | BB67: =BA67 -> -11870110 | BC67: =BB67 -> -11870110 | BD67: =BC67 -> -11870110 | BE67: =BD67 -> -11870110 | BF67: =BE67 -> -11870110 | BG67: =BF67 -> -11870110
AR68: Purchase Price | AS68: =SUM(AW12/AS14) -> 11640090 | AU68: =AU67+1 -> 1 | AW68: =AW17+AW29 -> 12206077 | AY68: =AW17 -> 692585.33 | AZ68: =AY68 -> 692585.33 | BA68: =AZ68 -> 692585.33 | BB68: =BA68 -> 692585.33 | BC68: =BB68 -> 692585.33 | BD68: =BC68 -> 692585.33 | BE68: =BD68 -> 692585.33 | BF68: =BE68 -> 692585.33 | BG68: =BF68 -> 692585.33 | BM68: Total Proiect Profit - Year 10
E69: Construction Loan | AR69: JV Closing Costs | AS69: =AS68*AS25 -> 58200.448 | AU69: =AU68+1 -> 2 | AY69: =AY17+AY29 -> 12450198 | AZ69: =AY17 -> 706437.04 | BA69: =AZ69 -> 706437.04 | BB69: =BA69 -> 706437.04 | BC69: =BB69 -> 706437.04 | BD69: =BC69 -> 706437.04 | BE69: =BD69 -> 706437.04 | BF69: =BE69 -> 706437.04 | BG69: =BF69 -> 706437.04 | BM69: Aspect Health Inc. Returns | BN69: Amount | BO69: $ PSF
E70: Beginning Balance | H70: 0 | I70: =H74 -> 6550000 | J70: =I74 -> 6550000 | K70: =J74 -> 6550000 | L70: =K74 -> 6550000 | M70: =L74 -> 6550000 | N70: =M74 -> 6550000 | O70: =N74 -> 6550000 | P70: =O74 -> 6550000 | ... AN70: =AM74 -> 0 | AR70: Nemark Venture Transaction Fee | AS70: =AS71*AS58*AS24 -> 171819.84 | AU70: =AU69+1 -> 3 | AZ70: =AZ17+AZ29 -> 12597688 | BA70: =AZ17 -> 720565.78 | BB70: =BA70 -> 720565.78 | BC70: =BB70 -> 720565.78 | BD70: =BC70 -> 720565.78 | BE70: =BD70 -> 720565.78 | BF70: =BE70 -> 720565.78 | BG70: =BF70 -> 720565.78 | BM70: Deal Profit | BN70: =BN48-BN46 -> 535961.77 | BO70: =BN70/SF -> 28.578531
E71: Loan Funding | H71: =H74-H70 -> 6550000 | I71: =I74-I70 -> 0 | J71: =J74-J70 -> 0 | K71: =K74-K70 -> 0 | L71: =L74-L70 -> 0 | M71: =M74-M70 -> 0 | N71: =N74-N70 -> 0 | O71: =O74-O70 -> 0 | ... AK71: =AK74-AK70 -> 0 | AL71: 0 | AM71: =AM74-AM70 -> 0 | AN71: 0 | AO71: =SUM(H71:AN71) -> 6550000 | AP71: =+AO71/SF -> 349.25882 | AR71: Total Acquisition Cost | AS71: =SUM(AS68:AS70) -> 11870110 | AU71: =AU70+1 -> 4 | BA71: =BA17+BA29 -> 12747838 | BB71: =BA17 -> 734977.09 | BC71: =BB71 -> 734977.09 | BD71: =BC71 -> 734977.09 | BE71: =BD71 -> 734977.09 | BF71: =BE71 -> 734977.09 | BG71: =BF71 -> 734977.09 | BM71: Developer Profit | BN71: =BJ34 -> 0 | BO71: =BN71/SF -> 0
E72: Loan Repayment | H72: 0 | I72: 0 | J72: 0 | K72: 0 | L72: 0 | M72: 0 | N72: 0 | O72: 0 | P72: 0 | Q72: 0 | R72: 0 | S72: 0 | T72: 0 | U72: 0 | V72: 0 | W72: 0 | X72: 0 | Y72: 0 | Z72: 0 | AA72: 0 | AB72: 0 | AC72: 0 | AD72: 0 | AE72: 0 | AF72: 0 | AG72: 0 | AH72: 0 | AI72: 0 | AJ72: 0 | AK72: 0 | AL72: =-(AL70+AL71) -> -6550000 | AM72: 0 | AN72: 0 | AO72: =SUM(H72:AN72) -> -6550000 | AP72: =-+AO72/SF -> 349.25882 | AU72: =AU71+1 -> 5 | BB72: =BB17+BB29 -> 12900685 | BC72: =BB17 -> 749676.64 | BD72: =BC72 -> 749676.64 | BE72: =BD72 -> 749676.64 | BF72: =BE72 -> 749676.64 | BG72: =BF72 -> 749676.64 | BM72: Total Profit | BN72: =BN70+BN71 -> 535961.77 | BO72: =BN72/SF -> 28.578531
E73: Additional Equity Contribution | H73: 0 | I73: 0 | J73: 0 | K73: 0 | L73: 0 | M73: 0 | N73: 0 | O73: 0 | P73: 0 | Q73: 0 | R73: 0 | S73: 0 | T73: 0 | U73: 0 | V73: 0 | W73: 0 | X73: 0 | Y73: 0 | Z73: =-Z44 -> 0 | AA73: =-AA44 -> 0 | AB73: =-AB44 -> 0 | AC73: 0 | AD73: 0 | AE73: 0 | AF73: 0 | AG73: 0 | AH73: 0 | AI73: 0 | AJ73: 0 | AK73: 0 | AL73: 0 | AM73: 0 | AN73: 0 | AR73: Exit Year Sale Assumptions | AU73: =AU72+1 -> 6 | BC73: =BC17+BC29 -> 13056269 | BD73: =BC17 -> 764670.17 | BE73: =BD73 -> 764670.17 | BF73: =BE73 -> 764670.17 | BG73: =BF73 -> 764670.17
E74: Ending Balance | H74: =IF(SUM($H$44:H44)<$C$16,0,SUM($H$44:H44)-$C$16)+SUM($H$73:H73) -> 6550000 | I74: =H74 -> 6550000 | J74: =I74 -> 6550000 | K74: =J74 -> 6550000 | L74: =K74 -> 6550000 | M74: =L74 -> 6550000 | N74: =M74 -> 6550000 | O74: =N74 -> 6550000 | P74: =O74 -> 6550000 | ... AK74: =AJ74 -> 6550000 | AL74: =SUM(AL70:AL72) -> 0 | AM74: 0 | AN74: 0 | AR74: December 2025 Exit | AU74: =AU73+1 -> 7 | BD74: =BD17+BD29 -> 13214629 | BE74: =BD17 -> 779963.57 | BF74: =BE74 -> 779963.57 | BG74: =BF74 -> 779963.57
AR75: Year 1 Forward NOI (January 2026 - December 2026) | AS75: =AW12 -> 692585.33 | AU75: =AU74+1 -> 8 | BE75: =BE17+BE29 -> 13375805 | BF75: =BE17 -> 795562.84 | BG75: =BF75 -> 795562.84
E76: Usage Rate | I76: =I70/$C$13 -> 1 | J76: =J70/$C$13 -> 1 | K76: =K70/$C$13 -> 1 | L76: =L70/$C$13 -> 1 | M76: =M70/$C$13 -> 1 | N76: =N70/$C$13 -> 1 | O76: =O70/$C$13 -> 1 | P76: =P70/$C$13 -> 1 | ... AN76: =AN70/$C$13 -> 0 | AR76: Exit Cap Rate | AS76: =AS14 -> 0.0595 | AU76: =AU75+1 -> 9 | BF76: =BF17+BF29 -> 13539838 | BG76: =BF17 -> 811474.1
E77: Effective Usage Rate | H77: =AVERAGE(I76:AN76) -> 0.9375 | AR77: Gross Sale Price | AS77: =AS68 -> 11640090 | AU77: =AU76+1 -> 10 | BG77: =BG17+BG29 -> 13706771
AR78: Cost of Sale | AU78: Year | AV78: =AV65 -> 0 | AW78: =AW65 -> 1 | AY78: =AY65 -> 2 | AZ78: =AZ65 -> 3 | BA78: =BA65 -> 4 | BB78: =BB65 -> 5 | BC78: =BC65 -> 6 | BD78: =BD65 -> 7 | BE78: =BE65 -> 8 | BF78: =BF65 -> 9 | BG78: =BG65 -> 10
E79: SOFR Fixed Rate | H79: =SUMPRODUCT(I81:AN81,I83:AN83)/SUM(I83:AN83) -> 0.065005865 | I79: 0.0536 | J79: 0.0543 | K79: 0.0544 | L79: 0.0545 | M79: ='Offering Memorandum'!BN4-C10 -> 0.0411 | N79: =M79 -> 0.0411 | O79: =N79 -> 0.0411 | P79: =O79 -> 0.0411 | Q79: =P79 -> 0.0411 | R79: =Q79 -> 0.0411 | S79: =R79 -> 0.0411 | T79: =S79 -> 0.0411 | U79: =T79 -> 0.0411 | ... AN79: =AM79 -> 0.0411 | AR79: =AR27 -> Connecticut State & Municipal Transfer Tax | AS79: =$AS$77*AS27 -> 174601.34 | AU79: Levered IRR | AV79: -- | AW79: =IRR(AW80:AW90) -> 0.0030499177 | AY79: =IRR(AY80:AY90) -> 0.075843861 | AZ79: =IRR(AZ80:AZ90) -> 0.092559787 | BA79: =IRR(BA80:BA90) -> 0.1009422 | BB79: =IRR(BB80:BB90) -> 0.10594725 | BC79: =IRR(BC80:BC90) -> 0.10925328 | BD79: =IRR(BD80:BD90) -> 0.11158595 | BE79: =IRR(BE80:BE90) -> 0.11331011 | BF79: =IRR(BF80:BF90) -> 0.1146292 | BG79: =IRR(BG80:BG90) -> 0.11579856
E80: Lender Base Rate | I80: ='Offering Memorandum'!BG4 -> 0.019 | J80: =I80 -> 0.019 | K80: =J80 -> 0.019 | L80: =K80 -> 0.019 | M80: =C10 -> 0.0226 | N80: =M80 -> 0.0226 | O80: =N80 -> 0.0226 | P80: =O80 -> 0.0226 | Q80: =P80 -> 0.0226 | R80: =Q80 -> 0.0226 | S80: =R80 -> 0.0226 | T80: =S80 -> 0.0226 | U80: =T80 -> 0.0226 | ... AN80: =AM80 -> 0.0226 | AR80: =AR28 -> Broker (Outside) Fee | AS80: =$AS$77*AS28 -> 174601.34 | AU80: 0 | AV80: =AW80 -> -4154538.5 | AW80: =AV44 -> -4154538.5 | AY80: =AW80 -> -4154538.5 | AZ80: =AY80 -> -4154538.5 | BA80: =AZ80 -> -4154538.5 | BB80: =BA80 -> -4154538.5 | BC80: =BB80 -> -4154538.5 | BD80: =BC80 -> -4154538.5 | BE80: =BD80 -> -4154538.5 | BF80: =BE80 -> -4154538.5 | BG80: =BF80 -> -4154538.5
E81: Total Interest Rate | I81: =I79+I80 -> 0.0726 | J81: =J79+J80 -> 0.0733 | K81: =K79+K80 -> 0.0734 | L81: =L79+L80 -> 0.0735 | M81: =M79+M80 -> 0.0637 | N81: =N79+N80 -> 0.0637 | O81: =O79+O80 -> 0.0637 | P81: =P79+P80 -> 0.0637 | ... AN81: =AN79+AN80 -> 0.0637 | AR81: =AR29 -> Aspect Health (Inside) Fee | AS81: =$AS$77*AS29 -> 232801.79 | AU81: =AU80+1 -> 1 | AW81: =AW39+AW44 -> 4167209.5 | AY81: =AW44 -> 369289.7 | AZ81: =AY81 -> 369289.7 | BA81: =AZ81 -> 369289.7 | BB81: =BA81 -> 369289.7 | BC81: =BB81 -> 369289.7 | BD81: =BC81 -> 369289.7 | BE81: =BD81 -> 369289.7 | BF81: =BE81 -> 369289.7 | BG81: =BF81 -> 369289.7
AR82: =AR30 -> Accrued Asset Management Fees | AS82: =AS30 -> 42919.789 | AU82: =AU81+1 -> 2 | AY82: =AY39+AY44 -> 4411331 | AZ82: =AY44 -> 383141.41 | BA82: =AZ82 -> 383141.41 | BB82: =BA82 -> 383141.41 | BC82: =BB82 -> 383141.41 | BD82: =BC82 -> 383141.41 | BE82: =BD82 -> 383141.41 | BF82: =BE82 -> 383141.41 | BG82: =BF82 -> 383141.41
E83: Interest Payment | I83: 24243.55 | J83: 40712.09 | K83: 39462 | L83: 40692.3 | M83: =(M81*(_xlfn.DAYS(M67,L67)/360))*M70 -> 34769.583 | N83: =(N81*(_xlfn.DAYS(N67,M67)/360))*N70 -> 35928.569 | O83: =(O81*(_xlfn.DAYS(O67,N67)/360))*O70 -> 35928.569 | P83: =(P81*(_xlfn.DAYS(P67,O67)/360))*P70 -> 33610.597 | Q83: =(Q81*(_xlfn.DAYS(Q67,P67)/360))*Q70 -> 35928.569 | R83: =(R81*(_xlfn.DAYS(R67,Q67)/360))*R70 -> 34769.583 | S83: =(S81*(_xlfn.DAYS(S67,R67)/360))*S70 -> 35928.569 | T83: =(T81*(_xlfn.DAYS(T67,S67)/360))*T70 -> 34769.583 | ... AN83: =(AN81*(_xlfn.DAYS(AN67,AM67)/360))*AN70 -> 0 | AO83: =SUM(H83:AN83) -> 1063026.9 | AP83: =+AO83/SF -> 56.682678 | AR83: =AR31 -> Swap Breakage Fees - Permanent Loan | AS83: =AS31 -> 28807.114 | AU83: =AU82+1 -> 3 | AZ83: =AZ39+AZ44 -> 4558821.1 | BA83: =AZ44 -> 397270.15 | BB83: =BA83 -> 397270.15 | BC83: =BB83 -> 397270.15 | BD83: =BC83 -> 397270.15 | BE83: =BD83 -> 397270.15 | BF83: =BE83 -> 397270.15 | BG83: =BF83 -> 397270.15
AR84: =AR32 -> Outstanding Rent/TIA Obligations | AS84: =AS32 -> 179865.22 | AU84: =AU83+1 -> 4 | BA84: =BA39+BA44 -> 4708970.9 | BB84: =BA44 -> 411681.46 | BC84: =BB84 -> 411681.46 | BD84: =BC84 -> 411681.46 | BE84: =BD84 -> 411681.46 | BF84: =BE84 -> 411681.46 | BG84: =BF84 -> 411681.46
E85: Construction Financing Schedule | AR85: Net Sale Price | AS85: =AS77-SUM(AS78:AS84) -> 10806493 | AU85: =AU84+1 -> 5 | BB85: =BB39+BB44 -> 4861818.4 | BC85: =BB44 -> 426381 | BD85: =BC85 -> 426381 | BE85: =BD85 -> 426381 | BF85: =BE85 -> 426381 | BG85: =BF85 -> 426381
H86: =0 -> 0 | I86: =H86+1 -> 1 | J86: =I86+1 -> 2 | K86: =J86+1 -> 3 | L86: =K86+1 -> 4 | M86: =L86+1 -> 5 | N86: =M86+1 -> 6 | O86: =N86+1 -> 7 | P86: =O86+1 -> 8 | ... AN86: =AM86+1 -> 32 | AO86: Total | AP86: PSF | AR86: Repayment of Loan | AS86: =AL58+AL54 -> 6585928.6 | AU86: =AU85+1 -> 6 | BC86: =BC39+BC44 -> 5017402.1 | BD86: =BC44 -> 441374.54 | BE86: =BD86 -> 441374.54 | BF86: =BE86 -> 441374.54 | BG86: =BF86 -> 441374.54
AR87: Return of Capital | AS87: =AL115 -> 3845210.2 | AU87: =AU86+1 -> 7 | BD87: =BD39+BD44 -> 5175761.7 | BE87: =BD44 -> 456667.94 | BF87: =BE87 -> 456667.94 | BG87: =BF87 -> 456667.94
E88: Month Ending | H88: =H67 -> 45120 | I88: =I67 -> 45138 | J88: =J67 -> 45169 | K88: =K67 -> 45199 | L88: =L67 -> 45230 | M88: =M67 -> 45260 | N88: =N67 -> 45291 | O88: =O67 -> 45322 | ... AN88: =AN67 -> 46081 | AR88: Payment of Doctors 0.00% Profit Interest | AS88: =AL123 -> 0 | AU88: =AU87+1 -> 8 | BE88: =BE39+BE44 -> 5336937.5 | BF88: =BE44 -> 472267.21 | BG88: =BF88 -> 472267.21
AR89: Preferred Return | AS89: =AL132 -> 375354.2 | AU89: =AU88+1 -> 9 | BF89: =BF39+BF44 -> 5500970.9 | BG89: =BF44 -> 488178.47
E90: Construction Loan | AR90: Cash Remaining to Distribute | AS90: =AS85-AS86-AS87-AS88-AS89 -> 0.0057739187 | AU90: =AU89+1 -> 10 | BG90: =BG39+BG42 -> 5678290.6
E91: Beginning Balance | H91: 0 | I91: =H95 -> 0 | J91: =I95 -> 0 | K91: =J95 -> 0 | L91: =K95 -> 0 | M91: =L95 -> 0 | N91: =M95 -> 0 | O91: =N95 -> 0 | P91: =O95 -> 0 | ... AN91: =AM95 -> 0 | AR91: Equity Kicker (20.00%) to Preferred Investors | AS91: =AL139 -> 0
E92: Loan Funding | H92: =H95-H91 -> 0 | I92: =I95-I91 -> 0 | J92: =J95-J91 -> 0 | K92: =K95-K91 -> 0 | L92: 0 | M92: 0 | N92: 0 | O92: =O95-O91 -> 0 | P92: =P95-P91 -> 0 | Q92: =Q95-Q91 -> 0 | R92: =R95-R91 -> 0 | S92: =S95-S91 -> 0 | T92: =T95-T91 -> 0 | U92: =U95-U91 -> 0 | V92: =V95-V91 -> 0 | ... AM92: =AM95-AM91 -> 0 | AN92: 0 | AO92: =SUM(H92:AN92) -> 0 | AP92: =+AO92/SF -> 0 | AR92: Cash Flow to House | AS92: =AS90-AS91 -> 0.0057739187 | AU92: CASH FLOW
E93: Loan Repayment | H93: 0 | I93: 0 | J93: 0 | K93: 0 | L93: 0 | M93: 0 | N93: 0 | O93: 0 | P93: 0 | Q93: 0 | R93: 0 | S93: 0 | T93: 0 | U93: 0 | V93: 0 | W93: 0 | X93: 0 | Y93: 0 | Z93: 0 | AA93: 0 | AB93: 0 | AC93: 0 | AD93: 0 | AE93: 0 | AF93: 0 | AG93: 0 | AH93: 0 | AI93: 0 | AJ93: 0 | AK93: 0 | AL93: 0 | AM93: 0 | AN93: =-(AN91+AN92) -> 0 | AO93: =SUM(H93:AN93) -> 0 | AP93: =-+AO93/SF -> 0 | AU93: Aspect GP Property Returns - Year 10
E94: Additional Equity Contribution | H94: 0 | I94: 0 | J94: 0 | K94: 0 | L94: 0 | M94: 0 | N94: 0 | O94: 0 | P94: 0 | Q94: 0 | R94: 0 | S94: 0 | T94: 0 | U94: 0 | V94: 0 | W94: 0 | X94: 0 | Y94: 0 | Z94: =Z73 -> 0 | AA94: =AA73 -> 0 | AB94: =AB73 -> 0 | AC94: 0 | AD94: 0 | AE94: 0 | AF94: 0 | AG94: 0 | AH94: 0 | AI94: 0 | AJ94: 0 | AK94: 0 | AL94: 0 | AM94: 0 | AN94: 0
E95: Ending Balance | H95: 0 | I95: 0 | J95: 0 | K95: 0 | L95: 0 | M95: 0 | N95: 0 | O95: 0 | P95: 0 | Q95: 0 | R95: 0 | S95: 0 | T95: 0 | U95: 0 | V95: 0 | W95: 0 | X95: 0 | Y95: 0 | Z95: 0 | AA95: 0 | AB95: 0 | AC95: 0 | AD95: 0 | AE95: 0 | AF95: 0 | AG95: 0 | AH95: 0 | AI95: 0 | AJ95: 0 | AK95: 0 | AL95: 0 | AM95: 0 | AN95: 0 | AV95: =AV78 -> 0 | AW95: =AW78 -> 1 | AY95: =AY78 -> 2 | AZ95: =AZ78 -> 3 | BA95: =BA78 -> 4 | BB95: =BB78 -> 5 | BC95: =BC78 -> 6 | BD95: =BD78 -> 7 | BE95: =BE78 -> 8 | BF95: =BF78 -> 9 | BG95: =BG78 -> 10
AU96: Year Ending | AV96: =AV8 -> 46022 | AW96: =EOMONTH(AV96,12) -> 46387 | AY96: =EOMONTH(AW96,12) -> 46752 | AZ96: =EOMONTH(AY96,12) -> 47118 | BA96: =EOMONTH(AZ96,12) -> 47483 | BB96: =EOMONTH(BA96,12) -> 47848 | BC96: =EOMONTH(BB96,12) -> 48213 | BD96: =EOMONTH(BC96,12) -> 48579 | BE96: =EOMONTH(BD96,12) -> 48944 | BF96: =EOMONTH(BE96,12) -> 49309 | BG96: =EOMONTH(BF96,12) -> 49674
E97: Usage Rate | I97: =I91/$C$13 -> 0 | J97: =J91/$C$13 -> 0 | K97: =K91/$C$13 -> 0 | L97: =L91/$C$13 -> 0 | M97: =M91/$C$13 -> 0 | N97: =N91/$C$13 -> 0 | O97: =O91/$C$13 -> 0 | P97: =P91/$C$13 -> 0 | ... AN97: =AN91/$C$13 -> 0
E98: Effective Usage Rate | H98: =AVERAGE(I97:AN97) -> 0 | AU98: Levered Cash Flow | AV98: ='JV Waterfall'!F40 -> -415453.85 | AW98: ='JV Waterfall'!G36 -> 36928.97 | AY98: ='JV Waterfall'!H36 -> 38314.141 | AZ98: ='JV Waterfall'!I36 -> 39727.015 | BA98: ='JV Waterfall'!J36 -> 41168.146 | BB98: ='JV Waterfall'!K36 -> 42638.1 | BC98: ='JV Waterfall'!L36 -> 44137.454 | BD98: ='JV Waterfall'!M36 -> 45666.794 | BE98: ='JV Waterfall'!N36 -> 47226.721 | BF98: ='JV Waterfall'!O36 -> 48817.847 | BG98: ='JV Waterfall'!P36 -> 566790.43
AU99: Asset Management Fees | AW99: ='JV Waterfall'!G37 -> 10386.346 | AY99: ='JV Waterfall'!H37 -> 10386.346 | AZ99: ='JV Waterfall'!I37 -> 10386.346 | BA99: ='JV Waterfall'!J37 -> 10386.346 | BB99: ='JV Waterfall'!K37 -> 10386.346 | BC99: ='JV Waterfall'!L37 -> 10386.346 | BD99: ='JV Waterfall'!M37 -> 10386.346 | BE99: ='JV Waterfall'!N37 -> 10386.346 | BF99: ='JV Waterfall'!O37 -> 10386.346 | BG99: ='JV Waterfall'!P37 -> 10386.346
E100: SOFR Floating Rate | H100: =SUMPRODUCT(I102:AN102,I104:AN104)/SUM(I104:AN104) -> #DIV/0! | I100: =I79 -> 0.0536 | J100: =J79 -> 0.0543 | K100: =K79 -> 0.0544 | L100: =L79 -> 0.0545 | M100: =M79 -> 0.0411 | N100: =N79 -> 0.0411 | O100: =O79 -> 0.0411 | P100: =P79 -> 0.0411 | ... AN100: =AN79 -> 0.0411 | AU100: Aspect GP Returns | AV100: =AV98+AV99 -> -415453.85 | AW100: =AW98+AW99 -> 47315.316 | AY100: =AY98+AY99 -> 48700.487 | AZ100: =AZ98+AZ99 -> 50113.361 | BA100: =BA98+BA99 -> 51554.492 | BB100: =BB98+BB99 -> 53024.447 | BC100: =BC98+BC99 -> 54523.8 | BD100: =BD98+BD99 -> 56053.14 | BE100: =BE98+BE99 -> 57613.067 | BF100: =BF98+BF99 -> 59204.193 | BG100: =BG98+BG99 -> 577176.77
E101: Lender Base Rate | I101: =I80 -> 0.019 | J101: =I101 -> 0.019 | K101: =J101 -> 0.019 | L101: =K101 -> 0.019 | M101: =L101 -> 0.019 | N101: =M101 -> 0.019 | O101: =N101 -> 0.019 | P101: =O101 -> 0.019 | Q101: =P101 -> 0.019 | ... AN101: =AM101 -> 0.019
E102: Total Interest Rate | I102: =I100+I101 -> 0.0726 | J102: =J100+J101 -> 0.0733 | K102: =K100+K101 -> 0.0734 | L102: =L100+L101 -> 0.0735 | M102: =M100+M101 -> 0.0601 | N102: =N100+N101 -> 0.0601 | O102: =O100+O101 -> 0.0601 | P102: =P100+P101 -> 0.0601 | ... AN102: =AN100+AN101 -> 0.0601 | AU102: Levered IRR | BG102: =IRR(AV100:BG100) -> 0.13861658
AU103: Levered Equity Multiple | BG103: =SUM(AW98:BG98)/-AV98 -> 2.2900633
...

Sheet JV Waterfall
B2: ASPECT HEALTH, INC. PROPETY RETURNS - 10 YEAR | R2: ASPECT HEALTH, INC. PROPETY RETURNS - 5 YEAR
B4: Promote Hurdle Method | D4: IRR | R4: Promote Hurdle Method | T4: IRR
B5: Return of Capital | D5: =IF(H14<Equity_Share_GP,"LP 1st","Pari Passu") -> Pari Passu | E5: Yes | R5: Return of Capital | T5: =IF(X14<Equity_Share_GP,"LP 1st","Pari Passu") -> Pari Passu | U5: Yes
B7: Equity Contributions | C7: % | D7: Amount | R7: Equity Contributions | S7: % | T7: Amount
B8: General Partner (GP) | C8: ='Property CF'!AS47 -> 0.1 | D8: =Equity_Share_GP*Total_Equity -> 415453.85 | R8: General Partner (GP) | S8: =Equity_Share_GP -> 0.1 | T8: =Equity_Share_GP*Total_Equity -> 415453.85
B9: Limited Partner (LP) | C9: ='Property CF'!AS48 -> 0.9 | D9: =Total_Equity*Equity_Share_LP -> 3739084.6 | R9: Limited Partner (LP) | S9: =Equity_Share_LP -> 0.9 | T9: =Total_Equity*Equity_Share_LP -> 3739084.6
B10: Total Equity | D10: =-SUMIF(F49:P49,"<0") -> 4154538.5 | R10: Total Equity | T10: =-SUMIF(V49:AA49,"<0") -> 4154538.5
B12: Hurdle Rate Method Used: | C12: =IF(D4="IRR","IRR") -> IRR | F12: Promote Structure Incentive Breakdown | H12: Distribution as % | R12: Hurdle Rate Method Used: | S12: =IF(T4="IRR","IRR") -> IRR | V12: Promote Structure Incentive Breakdown | X12: Distribution as %
B13: =IF(D4="Equity Multiple","Partnership Distribution Assumptions (Equity Multiple Hurdles)",IF(D4="IRR","Partnership Distribution Assumptions (IRR Hurdles)","Partnership Distribution Assumptions (Max of IRR or Emx Hurdles)")) -> Partnership Distribution Assumptions (IRR Hurdles) | H13: GP % | I13: LP % | R13: =IF(T4="Equity Multiple","Partnership Distribution Assumptions (Equity Multiple Hurdles)",IF(T4="IRR","Partnership Distribution Assumptions (IRR Hurdles)","Partnership Distribution Assumptions (Max of IRR or Emx Hurdles)")) -> Partnership Distribution Assumptions (IRR Hurdles) | X13: GP % | Y13: LP %
B14: Tier 1 (Pref + Return of Capital) | C14: Equity Multiple | D14: IRR | E14: =IF($D$4="Equity Multiple",C15,D15) -> 0 | F14: GP Promote | H14: =Equity_Share_GP -> 0.1 | I14: =1-H14 -> 0.9 | R14: Tier 1 (Pref + Return of Capital) | S14: Equity Multiple | T14: IRR | U14: =IF($T$4="Equity Multiple",S15,T15) -> 0 | V14: GP Promote | X14: =Equity_Share_GP -> 0.1 | Y14: =1-X14 -> 0.9
B15: Tier 2 (Promote) | C15: 2 | D15: 0 | E15: =IF($D$4="Equity Multiple",C16,D16) -> 0 | F15: 0 | H15: =H14+F15 -> 0.1 | I15: =1-H15 -> 0.9 | R15: Tier 2 (Promote) | S15: 2 | T15: 0 | U15: =IF($T$4="Equity Multiple",S16,T16) -> 0 | V15: 0 | X15: =X14+V15 -> 0.1 | Y15: =1-X15 -> 0.9
B16: Tier 3 (Promote) | C16: 2.5 | D16: 0 | E16: =IF($D$4="Equity Multiple",C17,D17) -> 0 | F16: 0 | H16: =F16+H14 -> 0.1 | I16: =1-H16 -> 0.9 | R16: Tier 3 (Promote) | S16: 2.5 | T16: 0 | U16: =IF($T$4="Equity Multiple",S17,T17) -> 0 | V16: 0 | X16: =V16+X14 -> 0.1 | Y16: =1-X16 -> 0.9
B17: Tier 4 (Promote) | C17: 3 | D17: 0 | F17: 0 | H17: =H14+F17 -> 0.1 | I17: =1-H17 -> 0.9 | R17: Tier 4 (Promote) | S17: 3 | T17: 0 | V17: 0 | X17: =X14+V17 -> 0.1 | Y17: =1-X17 -> 0.9
B19: Summary of Partnership-Level Returns | F19: 0 | G19: =IF(G45="","",F19+1) -> 1 | H19: =IF(H45="","",G19+1) -> 2 | I19: =IF(I45="","",H19+1) -> 3 | J19: =IF(J45="","",I19+1) -> 4 | K19: =IF(K45="","",J19+1) -> 5 | L19: =IF(L45="","",K19+1) -> 6 | M19: =IF(M45="","",L19+1) -> 7 | N19: =IF(N45="","",M19+1) -> 8 | ... P19: =IF(P45="","",O19+1) -> 10 | R19: Summary of Partnership-Level Returns | V19: 0 | W19: =IF(W45="","",V19+1) -> 1 | X19: =IF(X45="","",W19+1) -> 2 | Y19: =IF(Y45="","",X19+1) -> 3 | Z19: =IF(Z45="","",Y19+1) -> 4 | AA19: =IF(AA45="","",Z19+1) -> 5
B20: Limited Partner (LP) Returns | R20: Limited Partner (LP) Returns
C21: Check | S21: Check
B22: Preferred Return | C22: =IF(ROUND(D22,0)=ROUND(SUM(F22:P22),0),"OK","ERROR") -> OK | D22: =(C12="IRR")*(SUM(F94:P94)-D23) -> 4.6566129e-10 | F22: =IF(F19="","",MIN($D22-SUM($E22:E22),F25-F23)) -> 0 | G22: =IF(G19="","",MIN($D22-SUM($E22:F22),G25-G23)) -> 0 | H22: =IF(H19="","",MIN($D22-SUM($E22:G22),H25-H23)) -> 0 | I22: =IF(I19="","",MIN($D22-SUM($E22:H22),I25-I23)) -> 0 | J22: =IF(J19="","",MIN($D22-SUM($E22:I22),J25-J23)) -> 0 | K22: =IF(K19="","",MIN($D22-SUM($E22:J22),K25-K23)) -> 0 | L22: =IF(L19="","",MIN($D22-SUM($E22:K22),L25-L23)) -> 0 | M22: =IF(M19="","",MIN($D22-SUM($E22:L22),M25-M23)) -> 0 | ... P22: =IF(P19="","",MIN($D22-SUM($E22:O22),P25-P23)) -> 4.6566129e-10 | R22: Preferred Return | S22: =IF(ROUND(T22,0)=ROUND(SUM(V22:AA22),0),"OK","ERROR") -> OK | T22: =(S12="IRR")*(SUM(V94:AA94)-T23) -> 4.6566129e-10 | V22: =IF(V19="","",MIN($T22-SUM($U22:U22),V25-V23)) -> 0 | W22: =IF(W19="","",MIN($T22-SUM($U22:V22),W25-W23)) -> 0 | X22: =IF(X19="","",MIN($T22-SUM($U22:W22),X25-X23)) -> 0 | Y22: =IF(Y19="","",MIN($T22-SUM($U22:X22),Y25-Y23)) -> 0 | Z22: =IF(Z19="","",MIN($T22-SUM($U22:Y22),Z25-Z23)) -> 0 | AA22: =IF(AA19="","",MIN($T22-SUM($U22:Z22),AA25-AA23)) -> 4.6566129e-10
B23: Return of Capital | C23: =IF(ROUND(D23,0)=ROUND(SUM(F23:P23),0),"OK","ERROR") -> OK | D23: =MIN(D26,D25) -> 3739084.6 | F23: =IF(F19="","",MIN($D23-SUM($E23:E23),F25)) -> 0 | G23: =IF(G19="","",MIN($D23-SUM($E23:F23),G25)) -> 332360.73 | H23: =IF(H19="","",MIN($D23-SUM($E23:G23),H25)) -> 344827.26 | I23: =IF(I19="","",MIN($D23-SUM($E23:H23),I25)) -> 357543.13 | J23: =IF(J19="","",MIN($D23-SUM($E23:I23),J25)) -> 370513.32 | K23: =IF(K19="","",MIN($D23-SUM($E23:J23),K25)) -> 383742.9 | L23: =IF(L19="","",MIN($D23-SUM($E23:K23),L25)) -> 397237.08 | M23: =IF(M19="","",MIN($D23-SUM($E23:L23),M25)) -> 411001.15 | ... P23: =IF(P19="","",MIN($D23-SUM($E23:O23),P25)) -> 277457.93 | R23: Return of Capital | S23: =IF(ROUND(T23,0)=ROUND(SUM(V23:AA23),0),"OK","ERROR") -> OK | T23: =MIN(T26,T25) -> 3739084.6 | V23: =IF(V19="","",MIN($T23-SUM($U23:U23),V25)) -> 0 | W23: =IF(W19="","",MIN($T23-SUM($U23:V23),W25)) -> 332360.73 | X23: =IF(X19="","",MIN($T23-SUM($U23:W23),X25)) -> 344827.26 | Y23: =IF(Y19="","",MIN($T23-SUM($U23:X23),Y25)) -> 357543.13 | Z23: =IF(Z19="","",MIN($T23-SUM($U23:Y23),Z25)) -> 370513.32 | AA23: =IF(AA19="","",MIN($T23-SUM($U23:Z23),AA25)) -> 2333840.2
B24: Excess Cash Flow | C24: =IF(ROUND(D24,0)=ROUND(SUM(F24:P24),0),"OK","ERROR") -> OK | D24: =D25-D23-D22 -> 4823655.9 | F24: =IF(F19="","",F25-F23-F22) -> 0 | G24: =IF(G19="","",G25-G23-G22) -> 0 | H24: =IF(H19="","",H25-H23-H22) -> 0 | I24: =IF(I19="","",I25-I23-I22) -> 0 | J24: =IF(J19="","",J25-J23-J22) -> 0 | K24: =IF(K19="","",K25-K23-K22) -> 0 | L24: =IF(L19="","",L25-L23-L22) -> 0 | M24: =IF(M19="","",M25-M23-M22) -> 0 | ... P24: =IF(P19="","",P25-P23-P22) -> 4823655.9 | R24: Excess Cash Flow | S24: =IF(ROUND(T24,0)=ROUND(SUM(V24:AA24),0),"OK","ERROR") -> OK | T24: =T25-T23-T22 -> 2041796.4 | V24: =IF(V19="","",V25-V23-V22) -> 0 | W24: =IF(W19="","",W25-W23-W22) -> 0 | X24: =IF(X19="","",X25-X23-X22) -> 0 | Y24: =IF(Y19="","",Y25-Y23-Y22) -> 0 | Z24: =IF(Z19="","",Z25-Z23-Z22) -> 0 | AA24: =IF(AA19="","",AA25-AA23-AA22) -> 2041796.4
B25: Total LP Distributions | D25: =SUM(F25:P25) -> 8562740.5 | F25: =IF(F$19="","",($C$12="IRR")*F65) -> 0 | G25: =IF(G$19="","",($C$12="IRR")*G65) -> 332360.73 | H25: =IF(H$19="","",($C$12="IRR")*H65) -> 344827.26 | I25: =IF(I$19="","",($C$12="IRR")*I65) -> 357543.13 | J25: =IF(J$19="","",($C$12="IRR")*J65) -> 370513.32 | K25: =IF(K$19="","",($C$12="IRR")*K65) -> 383742.9 | L25: =IF(L$19="","",($C$12="IRR")*L65) -> 397237.08 | M25: =IF(M$19="","",($C$12="IRR")*M65) -> 411001.15 | ... P25: =IF(P$19="","",($C$12="IRR")*P65) -> 5101113.8 | R25: Total LP Distributions | T25: =SUM(V25:AA25) -> 5780881 | V25: =IF(V$19="","",($S$12="IRR")*V65) -> 0 | W25: =IF(W$19="","",($S$12="IRR")*W65) -> 332360.73 | X25: =IF(X$19="","",($S$12="IRR")*X65) -> 344827.26 | Y25: =IF(Y$19="","",($S$12="IRR")*Y65) -> 357543.13 | Z25: =IF(Z$19="","",($S$12="IRR")*Z65) -> 370513.32 | AA25: =IF(AA$19="","",($S$12="IRR")*AA65) -> 4375636.5
B26: Total LP Contributions | D26: =SUM(F26:P26) -> 3739084.6 | F26: =F93 -> 3739084.6 | G26: =G93 -> 0 | H26: =H93 -> 0 | I26: =I93 -> 0 | J26: =J93 -> 0 | K26: =K93 -> 0 | L26: =L93 -> 0 | M26: =M93 -> 0 | ... P26: =P93 -> 0 | R26: Total LP Contributions | T26: =SUM(V26:AA26) -> 3739084.6 | V26: =V93 -> 3739084.6 | W26: =W93 -> 0 | X26: =X93 -> 0 | Y26: =Y93 -> 0 | Z26: =Z93 -> 0 | AA26: =AA93 -> 0
B27: Total LP Profit | D27: =D25-D26 -> 4823655.9 | R27: Total LP Profit | T27: =T25-T26 -> 2041796.4
B28: LP IRR | D28: =IRR(F28:P28) -> 0.11566557 | F28: =IF(F19="","",(-F26)+F25) -> -3739084.6 | G28: =IF(G19="","",(-G26)+G25) -> 332360.73 | H28: =IF(H19="","",(-H26)+H25) -> 344827.26 | I28: =IF(I19="","",(-I26)+I25) -> 357543.13 | J28: =IF(J19="","",(-J26)+J25) -> 370513.32 | K28: =IF(K19="","",(-K26)+K25) -> 383742.9 | L28: =IF(L19="","",(-L26)+L25) -> 397237.08 | M28: =IF(M19="","",(-M26)+M25) -> 411001.15 | ... P28: =IF(P19="","",(-P26)+P25) -> 5101113.8 | R28: LP IRR | T28: =IRR(V28:AA28) -> 0.10594725 | V28: =IF(V19="","",(-V26)+V25) -> -3739084.6 | W28: =IF(W19="","",(-W26)+W25) -> 332360.73 | X28: =IF(X19="","",(-X26)+X25) -> 344827.26 | Y28: =IF(Y19="","",(-Y26)+Y25) -> 357543.13 | Z28: =IF(Z19="","",(-Z26)+Z25) -> 370513.32 | AA28: =IF(AA19="","",(-AA26)+AA25) -> 4375636.5
B29: LP Equity Multiple | D29: =D25/D26 -> 2.2900633 | R29: LP Equity Multiple | T29: =T25/T26 -> 1.5460685
B31: GP Returns | R31: GP Returns
B32: Preferred Return | C32: =IF(ROUND(D32,0)=ROUND(SUM(F32:P32),0),"OK","ERROR") -> OK | D32: =(C12="IRR")*(SUM(F102:P102)-D33) -> 0 | F32: =IF(F19="","",MIN($D32-SUM($E32:E32),F36-F33)) -> 0 | G32: =IF(G19="","",MIN($D32-SUM($E32:F32),G36-G33)) -> 0 | H32: =IF(H19="","",MIN($D32-SUM($E32:G32),H36-H33)) -> 0 | I32: =IF(I19="","",MIN($D32-SUM($E32:H32),I36-I33)) -> 0 | J32: =IF(J19="","",MIN($D32-SUM($E32:I32),J36-J33)) -> 0 | K32: =IF(K19="","",MIN($D32-SUM($E32:J32),K36-K33)) -> 0 | L32: =IF(L19="","",MIN($D32-SUM($E32:K32),L36-L33)) -> 0 | M32: =IF(M19="","",MIN($D32-SUM($E32:L32),M36-M33)) -> 0 | ... P32: =IF(P19="","",MIN($D32-SUM($E32:O32),P36-P33)) -> 0 | R32: Preferred Return | S32: =IF(ROUND(T32,0)=ROUND(SUM(V32:AA32),0),"OK","ERROR") -> OK | T32: =(S12="IRR")*(SUM(V102:AA102)-T33) -> 0 | V32: =IF(V19="","",MIN($T32-SUM($U32:U32),V36-V33)) -> 0 | W32: =IF(W19="","",MIN($T32-SUM($U32:V32),W36-W33)) -> 0 | X32: =IF(X19="","",MIN($T32-SUM($U32:W32),X36-X33)) -> 0 | Y32: =IF(Y19="","",MIN($T32-SUM($U32:X32),Y36-Y33)) -> 0 | Z32: =IF(Z19="","",MIN($T32-SUM($U32:Y32),Z36-Z33)) -> 0 | AA32: =IF(AA19="","",MIN($T32-SUM($U32:Z32),AA36-AA33)) -> 0
B33: Return of Capital | C33: =IF(ROUND(D33,0)=ROUND(SUM(F33:P33),0),"OK","ERROR") -> OK | D33: =MIN(D36,D38) -> 415453.85 | F33: =IF(F19="","",MIN($D33-SUM($E33:E33),F36)) -> 0 | G33: =IF(G19="","",MIN($D33-SUM($E33:F33),G36)) -> 36928.97 | H33: =IF(H19="","",MIN($D33-SUM($E33:G33),H36)) -> 38314.141 | I33: =IF(I19="","",MIN($D33-SUM($E33:H33),I36)) -> 39727.015 | J33: =IF(J19="","",MIN($D33-SUM($E33:I33),J36)) -> 41168.146 | K33: =IF(K19="","",MIN($D33-SUM($E33:J33),K36)) -> 42638.1 | L33: =IF(L19="","",MIN($D33-SUM($E33:K33),L36)) -> 44137.454 | M33: =IF(M19="","",MIN($D33-SUM($E33:L33),M36)) -> 45666.794 | ... P33: =IF(P19="","",MIN($D33-SUM($E33:O33),P36)) -> 30828.658 | R33: Return of Capital | S33: =IF(ROUND(T33,0)=ROUND(SUM(V33:AA33),0),"OK","ERROR") -> OK | T33: =MIN(T36,T38) -> 415453.85 | V33: =IF(V19="","",MIN($T33-SUM($U33:U33),V36)) -> 0 | W33: =IF(W19="","",MIN($T33-SUM($U33:V33),W36)) -> 36928.97 | X33: =IF(X19="","",MIN($T33-SUM($U33:W33),X36)) -> 38314.141 | Y33: =IF(Y19="","",MIN($T33-SUM($U33:X33),Y36)) -> 39727.015 | Z33: =IF(Z19="","",MIN($T33-SUM($U33:Y33),Z36)) -> 41168.146 | AA33: =IF(AA19="","",MIN($T33-SUM($U33:Z33),AA36)) -> 259315.57
B34: Promote | C34: =IF(ROUND(D34,0)=ROUND(SUM(F34:P34),0),"OK","ERROR") -> OK | D34: =D36-D33-D35-D32 -> 2.3283064e-10 | F34: =IF(F19="","",F36-F35-F33-F32) -> 0 | G34: =IF(G19="","",G36-G35-G33-G32) -> 0 | H34: =IF(H19="","",H36-H35-H33-H32) -> 0 | I34: =IF(I19="","",I36-I35-I33-I32) -> 0 | J34: =IF(J19="","",J36-J35-J33-J32) -> 0 | K34: =IF(K19="","",K36-K35-K33-K32) -> 0 | L34: =IF(L19="","",L36-L35-L33-L32) -> 0 | M34: =IF(M19="","",M36-M35-M33-M32) -> 0 | ... P34: =IF(P19="","",P36-P35-P33-P32) -> 1.7462298e-10 | R34: Promote | S34: =IF(ROUND(T34,0)=ROUND(SUM(V34:AA34),0),"OK","ERROR") -> OK | T34: =T36-T33-T35-T32 -> -8.7311491e-11 | V34: =IF(V19="","",V36-V35-V33-V32) -> 0 | W34: =IF(W19="","",W36-W35-W33-W32) -> 0 | X34: =IF(X19="","",X36-X35-X33-X32) -> 0 | Y34: =IF(Y19="","",Y36-Y35-Y33-Y32) -> 0 | Z34: =IF(Z19="","",Z36-Z35-Z33-Z32) -> 0 | AA34: =IF(AA19="","",AA36-AA35-AA33-AA32) -> -8.7311491e-11
B35: Excess Cash Flow | C35: =IF(ROUND(D35,0)=ROUND(SUM(F35:P35),0),"OK","ERROR") -> OK | D35: =D24/Equity_Share_LP*Equity_Share_GP -> 535961.77 | F35: =IF(F19="","",F24/Equity_Share_LP*Equity_Share_GP) -> 0 | G35: =IF(G19="","",G24/Equity_Share_LP*Equity_Share_GP) -> 0 | H35: =IF(H19="","",H24/Equity_Share_LP*Equity_Share_GP) -> 0 | I35: =IF(I19="","",I24/Equity_Share_LP*Equity_Share_GP) -> 0 | J35: =IF(J19="","",J24/Equity_Share_LP*Equity_Share_GP) -> 0 | K35: =IF(K19="","",K24/Equity_Share_LP*Equity_Share_GP) -> 0 | L35: =IF(L19="","",L24/Equity_Share_LP*Equity_Share_GP) -> 0 | M35: =IF(M19="","",M24/Equity_Share_LP*Equity_Share_GP) -> 0 | ... P35: =IF(P19="","",P24/Equity_Share_LP*Equity_Share_GP) -> 535961.77 | R35: Excess Cash Flow | S35: =IF(ROUND(T35,0)=ROUND(SUM(V35:AA35),0),"OK","ERROR") -> OK | T35: =T24/Equity_Share_LP*Equity_Share_GP -> 226866.26 | V35: =IF(V19="","",V24/Equity_Share_LP*Equity_Share_GP) -> 0 | W35: =IF(W19="","",W24/Equity_Share_LP*Equity_Share_GP) -> 0 | X35: =IF(X19="","",X24/Equity_Share_LP*Equity_Share_GP) -> 0 | Y35: =IF(Y19="","",Y24/Equity_Share_LP*Equity_Share_GP) -> 0 | Z35: =IF(Z19="","",Z24/Equity_Share_LP*Equity_Share_GP) -> 0 | AA35: =IF(AA19="","",AA24/Equity_Share_LP*Equity_Share_GP) -> 226866.26
B36: Total GP Distributions | D36: =SUM(F36:P36) -> 951415.61 | F36: =IF(F$19="","",($C$12="IRR")*F72) -> 0 | G36: =IF(G$19="","",($C$12="IRR")*G72) -> 36928.97 | H36: =IF(H$19="","",($C$12="IRR")*H72) -> 38314.141 | I36: =IF(I$19="","",($C$12="IRR")*I72) -> 39727.015 | J36: =IF(J$19="","",($C$12="IRR")*J72) -> 41168.146 | K36: =IF(K$19="","",($C$12="IRR")*K72) -> 42638.1 | L36: =IF(L$19="","",($C$12="IRR")*L72) -> 44137.454 | M36: =IF(M$19="","",($C$12="IRR")*M72) -> 45666.794 | ... P36: =IF(P$19="","",($C$12="IRR")*P72) -> 566790.43 | R36: Total GP Distributions | T36: =SUM(V36:AA36) -> 642320.11 | V36: =IF(V$19="","",($S$12="IRR")*V72) -> 0 | W36: =IF(W$19="","",($S$12="IRR")*W72) -> 36928.97 | X36: =IF(X$19="","",($S$12="IRR")*X72) -> 38314.141 | Y36: =IF(Y$19="","",($S$12="IRR")*Y72) -> 39727.015 | Z36: =IF(Z$19="","",($S$12="IRR")*Z72) -> 41168.146 | AA36: =IF(AA$19="","",($S$12="IRR")*AA72) -> 486181.84
B37: Total GP Fees | D37: =SUM(F37:P37) -> 103863.46 | F37: =IF(F19="","",SUM(F46:F47)) -> 0 | G37: =IF(G19="","",SUM(G46:G47)) -> 10386.346 | H37: =IF(H19="","",SUM(H46:H47)) -> 10386.346 | I37: =IF(I19="","",SUM(I46:I47)) -> 10386.346 | J37: =IF(J19="","",SUM(J46:J47)) -> 10386.346 | K37: =IF(K19="","",SUM(K46:K47)) -> 10386.346 | L37: =IF(L19="","",SUM(L46:L47)) -> 10386.346 | M37: =IF(M19="","",SUM(M46:M47)) -> 10386.346 | ... P37: =IF(P19="","",SUM(P46:P47)) -> 10386.346 | R37: Total GP Fees | T37: =SUM(V37:AA37) -> 51931.731 | V37: =IF(V19="","",SUM(V46:V47)) -> 0 | W37: =IF(W19="","",SUM(W46:W47)) -> 10386.346 | X37: =IF(X19="","",SUM(X46:X47)) -> 10386.346 | Y37: =IF(Y19="","",SUM(Y46:Y47)) -> 10386.346 | Z37: =IF(Z19="","",SUM(Z46:Z47)) -> 10386.346 | AA37: =IF(AA19="","",SUM(AA46:AA47)) -> 10386.346
B38: Total GP Contributions | D38: =SUM(F38:P38) -> 415453.85 | F38: =F101 -> 415453.85 | G38: =G101 -> 0 | H38: =H101 -> 0 | I38: =I101 -> 0 | J38: =J101 -> 0 | K38: =K101 -> 0 | L38: =L101 -> 0 | M38: =M101 -> 0 | ... P38: =P101 -> 0 | R38: Total GP Contributions | T38: =SUM(V38:AA38) -> 415453.85 | V38: =V101 -> 415453.85 | W38: =W101 -> 0 | X38: =X101 -> 0 | Y38: =Y101 -> 0 | Z38: =Z101 -> 0 | AA38: =AA101 -> 0
B39: Total GP Profit (Including Fees) | D39: =+D36+D37-D38 -> 639825.23 | R39: Total GP Profit (Including Fees) | T39: =+T36+T37-T38 -> 278797.99
B40: GP IRR | D40: =IFERROR(IRR(F40:P40),"NA") -> 0.13861658 | F40: =IF(F19="","",(-F38)+F36+F37) -> -415453.85 | G40: =IF(G19="","",(-G38)+G36+G37) -> 47315.316 | H40: =IF(H19="","",(-H38)+H36+H37) -> 48700.487 | I40: =IF(I19="","",(-I38)+I36+I37) -> 50113.361 | J40: =IF(J19="","",(-J38)+J36+J37) -> 51554.492 | K40: =IF(K19="","",(-K38)+K36+K37) -> 53024.447 | L40: =IF(L19="","",(-L38)+L36+L37) -> 54523.8 | M40: =IF(M19="","",(-M38)+M36+M37) -> 56053.14 | ... P40: =IF(P19="","",(-P38)+P36+P37) -> 577176.77 | R40: GP IRR | T40: =IFERROR(IRR(V40:AA40),"NA") -> 0.13028361 | V40: =IF(V19="","",(-V38)+V36+V37) -> -415453.85 | W40: =IF(W19="","",(-W38)+W36+W37) -> 47315.316 | X40: =IF(X19="","",(-X38)+X36+X37) -> 48700.487 | Y40: =IF(Y19="","",(-Y38)+Y36+Y37) -> 50113.361 | Z40: =IF(Z19="","",(-Z38)+Z36+Z37) -> 51554.492 | AA40: =IF(AA19="","",(-AA38)+AA36+AA37) -> 496568.18
B41: GP Equity Multiple | D41: =IFERROR(D36/D38,"NA") -> 2.2900633 | R41: GP Equity Multiple | T41: =IFERROR(T36/T38,"NA") -> 1.5460685
B43: Property-Level Cash and GP Fees | F43: Year 0 | G43: =G$19 -> 1 | H43: =H$19 -> 2 | I43: =I$19 -> 3 | J43: =J$19 -> 4 | K43: =K$19 -> 5 | L43: =L$19 -> 6 | M43: =M$19 -> 7 | N43: =N$19 -> 8 | ... P43: =P$19 -> 10 | R43: Property-Level Cash and GP Fees | V43: Year 0 | W43: =W$19 -> 1 | X43: =X$19 -> 2 | Y43: =Y$19 -> 3 | Z43: =Z$19 -> 4 | AA43: =AA$19 -> 5
E44: Year Ending | F44: ='Property CF'!AV8 -> 46022 | G44: =IF(G43="","",EOMONTH(F44,12)) -> 46387 | H44: =IF(H43="","",EOMONTH(G44,12)) -> 46752 | I44: =IF(I43="","",EOMONTH(H44,12)) -> 47118 | J44: =IF(J43="","",EOMONTH(I44,12)) -> 47483 | K44: =IF(K43="","",EOMONTH(J44,12)) -> 47848 | L44: =IF(L43="","",EOMONTH(K44,12)) -> 48213 | M44: =IF(M43="","",EOMONTH(L44,12)) -> 48579 | N44: =IF(N43="","",EOMONTH(M44,12)) -> 48944 | ... P44: =IF(P43="","",EOMONTH(O44,12)) -> 49674 | U44: Year Ending | V44: =F44 -> 46022 | W44: =IF(W43="","",EOMONTH(V44,12)) -> 46387 | X44: =IF(X43="","",EOMONTH(W44,12)) -> 46752 | Y44: =IF(Y43="","",EOMONTH(X44,12)) -> 47118 | Z44: =IF(Z43="","",EOMONTH(Y44,12)) -> 47483 | AA44: =IF(AA43="","",EOMONTH(Z44,12)) -> 47848
B45: Net Property-Level Cash Flow | F45: ='Property CF'!AV44 -> -4154538.5 | G45: ='Property CF'!AW42 -> 379676.05 | H45: ='Property CF'!AY42 -> 393527.75 | I45: ='Property CF'!AZ42 -> 407656.49 | J45: ='Property CF'!BA42 -> 422067.81 | K45: ='Property CF'!BB42 -> 436767.35 | L45: ='Property CF'!BC42 -> 451760.88 | M45: ='Property CF'!BD42 -> 467054.29 | N45: ='Property CF'!BE42 -> 482653.56 | O45: ='Property CF'!BF42 -> 498564.81 | P45: ='Property CF'!BG42+'Property CF'!BG39 -> 5678290.6 | R45: Net Property-Level Cash Flow | V45: ='Property CF'!AV44 -> -4154538.5 | W45: ='Property CF'!AW42 -> 379676.05 | X45: ='Property CF'!AY42 -> 393527.75 | Y45: ='Property CF'!AZ42 -> 407656.49 | Z45: ='Property CF'!BA42 -> 422067.81 | AA45: ='Property CF'!BB39+'Property CF'!BB42 -> 4872204.7
B46: Asset Management Fees | F46: 0 | G46: =-'Property CF'!AW43 -> 10386.346 | H46: =G46 -> 10386.346 | I46: =H46 -> 10386.346 | J46: =I46 -> 10386.346 | K46: =J46 -> 10386.346 | L46: =K46 -> 10386.346 | M46: =L46 -> 10386.346 | N46: =M46 -> 10386.346 | O46: =N46 -> 10386.346 | P46: =O46 -> 10386.346 | R46: Asset Management Fees | V46: ='Property CF'!AV43 -> 0 | W46: =-'Property CF'!AW43 -> 10386.346 | X46: =W46 -> 10386.346 | Y46: =X46 -> 10386.346 | Z46: =Y46 -> 10386.346 | AA46: =Z46 -> 10386.346
B47: Acquisition/Disposition Fees | F47: 0 | G47: 0 | H47: 0 | I47: 0 | J47: 0 | K47: 0 | L47: 0 | M47: 0 | N47: 0 | O47: 0 | P47: 0 | R47: Acquisition/Disposition Fees | V47: 0 | W47: 0 | X47: 0 | Y47: 0 | Z47: 0 | AA47: 0
B49: Adjusted Net Property-Level Cash Flow | F49: =IF(F43="","",F45-F46-F47) -> -4154538.5 | G49: =IF(G43="","",G45-G46-G47) -> 369289.7 | H49: =IF(H43="","",H45-H46-H47) -> 383141.41 | I49: =IF(I43="","",I45-I46-I47) -> 397270.15 | J49: =IF(J43="","",J45-J46-J47) -> 411681.46 | K49: =IF(K43="","",K45-K46-K47) -> 426381 | L49: =IF(L43="","",L45-L46-L47) -> 441374.54 | M49: =IF(M43="","",M45-M46-M47) -> 456667.94 | ... P49: =IF(P43="","",P45-P46-P47) -> 5667904.3 | R49: Adjusted Net Property-Level Cash Flow | V49: =IF(V43="","",V45-V46-V47) -> -4154538.5 | W49: =IF(W43="","",W45-W46-W47) -> 369289.7 | X49: =IF(X43="","",X45-X46-X47) -> 383141.41 | Y49: =IF(Y43="","",Y45-Y46-Y47) -> 397270.15 | Z49: =IF(Z43="","",Z45-Z46-Z47) -> 411681.46 | AA49: =IF(AA43="","",AA45-AA46-AA47) -> 4861818.4
B50: Levered IRR | F50: =IRR(F49:P49) -> 0.11566557 | R50: Levered IRR | V50: =IRR(V49:AA49) -> 0.10594725
B51: Equity Multiple | F51: =SUMIF(F49:P49,">0")/-SUMIF(F49:P49,"<0") -> 2.2900633 | R51: Equity Multiple | V51: =SUMIF(V49:AA49,">0")/-SUMIF(V49:AA49,"<0") -> 1.5460685
B54: PARTNERSHIP LEVEL RETURNS - IRR EQUITY WATERFALL | R54: PARTNERSHIP LEVEL RETURNS - IRR EQUITY WATERFALL
D55: IRR | T55: IRR
F56: Promote Structure Incentive Breakdown | H56: Distribution as % | V56: Promote Structure Incentive Breakdown | X56: Distribution as %
B57: =IF(D55="Equity Multiple","Partnership Distribution Assumptions (Equity Multiple Hurdles)","Partnership Distribution Assumptions (IRR Hurdles)") -> Partnership Distribution Assumptions (IRR Hurdles) | H57: GP % | I57: LP % | J57: Notes | R57: =IF(T55="Equity Multiple","Partnership Distribution Assumptions (Equity Multiple Hurdles)","Partnership Distribution Assumptions (IRR Hurdles)") -> Partnership Distribution Assumptions (IRR Hurdles) | X57: GP % | Y57: LP %
B58: Tier 1 (Pref + Return of Capital) | E58: =D59 -> 0 | F58: GP Promote | H58: =H14 -> 0.1 | I58: =1-H58 -> 0.9 | J58: =IF(I58=Equity_Share_LP,"Pref prorata to LP/GP, then Pro rata return of capital",IF(CU?,"Return of capital and Pref NOT pro rata + GP Catch Up","Return of capital and Pref NOT pro rata")) -> Pref prorata to LP/GP, then Pro rata return of capital | R58: Tier 1 (Pref + Return of Capital) | U58: =T59 -> 0 | V58: GP Promote | X58: =X14 -> 0.1 | Y58: =1-X58 -> 0.9
B59: Tier 2 (Promote) | D59: =D15 -> 0 | E59: =D60 -> 0 | F59: =F15 -> 0 | H59: =H15 -> 0.1 | I59: =1-H59 -> 0.9 | J59: =IF(Equity_Share_GP<>H58,TEXT(I58,"0.0%")&"/"&TEXT(H58,"0.0%")&" to "&(IF(D55="IRR",TEXT(E58,"0.0%"),TEXT(E58,"0.0X")))&", then "&TEXT(I59,"0.0%")&"/"&TEXT(H59,"0.0%")&" to "&(IF(D55="IRR",TEXT(E59,"0.0%"),TEXT(E59,"0.0X"))),"Prorata to LP/GP to "&(IF(D55="IRR",TEXT(E58,"0.0%"),TEXT(E58,"0.0X")))&", then "&TEXT(I59,"0.0%")&"/"&TEXT(H59,"0.0%")&" to "&(IF(D55="IRR",TEXT(E59,"0.0%"),TEXT(E59,"0.0X")))) -> Prorata to LP/GP to 0.0%, then 90.0%/10.0% to 0.0% | R59: Tier 2 (Promote) | T59: =T15 -> 0 | U59: =T60 -> 0 | V59: =V15 -> 0 | X59: =X15 -> 0.1 | Y59: =1-X59 -> 0.9
B60: Tier 3 (Promote) | D60: =D16 -> 0 | E60: =D61 -> 0 | F60: =F16 -> 0 | H60: =H16 -> 0.1 | I60: =1-H60 -> 0.9 | J60: =TEXT(I59,"0.0%")&"/"&TEXT(H59,"0.0%")&" to "&(IF(D55="IRR",TEXT(E59,"0.0%"),TEXT(E59,"0.0X")))&", then "&TEXT(I60,"0.0%")&"/"&TEXT(H60,"0.0%")&" to "&(IF(D55="IRR",TEXT(E60,"0.0%"),TEXT(E60,"0.0X"))) -> 90.0%/10.0% to 0.0%, then 90.0%/10.0% to 0.0% | R60: Tier 3 (Promote) | T60: =T16 -> 0 | U60: =T61 -> 0 | V60: =V16 -> 0 | X60: =X16 -> 0.1 | Y60: =1-X60 -> 0.9
B61: Tier 4 (Promote) | D61: =D17 -> 0 | F61: =F17 -> 0 | H61: =H17 -> 0.1 | I61: =1-H61 -> 0.9 | J61: =TEXT(I60,"0.0%")&"/"&TEXT(H60,"0.0%")&" to "&(IF(D55="IRR",TEXT(E60,"0.0%"),TEXT(E60,"0.0X")))&", then "&TEXT(I61,"0.0%")&"/"&TEXT(H61,"0.0%")&" thereafter" -> 90.0%/10.0% to 0.0%, then 90.0%/10.0% thereafter | R61: Tier 4 (Promote) | T61: =T17 -> 0 | V61: =V17 -> 0 | X61: =X17 -> 0.1 | Y61: =1-X61 -> 0.9
B63: Summary of Partnership-Level Returns | F63: 0 | G63: =IF(G81="","",F63+1) -> 1 | H63: =IF(H81="","",G63+1) -> 2 | I63: =IF(I81="","",H63+1) -> 3 | J63: =IF(J81="","",I63+1) -> 4 | K63: =IF(K81="","",J63+1) -> 5 | L63: =IF(L81="","",K63+1) -> 6 | M63: =IF(M81="","",L63+1) -> 7 | N63: =IF(N81="","",M63+1) -> 8 | ... P63: =IF(P81="","",O63+1) -> 10 | R63: Summary of Partnership-Level Returns | V63: 0 | W63: =IF(W81="","",V63+1) -> 1 | X63: =IF(X81="","",W63+1) -> 2 | Y63: =IF(Y81="","",X63+1) -> 3 | Z63: =IF(Z81="","",Y63+1) -> 4 | AA63: =IF(AA81="","",Z63+1) -> 5
B64: Limited Partner (LP) Returns | R64: Limited Partner (LP) Returns
B65: Total LP Distributions | D65: =SUM(F65:P65) -> 8562740.5 | F65: =IF(F63="","",F97+F119+F134+F141) -> 0 | G65: =IF(G63="","",G97+G119+G134+G141) -> 332360.73 | H65: =IF(H63="","",H97+H119+H134+H141) -> 344827.26 | I65: =IF(I63="","",I97+I119+I134+I141) -> 357543.13 | J65: =IF(J63="","",J97+J119+J134+J141) -> 370513.32 | K65: =IF(K63="","",K97+K119+K134+K141) -> 383742.9 | L65: =IF(L63="","",L97+L119+L134+L141) -> 397237.08 | M65: =IF(M63="","",M97+M119+M134+M141) -> 411001.15 | ... P65: =IF(P63="","",P97+P119+P134+P141) -> 5101113.8 | R65: Total LP Distributions | T65: =SUM(V65:AA65) -> 5780881 | V65: =IF(V63="","",V97+V119+V134+V141) -> 0 | W65: =IF(W63="","",W97+W119+W134+W141) -> 332360.73 | X65: =IF(X63="","",X97+X119+X134+X141) -> 344827.26 | Y65: =IF(Y63="","",Y97+Y119+Y134+Y141) -> 357543.13 | Z65: =IF(Z63="","",Z97+Z119+Z134+Z141) -> 370513.32 | AA65: =IF(AA63="","",AA97+AA119+AA134+AA141) -> 4375636.5
B66: Total LP Contributions | D66: =SUM(F66:P66) -> 3739084.6 | F66: =F93 -> 3739084.6 | G66: =G93 -> 0 | H66: =H93 -> 0 | I66: =I93 -> 0 | J66: =J93 -> 0 | K66: =K93 -> 0 | L66: =L93 -> 0 | M66: =M93 -> 0 | ... P66: =P93 -> 0 | R66: Total LP Contributions | T66: =SUM(V66:AA66) -> 3739084.6 | V66: =V93 -> 3739084.6 | W66: =W93 -> 0 | X66: =X93 -> 0 | Y66: =Y93 -> 0 | Z66: =Z93 -> 0 | AA66: =AA93 -> 0
B67: Total LP Profit | D67: =D65-D66 -> 4823655.9 | R67: Total LP Profit | T67: =T65-T66 -> 2041796.4
B68: LP IRR | D68: =IRR(F68:Q68) -> 0.11566557 | F68: =IF(F63="","",(-F66)+F65) -> -3739084.6 | G68: =IF(G63="","",(-G66)+G65) -> 332360.73 | H68: =IF(H63="","",(-H66)+H65) -> 344827.26 | I68: =IF(I63="","",(-I66)+I65) -> 357543.13 | J68: =IF(J63="","",(-J66)+J65) -> 370513.32 | K68: =IF(K63="","",(-K66)+K65) -> 383742.9 | L68: =IF(L63="","",(-L66)+L65) -> 397237.08 | M68: =IF(M63="","",(-M66)+M65) -> 411001.15 | ... P68: =IF(P63="","",(-P66)+P65) -> 5101113.8 | R68: LP IRR | T68: =IRR(V68:AA68) -> 0.10594725 | V68: =IF(V63="","",(-V66)+V65) -> -3739084.6 | W68: =IF(W63="","",(-W66)+W65) -> 332360.73 | X68: =IF(X63="","",(-X66)+X65) -> 344827.26 | Y68: =IF(Y63="","",(-Y66)+Y65) -> 357543.13 | Z68: =IF(Z63="","",(-Z66)+Z65) -> 370513.32 | AA68: =IF(AA63="","",(-AA66)+AA65) -> 4375636.5
B69: LP Equity Multiple | D69: =D65/D66 -> 2.2900633 | R69: LP Equity Multiple | T69: =T65/T66 -> 1.5460685
B71: GP Returns | R71: GP Returns
B72: Total GP Distributions | D72: =SUM(F72:P72) -> 951415.61 | F72: =IF(F63="","",F102+F120+F135+F142) -> 0 | G72: =IF(G63="","",G102+G120+G135+G142) -> 36928.97 | H72: =IF(H63="","",H102+H120+H135+H142) -> 38314.141 | I72: =IF(I63="","",I102+I120+I135+I142) -> 39727.015 | J72: =IF(J63="","",J102+J120+J135+J142) -> 41168.146 | K72: =IF(K63="","",K102+K120+K135+K142) -> 42638.1 | L72: =IF(L63="","",L102+L120+L135+L142) -> 44137.454 | M72: =IF(M63="","",M102+M120+M135+M142) -> 45666.794 | ... P72: =IF(P63="","",P102+P120+P135+P142) -> 566790.43 | R72: Total GP Distributions | T72: =SUM(V72:AA72) -> 642320.11 | V72: =IF(V63="","",V102+V120+V135+V142) -> 0 | W72: =IF(W63="","",W102+W120+W135+W142) -> 36928.97 | X72: =IF(X63="","",X102+X120+X135+X142) -> 38314.141 | Y72: =IF(Y63="","",Y102+Y120+Y135+Y142) -> 39727.015 | Z72: =IF(Z63="","",Z102+Z120+Z135+Z142) -> 41168.146 | AA72: =IF(AA63="","",AA102+AA120+AA135+AA142) -> 486181.84
B73: Total GP Fees | D73: =SUM(F73:Q73) -> 103863.46 | F73: =IF(F63="","",SUM(F82:F83)) -> 0 | G73: =IF(G63="","",SUM(G82:G83)) -> 10386.346 | H73: =IF(H63="","",SUM(H82:H83)) -> 10386.346 | I73: =IF(I63="","",SUM(I82:I83)) -> 10386.346 | J73: =IF(J63="","",SUM(J82:J83)) -> 10386.346 | K73: =IF(K63="","",SUM(K82:K83)) -> 10386.346 | L73: =IF(L63="","",SUM(L82:L83)) -> 10386.346 | M73: =IF(M63="","",SUM(M82:M83)) -> 10386.346 | ... P73: =IF(P63="","",SUM(P82:P83)) -> 10386.346 | R73: Total GP Fees | T73: =SUM(V73:AA73) -> 51931.731 | V73: =IF(V63="","",SUM(V82:V83)) -> 0 | W73: =IF(W63="","",SUM(W82:W83)) -> 10386.346 | X73: =IF(X63="","",SUM(X82:X83)) -> 10386.346 | Y73: =IF(Y63="","",SUM(Y82:Y83)) -> 10386.346 | Z73: =IF(Z63="","",SUM(Z82:Z83)) -> 10386.346 | AA73: =IF(AA63="","",SUM(AA82:AA83)) -> 10386.346
B74: Total GP Contributions | D74: =SUM(F74:P74) -> 415453.85 | F74: =IF(F63="","",-(MIN(F84,0)+F93)) -> 415453.85 | G74: =IF(G63="","",-(MIN(G84,0)+G93)) -> 0 | H74: =IF(H63="","",-(MIN(H84,0)+H93)) -> 0 | I74: =IF(I63="","",-(MIN(I84,0)+I93)) -> 0 | J74: =IF(J63="","",-(MIN(J84,0)+J93)) -> 0 | K74: =IF(K63="","",-(MIN(K84,0)+K93)) -> 0 | L74: =IF(L63="","",-(MIN(L84,0)+L93)) -> 0 | M74: =IF(M63="","",-(MIN(M84,0)+M93)) -> 0 | ... P74: =IF(P63="","",-(MIN(P84,0)+P93)) -> 0 | R74: Total GP Contributions | T74: =SUM(V74:AA74) -> 415453.85 | V74: =IF(V63="","",-(MIN(V84,0)+V93)) -> 415453.85 | W74: =IF(W63="","",-(MIN(W84,0)+W93)) -> 0 | X74: =IF(X63="","",-(MIN(X84,0)+X93)) -> 0 | Y74: =IF(Y63="","",-(MIN(Y84,0)+Y93)) -> 0 | Z74: =IF(Z63="","",-(MIN(Z84,0)+Z93)) -> 0 | AA74: =IF(AA63="","",-(MIN(AA84,0)+AA93)) -> 0
B75: Total GP Profit | D75: =+D72+D73-D74 -> 639825.23 | R75: Total GP Profit | T75: =+T72+T73-T74 -> 278797.99
B76: GP IRR | D76: =IFERROR(IRR(F76:Q76),"NA") -> 0.13861658 | F76: =IF(F63="","",(-F74)+F72+F73) -> -415453.85 | G76: =IF(G63="","",(-G74)+G72+G73) -> 47315.316 | H76: =IF(H63="","",(-H74)+H72+H73) -> 48700.487 | I76: =IF(I63="","",(-I74)+I72+I73) -> 50113.361 | J76: =IF(J63="","",(-J74)+J72+J73) -> 51554.492 | K76: =IF(K63="","",(-K74)+K72+K73) -> 53024.447 | L76: =IF(L63="","",(-L74)+L72+L73) -> 54523.8 | M76: =IF(M63="","",(-M74)+M72+M73) -> 56053.14 | ... P76: =IF(P63="","",(-P74)+P72+P73) -> 577176.77 | R76: GP IRR | T76: =IFERROR(IRR(V76:AA76),"NA") -> 0.13028361 | V76: =IF(V63="","",(-V74)+V72+V73) -> -415453.85 | W76: =IF(W63="","",(-W74)+W72+W73) -> 47315.316 | X76: =IF(X63="","",(-X74)+X72+X73) -> 48700.487 | Y76: =IF(Y63="","",(-Y74)+Y72+Y73) -> 50113.361 | Z76: =IF(Z63="","",(-Z74)+Z72+Z73) -> 51554.492 | AA76: =IF(AA63="","",(-AA74)+AA72+AA73) -> 496568.18
B77: GP Equity Multiple | D77: =IFERROR(D72/D74,"NA") -> 2.2900633 | R77: GP Equity Multiple | T77: =IFERROR(T72/T74,"NA") -> 1.5460685
B79: Property-Level Cash and GP Fees | F79: Year 0 | G79: =G$19 -> 1 | H79: =H$19 -> 2 | I79: =I$19 -> 3 | J79: =J$19 -> 4 | K79: =K$19 -> 5 | L79: =L$19 -> 6 | M79: =M$19 -> 7 | N79: =N$19 -> 8 | ... P79: =P$19 -> 10 | R79: Property-Level Cash and GP Fees | V79: Year 0 | W79: =W$19 -> 1 | X79: =X$19 -> 2 | Y79: =Y$19 -> 3 | Z79: =Z$19 -> 4 | AA79: =AA$19 -> 5
E80: Year Ending | F80: =IF(F44="","",F44) -> 46022 | G80: =IF(G44="","",G44) -> 46387 | H80: =IF(H44="","",H44) -> 46752 | I80: =IF(I44="","",I44) -> 47118 | J80: =IF(J44="","",J44) -> 47483 | K80: =IF(K44="","",K44) -> 47848 | L80: =IF(L44="","",L44) -> 48213 | M80: =IF(M44="","",M44) -> 48579 | ... P80: =IF(P44="","",P44) -> 49674 | U80: Year Ending | V80: =IF(V44="","",V44) -> 46022 | W80: =IF(W44="","",W44) -> 46387 | X80: =IF(X44="","",X44) -> 46752 | Y80: =IF(Y44="","",Y44) -> 47118 | Z80: =IF(Z44="","",Z44) -> 47483 | AA80: =IF(AA44="","",AA44) -> 47848
B81: Net Property-Level Cash Flow | F81: =IF(F45="","",F45) -> -4154538.5 | G81: =IF(G45="","",G45) -> 379676.05 | H81: =IF(H45="","",H45) -> 393527.75 | I81: =IF(I45="","",I45) -> 407656.49 | J81: =IF(J45="","",J45) -> 422067.81 | K81: =IF(K45="","",K45) -> 436767.35 | L81: =IF(L45="","",L45) -> 451760.88 | M81: =IF(M45="","",M45) -> 467054.29 | ... P81: =IF(P45="","",P45) -> 5678290.6 | R81: Net Property-Level Cash Flow | V81: =IF(V45="","",V45) -> -4154538.5 | W81: =IF(W45="","",W45) -> 379676.05 | X81: =IF(X45="","",X45) -> 393527.75 | Y81: =IF(Y45="","",Y45) -> 407656.49 | Z81: =IF(Z45="","",Z45) -> 422067.81 | AA81: =IF(AA45="","",AA45) -> 4872204.7
B82: =IF(B46="","",B46) -> Asset Management Fees | F82: =IF(F46="","",F46) -> 0 | G82: =IF(G46="","",G46) -> 10386.346 | H82: =IF(H46="","",H46) -> 10386.346 | I82: =IF(I46="","",I46) -> 10386.346 | J82: =IF(J46="","",J46) -> 10386.346 | K82: =IF(K46="","",K46) -> 10386.346 | L82: =IF(L46="","",L46) -> 10386.346 | M82: =IF(M46="","",M46) -> 10386.346 | ... P82: =IF(P46="","",P46) -> 10386.346 | R82: =IF(R46="","",R46) -> Asset Management Fees | V82: =IF(V46="","",V46) -> 0 | W82: =IF(W46="","",W46) -> 10386.346 | X82: =IF(X46="","",X46) -> 10386.346 | Y82: =IF(Y46="","",Y46) -> 10386.346 | Z82: =IF(Z46="","",Z46) -> 10386.346 | AA82: =IF(AA46="","",AA46) -> 10386.346
B83: =IF(B47="","",B47) -> Acquisition/Disposition Fees | F83: =IF(F47="","",F47) -> 0 | G83: =IF(G47="","",G47) -> 0 | H83: =IF(H47="","",H47) -> 0 | I83: =IF(I47="","",I47) -> 0 | J83: =IF(J47="","",J47) -> 0 | K83: =IF(K47="","",K47) -> 0 | L83: =IF(L47="","",L47) -> 0 | M83: =IF(M47="","",M47) -> 0 | ... P83: =IF(P47="","",P47) -> 0 | R83: =IF(R47="","",R47) -> Acquisition/Disposition Fees | V83: =IF(V47="","",V47) -> 0 | W83: =IF(W47="","",W47) -> 0 | X83: =IF(X47="","",X47) -> 0 | Y83: =IF(Y47="","",Y47) -> 0 | Z83: =IF(Z47="","",Z47) -> 0 | AA83: =IF(AA47="","",AA47) -> 0
B84: Adjusted Net Property-Level Cash Flow | F84: =IF(F79="","",F81-F82-F83) -> -4154538.5 | G84: =IF(G79="","",G81-G82-G83) -> 369289.7 | H84: =IF(H79="","",H81-H82-H83) -> 383141.41 | I84: =IF(I79="","",I81-I82-I83) -> 397270.15 | J84: =IF(J79="","",J81-J82-J83) -> 411681.46 | K84: =IF(K79="","",K81-K82-K83) -> 426381 | L84: =IF(L79="","",L81-L82-L83) -> 441374.54 | M84: =IF(M79="","",M81-M82-M83) -> 456667.94 | ... P84: =IF(P79="","",P81-P82-P83) -> 5667904.3 | R84: Adjusted Net Property-Level Cash Flow | V84: =IF(V79="","",V81-V82-V83) -> -4154538.5 | W84: =IF(W79="","",W81-W82-W83) -> 369289.7 | X84: =IF(X79="","",X81-X82-X83) -> 383141.41 | Y84: =IF(Y79="","",Y81-Y82-Y83) -> 397270.15 | Z84: =IF(Z79="","",Z81-Z82-Z83) -> 411681.46 | AA84: =IF(AA79="","",AA81-AA82-AA83) -> 4861818.4
B85: Levered IRR | F85: =IRR(F84:Q84) -> 0.11566557 | R85: Levered IRR | V85: =IRR(V84:AA84) -> 0.10594725
B86: Equity Multiple | F86: =SUMIF(F84:Q84,">0")/-SUMIF(F84:Q84,"<0") -> 2.2900633 | R86: Equity Multiple | V86: =SUMIF(V84:AA84,">0")/-SUMIF(V84:AA84,"<0") -> 1.5460685
B88: Tier 1 - Preferred Return + Return of Capital | R88: Tier 1 - Preferred Return + Return of Capital
B89: Return Threshold - Up to: | C89: =E58 -> 0 | F89: Year 0 | G89: =G$19 -> 1 | H89: =H$19 -> 2 | I89: =I$19 -> 3 | J89: =J$19 -> 4 | K89: =K$19 -> 5 | L89: =L$19 -> 6 | M89: =M$19 -> 7 | N89: =N$19 -> 8 | ... P89: =P$19 -> 10 | R89: Return Threshold - Up to: | S89: =U58 -> 0 | V89: Year 0 | W89: =W$19 -> 1 | X89: =X$19 -> 2 | Y89: =Y$19 -> 3 | Z89: =Z$19 -> 4 | AA89: =AA$19 -> 5
B90: Beginning Balance (LP Capital Account) | F90: =IF(F79="","",E95) -> 0 | G90: =IF(G79="","",F95) -> 3739084.6 | H90: =IF(H79="","",G95) -> 3406723.9 | I90: =IF(I79="","",H95) -> 3061896.6 | J90: =IF(J79="","",I95) -> 2704353.5 | K90: =IF(K79="","",J95) -> 2333840.2 | L90: =IF(L79="","",K95) -> 1950097.3 | M90: =IF(M79="","",L95) -> 1552860.2 | ... P90: =IF(P79="","",O95) -> 277457.93 | R90: Beginning Balance (LP Capital Account) | V90: =IF(V79="","",U95) -> 0 | W90: =IF(W79="","",V95) -> 3739084.6 | X90: =IF(X79="","",W95) -> 3406723.9 | Y90: =IF(Y79="","",X95) -> 3061896.6 | Z90: =IF(Z79="","",Y95) -> 2704353.5 | AA90: =IF(AA79="","",Z95) -> 2333840.2
B91: LP Return of Capital | F91: =IF(ROUND(SUM(G91:Q91),0)=ROUND(SUM(F93:Q93),0),"All Capital Returned","Capital Not Returned") -> All Capital Returned | G91: =IF(G79="","",G97-G92) -> 332360.73 | H91: =IF(H79="","",H97-H92) -> 344827.26 | I91: =IF(I79="","",I97-I92) -> 357543.13 | J91: =IF(J79="","",J97-J92) -> 370513.32 | K91: =IF(K79="","",K97-K92) -> 383742.9 | L91: =IF(L79="","",L97-L92) -> 397237.08 | M91: =IF(M79="","",M97-M92) -> 411001.15 | N91: =IF(N79="","",N97-N92) -> 425040.49 | ... P91: =IF(P79="","",P97-P92) -> 277457.93 | R91: LP Return of Capital | V91: =IF(ROUND(SUM(W91:AA91),0)=ROUND(SUM(V93:AA93),0),"All Capital Returned","Capital Not Returned") -> All Capital Returned | W91: =IF(W79="","",W97-W92) -> 332360.73 | X91: =IF(X79="","",X97-X92) -> 344827.26 | Y91: =IF(Y79="","",Y97-Y92) -> 357543.13 | Z91: =IF(Z79="","",Z97-Z92) -> 370513.32 | AA91: =IF(AA79="","",AA97-AA92) -> 2333840.2
B92: Req'd Return by LP to hit Hurdle 1 | F92: =IF(F90="","",IF($D$55="Equity Multiple",E93*$C89-E93,F90*Preferred_Return)) -> 0 | G92: =G90*Preferred_Return -> 0 | H92: =H90*Preferred_Return -> 0 | I92: =I90*Preferred_Return -> 0 | J92: =IF(J90="","",IF($D$55="Equity Multiple",I93*$C89-I93,J90*Preferred_Return)) -> 0 | K92: =IF(K90="","",IF($D$55="Equity Multiple",J93*$C89-J93,K90*Preferred_Return)) -> 0 | L92: =IF(L90="","",IF($D$55="Equity Multiple",K93*$C89-K93,L90*Preferred_Return)) -> 0 | M92: =IF(M90="","",IF($D$55="Equity Multiple",L93*$C89-L93,M90*Preferred_Return)) -> 0 | N92: =IF(N90="","",IF($D$55="Equity Multiple",M93*$C89-M93,N90*Preferred_Return)) -> 0 | O92: =IF(O90="","",IF($D$55="Equity Multiple",N93*$C89-N93,O90*Preferred_Return)) -> 0 | P92: =IF(P90="","",IF($D$55="Equity Multiple",O93*$C89-O93,P90*Preferred_Return)) -> 0 | R92: Req'd Return by LP to hit Hurdle 1 | V92: =IF(V90="","",IF($T$55="Equity Multiple",U93*$S89-U93,V90*Preferred_Return)) -> 0 | W92: =W90*Preferred_Return -> 0 | X92: =X90*Preferred_Return -> 0 | Y92: =Y90*Preferred_Return -> 0 | Z92: =IF(Z90="","",IF($T$55="Equity Multiple",Y93*$S89-Y93,Z90*Preferred_Return)) -> 0 | AA92: =IF(AA90="","",IF($T$55="Equity Multiple",Z93*$S89-Z93,AA90*Preferred_Return)) -> 0
B93: Contributions from LP | F93: =IF(F90="","",-MIN(0,F84*Equity_Share_LP)) -> 3739084.6 | G93: =IF(G90="","",-MIN(0,G84*Equity_Share_LP)) -> 0 | H93: =IF(H90="","",-MIN(0,H84*Equity_Share_LP)) -> 0 | I93: =IF(I90="","",-MIN(0,I84*Equity_Share_LP)) -> 0 | J93: =IF(J90="","",-MIN(0,J84*Equity_Share_LP)) -> 0 | K93: =IF(K90="","",-MIN(0,K84*Equity_Share_LP)) -> 0 | L93: =IF(L90="","",-MIN(0,L84*Equity_Share_LP)) -> 0 | M93: =IF(M90="","",-MIN(0,M84*Equity_Share_LP)) -> 0 | ... P93: =IF(P90="","",-MIN(0,P84*Equity_Share_LP)) -> 0 | R93: Contributions from LP | V93: =IF(V90="","",-MIN(0,V84*Equity_Share_LP)) -> 3739084.6 | W93: =IF(W90="","",-MIN(0,W84*Equity_Share_LP)) -> 0 | X93: =IF(X90="","",-MIN(0,X84*Equity_Share_LP)) -> 0 | Y93: =IF(Y90="","",-MIN(0,Y84*Equity_Share_LP)) -> 0 | Z93: =IF(Z90="","",-MIN(0,Z84*Equity_Share_LP)) -> 0 | AA93: =IF(AA90="","",-MIN(0,AA84*Equity_Share_LP)) -> 0
B94: Distributions to LP (Hurdle 1) | F94: =MAX(F84,F92) -> 0 | G94: =IF(G90="","",MIN(G90+G92,MAX(G84,0)*$I$14)) -> 332360.73 | H94: =IF(H90="","",MIN(H90+H92,MAX(H84,0)*$I$14)) -> 344827.26 | I94: =IF(I90="","",MIN(I90+I92,MAX(I84,0)*$I$14)) -> 357543.13 | J94: =IF(J90="","",MIN(J90+J92,MAX(J84,0)*$I$14)) -> 370513.32 | K94: =IF(K90="","",MIN(K90+K92,MAX(K84,0)*$I$14)) -> 383742.9 | L94: =IF(L90="","",MIN(L90+L92,MAX(L84,0)*$I$14)) -> 397237.08 | M94: =IF(M90="","",MIN(M90+M92,MAX(M84,0)*$I$14)) -> 411001.15 | N94: =IF(N90="","",MIN(N90+N92,MAX(N84,0)*$I$14)) -> 425040.49 | ... P94: =IF(P90="","",MIN(P90+P92,MAX(P84,0)*$I$14)) -> 277457.93 | R94: Distributions to LP (Hurdle 1) | V94: =MAX(V84,V92) -> 0 | W94: =IF(W90="","",MIN(W90+W92,MAX(W84,0)*$Y$14)) -> 332360.73 | X94: =IF(X90="","",MIN(X90+X92,MAX(X84,0)*$Y$14)) -> 344827.26 | Y94: =IF(Y90="","",MIN(Y90+Y92,MAX(Y84,0)*$Y$14)) -> 357543.13 | Z94: =IF(Z90="","",MIN(Z90+Z92,MAX(Z84,0)*$Y$14)) -> 370513.32 | AA94: =IF(AA90="","",MIN(AA90+AA92,MAX(AA84,0)*$Y$14)) -> 2333840.2
B95: Ending Balance (LP Capital Account) | F95: =F90+F93-F94 -> 3739084.6 | G95: =IF(G90="","",G90+G92+G93-G94) -> 3406723.9 | H95: =IF(H90="","",H90+H92+H93-H94) -> 3061896.6 | I95: =IF(I90="","",I90+I92+I93-I94) -> 2704353.5 | J95: =IF(J90="","",J90+J92+J93-J94) -> 2333840.2 | K95: =IF(K90="","",K90+K92+K93-K94) -> 1950097.3 | L95: =IF(L90="","",L90+L92+L93-L94) -> 1552860.2 | M95: =IF(M90="","",M90+M92+M93-M94) -> 1141859 | N95: =IF(N90="","",N90+N92+N93-N94) -> 716818.55 | ... P95: =IF(P90="","",P90+P92+P93-P94) -> 0 | R95: Ending Balance (LP Capital Account) | V95: =V90+V93-V94 -> 3739084.6 | W95: =IF(W90="","",W90+W92+W93-W94) -> 3406723.9 | X95: =IF(X90="","",X90+X92+X93-X94) -> 3061896.6 | Y95: =IF(Y90="","",Y90+Y92+Y93-Y94) -> 2704353.5 | Z95: =IF(Z90="","",Z90+Z92+Z93-Z94) -> 2333840.2 | AA95: =IF(AA90="","",AA90+AA92+AA93-AA94) -> 0
B96: =IF(D55="Equity Multiple", "LP EMx Check","LP IRR Check") -> LP IRR Check | E96: =IF($D$55="IRR",IRR(F96:Q96),SUMIF(F96:Q96,">0")/-SUMIF(F96:Q96,"<0")) -> 0 | F96: =IF(F90="","",-F93+F94) -> -3739084.6 | G96: =IF(G90="","",-G93+G94) -> 332360.73 | H96: =IF(H90="","",-H93+H94) -> 344827.26 | I96: =IF(I90="","",-I93+I94) -> 357543.13 | J96: =IF(J90="","",-J93+J94) -> 370513.32 | K96: =IF(K90="","",-K93+K94) -> 383742.9 | L96: =IF(L90="","",-L93+L94) -> 397237.08 | M96: =IF(M90="","",-M93+M94) -> 411001.15 | ... P96: =IF(P90="","",-P93+P94) -> 277457.93 | R96: =IF(T55="Equity Multiple", "LP EMx Check","LP IRR Check") -> LP IRR Check | U96: =IF($T$55="IRR",IRR(V96:AA96),SUMIF(V96:AA96,">0")/-SUMIF(V96:AA96,"<0")) -> 0 | V96: =IF(V90="","",-V93+V94) -> -3739084.6 | W96: =IF(W90="","",-W93+W94) -> 332360.73 | X96: =IF(X90="","",-X93+X94) -> 344827.26 | Y96: =IF(Y90="","",-Y93+Y94) -> 357543.13 | Z96: =IF(Z90="","",-Z93+Z94) -> 370513.32 | AA96: =IF(AA90="","",-AA93+AA94) -> 2333840.2
B97: Distribution to LP | F97: =MAX(F84,F92) -> 0 | G97: =IF(G90="","",MIN(G90+G92,MAX(G84,0)*$I$14)) -> 332360.73 | H97: =H94 -> 344827.26 | I97: =I94 -> 357543.13 | J97: =J94 -> 370513.32 | K97: =K94 -> 383742.9 | L97: =L94 -> 397237.08 | M97: =M94 -> 411001.15 | N97: =N94 -> 425040.49 | O97: =O94 -> 439360.62 | P97: =P94 -> 277457.93 | R97: Distribution to LP | V97: =MAX(V84,V92) -> 0 | W97: =IF(W90="","",MIN(W90+W92,MAX(W84,0)*$Y$14)) -> 332360.73 | X97: =X94 -> 344827.26 | Y97: =Y94 -> 357543.13 | Z97: =Z94 -> 370513.32 | AA97: =AA94 -> 2333840.2
B99: Beginning Balance (GP Capital Account) | F99: =IF(F79="","",E103) -> 0 | G99: =IF(G79="","",F103) -> 415453.85 | H99: =IF(H79="","",G103) -> 378524.88 | I99: =IF(I79="","",H103) -> 340210.74 | J99: =IF(J79="","",I103) -> 300483.72 | K99: =IF(K79="","",J103) -> 259315.57 | L99: =IF(L79="","",K103) -> 216677.47 | M99: =IF(M79="","",L103) -> 172540.02 | ... P99: =IF(P79="","",O103) -> 30828.658 | R99: Beginning Balance (GP Capital Account) | V99: =IF(V79="","",U103) -> 0 | W99: =IF(W79="","",V103) -> 415453.85 | X99: =IF(X79="","",W103) -> 378524.88 | Y99: =IF(Y79="","",X103) -> 340210.74 | Z99: =IF(Z79="","",Y103) -> 300483.72 | AA99: =IF(AA79="","",Z103) -> 259315.57
B100: Req'd Return by GP (Pref) | F100: =IF(F99="","",IF($D$55="Equity Multiple",E101*$C89-E101,F99*Preferred_Return)) -> 0 | G100: =IF(G99="","",IF($D$55="Equity Multiple",F101*$C89-F101,G99*Preferred_Return)) -> 0 | H100: =IF(H99="","",IF($D$55="Equity Multiple",G101*$C89-G101,H99*Preferred_Return)) -> 0 | I100: =IF(I99="","",IF($D$55="Equity Multiple",H101*$C89-H101,I99*Preferred_Return)) -> 0 | J100: =IF(J99="","",IF($D$55="Equity Multiple",I101*$C89-I101,J99*Preferred_Return)) -> 0 | K100: =IF(K99="","",IF($D$55="Equity Multiple",J101*$C89-J101,K99*Preferred_Return)) -> 0 | L100: =IF(L99="","",IF($D$55="Equity Multiple",K101*$C89-K101,L99*Preferred_Return)) -> 0 | M100: =IF(M99="","",IF($D$55="Equity Multiple",L101*$C89-L101,M99*Preferred_Return)) -> 0 | ... P100: =IF(P99="","",IF($D$55="Equity Multiple",O101*$C89-O101,P99*Preferred_Return)) -> 0 | R100: Req'd Return by GP (Pref) | V100: =IF(V99="","",IF($T$55="Equity Multiple",U101*$S89-U101,V99*Preferred_Return)) -> 0 | W100: =IF(W99="","",IF($T$55="Equity Multiple",V101*$S89-V101,W99*Preferred_Return)) -> 0 | X100: =IF(X99="","",IF($T$55="Equity Multiple",W101*$S89-W101,X99*Preferred_Return)) -> 0 | Y100: =IF(Y99="","",IF($T$55="Equity Multiple",X101*$S89-X101,Y99*Preferred_Return)) -> 0 | Z100: =IF(Z99="","",IF($T$55="Equity Multiple",Y101*$S89-Y101,Z99*Preferred_Return)) -> 0 | AA100: =IF(AA99="","",IF($T$55="Equity Multiple",Z101*$S89-Z101,AA99*Preferred_Return)) -> 0
B101: Contributions from GP | F101: =IF(F79="","",-MIN(0,F84*Equity_Share_GP)) -> 415453.85 | G101: =IF(G79="","",-MIN(0,G84*Equity_Share_GP)) -> 0 | H101: =IF(H79="","",-MIN(0,H84*Equity_Share_GP)) -> 0 | I101: =IF(I79="","",-MIN(0,I84*Equity_Share_GP)) -> 0 | J101: =IF(J79="","",-MIN(0,J84*Equity_Share_GP)) -> 0 | K101: =IF(K79="","",-MIN(0,K84*Equity_Share_GP)) -> 0 | L101: =IF(L79="","",-MIN(0,L84*Equity_Share_GP)) -> 0 | M101: =IF(M79="","",-MIN(0,M84*Equity_Share_GP)) -> 0 | ... P101: =IF(P79="","",-MIN(0,P84*Equity_Share_GP)) -> 0 | R101: Contributions from GP | V101: =IF(V79="","",-MIN(0,V84*Equity_Share_GP)) -> 415453.85 | W101: =IF(W79="","",-MIN(0,W84*Equity_Share_GP)) -> 0 | X101: =IF(X79="","",-MIN(0,X84*Equity_Share_GP)) -> 0 | Y101: =IF(Y79="","",-MIN(0,Y84*Equity_Share_GP)) -> 0 | Z101: =IF(Z79="","",-MIN(0,Z84*Equity_Share_GP)) -> 0 | AA101: =IF(AA79="","",-MIN(0,AA84*Equity_Share_GP)) -> 0
B102: Distribution to GP | F102: =IF(F79="","",IF(CU?,MAX(MIN(F84-F97,F99+F100+F101),0),F94/$I$14*$H$14)) -> 0 | G102: =IF(G79="","",IF(CU?,MAX(MIN(G84-G97,G99+G100+G101),0),G94/$I$14*$H$14)) -> 36928.97 | H102: =IF(H79="","",IF(CU?,MAX(MIN(H84-H97,H99+H100+H101),0),H94/$I$14*$H$14)) -> 38314.141 | I102: =IF(I79="","",IF(CU?,MAX(MIN(I84-I97,I99+I100+I101),0),I94/$I$14*$H$14)) -> 39727.015 | J102: =IF(J79="","",IF(CU?,MAX(MIN(J84-J97,J99+J100+J101),0),J94/$I$14*$H$14)) -> 41168.146 | K102: =IF(K79="","",IF(CU?,MAX(MIN(K84-K97,K99+K100+K101),0),K94/$I$14*$H$14)) -> 42638.1 | L102: =IF(L79="","",IF(CU?,MAX(MIN(L84-L97,L99+L100+L101),0),L94/$I$14*$H$14)) -> 44137.454 | M102: =IF(M79="","",IF(CU?,MAX(MIN(M84-M97,M99+M100+M101),0),M94/$I$14*$H$14)) -> 45666.794 | ... P102: =IF(P79="","",IF(CU?,MAX(MIN(P84-P97,P99+P100+P101),0),P94/$I$14*$H$14)) -> 30828.658 | R102: Distribution to GP | V102: =IF(V79="","",IF(CU?,MAX(MIN(V84-V97,V99+V100+V101),0),V94/$Y$14*$X$14)) -> 0 | W102: =IF(W79="","",IF(CU?,MAX(MIN(W84-W97,W99+W100+W101),0),W94/$Y$14*$X$14)) -> 36928.97 | X102: =IF(X79="","",IF(CU?,MAX(MIN(X84-X97,X99+X100+X101),0),X94/$Y$14*$X$14)) -> 38314.141 | Y102: =IF(Y79="","",IF(CU?,MAX(MIN(Y84-Y97,Y99+Y100+Y101),0),Y94/$Y$14*$X$14)) -> 39727.015 | Z102: =IF(Z79="","",IF(CU?,MAX(MIN(Z84-Z97,Z99+Z100+Z101),0),Z94/$Y$14*$X$14)) -> 41168.146 | AA102: =IF(AA79="","",IF(CU?,MAX(MIN(AA84-AA97,AA99+AA100+AA101),0),AA94/$Y$14*$X$14)) -> 259315.57
B103: Ending Balance (GP Capital Account) | F103: =IF(F79="","",F99+F100+F101-F102) -> 415453.85 | G103: =IF(G79="","",G99+G100+G101-G102) -> 378524.88 | H103: =IF(H79="","",H99+H100+H101-H102) -> 340210.74 | I103: =IF(I79="","",I99+I100+I101-I102) -> 300483.72 | J103: =IF(J79="","",J99+J100+J101-J102) -> 259315.57 | K103: =IF(K79="","",K99+K100+K101-K102) -> 216677.47 | L103: =IF(L79="","",L99+L100+L101-L102) -> 172540.02 | M103: =IF(M79="","",M99+M100+M101-M102) -> 126873.23 | ... P103: =IF(P79="","",P99+P100+P101-P102) -> -4.7293724e-11 | R103: Ending Balance (GP Capital Account) | V103: =IF(V79="","",V99+V100+V101-V102) -> 415453.85 | W103: =IF(W79="","",W99+W100+W101-W102) -> 378524.88 | X103: =IF(X79="","",X99+X100+X101-X102) -> 340210.74 | Y103: =IF(Y79="","",Y99+Y100+Y101-Y102) -> 300483.72 | Z103: =IF(Z79="","",Z99+Z100+Z101-Z102) -> 259315.57 | AA103: =IF(AA79="","",AA99+AA100+AA101-AA102) -> -5.8207661e-11
B104: =IF(D55="Equity Multiple", "GP EMx Check","GP IRR Check") -> GP IRR Check | E104: =IF($D$55="IRR",IFERROR(IRR(F104:Q104),"NA"),SUMIF(F104:Q104,">0")/-SUMIF(F104:Q104,"<0")) -> 0 | F104: =IF(F79="","",-F101+F102) -> -415453.85 | G104: =IF(G79="","",-G101+G102) -> 36928.97 | H104: =IF(H79="","",-H101+H102) -> 38314.141 | I104: =IF(I79="","",-I101+I102) -> 39727.015 | J104: =IF(J79="","",-J101+J102) -> 41168.146 | K104: =IF(K79="","",-K101+K102) -> 42638.1 | L104: =IF(L79="","",-L101+L102) -> 44137.454 | M104: =IF(M79="","",-M101+M102) -> 45666.794 | ... P104: =IF(P79="","",-P101+P102) -> 30828.658 | R104: =IF(T55="Equity Multiple", "GP EMx Check","GP IRR Check") -> GP IRR Check | U104: =IF($T$55="IRR",IFERROR(IRR(V104:AA104),"NA"),SUMIF(V104:AA104,">0")/-SUMIF(V104:AA104,"<0")) -> 0 | V104: =IF(V79="","",-V101+V102) -> -415453.85 | W104: =IF(W79="","",-W101+W102) -> 36928.97 | X104: =IF(X79="","",-X101+X102) -> 38314.141 | Y104: =IF(Y79="","",-Y101+Y102) -> 39727.015 | Z104: =IF(Z79="","",-Z101+Z102) -> 41168.146 | AA104: =IF(AA79="","",-AA101+AA102) -> 259315.57
B106: ="Total Distributions ("&B88&")" -> Total Distributions (Tier 1 - Preferred Return + Return of Capital) | F106: =IF(F90="","",F102+F97) -> 0 | G106: =IF(G90="","",G102+G97) -> 369289.7 | H106: =IF(H90="","",H102+H97) -> 383141.41 | I106: =IF(I90="","",I102+I97) -> 397270.15 | J106: =IF(J90="","",J102+J97) -> 411681.46 | K106: =IF(K90="","",K102+K97) -> 426381 | L106: =IF(L90="","",L102+L97) -> 441374.54 | M106: =IF(M90="","",M102+M97) -> 456667.94 | ... P106: =IF(P90="","",P102+P97) -> 308286.58 | R106: ="Total Distributions ("&R88&")" -> Total Distributions (Tier 1 - Preferred Return + Return of Capital) | V106: =IF(V90="","",V102+V97) -> 0 | W106: =IF(W90="","",W102+W97) -> 369289.7 | X106: =IF(X90="","",X102+X97) -> 383141.41 | Y106: =IF(Y90="","",Y102+Y97) -> 397270.15 | Z106: =IF(Z90="","",Z102+Z97) -> 411681.46 | AA106: =IF(AA90="","",AA102+AA97) -> 2593155.7
B107: Cash Flow Remaining | F107: =IF(F90="","",MAX(F84-F106,0)) -> 0 | G107: =IF(G90="","",MAX(G84-G106,0)) -> 0 | H107: =IF(H90="","",MAX(H84-H106,0)) -> 0 | I107: =IF(I90="","",MAX(I84-I106,0)) -> 0 | J107: =IF(J90="","",MAX(J84-J106,0)) -> 0 | K107: =IF(K90="","",MAX(K84-K106,0)) -> 0 | L107: =IF(L90="","",MAX(L84-L106,0)) -> 0 | M107: =IF(M90="","",MAX(M84-M106,0)) -> 0 | ... P107: =IF(P90="","",MAX(P84-P106,0)) -> 5359617.7 | R107: Cash Flow Remaining | V107: =IF(V90="","",MAX(V84-V106,0)) -> 0 | W107: =IF(W90="","",MAX(W84-W106,0)) -> 0 | X107: =IF(X90="","",MAX(X84-X106,0)) -> 0 | Y107: =IF(Y90="","",MAX(Y84-Y106,0)) -> 0 | Z107: =IF(Z90="","",MAX(Z84-Z106,0)) -> 0 | AA107: =IF(AA90="","",MAX(AA84-AA106,0)) -> 2268662.6
B109: Tier 2 | F109: Year 0 | G109: =G$19 -> 1 | H109: =H$19 -> 2 | I109: =I$19 -> 3 | J109: =J$19 -> 4 | K109: =K$19 -> 5 | L109: =L$19 -> 6 | M109: =M$19 -> 7 | N109: =N$19 -> 8 | ... P109: =P$19 -> 10 | R109: Tier 2 | V109: Year 0 | W109: =W$19 -> 1 | X109: =X$19 -> 2 | Y109: =Y$19 -> 3 | Z109: =Z$19 -> 4 | AA109: =AA$19 -> 5
B110: Return Threshold - Up to: | C110: =E59 -> 0 | R110: Return Threshold - Up to: | S110: =U59 -> 0
B111: Beginning Balance (LP Capital Account) | F111: =IF(F79="","",E116) -> 0 | G111: =IF(G79="","",F116) -> 3739084.6 | H111: =IF(H79="","",G116) -> 3406723.9 | I111: =IF(I79="","",H116) -> 3061896.6 | J111: =IF(J79="","",I116) -> 2704353.5 | K111: =IF(K79="","",J116) -> 2333840.2 | L111: =IF(L79="","",K116) -> 1950097.3 | M111: =IF(M79="","",L116) -> 1552860.2 | ... P111: =IF(P79="","",O116) -> 277457.93 | R111: Beginning Balance (LP Capital Account) | V111: =IF(V79="","",U116) -> 0 | W111: =IF(W79="","",V116) -> 3739084.6 | X111: =IF(X79="","",W116) -> 3406723.9 | Y111: =IF(Y79="","",X116) -> 3061896.6 | Z111: =IF(Z79="","",Y116) -> 2704353.5 | AA111: =IF(AA79="","",Z116) -> 2333840.2
B112: Req'd Return by LP to hit Hurdle 2 | F112: =IF(F111="","",IF($D$55="Equity Multiple",E113*$C110-E113,F111*$C110)) -> 0 | G112: =IF(G111="","",IF($D$55="Equity Multiple",F113*$C110-F113,G111*$C110)) -> 0 | H112: =IF(H111="","",IF($D$55="Equity Multiple",G113*$C110-G113,H111*$C110)) -> 0 | I112: =IF(I111="","",IF($D$55="Equity Multiple",H113*$C110-H113,I111*$C110)) -> 0 | J112: =IF(J111="","",IF($D$55="Equity Multiple",I113*$C110-I113,J111*$C110)) -> 0 | K112: =IF(K111="","",IF($D$55="Equity Multiple",J113*$C110-J113,K111*$C110)) -> 0 | L112: =IF(L111="","",IF($D$55="Equity Multiple",K113*$C110-K113,L111*$C110)) -> 0 | M112: =IF(M111="","",IF($D$55="Equity Multiple",L113*$C110-L113,M111*$C110)) -> 0 | ... P112: =IF(P111="","",IF($D$55="Equity Multiple",O113*$C110-O113,P111*$C110)) -> 0 | R112: Req'd Return by LP to hit Hurdle 2 | V112: =IF(V111="","",IF($T$55="Equity Multiple",U113*$S110-U113,V111*$S110)) -> 0 | W112: =IF(W111="","",IF($T$55="Equity Multiple",V113*$S110-V113,W111*$S110)) -> 0 | X112: =IF(X111="","",IF($T$55="Equity Multiple",W113*$S110-W113,X111*$S110)) -> 0 | Y112: =IF(Y111="","",IF($T$55="Equity Multiple",X113*$S110-X113,Y111*$S110)) -> 0 | Z112: =IF(Z111="","",IF($T$55="Equity Multiple",Y113*$S110-Y113,Z111*$S110)) -> 0 | AA112: =IF(AA111="","",IF($T$55="Equity Multiple",Z113*$S110-Z113,AA111*$S110)) -> 0
B113: Contributions from LP | F113: =IF(F111="","",-MIN(0,F$49*Equity_Share_LP)) -> 3739084.6 | G113: =IF(G111="","",-MIN(0,G$49*Equity_Share_LP)) -> 0 | H113: =IF(H111="","",-MIN(0,H$49*Equity_Share_LP)) -> 0 | I113: =IF(I111="","",-MIN(0,I$49*Equity_Share_LP)) -> 0 | J113: =IF(J111="","",-MIN(0,J$49*Equity_Share_LP)) -> 0 | K113: =IF(K111="","",-MIN(0,K$49*Equity_Share_LP)) -> 0 | L113: =IF(L111="","",-MIN(0,L$49*Equity_Share_LP)) -> 0 | M113: =IF(M111="","",-MIN(0,M$49*Equity_Share_LP)) -> 0 | ... P113: =IF(P111="","",-MIN(0,P$49*Equity_Share_LP)) -> 0 | R113: Contributions from LP | V113: =IF(V111="","",-MIN(0,V$49*Equity_Share_LP)) -> 3739084.6 | W113: =IF(W111="","",-MIN(0,W$49*Equity_Share_LP)) -> 0 | X113: =IF(X111="","",-MIN(0,X$49*Equity_Share_LP)) -> 0 | Y113: =IF(Y111="","",-MIN(0,Y$49*Equity_Share_LP)) -> 0 | Z113: =IF(Z111="","",-MIN(0,Z$49*Equity_Share_LP)) -> 0 | AA113: =IF(AA111="","",-MIN(0,AA$49*Equity_Share_LP)) -> 0
B114: Prior Distributions | F114: =F97 -> 0 | G114: =G97 -> 332360.73 | H114: =H97 -> 344827.26 | I114: =I97 -> 357543.13 | J114: =J97 -> 370513.32 | K114: =K97 -> 383742.9 | L114: =L97 -> 397237.08 | M114: =M97 -> 411001.15 | ... P114: =P97 -> 277457.93 | R114: Prior Distributions | V114: =V97 -> 0 | W114: =W97 -> 332360.73 | X114: =X97 -> 344827.26 | Y114: =Y97 -> 357543.13 | Z114: =Z97 -> 370513.32 | AA114: =AA97 -> 2333840.2
B115: ="Distributions to LP "&B109 -> Distributions to LP Tier 2 | F115: =IF(F111="","",MIN(F111+F112-F114,F107*$I$15)) -> 0 | G115: =IF(G111="","",MIN(G111+G112-G114,G107*$I$15)) -> 0 | H115: =IF(H111="","",MIN(H111+H112-H114,H107*$I$15)) -> 0 | I115: =IF(I111="","",MIN(I111+I112-I114,I107*$I$15)) -> 0 | J115: =IF(J111="","",MIN(J111+J112-J114,J107*$I$15)) -> 0 | K115: =IF(K111="","",MIN(K111+K112-K114,K107*$I$15)) -> 0 | L115: =IF(L111="","",MIN(L111+L112-L114,L107*$I$15)) -> 0 | M115: =IF(M111="","",MIN(M111+M112-M114,M107*$I$15)) -> 0 | ... P115: =IF(P111="","",MIN(P111+P112-P114,P107*$I$15)) -> 0 | R115: ="Distributions to LP "&R109 -> Distributions to LP Tier 2 | V115: =IF(V111="","",MIN(V111+V112-V114,V107*$Y$15)) -> 0 | W115: =IF(W111="","",MIN(W111+W112-W114,W107*$Y$15)) -> 0 | X115: =IF(X111="","",MIN(X111+X112-X114,X107*$Y$15)) -> 0 | Y115: =IF(Y111="","",MIN(Y111+Y112-Y114,Y107*$Y$15)) -> 0 | Z115: =IF(Z111="","",MIN(Z111+Z112-Z114,Z107*$Y$15)) -> 0 | AA115: =IF(AA111="","",MIN(AA111+AA112-AA114,AA107*$Y$15)) -> 0
B116: Ending Balance (LP Capital Account) | F116: =F111+F113-F115 -> 3739084.6 | G116: =IF(G111="","",G111+G112+G113-G114-G115) -> 3406723.9 | H116: =IF(H111="","",H111+H112+H113-H114-H115) -> 3061896.6 | I116: =IF(I111="","",I111+I112+I113-I114-I115) -> 2704353.5 | J116: =IF(J111="","",J111+J112+J113-J114-J115) -> 2333840.2 | K116: =IF(K111="","",K111+K112+K113-K114-K115) -> 1950097.3 | L116: =IF(L111="","",L111+L112+L113-L114-L115) -> 1552860.2 | M116: =IF(M111="","",M111+M112+M113-M114-M115) -> 1141859 | N116: =IF(N111="","",N111+N112+N113-N114-N115) -> 716818.55 | ... P116: =IF(P111="","",P111+P112+P113-P114-P115) -> 0 | R116: Ending Balance (LP Capital Account) | V116: =V111+V113-V115 -> 3739084.6 | W116: =IF(W111="","",W111+W112+W113-W114-W115) -> 3406723.9 | X116: =IF(X111="","",X111+X112+X113-X114-X115) -> 3061896.6 | Y116: =IF(Y111="","",Y111+Y112+Y113-Y114-Y115) -> 2704353.5 | Z116: =IF(Z111="","",Z111+Z112+Z113-Z114-Z115) -> 2333840.2 | AA116: =IF(AA111="","",AA111+AA112+AA113-AA114-AA115) -> 0
B117: =C110 -> 0 | E117: =IF($D$55="IRR",IRR(F117:Q117),SUMIF(F117:Q117,">0")/-SUMIF(F117:Q117,"<0")) -> 0 | F117: =IF(F111="","",-F113+F115) -> -3739084.6 | G117: =IF(G111="","",-G113+G114+G115) -> 332360.73 | H117: =IF(H111="","",-H113+H114+H115) -> 344827.26 | I117: =IF(I111="","",-I113+I114+I115) -> 357543.13 | J117: =IF(J111="","",-J113+J114+J115) -> 370513.32 | K117: =IF(K111="","",-K113+K114+K115) -> 383742.9 | L117: =IF(L111="","",-L113+L114+L115) -> 397237.08 | M117: =IF(M111="","",-M113+M114+M115) -> 411001.15 | N117: =IF(N111="","",-N113+N114+N115) -> 425040.49 | ... P117: =IF(P111="","",-P113+P114+P115) -> 277457.93 | R117: =S110 -> 0 | U117: =IF($T$55="IRR",IRR(V117:AA117),SUMIF(V117:AA117,">0")/-SUMIF(V117:AA117,"<0")) -> 0 | V117: =IF(V111="","",-V113+V115) -> -3739084.6 | W117: =IF(W111="","",-W113+W114+W115) -> 332360.73 | X117: =IF(X111="","",-X113+X114+X115) -> 344827.26 | Y117: =IF(Y111="","",-Y113+Y114+Y115) -> 357543.13 | Z117: =IF(Z111="","",-Z113+Z114+Z115) -> 370513.32 | AA117: =IF(AA111="","",-AA113+AA114+AA115) -> 2333840.2
...

Sheet Refinance Analysis
B2: Assumptions | E2: Amortization Calculator | O2: Amortization Summary | S2: Project Name | W2: Loan Covenant Analysis
B3: Loan Amortization | E3: Construction Loan | O3: Year | P3: Principle | Q3: Interest | S3: Project Capitalization | W3: Refinance
B4: Loan Months | C4: 360 | E4: Period | F4: Month | G4: Beginning Balance | H4: Payment | I4: Principal | J4: Interest | K4: Cumulative Principal | L4: Cumulative Interest | M4: Ending Balance | O4: Year 1 | P4: =SUM(I5:I16) -> 113826.35 | Q4: =SUM(J5:J16) -> 381098.17 | W4: Month Ending | X4: =F5 -> 46053 | Y4: =EOMONTH(X4,1) -> 46081 | Z4: =EOMONTH(Y4,1) -> 46112 | AA4: =EOMONTH(Z4,1) -> 46142 | AB4: =EOMONTH(AA4,1) -> 46173 | AC4: =EOMONTH(AB4,1) -> 46203 | AD4: =EOMONTH(AC4,1) -> 46234 | AE4: =EOMONTH(AD4,1) -> 46265 | AF4: =EOMONTH(AE4,1) -> 46295 | ... FS4: =EOMONTH(FR4,1) -> 50648
B5: Amortization Months | C5: 360 | E5: =1 -> 1 | F5: 46053 | G5: =C8 -> 7695392.6 | H5: =J5+I5 -> 41243.71 | I5: =IF(E5<=$C$6,0,$C$12-J5) -> 9270.7178 | J5: =G5*($C$9/12) -> 31972.992 | K5: =I5 -> 9270.7178 | L5: =J5 -> 31972.992 | M5: =G5-I5 -> 7686121.8 | O5: Year 2 | P5: =SUM(I17:I28) -> 119632.99 | Q5: =SUM(J17:J28) -> 375291.53 | S5: Total Capitalization | T5: =MIN(T18,T23,T32) -> 7695392.6
B6: Interest Only Months | C6: 0 | E6: =1+E5 -> 2 | F6: =EOMONTH(F5,1) -> 46081 | G6: =M5 -> 7686121.8 | H6: =J6+I6 -> 41243.71 | I6: =IF(E6<=$C$6,0,$C$12-J6) -> 9309.236 | J6: =G6*($C$9/12) -> 31934.474 | K6: =I6+K5 -> 18579.954 | L6: =L5+J6 -> 63907.466 | M6: =G6-I6 -> 7676812.6 | O6: Year 3 | P6: =SUM(I29:I40) -> 125735.84 | Q6: =SUM(J29:J40) -> 369188.68 | W6: Base Rent | X6: ='Property CF'!AW12/12 -> 57715.444 | Y6: =X6 -> 57715.444 | Z6: =Y6 -> 57715.444 | AA6: =Z6 -> 57715.444 | AB6: =AA6 -> 57715.444 | AC6: =AB6 -> 57715.444 | AD6: =AC6 -> 57715.444 | AE6: =AD6 -> 57715.444 | AF6: =AE6 -> 57715.444 | ... AI6: =AH6 -> 57715.444 | AJ6: =X6*(1+'Property CF'!$AS$13) -> 58869.753 | AK6: =Y6*(1+'Property CF'!$AS$13) -> 58869.753 | AL6: =Z6*(1+'Property CF'!$AS$13) -> 58869.753 | AM6: =AA6*(1+'Property CF'!$AS$13) -> 58869.753 | AN6: =AB6*(1+'Property CF'!$AS$13) -> 58869.753 | AO6: =AC6*(1+'Property CF'!$AS$13) -> 58869.753 | AP6: =AD6*(1+'Property CF'!$AS$13) -> 58869.753 | AQ6: =AE6*(1+'Property CF'!$AS$13) -> 58869.753 | ... FR6: =FF6*(1+'Property CF'!$AS$13) -> 73197.139 | FS6: =FR6 -> 73197.139
E7: =1+E6 -> 3 | F7: =EOMONTH(F6,1) -> 46112 | G7: =M6 -> 7676812.6 | H7: =J7+I7 -> 41243.71 | I7: =IF(E7<=$C$6,0,$C$12-J7) -> 9347.9142 | J7: =G7*($C$9/12) -> 31895.796 | K7: =I7+K6 -> 27927.868 | L7: =L6+J7 -> 95803.262 | M7: =G7-I7 -> 7667464.7 | O7: Year 4 | P7: =SUM(I41:I52) -> 132150.02 | Q7: =SUM(J41:J52) -> 362774.5 | S7: =+"Total Loan Amount @ "&(TEXT(U7,"0.00% LTC")) -> Total Loan Amount @ 100.00% LTC | T7: =T5*U7 -> 7695392.6 | U7: 1 | W7: NOI | X7: =X6 -> 57715.444 | Y7: =Y6 -> 57715.444 | Z7: =Z6 -> 57715.444 | AA7: =AA6 -> 57715.444 | AB7: =AB6 -> 57715.444 | AC7: =AC6 -> 57715.444 | AD7: =AD6 -> 57715.444 | AE7: =AE6 -> 57715.444 | ... FS7: =FS6 -> 73197.139
B8: Loan Amount | C8: =T7 -> 7695392.6 | E8: =1+E7 -> 4 | F8: =EOMONTH(F7,1) -> 46142 | G8: =M7 -> 7667464.7 | H8: =J8+I8 -> 41243.71 | I8: =IF(E8<=$C$6,0,$C$12-J8) -> 9386.7531 | J8: =G8*($C$9/12) -> 31856.957 | K8: =I8+K7 -> 37314.621 | L8: =L7+J8 -> 127660.22 | M8: =G8-I8 -> 7658077.9 | O8: Year 5 | P8: =SUM(I53:I64) -> 138891.41 | Q8: =SUM(J53:J64) -> 356033.11 | S8: =+"Equity Contribution @ "&(TEXT(U8,"0.00% LTC")) -> Equity Contribution @ 0.00% LTC | T8: =T5*U8 -> 0 | U8: =1-U7 -> 0
B9: Interest Rate | C9: =T27 -> 0.049857873 | E9: =1+E8 -> 5 | F9: =EOMONTH(F8,1) -> 46173 | G9: =M8 -> 7658077.9 | H9: =J9+I9 -> 41243.71 | I9: =IF(E9<=$C$6,0,$C$12-J9) -> 9425.7534 | J9: =G9*($C$9/12) -> 31817.957 | K9: =I9+K8 -> 46740.374 | L9: =L8+J9 -> 159478.18 | M9: =G9-I9 -> 7648652.2 | O9: Year 6 | P9: =SUM(I65:I76) -> 145976.7 | Q9: =SUM(J65:J76) -> 348947.82 | W9: All-In Interest Rate | X9: 0.05 | Y9: =X9 -> 0.05 | Z9: =Y9 -> 0.05 | AA9: =Z9 -> 0.05 | AB9: =AA9 -> 0.05 | AC9: =AB9 -> 0.05 | AD9: =AC9 -> 0.05 | AE9: =AD9 -> 0.05 | AF9: =AE9 -> 0.05 | ... FS9: =FR9 -> 0.05
B10: Months | C10: 360 | E10: =1+E9 -> 6 | F10: =EOMONTH(F9,1) -> 46203 | G10: =M9 -> 7648652.2 | H10: =J10+I10 -> 41243.71 | I10: =IF(E10<=$C$6,0,$C$12-J10) -> 9464.9157 | J10: =G10*($C$9/12) -> 31778.794 | K10: =I10+K9 -> 56205.29 | L10: =L9+J10 -> 191256.97 | M10: =G10-I10 -> 7639187.3 | O10: Year 7 | P10: =SUM(I77:I88) -> 153423.42 | Q10: =SUM(J77:J88) -> 341501.1 | S10: Preferred Return | T10: 0
E11: =1+E10 -> 7 | F11: =EOMONTH(F10,1) -> 46234 | G11: =M10 -> 7639187.3 | H11: =J11+I11 -> 41243.71 | I11: =IF(E11<=$C$6,0,$C$12-J11) -> 9504.2408 | J11: =G11*($C$9/12) -> 31739.469 | K11: =I11+K10 -> 65709.531 | L11: =L10+J11 -> 222996.44 | M11: =G11-I11 -> 7629683 | O11: Year 8 | P11: =SUM(I89:I100) -> 161250.03 | Q11: =SUM(J89:J100) -> 333674.49 | W11: Debt Yield (Trailing 12-Month NOI) | X11: =T21 -> 0.09 | Y11: =X11 -> 0.09 | Z11: =Y11 -> 0.09 | AA11: =Z11 -> 0.09 | AB11: =AA11 -> 0.09 | AC11: =AB11 -> 0.09 | AD11: =AC11 -> 0.09 | AE11: =AD11 -> 0.09 | AF11: =AE11 -> 0.09 | ... FS11: =FR11 -> 0.09
B12: Monthly Payment | C12: =ROUND(PMT($C$9/12,$C$10,-$C$8,0), 2) -> 41243.71 | E12: =1+E11 -> 8 | F12: =EOMONTH(F11,1) -> 46265 | G12: =M11 -> 7629683 | H12: =J12+I12 -> 41243.71 | I12: =IF(E12<=$C$6,0,$C$12-J12) -> 9543.7292 | J12: =G12*($C$9/12) -> 31699.981 | K12: =I12+K11 -> 75253.26 | L12: =L11+J12 -> 254696.42 | M12: =G12-I12 -> 7620139.3 | O12: Year 9 | P12: =SUM(I101:I112) -> 169475.9 | Q12: =SUM(J101:J112) -> 325448.62 | S12: Permanent Loan Amount Analysis | W12: Maximum Loan Size | X12: -- | Y12: -- | Z12: -- | AA12: -- | AB12: -- | AC12: -- | AD12: -- | AE12: -- | AF12: -- | AG12: -- | AH12: -- | AI12: =SUM(X7:AI7)/AI11 -> 7695392.6 | AJ12: =SUM(Y7:AJ7)/AJ11 -> 7708218.2 | AK12: =SUM(Z7:AK7)/AK11 -> 7721043.9 | AL12: =SUM(AA7:AL7)/AL11 -> 7733869.5 | AM12: =SUM(AB7:AM7)/AM11 -> 7746695.2 | AN12: =SUM(AC7:AN7)/AN11 -> 7759520.8 | AO12: =SUM(AD7:AO7)/AO11 -> 7772346.5 | AP12: =SUM(AE7:AP7)/AP11 -> 7785172.1 | ... FS12: =SUM(FH7:FS7)/FS11 -> 9695830.1
B13: Yearly Payment | C13: =C12*12 -> 494924.52 | E13: =1+E12 -> 9 | F13: =EOMONTH(F12,1) -> 46295 | G13: =M12 -> 7620139.3 | H13: =J13+I13 -> 41243.71 | I13: =IF(E13<=$C$6,0,$C$12-J13) -> 9583.3817 | J13: =G13*($C$9/12) -> 31660.328 | K13: =I13+K12 -> 84836.642 | L13: =L12+J13 -> 286356.75 | M13: =G13-I13 -> 7610555.9 | O13: Year 10 | P13: =SUM(I113:I124) -> 178121.4 | Q13: =SUM(J113:J124) -> 316803.12 | S13: As of Disposition Date (12/31/2025)
E14: =1+E13 -> 10 | F14: =EOMONTH(F13,1) -> 46326 | G14: =M13 -> 7610555.9 | H14: =J14+I14 -> 41243.71 | I14: =IF(E14<=$C$6,0,$C$12-J14) -> 9623.199 | J14: =G14*($C$9/12) -> 31620.511 | K14: =I14+K13 -> 94459.841 | L14: =L13+J14 -> 317977.26 | M14: =G14-I14 -> 7600932.7 | O14: Year 11 | P14: =SUM(I125:I136) -> 187207.93 | Q14: =SUM(J125:J136) -> 307716.59 | W14: Appraised Value Cap Rate (Forward 12-Month NOI) | X14: 0.06 | Y14: =X14 -> 0.06 | Z14: =Y14 -> 0.06 | AA14: =Z14 -> 0.06 | AB14: =AA14 -> 0.06 | AC14: =AB14 -> 0.06 | AD14: =AC14 -> 0.06 | AE14: =AD14 -> 0.06 | AF14: =AE14 -> 0.06 | ... FS14: =FR14 -> 0.06
B15: Year 1 Loan Constant | C15: =SUM(P4:Q4)/C8 -> 0.064314395 | E15: =1+E14 -> 11 | F15: =EOMONTH(F14,1) -> 46356 | G15: =M14 -> 7600932.7 | H15: =J15+I15 -> 41243.71 | I15: =IF(E15<=$C$6,0,$C$12-J15) -> 9663.1817 | J15: =G15*($C$9/12) -> 31580.528 | K15: =I15+K14 -> 104123.02 | L15: =L14+J15 -> 349557.79 | M15: =G15-I15 -> 7591269.5 | O15: Year 12 | P15: =SUM(I137:I148) -> 196757.99 | Q15: =SUM(J137:J148) -> 298166.53 | S15: Loan-to-Value Method | W15: Maximum Loan-to-Value | X15: =T17 -> 0.7 | Y15: =X15 -> 0.7 | Z15: =Y15 -> 0.7 | AA15: =Z15 -> 0.7 | AB15: =AA15 -> 0.7 | AC15: =AB15 -> 0.7 | AD15: =AC15 -> 0.7 | AE15: =AD15 -> 0.7 | AF15: =AE15 -> 0.7 | ... FS15: =FR15 -> 0.7
B16: Year 1 Payment | C16: =SUM(P4:Q4) -> 494924.52 | E16: =1+E15 -> 12 | F16: =EOMONTH(F15,1) -> 46387 | G16: =M15 -> 7591269.5 | H16: =J16+I16 -> 41243.71 | I16: =IF(E16<=$C$6,0,$C$12-J16) -> 9703.3305 | J16: =G16*($C$9/12) -> 31540.38 | K16: =I16+K15 -> 113826.35 | L16: =L15+J16 -> 381098.17 | M16: =G16-I16 -> 7581566.2 | O16: Year 13 | P16: =SUM(I149:I160) -> 206795.23 | Q16: =SUM(J149:J160) -> 288129.29 | S16: Appraised Value | T16: =(SUM(X7:AI7)/X14) -> 11543089 | W16: Maximum Loan Size | X16: =(SUM(X7:AI7)/X14)*X15 -> 8080162.2 | Y16: =(SUM(Y7:AJ7)/Y14)*Y15 -> 8093629.1 | Z16: =(SUM(Z7:AK7)/Z14)*Z15 -> 8107096.1 | AA16: =(SUM(AA7:AL7)/AA14)*AA15 -> 8120563 | AB16: =(SUM(AB7:AM7)/AB14)*AB15 -> 8134029.9 | AC16: =(SUM(AC7:AN7)/AC14)*AC15 -> 8147496.9 | AD16: =(SUM(AD7:AO7)/AD14)*AD15 -> 8160963.8 | AE16: =(SUM(AE7:AP7)/AE14)*AE15 -> 8174430.7 | ... FH16: =(SUM(FH7:FS7)/FH14)*FH15 -> 10180622 | FI16: -- | FJ16: =FI16 -> -- | FK16: =FJ16 -> -- | FL16: =FK16 -> -- | FM16: =FL16 -> -- | FN16: =FM16 -> -- | FO16: =FN16 -> -- | FP16: =FO16 -> -- | FQ16: =FP16 -> -- | ... FS16: =FR16 -> --
B17: Year 1 % Interest | C17: =(Q4)/(P4+Q4) -> 0.7700127 | E17: =1+E16 -> 13 | F17: =EOMONTH(F16,1) -> 46418 | G17: =M16 -> 7581566.2 | H17: =J17+I17 -> 41243.71 | I17: =IF(E17<=$C$6,0,$C$12-J17) -> 9743.6461 | J17: =G17*($C$9/12) -> 31500.064 | K17: =I17+K16 -> 123570 | L17: =L16+J17 -> 412598.23 | M17: =G17-I17 -> 7571822.6 | S17: Maximum Loan-to-Value Covenant | T17: 0.7
B18: Year 1 % Principle | C18: =P4/(P4+Q4) -> 0.2299873 | E18: =1+E17 -> 14 | F18: =EOMONTH(F17,1) -> 46446 | G18: =M17 -> 7571822.6 | H18: =J18+I18 -> 41243.71 | I18: =IF(E18<=$C$6,0,$C$12-J18) -> 9784.1292 | J18: =G18*($C$9/12) -> 31459.581 | K18: =I18+K17 -> 133354.13 | L18: =L17+J18 -> 444057.81 | M18: =G18-I18 -> 7562038.4 | S18: Maximum Loan | T18: =T16*T17 -> 8080162.2 | W18: Minimum DSCR | X18: =T26 -> 1.25 | Y18: =X18 -> 1.25 | Z18: =Y18 -> 1.25 | AA18: =Z18 -> 1.25 | AB18: =AA18 -> 1.25 | AC18: =AB18 -> 1.25 | AD18: =AC18 -> 1.25 | AE18: =AD18 -> 1.25 | AF18: =AE18 -> 1.25 | ... FS18: =FR18 -> 1.25
E19: =1+E18 -> 15 | F19: =EOMONTH(F18,1) -> 46477 | G19: =M18 -> 7562038.4 | H19: =J19+I19 -> 41243.71 | I19: =IF(E19<=$C$6,0,$C$12-J19) -> 9824.7805 | J19: =G19*($C$9/12) -> 31418.929 | K19: =I19+K18 -> 143178.91 | L19: =L18+J19 -> 475476.74 | M19: =G19-I19 -> 7552213.7 | W19: Maximum Yearly Payment | X19: =SUM(X7:AI7)/X18 -> 554068.26 | Y19: =SUM(Y7:AJ7)/Y18 -> 554991.71 | Z19: =SUM(Z7:AK7)/Z18 -> 555915.16 | AA19: =SUM(AA7:AL7)/AA18 -> 556838.61 | AB19: =SUM(AB7:AM7)/AB18 -> 557762.05 | AC19: =SUM(AC7:AN7)/AC18 -> 558685.5 | AD19: =SUM(AD7:AO7)/AD18 -> 559608.95 | AE19: =SUM(AE7:AP7)/AE18 -> 560532.39 | ... FH19: =SUM(FH7:FS7)/FH18 -> 698099.77 | FI19: =SUM(FI5:FT5)/FI18 -> 0 | FJ19: =SUM(FJ5:FU5)/FJ18 -> 0 | FK19: =SUM(FK5:FV5)/FK18 -> 0 | FL19: =SUM(FL5:FW5)/FL18 -> 0 | FM19: =SUM(FM5:FX5)/FM18 -> 0 | FN19: =SUM(FN5:FY5)/FN18 -> 0 | FO19: =SUM(FO5:FZ5)/FO18 -> 0 | FP19: =SUM(FP5:GA5)/FP18 -> 0 | ... FS19: =SUM(FS5:GD5)/FS18 -> 0
B20: Year 6 Loan Constant | C20: =SUM(P9:Q9)/C8 -> 0.064314395 | E20: =1+E19 -> 16 | F20: =EOMONTH(F19,1) -> 46507 | G20: =M19 -> 7552213.7 | H20: =J20+I20 -> 41243.71 | I20: =IF(E20<=$C$6,0,$C$12-J20) -> 9865.6008 | J20: =G20*($C$9/12) -> 31378.109 | K20: =I20+K19 -> 153044.51 | L20: =L19+J20 -> 506854.85 | M20: =G20-I20 -> 7542348 | S20: Debt Yield Method | W20: Loan Constant | X20: =(X9/12)/(1 - (1 / (1 + X9/12))^$T$28)*12 -> 0.06756468 | Y20: =(Y9/12)/(1 - (1 / (1 + Y9/12))^$T$28)*12 -> 0.06756468 | Z20: =(Z9/12)/(1 - (1 / (1 + Z9/12))^$T$28)*12 -> 0.06756468 | AA20: =(AA9/12)/(1 - (1 / (1 + AA9/12))^$T$28)*12 -> 0.06756468 | AB20: =(AB9/12)/(1 - (1 / (1 + AB9/12))^$T$28)*12 -> 0.06756468 | AC20: =(AC9/12)/(1 - (1 / (1 + AC9/12))^$T$28)*12 -> 0.06756468 | AD20: =(AD9/12)/(1 - (1 / (1 + AD9/12))^$T$28)*12 -> 0.06756468 | AE20: =(AE9/12)/(1 - (1 / (1 + AE9/12))^$T$28)*12 -> 0.06756468 | ... FS20: =(FS9/12)/(1 - (1 / (1 + FS9/12))^$T$28)*12 -> 0.06756468
B21: Year 6 Payment | C21: =SUM(P9:Q9) -> 494924.52 | E21: =1+E20 -> 17 | F21: =EOMONTH(F20,1) -> 46538 | G21: =M20 -> 7542348 | H21: =J21+I21 -> 41243.71 | I21: =IF(E21<=$C$6,0,$C$12-J21) -> 9906.5906 | J21: =G21*($C$9/12) -> 31337.119 | K21: =I21+K20 -> 162951.1 | L21: =L20+J21 -> 538191.97 | M21: =G21-I21 -> 7532441.5 | S21: Minimum Debt Yield Covenant | T21: 0.09 | W21: Maximum Loan Amount | X21: =X19/X20 -> 8200560.8 | Y21: =Y19/Y20 -> 8214228.4 | Z21: =Z19/Z20 -> 8227896 | AA21: =AA19/AA20 -> 8241563.6 | AB21: =AB19/AB20 -> 8255231.2 | AC21: =AC19/AC20 -> 8268898.8 | AD21: =AD19/AD20 -> 8282566.4 | AE21: =AE19/AE20 -> 8296234 | ... FH21: =FH19/FH20 -> 10332318 | FI21: -- | FJ21: =FI21 -> -- | FK21: =FJ21 -> -- | FL21: =FK21 -> -- | FM21: =FL21 -> -- | FN21: =FM21 -> -- | FO21: =FN21 -> -- | FP21: =FO21 -> -- | FQ21: =FP21 -> -- | ... FS21: =FR21 -> --
B22: Year 6 % Interest | C22: =(Q9)/(P9+Q9) -> 0.70505261 | E22: =1+E21 -> 18 | F22: =EOMONTH(F21,1) -> 46568 | G22: =M21 -> 7532441.5 | H22: =J22+I22 -> 41243.71 | I22: =IF(E22<=$C$6,0,$C$12-J22) -> 9947.7507 | J22: =G22*($C$9/12) -> 31295.959 | K22: =I22+K21 -> 172898.85 | L22: =L21+J22 -> 569487.93 | M22: =G22-I22 -> 7522493.7 | S22: 12-Month Trailing NOI | T22: ='Property CF'!AW12 -> 692585.33
B23: Year 6 % Principle | C23: =P9/(P9+Q9) -> 0.29494739 | E23: =1+E22 -> 19 | F23: =EOMONTH(F22,1) -> 46599 | G23: =M22 -> 7522493.7 | H23: =J23+I23 -> 41243.71 | I23: =IF(E23<=$C$6,0,$C$12-J23) -> 9989.0819 | J23: =G23*($C$9/12) -> 31254.628 | K23: =I23+K22 -> 182887.93 | L23: =L22+J23 -> 600742.56 | M23: =G23-I23 -> 7512504.6 | S23: Maximum Loan | T23: =T22/T21 -> 7695392.6 | W23: Permanent Loan Amount | X23: {=TRANSPOSE(M5:M156)+$C$38} -> 10478116 | Y23: 10468806 | Z23: 10459458 | AA23: 10450072 | AB23: 10440646 | AC23: 10431181 | AD23: 10421677 | AE23: 10412133 | AF23: 10402550 | AG23: 10392926 | AH23: 10383263 | AI23: 10373560 | AJ23: 10363816 | AK23: 10354032 | AL23: 10344207 | AM23: 10334342 | AN23: 10324435 | AO23: 10314487 | AP23: 10304498 | AQ23: 10294468 | AR23: 10284395 | AS23: 10274281 | AT23: 10264125 | AU23: 10253927 | AV23: 10243686 | AW23: 10233403 | AX23: 10223077 | AY23: 10212708 | AZ23: 10202296 | BA23: 10191841 | BB23: 10181342 | BC23: 10170800 | BD23: 10160214 | BE23: 10149584 | BF23: 10138910 | BG23: 10128191 | BH23: 10117428 | BI23: 10106620 | BJ23: 10095767 | BK23: 10084870 | BL23: 10073926 | BM23: 10062938 | BN23: 10051904 | BO23: 10040824 | BP23: 10029697 | BQ23: 10018525 | BR23: 10007306 | BS23: 9996041 | BT23: 9984728.9 | BU23: 9973369.7 | BV23: 9961963.3 | BW23: 9950509.6 | BX23: 9939008.2 | BY23: 9927459.1 | BZ23: 9915862 | CA23: 9904216.7 | CB23: 9892523 | CC23: 9880780.7 | CD23: 9868989.7 | CE23: 9857149.6 | CF23: 9845260.4 | CG23: 9833321.8 | CH23: 9821333.5 | CI23: 9809295.5 | CJ23: 9797207.4 | CK23: 9785069.1 | CL23: 9772880.4 | CM23: 9760641 | CN23: 9748350.8 | CO23: 9736009.5 | CP23: 9723617 | CQ23: 9711172.9 | CR23: 9698677.2 | CS23: 9686129.5 | CT23: 9673529.7 | CU23: 9660877.6 | CV23: 9648172.9 | CW23: 9635415.4 | CX23: 9622604.9 | CY23: 9609741.1 | CZ23: 9596824 | DA23: 9583853.1 | DB23: 9570828.4 | DC23: 9557749.5 | DD23: 9544616.3 | DE23: 9531428.6 | DF23: 9518186 | DG23: 9504888.4 | DH23: 9491535.6 | DI23: 9478127.3 | DJ23: 9464663.3 | DK23: 9451143.4 | DL23: 9437567.2 | DM23: 9423934.7 | DN23: 9410245.5 | DO23: 9396499.5 | DP23: 9382696.3 | DQ23: 9368835.8 | DR23: 9354917.7 | DS23: 9340941.8 | DT23: 9326907.8 | DU23: 9312815.5 | DV23: 9298664.7 | DW23: 9284455 | DX23: 9270186.3 | DY23: 9255858.4 | DZ23: 9241470.9 | EA23: 9227023.6 | EB23: 9212516.3 | EC23: 9197948.7 | ED23: 9183320.6 | EE23: 9168631.7 | EF23: 9153881.8 | EG23: 9139070.6 | EH23: 9124197.9 | EI23: 9109263.4 | EJ23: 9094266.8 | EK23: 9079207.9 | EL23: 9064086.5 | EM23: 9048902.2 | EN23: 9033654.8 | EO23: 9018344.1 | EP23: 9002969.8 | EQ23: 8987531.6 | ER23: 8972029.2 | ES23: 8956462.5 | ET23: 8940831 | EU23: 8925134.7 | EV23: 8909373.1 | EW23: 8893546 | EX23: 8877653.1 | EY23: 8861694.3 | EZ23: 8845669.1 | FA23: 8829577.3 | FB23: 8813418.7 | FC23: 8797192.9 | FD23: 8780899.8 | FE23: 8764538.9 | FF23: 8748110.1 | FG23: 8731613 | FH23: 8715047.3 | FI23: 8698412.8 | FJ23: 8681709.3 | FK23: 8664936.3 | FL23: 8648093.6 | FM23: 8631180.9 | FN23: 8614198 | FO23: 8597144.5 | FP23: 8580020.2 | FQ23: 8562824.7 | FR23: 8545557.8 | FS23: 8528219.1
E24: =1+E23 -> 20 | F24: =EOMONTH(F23,1) -> 46630 | G24: =M23 -> 7512504.6 | H24: =J24+I24 -> 41243.71 | I24: =IF(E24<=$C$6,0,$C$12-J24) -> 10030.585 | J24: =G24*($C$9/12) -> 31213.125 | K24: =I24+K23 -> 192918.52 | L24: =L23+J24 -> 631955.68 | M24: =G24-I24 -> 7502474
B25: Balloon Payment | C25: =VLOOKUP(C4,E5:M364,9) -> 2.9038194 | E25: =1+E24 -> 21 | F25: =EOMONTH(F24,1) -> 46660 | G25: =M24 -> 7502474 | H25: =J25+I25 -> 41243.71 | I25: =IF(E25<=$C$6,0,$C$12-J25) -> 10072.26 | J25: =G25*($C$9/12) -> 31171.45 | K25: =I25+K24 -> 202990.78 | L25: =L24+J25 -> 663127.13 | M25: =G25-I25 -> 7492401.8 | S25: DSCR Method
E26: =1+E25 -> 22 | F26: =EOMONTH(F25,1) -> 46691 | G26: =M25 -> 7492401.8 | H26: =J26+I26 -> 41243.71 | I26: =IF(E26<=$C$6,0,$C$12-J26) -> 10114.108 | J26: =G26*($C$9/12) -> 31129.602 | K26: =I26+K25 -> 213104.89 | L26: =L25+J26 -> 694256.73 | M26: =G26-I26 -> 7482287.7 | S26: Minimum DSCR | T26: 1.25
B27: Permanent Financing | E27: =1+E26 -> 23 | F27: =EOMONTH(F26,1) -> 46721 | G27: =M26 -> 7482287.7 | H27: =J27+I27 -> 41243.71 | I27: =IF(E27<=$C$6,0,$C$12-J27) -> 10156.131 | J27: =G27*($C$9/12) -> 31087.579 | K27: =I27+K26 -> 223261.02 | L27: =L26+J27 -> 725344.31 | M27: =G27-I27 -> 7472131.5 | S27: All-In Interest Rate | T27: =2%+'Offering Memorandum'!BF39 -> 0.049857873
B28: Loan Back-Up Calculation | E28: =1+E27 -> 24 | F28: =EOMONTH(F27,1) -> 46752 | G28: =M27 -> 7472131.5 | H28: =J28+I28 -> 41243.71 | I28: =IF(E28<=$C$6,0,$C$12-J28) -> 10198.328 | J28: =G28*($C$9/12) -> 31045.382 | K28: =I28+K27 -> 233459.34 | L28: =L27+J28 -> 756389.7 | M28: =G28-I28 -> 7461933.2 | S28: Amortization Months | T28: 324
B29: Development Budget | C29: =Budget!E31 -> 10395210 | E29: =1+E28 -> 25 | F29: =EOMONTH(F28,1) -> 46783 | G29: =M28 -> 7461933.2 | H29: =J29+I29 -> 41243.71 | I29: =IF(E29<=$C$6,0,$C$12-J29) -> 10240.7 | J29: =G29*($C$9/12) -> 31003.01 | K29: =I29+K28 -> 243700.04 | L29: =L28+J29 -> 787392.71 | M29: =G29-I29 -> 7451692.5 | S29: 12-Month Forward NOI | T29: =SUM(X7:AI7) -> 692585.33
B30: Accrued Preferred Return | C30: ='Property CF'!AN132 -> 0 | E30: =1+E29 -> 26 | F30: =EOMONTH(F29,1) -> 46812 | G30: =M29 -> 7451692.5 | H30: =J30+I30 -> 41243.71 | I30: =IF(E30<=$C$6,0,$C$12-J30) -> 10283.248 | J30: =G30*($C$9/12) -> 30960.462 | K30: =I30+K29 -> 253983.29 | L30: =L29+J30 -> 818353.17 | M30: =G30-I30 -> 7441409.3 | S30: Maximum Yearly Payment | T30: =T29/T26 -> 554068.26
B31: Loan Closing Costs | C31: 40000 | E31: =1+E30 -> 27 | F31: =EOMONTH(F30,1) -> 46843 | G31: =M30 -> 7441409.3 | H31: =J31+I31 -> 41243.71 | I31: =IF(E31<=$C$6,0,$C$12-J31) -> 10325.973 | J31: =G31*($C$9/12) -> 30917.737 | K31: =I31+K30 -> 264309.27 | L31: =L30+J31 -> 849270.9 | M31: =G31-I31 -> 7431083.3 | S31: Loan Constant | T31: =(T27/12)/(1 - (1 / (1 + T27/12))^T28)*12 -> 0.067463366
B32: Lender Origination Fee | C32: =SUM(C29:C31)*Budget!S28 -> 52176.051 | E32: =1+E31 -> 28 | F32: =EOMONTH(F31,1) -> 46873 | G32: =M31 -> 7431083.3 | H32: =J32+I32 -> 41243.71 | I32: =IF(E32<=$C$6,0,$C$12-J32) -> 10368.876 | J32: =G32*($C$9/12) -> 30874.834 | K32: =I32+K31 -> 274678.14 | L32: =L31+J32 -> 880145.74 | M32: =G32-I32 -> 7420714.4 | S32: Maximum Loan | T32: =T30/T31 -> 8212876
B33: Unreturned Equity | C33: =C34-SUM(C29:C32) -> -2791993.7 | E33: =1+E32 -> 29 | F33: =EOMONTH(F32,1) -> 46904 | G33: =M32 -> 7420714.4 | H33: =J33+I33 -> 41243.71 | I33: =IF(E33<=$C$6,0,$C$12-J33) -> 10411.957 | J33: =G33*($C$9/12) -> 30831.753 | K33: =I33+K32 -> 285090.1 | L33: =L32+J33 -> 910977.49 | M33: =G33-I33 -> 7410302.5
B34: Total | C34: =C8 -> 7695392.6 | E34: =1+E33 -> 30 | F34: =EOMONTH(F33,1) -> 46934 | G34: =M33 -> 7410302.5 | H34: =J34+I34 -> 41243.71 | I34: =IF(E34<=$C$6,0,$C$12-J34) -> 10455.217 | J34: =G34*($C$9/12) -> 30788.493 | K34: =I34+K33 -> 295545.32 | L34: =L33+J34 -> 941765.98 | M34: =G34-I34 -> 7399847.2
E35: =1+E34 -> 31 | F35: =EOMONTH(F34,1) -> 46965 | G35: =M34 -> 7399847.2 | H35: =J35+I35 -> 41243.71 | I35: =IF(E35<=$C$6,0,$C$12-J35) -> 10498.656 | J35: =G35*($C$9/12) -> 30745.054 | K35: =I35+K34 -> 306043.97 | L35: =L34+J35 -> 972511.04 | M35: =G35-I35 -> 7389348.6
B36: Accrued Preferred Return | E36: =1+E35 -> 32 | F36: =EOMONTH(F35,1) -> 46996 | G36: =M35 -> 7389348.6 | H36: =J36+I36 -> 41243.71 | I36: =IF(E36<=$C$6,0,$C$12-J36) -> 10542.276 | J36: =G36*($C$9/12) -> 30701.434 | K36: =I36+K35 -> 316586.25 | L36: =L35+J36 -> 1003212.5 | M36: =G36-I36 -> 7378806.3
B37: Preferred Return Calculation | E37: =1+E36 -> 33 | F37: =EOMONTH(F36,1) -> 47026 | G37: =M36 -> 7378806.3 | H37: =J37+I37 -> 41243.71 | I37: =IF(E37<=$C$6,0,$C$12-J37) -> 10586.078 | J37: =G37*($C$9/12) -> 30657.632 | K37: =I37+K36 -> 327172.33 | L37: =L36+J37 -> 1033870.1 | M37: =G37-I37 -> 7368220.2
B38: Unreturned Equity | C38: =-C33 -> 2791993.7 | E38: =1+E37 -> 34 | F38: =EOMONTH(F37,1) -> 47057 | G38: =M37 -> 7368220.2 | H38: =J38+I38 -> 41243.71 | I38: =IF(E38<=$C$6,0,$C$12-J38) -> 10630.061 | J38: =G38*($C$9/12) -> 30613.649 | K38: =I38+K37 -> 337802.39 | L38: =L37+J38 -> 1064483.8 | M38: =G38-I38 -> 7357590.2
B39: Total Accruing | C39: =SUM(C38:C38) -> 2791993.7 | E39: =1+E38 -> 35 | F39: =EOMONTH(F38,1) -> 47087 | G39: =M38 -> 7357590.2 | H39: =J39+I39 -> 41243.71 | I39: =IF(E39<=$C$6,0,$C$12-J39) -> 10674.227 | J39: =G39*($C$9/12) -> 30569.483 | K39: =I39+K38 -> 348476.61 | L39: =L38+J39 -> 1095053.2 | M39: =G39-I39 -> 7346915.9
B40: Preferred Return | C40: =C39*'Property CF'!$C$28 -> 307119.31 | E40: =1+E39 -> 36 | F40: =EOMONTH(F39,1) -> 47118 | G40: =M39 -> 7346915.9 | H40: =J40+I40 -> 41243.71 | I40: =IF(E40<=$C$6,0,$C$12-J40) -> 10718.576 | J40: =G40*($C$9/12) -> 30525.134 | K40: =I40+K39 -> 359195.19 | L40: =L39+J40 -> 1125578.4 | M40: =G40-I40 -> 7336197.4
E41: =1+E40 -> 37 | F41: =EOMONTH(F40,1) -> 47149 | G41: =M40 -> 7336197.4 | H41: =J41+I41 -> 41243.71 | I41: =IF(E41<=$C$6,0,$C$12-J41) -> 10763.11 | J41: =G41*($C$9/12) -> 30480.6 | K41: =I41+K40 -> 369958.3 | L41: =L40+J41 -> 1156059 | M41: =G41-I41 -> 7325434.3
E42: =1+E41 -> 38 | F42: =EOMONTH(F41,1) -> 47177 | G42: =M41 -> 7325434.3 | H42: =J42+I42 -> 41243.71 | I42: =IF(E42<=$C$6,0,$C$12-J42) -> 10807.829 | J42: =G42*($C$9/12) -> 30435.881 | K42: =I42+K41 -> 380766.13 | L42: =L41+J42 -> 1186494.9 | M42: =G42-I42 -> 7314626.4
E43: =1+E42 -> 39 | F43: =EOMONTH(F42,1) -> 47208 | G43: =M42 -> 7314626.4 | H43: =J43+I43 -> 41243.71 | I43: =IF(E43<=$C$6,0,$C$12-J43) -> 10852.734 | J43: =G43*($C$9/12) -> 30390.976 | K43: =I43+K42 -> 391618.86 | L43: =L42+J43 -> 1216885.8 | M43: =G43-I43 -> 7303773.7
E44: =1+E43 -> 40 | F44: =EOMONTH(F43,1) -> 47238 | G44: =M43 -> 7303773.7 | H44: =J44+I44 -> 41243.71 | I44: =IF(E44<=$C$6,0,$C$12-J44) -> 10897.825 | J44: =G44*($C$9/12) -> 30345.885 | K44: =I44+K43 -> 402516.69 | L44: =L43+J44 -> 1247231.7 | M44: =G44-I44 -> 7292875.9
E45: =1+E44 -> 41 | F45: =EOMONTH(F44,1) -> 47269 | G45: =M44 -> 7292875.9 | H45: =J45+I45 -> 41243.71 | I45: =IF(E45<=$C$6,0,$C$12-J45) -> 10943.103 | J45: =G45*($C$9/12) -> 30300.607 | K45: =I45+K44 -> 413459.79 | L45: =L44+J45 -> 1277532.3 | M45: =G45-I45 -> 7281932.8
E46: =1+E45 -> 42 | F46: =EOMONTH(F45,1) -> 47299 | G46: =M45 -> 7281932.8 | H46: =J46+I46 -> 41243.71 | I46: =IF(E46<=$C$6,0,$C$12-J46) -> 10988.57 | J46: =G46*($C$9/12) -> 30255.14 | K46: =I46+K45 -> 424448.36 | L46: =L45+J46 -> 1307787.5 | M46: =G46-I46 -> 7270944.2
E47: =1+E46 -> 43 | F47: =EOMONTH(F46,1) -> 47330 | G47: =M46 -> 7270944.2 | H47: =J47+I47 -> 41243.71 | I47: =IF(E47<=$C$6,0,$C$12-J47) -> 11034.225 | J47: =G47*($C$9/12) -> 30209.485 | K47: =I47+K46 -> 435482.59 | L47: =L46+J47 -> 1337996.9 | M47: =G47-I47 -> 7259910
E48: =1+E47 -> 44 | F48: =EOMONTH(F47,1) -> 47361 | G48: =M47 -> 7259910 | H48: =J48+I48 -> 41243.71 | I48: =IF(E48<=$C$6,0,$C$12-J48) -> 11080.071 | J48: =G48*($C$9/12) -> 30163.639 | K48: =I48+K47 -> 446562.66 | L48: =L47+J48 -> 1368160.6 | M48: =G48-I48 -> 7248829.9
E49: =1+E48 -> 45 | F49: =EOMONTH(F48,1) -> 47391 | G49: =M48 -> 7248829.9 | H49: =J49+I49 -> 41243.71 | I49: =IF(E49<=$C$6,0,$C$12-J49) -> 11126.106 | J49: =G49*($C$9/12) -> 30117.604 | K49: =I49+K48 -> 457688.76 | L49: =L48+J49 -> 1398278.2 | M49: =G49-I49 -> 7237703.8
E50: =1+E49 -> 46 | F50: =EOMONTH(F49,1) -> 47422 | G50: =M49 -> 7237703.8 | H50: =J50+I50 -> 41243.71 | I50: =IF(E50<=$C$6,0,$C$12-J50) -> 11172.333 | J50: =G50*($C$9/12) -> 30071.377 | K50: =I50+K49 -> 468861.1 | L50: =L49+J50 -> 1428349.6 | M50: =G50-I50 -> 7226531.5
E51: =1+E50 -> 47 | F51: =EOMONTH(F50,1) -> 47452 | G51: =M50 -> 7226531.5 | H51: =J51+I51 -> 41243.71 | I51: =IF(E51<=$C$6,0,$C$12-J51) -> 11218.753 | J51: =G51*($C$9/12) -> 30024.957 | K51: =I51+K50 -> 480079.85 | L51: =L50+J51 -> 1458374.5 | M51: =G51-I51 -> 7215312.7
E52: =1+E51 -> 48 | F52: =EOMONTH(F51,1) -> 47483 | G52: =M51 -> 7215312.7 | H52: =J52+I52 -> 41243.71 | I52: =IF(E52<=$C$6,0,$C$12-J52) -> 11265.364 | J52: =G52*($C$9/12) -> 29978.346 | K52: =I52+K51 -> 491345.21 | L52: =L51+J52 -> 1488352.9 | M52: =G52-I52 -> 7204047.3
... E364: =1+E363 -> 360 | F364: =EOMONTH(F363,1) -> 56979 | G364: =M363 -> 41075.951 | H364: =J364+I364 -> 41243.71 | I364: =IF(E364<=$C$6,0,$C$12-J364) -> 41073.047 | J364: =G364*($C$9/12) -> 170.66329 | K364: =I364+K363 -> 7695389.7 | L364: =L363+J364 -> 7152345.9 | M364: =G364-I364 -> 2.9038194

Sheet Strategy Summary
B2: Strategy Summary Page - Aspect Health, Inc. | E2: =TODAY() -> 46097
B4: Property Name: | C4: 1500 Boston Post Road, Darien | D4: Lender: | E4: Washington Trust or Union Savings Bank
B5: Property Size: | C5: =SF -> 18754 | D5: Loan Amount: | E5: =Budget!Q6 -> 6550000
B6: Year Built/Renovated: | C6: 1997 | D6: Debt Loan-to-Cost | E6: =Budget!S24 -> 0.64245855
B7: Land Area: | C7: 1.27 Acres | D7: Loan Term: | E7: 3 Year Fixed, Interest Only
B8: Tenants: | C8: 1 Tenant | D8: Loan Maturity | E8: 46203
B9: WALT: | C9: ='Offering Memorandum'!AF10 -> 5.0438356 | D9: Extension Requirement: | E9: No
B10: % Occupied: | C10: 1 | D10: Initial Equity: | E10: =Budget!Q7 -> 3551440.2
B11: % NNN: | C11: =C10 -> 1 | D11: Equity Loan-to-Cost: | E11: =1-E6 -> 0.35754145
B12: Stabilization Date: | C12: ='Property CF'!H7 -> 45120 | D12: Preferred Return: | E12: ='Property CF'!C28 -> 0.11
B13: Average Rental Rate: | C13: =Budget!F33 -> 35.436907 | D13: Equity Kicker: | E13: ='Property CF'!C30 -> 0.2
B14: Forward NOI: | C14: =C5*C13 -> 664583.76 | D14: Hold Period Begins Date: | E14: ='Property CF'!H7 -> 45120
B15: Development Budget: | C15: =Budget!E31 -> 10395210 | D15: Target Disposition Date: | E15: ='Property CF'!AN7 -> 46081
B16: Development Price per RSF: | C16: =C15/C5 -> 554.29296 | D16: Hold Period: | E16: ='Property CF'!AN5 -> 32
B17: Developer Yield: | C17: =C14/C15 -> 0.063931729 | D17: Target Acquirer: | E17: Healthcare REIT, 1031 Exchange, Private Equity
B19: Project Returns:
B21: Initial/Accrued Preferred Return at Disposition: | C21: ='Property CF'!AL132+'Property CF'!AL115 -> 4220564.4 | D21: Equity Kicker: | E21: ='Property CF'!AL139 -> 0
B22: Loan Amount at Disposition | C22: =E5 -> 6550000 | D22: Preferred Return | E22: =E26-E21 -> 801032.86
B23: Total Outstanding Funding: | C23: =E5+C21 -> 10770564 | D23: Average Current Pay from Stabilization: | E23: ='Property CF'!AK163 -> 0.050909655
B24: Hold Period Blended Cost of Capital: | C24: ='Property CF'!C35 -> 0.081093133 | D24: Preferred Equity Levered IRR | E24: ='Property CF'!F144 -> 0.089599493
B25: Forward Exit Year NOI: | C25: ='Property CF'!AW12 -> 692585.33 | D25: Preferred Equity Equity Multiple | E25: ='Property CF'!BJ30 -> 1.2056384
B26: Hold Period NOI Growth %: | C26: =(C25-C14)/C14 -> 0.042134 | D26: Preferred Equity Net Proceeds: | E26: ='Property CF'!BJ26 -> 801032.86
B27: Implied Exit Cap Rate: | C27: =C25/C23 -> 0.064303532 | D27: Aspect Net Proceeds: | E27: ='Property CF'!BJ34 -> 0
B28: Actual Exit Cap Rate | C28: ='Property CF'!AS14 -> 0.0595 | D28: Aspect Project Fees: | E28: ='Property CF'!BR15 -> 480321.99
B29: Accreditive Cap Spread: | C29: =C27-C28 -> 0.0048035317 | D29: Project Unlevered IRR: | E29: ='Property CF'!F51 -> 0.075689134
B30: Gross Exit Year Price: | C30: =C25/C28 -> 11640090 | D30: Project Levered IRR: | E30: ='Property CF'!F61 -> 0.089599493
B31: Cost of Sale: | C31: ='Property CF'!AS26 -> 0.05 | D31: Project Proceeds: | E31: ='Property CF'!BJ8 -> 801032.86
B32: Net Exit Year Price: | C32: ='Property CF'!AL49 -> 10806493 | D32: Project Equity Multiple: | E32: ='Property CF'!BJ11 -> 1.2056384
B33: Exit Year Price per RSF: | C33: =C30/C5 -> 620.67237 | D33: Average Cash-on-Cash: | E33: N/A
B34: Exit Year WALT: | C34: ='Property CF'!AS10 -> 15.25 | D34: Aspect Levered IRR: | E34: --
B35: Exit Year DSCR: | C35: N/A | D35: Aspect Equity Multiple: | E35: --
B37: Refinance Analysis:
B39: Analysis Date: | C39: =E15 -> 46081 | D39: Forward Exit Year NOI: | E39: =C25 -> 692585.33
B40: Minimum DSCR: | C40: ='Refinance Analysis'!T26 -> 1.25 | D40: Appraisal Cap Rate: | E40: ='Refinance Analysis'!X14 -> 0.06
B41: All-In Interest Rate: | C41: ='Refinance Analysis'!T27 -> 0.049857873 | D41: Appraised Value: | E41: =E39/E40 -> 11543089
B42: Amortization Months: | C42: ='Refinance Analysis'!T28 -> 324 | D42: Maximum Loan-to-Value Covenant: | E42: ='Refinance Analysis'!T17 -> 0.7
B43: 12-Month Forward NOI: | C43: =C25 -> 692585.33 | D43: Maximum Loan (Appraisal Method): | E43: =E41*E42 -> 8080162.2
B44: Maximum Yearly Payment: | C44: =C43/C40 -> 554068.26 | D44: Unreturned Equity: | E44: =-(E43-SUM('Refinance Analysis'!C29:C32)) -> 2407224.1
B45: Loan Constant: | C45: =(C41/12)/(1 - (1 / (1 + C41/12))^C42)*12 -> 0.067463366
B46: Maximum Loan (DSCR Method): | C46: =C44/C45 -> 8212876 | D46: Minimum Debt Yield Covenant: | E46: ='Refinance Analysis'!T21 -> 0.09
B47: Unreturned Equity: | C47: =-(C46-SUM('Refinance Analysis'!C29:C32)) -> 2274510.2 | D47: 12-Month Trailing NOI: | E47: ='Refinance Analysis'!T22 -> 692585.33
D48: Maximum Loan (Debt Yield Method): | E48: =E47/E46 -> 7695392.6
D49: Unreturned Equity: | E49: =-(E48-SUM('Refinance Analysis'!C29:C32)) -> 2791993.7
B51: Strategy Considerations:

Sheet Offering Memorandum
B2: Pro Forma | J2: Leasing Overview | T2: Comparable Medical Office Sale | AH2: Summary of Comparable Medical Office Leases | AT2: Permanent Financing | AW2: Covenant Analysis | AZ2: Rental Rate Calculation | BC2: Fixed Rate Swap Analysis | BS2: Lender Escrow | BV2: Capital Contribution Schedule | CC2: Next Buyer Analysis | CS2: Cap Rate Sensitivity Analysis | DF2: Cash-on-Cash Return | DR2: Levered Returns to Equity | DY2: Former Owner | EB2: Aspect Health | EG2: Former Owner
B3: (Beginning July 2023) | C3: 2023-2024 | D3: $ PSF | E3: 2024-2025 | F3: $ PSF | G3: 2025-2026 | H3: $ PSF | J3: Tenant | K3: Sq. Ft. | L3: % Bldg | M3: End | N3: $/PSF | O3: Annual | P3: Increases | Q3: Structure | R3: Term | T3: No. | U3: Property Name | V3: Sale Date | W3: Year Built | X3: Square Feet | Y3: Price | Z3: $ PSF | AA3: Cap Rate | AB3: NOI | AC3: Occupancy | AD3: Single/Multi Tenant | AE3: Anchor Tentant | AF3: Lease Term | AH3: No. | AI3: Property Name | AJ3: Year Built | AK3: Building SQFT | AL3: Lease Date | AM3: Lease SQFT | AN3: Rental Rate | AO3: Rent Steps | AP3: Tentant | AQ3: Lease Term | AR3: Lease Type | AT3: Permanent Loan Request | AW3: Key Underwriting Metrics | AZ3: CPI Index Adjustment | BC3: Number | BD3: Date | BE3: Loan Amount | BF3: Index Rate | BG3: Lender Spread | BH3: Profit Spread | BI3: Lender Consultant | BJ3: Dealer Fees | BK3: Floating Rate | BL3: Floating Interest | BM3: 3-Year Swap | BN3: Fixed Rate | BO3: Fixed Interest | BP3: NPV Floating | BQ3: NPV Fixed | BS3: Calculation | BV3: Preferred Investors | CC3: Next Buyer Returns | CS3: Net Sale Proceeds for Distribution | DF3: Quarterly Projections | DR3: Preferred Investors | DY3: 7 Year 4 Month Extension | EB3: 10 Year 0 Month Extension | EE3: 7 Year 4 Month Extension | EM3: 1
AW4: NOI | AX4: =Budget!E33 -> 664583.76 | AZ4: Index as of 11/2018 | BA4: 252.594 | BC4: 1 | BD4: ='Forward Curve'!A2 -> 45211 | BE4: =Budget!Q24 -> 6550000 | BF4: ='Forward Curve'!B2 -> 0.0533 | BG4: 0.019 | BH4: 0.002 | BI4: 0.0006 | BJ4: 0.001 | BK4: =BF4+BG4+BH4+BI4+BJ4 -> 0.0759 | BL4: =BK4*(_xlfn.DAYS(BD5,BD4)/360)*BE4 -> 42809.708 | BM4: =BN4-BG4-BH4-BI4-BJ4 -> 0.0411 | BN4: 0.0637 | BO4: =BN4*(_xlfn.DAYS(BD5,BD4)/360)*BE4 -> 35928.569 | BP4: =NPV((1+BK4)^(BC4/12)-1,BL4:BL4) -> 42549.515 | BQ4: =NPV((1+BK4)^(BC4/12)-1,BO4) -> 35710.199 | BS4: Closing Date | BT4: 45118 | CG4: 46022 | CH4: =EOMONTH(CG4,6) -> 46203 | CI4: =EOMONTH(CH4,12) -> 46568 | CJ4: =EOMONTH(CI4,12) -> 46934 | CK4: =EOMONTH(CJ4,12) -> 47299 | CL4: =EOMONTH(CK4,12) -> 47664 | CM4: =EOMONTH(CL4,12) -> 48029 | CN4: =EOMONTH(CM4,12) -> 48395 | CO4: =EOMONTH(CN4,12) -> 48760 | CP4: =EOMONTH(CO4,12) -> 49125 | CQ4: =EOMONTH(CP4,18) -> 49674 | DY4: 43983 | EB4: 45231 | EE4: NPV | EF4: Item | EG4: 44196 | EH4: =EOMONTH(EG4,12) -> 44561 | EI4: =EOMONTH(EH4,12) -> 44926 | EJ4: =EOMONTH(EI4,12) -> 45291 | EM4: =EM3+1 -> 2
B5: Potential Gross Revenue | J5: Stamford Health Medical Group | K5: =SF -> 18754 | L5: =K5/SF -> 1 | M5: 47938 | N5: ='Property CF'!AS7 -> 36.930006 | O5: =K5*N5 -> 692585.33 | P5: CPI Adjustment Every 5 Years | Q5: NNN | R5: =_xlfn.DAYS(M5,TODAY())/365 -> 5.0438356 | T5: 1 | U5: 191 Post Road West | V5: 45078 | W5: 1980/2022 | X5: 31492 | Y5: 20514155 | Z5: =Y5/X5 -> 651.40845 | AA5: 0.0568 | AB5: =AA5*Y5 -> 1165204 | AC5: 1 | AD5: ST | AE5: Connecticut Children's Medical Group | AF5: 13 | AH5: 1 | AI5: 191 Post Road West | AJ5: 1980/2022 | AK5: 31492 | AL5: 45292 | AM5: 31492 | AN5: 37 | AO5: 0.02 | AP5: Connecticut Children's Medical Group | AQ5: 13 | AR5: NNN | AT5: Amount | AU5: =Budget!Q24 -> 6550000 | AW5: Loan Amount | AX5: =Budget!Q6+Budget!Q11 -> 6550000 | AZ5: Annual Rent | BA5: 545178.96 | BC5: =BC4+1 -> 2 | BD5: ='Forward Curve'!A3 -> 45242 | BE5: =BE4 -> 6550000 | BF5: ='Forward Curve'!B3 -> 0.0536 | BG5: =BG4 -> 0.019 | BH5: =BH4 -> 0.002 | BI5: =BI4 -> 0.0006 | BJ5: =BJ4 -> 0.001 | BK5: =BF5+BG5+BH5+BI5+BJ5 -> 0.0762 | BL5: =BK5*(_xlfn.DAYS(BD6,BD5)/360)*BE5 -> 41592.5 | BM5: =BM4 -> 0.0411 | BN5: =BN4 -> 0.0637 | BO5: =BN5*(_xlfn.DAYS(BD6,BD5)/360)*BE5 -> 34769.583 | BP5: =NPV((1+BK5)^(BC5/12)-1,BL5:BL5) -> 41086.536 | BQ5: =NPV((1+BK5)^(BC5/12)-1,BO5) -> 34346.619 | BS5: CPI Increase Date | BT5: 45260 | BW5: Year 0 | BX5: Year 1 | BY5: Year 2 | BZ5: Year 3 | CA5: Total | CC5: Assumptions | CF5: Year | CG5: 0 | CH5: 1 | CI5: 2 | CJ5: 3 | CK5: 4 | CL5: 5 | CM5: 6 | CN5: 7 | CO5: 8 | CP5: 9 | CQ5: 10 | CS5: Cap Rate | CT5: 0.0575 | CU5: =CT5+0.0005 -> 0.058 | CV5: =CU5+0.0005 -> 0.0585 | CW5: =CV5+0.0005 -> 0.059 | CX5: =CW5+0.0005 -> 0.0595 | CY5: =CX5+0.0005 -> 0.06 | CZ5: =CY5+0.0005 -> 0.0605 | DA5: =CZ5+0.0005 -> 0.061 | DB5: =DA5+0.0005 -> 0.0615 | ... DD5: =DC5+0.0005 -> 0.0625 | DG5: Quarter 1 | DH5: Quarter 2 | DI5: Quarter 3 | DJ5: Quarter 4 | DK5: Quarter 5 | DL5: Quarter 6 | DM5: Quarter 7 | DN5: Quarter 8 | DO5: Quarter 9 | DP5: Quarter 10 | DS5: Year 0 | DT5: Year 1 | DU5: Year 2 | DV5: Year 3 | DW5: Total | DY5: =BT8/12*2.5 -> 113578.95 | DZ5: Free Rent | EB5: =SUM(EG14:EL14) -> 404738.21 | EC5: Free Rent | EE5: =EG5+NPV(0.07,EH5:EJ5) -> 113578.95 | EF5: Free Rent | EG5: =DY5 -> 113578.95 | EH5: 0 | EI5: 0 | EJ5: 0 | EM5: =EM4+1 -> 3
B6: Schedule Base Rental Revenue | C6: =Budget!E33 -> 664583.76 | D6: =+C6/SF -> 35.436907 | E6: =SUM('Property CF'!V12:AG12) -> 616955.26 | F6: =+E6/SF -> 32.897262 | G6: =E6 -> 616955.26 | H6: =+G6/SF -> 32.897262 | U6: Wesport, Connecticut | AI6: Wesport, Connecticut | AT6: Term | AU6: 3 Years | AW6: Debt Yield | AX6: =AX4/AX5 -> 0.10146317 | AZ6: Annual Rent per RSF | BA6: =BA5/SF -> 29.07001 | BC6: =BC5+1 -> 3 | BD6: ='Forward Curve'!A4 -> 45272 | BE6: =BE5 -> 6550000 | BF6: ='Forward Curve'!B4 -> 0.0543 | BG6: =BG5 -> 0.019 | BH6: =BH5 -> 0.002 | BI6: 0.0006 | BJ6: =BJ5 -> 0.001 | BK6: =BF6+BG6+BH6+BI6+BJ6 -> 0.0769 | BL6: =BK6*(_xlfn.DAYS(BD7,BD6)/360)*BE6 -> 43373.736 | BM6: =BM5 -> 0.0411 | BN6: =BN5 -> 0.0637 | BO6: =BN6*(_xlfn.DAYS(BD7,BD6)/360)*BE6 -> 35928.569 | BP6: =NPV((1+BK6)^(BC6/12)-1,BL6:BL6) -> 42577.778 | BQ6: =NPV((1+BK6)^(BC6/12)-1,BO6) -> 35269.238 | BS6: Days Between | BT6: =_xlfn.DAYS(BT5,BT4) -> 142 | CS6: Gross Sale Price | CT6: =$CH$7/CT5 -> 12044962 | CU6: =$CH$7/CU5 -> 11941126 | CV6: =$CH$7/CV5 -> 11839065 | CW6: =$CH$7/CW5 -> 11738734 | CX6: =$CH$7/CX5 -> 11640090 | CY6: =$CH$7/CY5 -> 11543089 | CZ6: =$CH$7/CZ5 -> 11447691 | DA6: =$CH$7/DA5 -> 11353858 | ... DD6: =$CH$7/DD5 -> 11081365 | DF6: Quarter Ended | DG6: ='Property CF'!K151 -> 45199 | DH6: =EOMONTH(DG6,3) -> 45291 | DI6: =EOMONTH(DH6,3) -> 45382 | DJ6: =EOMONTH(DI6,3) -> 45473 | DK6: =EOMONTH(DJ6,3) -> 45565 | DL6: =EOMONTH(DK6,3) -> 45657 | DM6: =EOMONTH(DL6,3) -> 45747 | DN6: =EOMONTH(DM6,3) -> 45838 | DO6: =EOMONTH(DN6,3) -> 45930 | DP6: =EOMONTH(DO6,3) -> 46022 | DY6: =93770+83716 -> 177486 | DZ6: Improvements | EB6: 200000 | EC6: Improvements | EE6: =EG6+NPV(0.07,EH6:EJ6) -> 149665.05 | EF6: TIA | EG6: 0 | EH6: 0 | EI6: 83716 | EJ6: 93770 | EM6: =EM5+1 -> 4
B7: Expense Recoveries | C7: =SUM('Property CF'!J11:U11) -> 300064 | D7: =+C7/SF -> 16 | E7: =SUM('Property CF'!V11:AG11) -> 306065.28 | F7: =+E7/SF -> 16.32 | G7: =SUM('Property CF'!AH11*12) -> 312186.59 | H7: =+G7/SF -> 16.6464 | AT7: Interest Rate | AU7: Fixed at 3 Year SWAP Equivalent + 190 bps | BC7: =BC6+1 -> 4 | BD7: ='Forward Curve'!A5 -> 45303 | BE7: =BE6 -> 6550000 | BF7: ='Forward Curve'!B5 -> 0.0544 | BG7: =BG6 -> 0.019 | BH7: =BH6 -> 0.002 | BI7: 0.0006 | BJ7: =BJ6 -> 0.001 | BK7: =BF7+BG7+BH7+BI7+BJ7 -> 0.077 | BL7: =BK7*(_xlfn.DAYS(BD8,BD7)/360)*BE7 -> 43430.139 | BM7: =BM6 -> 0.0411 | BN7: =BN6 -> 0.0637 | BO7: =BN7*(_xlfn.DAYS(BD8,BD7)/360)*BE7 -> 35928.569 | BP7: =NPV((1+BK7)^(BC7/12)-1,BL7:BL7) -> 42369.433 | BQ7: =NPV((1+BK7)^(BC7/12)-1,BO7) -> 35051.076 | BV7: Capital Contribution | BW7: =-Budget!I6 -> -3551440.2 | BX7: ='Property CF'!N115 -> 0 | BY7: ='Property CF'!Z115 -> 0 | BZ7: ='Property CF'!AK115 -> -293770 | CA7: =SUM(BW7:BZ7) -> -3845210.2 | CC7: Purchase Price | CD7: ='Property CF'!AS68 -> 11640090 | CF7: Net Operating Income | CH7: ='Property CF'!AW12 -> 692585.33 | CI7: ='Property CF'!AY12 -> 706437.04 | CJ7: ='Property CF'!AZ12 -> 720565.78 | CK7: ='Property CF'!BA12 -> 734977.09 | CL7: ='Property CF'!BB12 -> 749676.64 | CM7: ='Property CF'!BC12 -> 764670.17 | CN7: ='Property CF'!BD12 -> 779963.57 | CO7: ='Property CF'!BE12 -> 795562.84 | CP7: ='Property CF'!BF12 -> 811474.1 | CQ7: ='Property CF'!BG12 -> 827703.58 | CS7: Price per RSF | CT7: =CT6/SF -> 642.26097 | CU7: =CU6/SF -> 636.72424 | CV7: =CV6/SF -> 631.28215 | CW7: =CW6/SF -> 625.9323 | CX7: =CX6/SF -> 620.67237 | CY7: =CY6/SF -> 615.5001 | CZ7: =CZ6/SF -> 610.41332 | DA7: =DA6/SF -> 605.40993 | ... DD7: =DD6/SF -> 590.88009 | DR7: Capital Contribution | DS7: =BW7 -> -3551440.2 | DT7: =BX7 -> 0 | DU7: =BY7 -> 0 | DV7: =BZ7 -> -293770 | DW7: =SUM(DS7:DV7) -> -3845210.2 | DY7: =Budget!AL32 -> 139989.84 | DZ7: Broker | EB7: 0 | EC7: Broker | EE7: =EG7+NPV(0.07,EH7:EJ7) -> 139989.84 | EF7: Broker | EG7: =DY7 -> 139989.84 | EH7: 0 | EI7: 0 | EJ7: 0 | EM7: =EM6+1 -> 5
B8: Effective Revenue | C8: =SUM(C6:C7) -> 964647.76 | D8: =+C8/SF -> 51.436907 | E8: =SUM(E6:E7) -> 923020.54 | F8: =+E8/SF -> 49.217262 | G8: =SUM(G6:G7) -> 929141.84 | H8: =+G8/SF -> 49.543662 | U8: Weighted Average | X8: =+SUM(X5:X7)/2 -> 15746 | Y8: =+SUMPRODUCT(X5:X7,Y5:Y7)/SUM(X5:X7) -> 20514155 | Z8: =+SUMPRODUCT($X$5:$X$7,Z5:Z7)/SUM(X5:X7) -> 651.40845 | AA8: =+SUMPRODUCT(X5:X7,AA5:AA7)/SUM(X5:X7) -> 0.0568 | AB8: =+SUMPRODUCT(X5:X7,AB5:AB7)/SUM(X5:X7) -> 1165204 | AC8: =+SUMPRODUCT($X$5:$X$7,AC5:AC7)/SUM(X5:X7) -> 1 | AF8: =+SUMPRODUCT(X5:X7,AF5:AF7)/SUM(X5:X7) -> 13 | AH8: 2 | AI8: 33 Hospital Avenue | AJ8: 1984/2022 | AK8: 11381 | AL8: 45200 | AM8: 11381 | AN8: 37.25 | AO8: 0.02 | AP8: Nuvance Health | AQ8: 15 | AR8: NNN | AT8: Origination Fee | AU8: 0.005 | AW8: Total Cost | AX8: =Budget!E31 -> 10395210 | AZ8: Index as of 11/2022 | BA8: 298.598 | BC8: =BC7+1 -> 5 | BD8: ='Forward Curve'!A6 -> 45334 | BE8: =BE7 -> 6550000 | BF8: ='Forward Curve'!B6 -> 0.0545 | BG8: =BG7 -> 0.019 | BH8: =BH7 -> 0.002 | BI8: 0.0006 | BJ8: =BJ7 -> 0.001 | BK8: =BF8+BG8+BH8+BI8+BJ8 -> 0.0771 | BL8: =BK8*(_xlfn.DAYS(BD9,BD8)/360)*BE8 -> 40680.958 | BM8: =BM7 -> 0.0411 | BN8: =BN7 -> 0.0637 | BO8: =BN8*(_xlfn.DAYS(BD9,BD8)/360)*BE8 -> 33610.597 | BP8: =NPV((1+BK8)^(BC8/12)-1,BL8:BL8) -> 39441.295 | BQ8: =NPV((1+BK8)^(BC8/12)-1,BO8) -> 32586.388 | BS8: Old Rent | BT8: =BA5 -> 545178.96 | CC8: Closing Costs | CD8: 70000 | CF8: Interest Expense | CH8: =CD21*CD12 -> 450838.45 | CI8: =CH8 -> 450838.45 | CJ8: =CI8 -> 450838.45 | CK8: =CJ8 -> 450838.45 | CL8: =CK8 -> 450838.45 | CM8: =CL8 -> 450838.45 | CN8: =CM8 -> 450838.45 | CO8: =CN8 -> 450838.45 | CP8: =CO8 -> 450838.45 | CQ8: =CP8 -> 450838.45 | CS8: Cost of Sale | CT8: ='Property CF'!AS26 -> 0.05 | CU8: =CT8 -> 0.05 | CV8: =CU8 -> 0.05 | CW8: =CV8 -> 0.05 | CX8: =CW8 -> 0.05 | CY8: =CX8 -> 0.05 | CZ8: =CY8 -> 0.05 | DA8: =CZ8 -> 0.05 | DB8: =DA8 -> 0.05 | ... DD8: =DC8 -> 0.05 | DF8: Cash-on-Cash | DG8: ='Property CF'!K165 -> 0.027698155 | DH8: ='Property CF'!N165 -> 0.053032796 | DI8: ='Property CF'!Q165 -> 0.0059815436 | DJ8: ='Property CF'!T165 -> 0.068529834 | DK8: ='Property CF'!W165 -> 0.066490216 | DL8: ='Property CF'!Z165 -> 0.0046217982 | DM8: ='Property CF'!AC165 -> 0.074409373 | DN8: ='Property CF'!AF165 -> 0.072282731 | DO8: ='Property CF'!AI165 -> 0.070202321 | DP8: ='Property CF'!AL165 -> 0.068452123 | DR8: Return of Capital | DS8: 0 | DT8: 0 | DU8: 0 | DV8: =-DW7 -> 3845210.2 | DW8: =-DW7 -> 3845210.2 | DY8: =SUM(DY5:DY7) -> 431054.79 | DZ8: Total | EB8: =SUM(EB5:EB6) -> 604738.21 | EC8: Total | EE8: =SUM(EE5:EE7) -> 403233.84 | EF8: Total NPV | EM8: =EM7+1 -> 6
AI9: Danbury, Connecticut | AT9: Payments | AU9: Interest Only Through Maturity | AW9: Loan Amount | AX9: =AX5 -> 6550000 | AZ9: Estimated Index as of 11/2023 | BA9: 307.917 | BC9: =BC8+1 -> 6 | BD9: ='Forward Curve'!A7 -> 45363 | BE9: =BE8 -> 6550000 | BF9: ='Forward Curve'!B7 -> 0.054 | BG9: =BG8 -> 0.019 | BH9: =BH8 -> 0.002 | BI9: 0.0006 | BJ9: =BJ8 -> 0.001 | BK9: =BF9+BG9+BH9+BI9+BJ9 -> 0.0766 | BL9: =BK9*(_xlfn.DAYS(BD10,BD9)/360)*BE9 -> 43204.528 | BM9: =BM8 -> 0.0411 | BN9: =BN8 -> 0.0637 | BO9: =BN9*(_xlfn.DAYS(BD10,BD9)/360)*BE9 -> 35928.569 | BP9: =NPV((1+BK9)^(BC9/12)-1,BL9:BL9) -> 41639.171 | BQ9: =NPV((1+BK9)^(BC9/12)-1,BO9) -> 34626.83 | BS9: New Rent | BT9: =BA14 -> 664583.76 | CC9: Total | CD9: =SUM(CD7:CD8) -> 11710090 | CF9: Levered Cash Flow | CH9: =CH7-CH8 -> 241746.88 | CI9: =CI7-CI8 -> 255598.59 | CJ9: =CJ7-CJ8 -> 269727.33 | CK9: =CK7-CK8 -> 284138.64 | CL9: =CL7-CL8 -> 298838.19 | CM9: =CM7-CM8 -> 313831.72 | CN9: =CN7-CN8 -> 329125.12 | CO9: =CO7-CO8 -> 344724.39 | ... CQ9: =CQ7-CQ8 -> 376865.13 | CS9: Net Sale Price | CT9: =(CT6*(1-CT8))-'Property CF'!$AS$31-'Property CF'!$AS$33 -> 11413907 | CU9: =(CU6*(1-CU8))-'Property CF'!$AS$31-'Property CF'!$AS$33 -> 11315263 | CV9: =(CV6*(1-CV8))-'Property CF'!$AS$31-'Property CF'!$AS$33 -> 11218305 | CW9: =(CW6*(1-CW8))-'Property CF'!$AS$31-'Property CF'!$AS$33 -> 11122991 | CX9: =(CX6*(1-CX8))-'Property CF'!$AS$31-'Property CF'!$AS$33 -> 11029278 | CY9: =(CY6*(1-CY8))-'Property CF'!$AS$31-'Property CF'!$AS$33 -> 10937127 | CZ9: =(CZ6*(1-CZ8))-'Property CF'!$AS$31-'Property CF'!$AS$33 -> 10846500 | DA9: =(DA6*(1-DA8))-'Property CF'!$AS$31-'Property CF'!$AS$33 -> 10757358 | ... DD9: =(DD6*(1-DD8))-'Property CF'!$AS$31-'Property CF'!$AS$33 -> 10498490 | DR9: Preferred Return | DS9: 0 | DT9: =SUM('Property CF'!I132:T132) -> 134737.82 | DU9: =SUM('Property CF'!U132:AF132) -> 192817.69 | DV9: =SUM('Property CF'!AG132:AN132) -> 480477.42 | DW9: =SUM(DT9:DV9) -> 808032.92 | DY9: =DY8/SF -> 22.984685 | DZ9: TotalSF | EB9: =EB8/SF -> 32.245825 | EC9: TotalSF | EE9: =EE8/SF -> 21.501218 | EF9: Total NPV/SF | EM9: =EM8+1 -> 7
B10: Operating Expenses | C10: =C7 -> 300064 | D10: =+C10/SF -> 16 | E10: =E7 -> 306065.28 | F10: =+E10/SF -> 16.32 | G10: =G7 -> 312186.59 | H10: =+G10/SF -> 16.6464 | T10: 2 | U10: 1500 Boston Post Road | V10: N/A | W10: 1997 | X10: =SF -> 18754 | Y10: =AB10/AA10 -> 9700000 | Z10: =Y10/X10 -> 517.22299 | AA10: =Budget!G8 -> 0.06851379 | AB10: =C12 -> 664583.76 | AC10: 1 | AD10: ST | AE10: Stamford Health | AF10: =R5 -> 5.0438356 | AT10: Prepayment Fee | AU10: SWAP Breakage Fees | AW10: Loan-to-Cost | AX10: =AX9/AX8 -> 0.63009789 | AZ10: Index Increase 11/2022 to 11/2023 | BA10: =(BA9-BA8)/BA8 -> 0.031209184 | BC10: =BC9+1 -> 7 | BD10: ='Forward Curve'!A8 -> 45394 | BE10: =BE9 -> 6550000 | BF10: ='Forward Curve'!B8 -> 0.0535 | BG10: =BG9 -> 0.019 | BH10: =BH9 -> 0.002 | BI10: 0.0006 | BJ10: =BJ9 -> 0.001 | BK10: =BF10+BG10+BH10+BI10+BJ10 -> 0.0761 | BL10: =BK10*(_xlfn.DAYS(BD11,BD10)/360)*BE10 -> 41537.917 | BM10: =BM9 -> 0.0411 | BN10: =BN9 -> 0.0637 | BO10: =BN10*(_xlfn.DAYS(BD11,BD10)/360)*BE10 -> 34769.583 | BP10: =NPV((1+BK10)^(BC10/12)-1,BL10:BL10) -> 39798.253 | BQ10: =NPV((1+BK10)^(BC10/12)-1,BO10) -> 33313.387 | CC10: Debt LTC % | CD10: 0.7 | CF10: Cash-on-Cash | CH10: =CH9/$CD$13 -> 0.068814413 | CI10: =CI9/$CD$13 -> 0.072757368 | CJ10: =CJ9/$CD$13 -> 0.076779182 | CK10: =CK9/$CD$13 -> 0.080881432 | CL10: =CL9/$CD$13 -> 0.085065727 | CM10: =CM9/$CD$13 -> 0.089333708 | CN10: =CN9/$CD$13 -> 0.093687049 | CO10: =CO9/$CD$13 -> 0.098127457 | ... CQ10: =CQ9/$CD$13 -> 0.10727647 | DR10: Profits Interest | DS10: 0 | DT10: 0 | DU10: 0 | DV10: ='Property CF'!AN139 -> 0 | DW10: =SUM(DT10:DV10) -> 0 | DY10: =DY9/7.33 -> 3.1357006 | DZ10: Total/SF/Year | EB10: =EB9/10 -> 3.2245825 | EC10: Total/SF/Year | EE10: =EE9/7.33 -> 2.9333176 | EF10: Total/NPV/SF/Year | EM10: =EM9+1 -> 8
U11: Darien, CT | AH11: 3 | AI11: 637 West Avenue | AJ11: 1955/2021 | AK11: 22866 | AL11: 44621 | AM11: 22866 | AN11: 27 | AO11: 0.025 | AP11: Stamford Health | AQ11: 15 | AR11: NNN | BC11: =BC10+1 -> 8 | BD11: ='Forward Curve'!A9 -> 45424 | BE11: =BE10 -> 6550000 | BF11: ='Forward Curve'!B9 -> 0.0528 | BG11: =BG10 -> 0.019 | BH11: =BH10 -> 0.002 | BI11: 0.0006 | BJ11: =BJ10 -> 0.001 | BK11: =BF11+BG11+BH11+BI11+BJ11 -> 0.0754 | BL11: =BK11*(_xlfn.DAYS(BD12,BD11)/360)*BE11 -> 42527.694 | BM11: =BM10 -> 0.0411 | BN11: =BN10 -> 0.0637 | BO11: =BN11*(_xlfn.DAYS(BD12,BD11)/360)*BE11 -> 35928.569 | BP11: =NPV((1+BK11)^(BC11/12)-1,BL11:BL11) -> 40515.868 | BQ11: =NPV((1+BK11)^(BC11/12)-1,BO11) -> 34228.923 | BS11: Escrow Amount | BT11: =(BT9-BT8)*(BT6/365) -> 46453.374 | CC11: Equity LTC % | CD11: =1-CD10 -> 0.3 | CF11: Average Cash-on-Cash | CH11: =AVERAGE(CH$10:$CH10) -> 0.068814413 | CI11: =AVERAGE($CH$10:CI10) -> 0.07078589 | CJ11: =AVERAGE($CH$10:CJ10) -> 0.072783654 | CK11: =AVERAGE($CH$10:CK10) -> 0.074808098 | CL11: =AVERAGE($CH$10:CL10) -> 0.076859624 | CM11: =AVERAGE($CH$10:CM10) -> 0.078938638 | CN11: =AVERAGE($CH$10:CN10) -> 0.081045554 | CO11: =AVERAGE($CH$10:CO10) -> 0.083180792 | CP11: =AVERAGE($CH$10:CP10) -> 0.085344779 | CQ11: =AVERAGE($CH$10:CQ10) -> 0.087537948 | CS11: Total Project Cost | CT11: =Budget!E31 -> 10395210 | CU11: =CT11 -> 10395210 | CV11: =CU11 -> 10395210 | CW11: =CV11 -> 10395210 | CX11: =CW11 -> 10395210 | CY11: =CX11 -> 10395210 | CZ11: =CY11 -> 10395210 | DA11: =CZ11 -> 10395210 | DB11: =DA11 -> 10395210 | ... DD11: =DC11 -> 10395210 | EH11: Aspect Health | EM11: =EM10+1 -> 9
B12: Net Operating Income | C12: =+C8-C10 -> 664583.76 | D12: =+C12/SF -> 35.436907 | E12: =+E8-E10 -> 616955.26 | F12: =+E12/SF -> 32.897262 | G12: =+G8-G10 -> 616955.26 | H12: =+G12/SF -> 32.897262 | AI12: Norwalk, Connecticut | AT12: Construction Financing | AW12: NOI | AX12: =AX4 -> 664583.76 | AZ12: Projected Rent Increase % | BA12: =(BA9-BA4)/BA4 -> 0.21901945 | BC12: =BC11+1 -> 9 | BD12: ='Forward Curve'!A10 -> 45455 | BE12: =BE11 -> 6550000 | BF12: ='Forward Curve'!B10 -> 0.0521 | BG12: =BG11 -> 0.019 | BH12: =BH11 -> 0.002 | BI12: 0.0006 | BJ12: =BJ11 -> 0.001 | BK12: =BF12+BG12+BH12+BI12+BJ12 -> 0.0747 | BL12: =BK12*(_xlfn.DAYS(BD13,BD12)/360)*BE12 -> 40773.75 | BM12: =BM11 -> 0.0411 | BN12: =BN11 -> 0.0637 | BO12: =BN12*(_xlfn.DAYS(BD13,BD12)/360)*BE12 -> 34769.583 | BP12: =NPV((1+BK12)^(BC12/12)-1,BL12:BL12) -> 38629.156 | BQ12: =NPV((1+BK12)^(BC12/12)-1,BO12) -> 32940.793 | CC12: Debt | CD12: =CD9*CD10 -> 8197062.7 | DR12: Total Investment Return | DS12: =SUM(DS7:DS10) -> -3551440.2 | DT12: =SUM(DT7:DT10) -> 134737.82 | DU12: =SUM(DU7:DU10) -> 192817.69 | DV12: =SUM(DV7:DV10) -> 4031917.6 | DW12: =SUM(DW7:DW10) -> 808032.92 | EE12: 10 Year 0 Month Extension | EM12: =EM11+1 -> 10
B13: Occupancy | C13: 1 | E13: 1 | G13: 1 | AT13: Construction Loan Request | AW13: Interest Rate | AX13: =BN4 -> 0.0637 | AZ13: Projected New Rent/SF | BA13: =(1+BA12)*BA6 -> 35.436907 | BC13: =BC12+1 -> 10 | BD13: ='Forward Curve'!A11 -> 45485 | BE13: =BE12 -> 6550000 | BF13: ='Forward Curve'!B11 -> 0.0513 | BG13: =BG12 -> 0.019 | BH13: =BH12 -> 0.002 | BI13: 0.0006 | BJ13: =BJ12 -> 0.001 | BK13: =BF13+BG13+BH13+BI13+BJ13 -> 0.0739 | BL13: =BK13*(_xlfn.DAYS(BD14,BD13)/360)*BE13 -> 41681.653 | BM13: =BM12 -> 0.0411 | BN13: =BN12 -> 0.0637 | BO13: =BN13*(_xlfn.DAYS(BD14,BD13)/360)*BE13 -> 35928.569 | BP13: =NPV((1+BK13)^(BC13/12)-1,BL13:BL13) -> 39277.309 | BQ13: =NPV((1+BK13)^(BC13/12)-1,BO13) -> 33856.084 | CC13: Equity | CD13: =CD9-CD12 -> 3513026.9 | CF13: TI Allowance | CS13: Net Sale Proceeds for Distribution | CT13: =CT9-CT11 -> 1018696.8 | CU13: =CU9-CU11 -> 920052.74 | CV13: =CV9-CV11 -> 823094.88 | CW13: =CW9-CW11 -> 727780.37 | CX13: =CX9-CX11 -> 634067.78 | CY13: =CY9-CY11 -> 541917.07 | CZ13: =CZ9-CZ11 -> 451289.51 | DA13: =DA9-DA11 -> 362147.66 | ... DD13: =DD9-DD11 -> 103279.7 | EE13: NPV | EF13: Item | EG13: 45291 | EH13: =EOMONTH(EG13,12) -> 45657 | EI13: =EOMONTH(EH13,12) -> 46022 | EJ13: =EOMONTH(EI13,12) -> 46387 | EK13: =EOMONTH(EJ13,12) -> 46752 | EL13: =EOMONTH(EK13,12) -> 47118
AH14: 4 | AI14: 50 Old Kings Highway North | AJ14: 2002 | AK14: 8400 | AL14: 44166 | AM14: 2400 | AN14: 31 | AO14: 0.02 | AP14: Hartford Healthcare | AQ14: 5 | AR14: NNN | AW14: Amortization Months | AX14: 324 | AZ14: Projected Annual Rent | BA14: =BA13*SF -> 664583.76 | BC14: =BC13+1 -> 11 | BD14: ='Forward Curve'!A12 -> 45516 | BE14: =BE13 -> 6550000 | BF14: ='Forward Curve'!B12 -> 0.0508 | BG14: =BG13 -> 0.019 | BH14: =BH13 -> 0.002 | BI14: 0.0006 | BJ14: =BJ13 -> 0.001 | BK14: =BF14+BG14+BH14+BI14+BJ14 -> 0.0734 | BL14: =BK14*(_xlfn.DAYS(BD15,BD14)/360)*BE14 -> 41399.639 | BM14: =BM13 -> 0.0411 | BN14: =BN13 -> 0.0637 | BO14: =BN14*(_xlfn.DAYS(BD15,BD14)/360)*BE14 -> 35928.569 | BP14: =NPV((1+BK14)^(BC14/12)-1,BL14:BL14) -> 38797.025 | BQ14: =NPV((1+BK14)^(BC14/12)-1,BO14) -> 33669.898 | CS14: Accrued Preferred Return at Disposition | CT14: =-'Property CF'!AL128-'Property CF'!AL129 -> 612566.73 | CU14: =CT14 -> 612566.73 | CV14: =CU14 -> 612566.73 | CW14: =CV14 -> 612566.73 | CX14: =CW14 -> 612566.73 | CY14: =CX14 -> 612566.73 | CZ14: =CY14 -> 612566.73 | DA14: =CZ14 -> 612566.73 | DB14: =DA14 -> 612566.73 | ... DD14: =DC14 -> 612566.73 | DR14: IRR | DS14: ='Property CF'!BJ28 -> 0.089599493 | EE14: =EG14+NPV(0.07,EH14:EL14) -> 351190.16 | EF14: Free Rent | EG14: =BA14/6 -> 110763.96 | EH14: =EG14*1.02/2 -> 56489.619 | EI14: =EH14*1.02 -> 57619.412 | EJ14: =EI14*1.02 -> 58771.8 | EK14: =EJ14*1.02 -> 59947.236 | EL14: =EK14*1.02 -> 61146.181
B15: Debt Service (Interest Only) | C15: =SUM(BO4:BO15) -> 424188.92 | D15: =+C15/SF -> 22.618584 | E15: =SUM(BO16:BO27) -> 423029.93 | F15: =+E15/SF -> 22.556784 | G15: =SUM(BO28:BO39) -> 423029.93 | H15: =+G15/SF -> 22.556784 | AI15: Darien, Connecticut | AT15: Amount | AU15: =AX22 -> 0 | AW15: Loan Constant % | AX15: =(AX13/12)/(1 - (1 / (1 + AX13/12))^AX14)*12 -> 0.077673505 | BC15: =BC14+1 -> 12 | BD15: ='Forward Curve'!A13 -> 45547 | BE15: =BE14 -> 6550000 | BF15: ='Forward Curve'!B13 -> 0.0494 | BG15: =BG14 -> 0.019 | BH15: =BH14 -> 0.002 | BI15: 0.0006 | BJ15: =BJ14 -> 0.001 | BK15: =BF15+BG15+BH15+BI15+BJ15 -> 0.072 | BL15: =BK15*(_xlfn.DAYS(BD16,BD15)/360)*BE15 -> 39300 | BM15: =BM14 -> 0.0411 | BN15: =BN14 -> 0.0637 | BO15: =BN15*(_xlfn.DAYS(BD16,BD15)/360)*BE15 -> 34769.583 | BP15: =NPV((1+BK15)^(BC15/12)-1,BL15:BL15) -> 36660.448 | BQ15: =NPV((1+BK15)^(BC15/12)-1,BO15) -> 32434.313 | CC15: Exit Cap Rate | CD15: ='Property CF'!AS14+0.25% -> 0.062 | CF15: Levered | CG15: =-CD13 -> -3513026.9 | CH15: =CH9 -> 241746.88 | CI15: =CI9 -> 255598.59 | CJ15: =CJ9 -> 269727.33 | CK15: =CK9 -> 284138.64 | CL15: =CL9+CL13 -> 298838.19 | CM15: =CM9+CM13 -> 313831.72 | CN15: =CN9+CN13 -> 329125.12 | CO15: =CO9+CO13 -> 344724.39 | CP15: =CP9+CP13 -> 360635.65 | CQ15: =CQ9+CQ13+CD19 -> 5456434.9 | DR15: Average Cash-on-Cash | DS15: ='Property CF'!BJ29 -> 0 | EE15: =EG15+NPV(0.07,EH15:EJ15) -> 180801.82 | EF15: TIA | EG15: 0 | EH15: 100000 | EI15: 100000 | EJ15: 0 | EK15: 0 | EL15: 0
B16: DSCR Coverage | C16: =+C12/C15 -> 1.5667165 | E16: =+E12/E15 -> 1.4584199 | G16: =+G12/G15 -> 1.4584199 | AT16: Term | AU16: 3 Years | AW16: Loan Constant Amount | AX16: =AX9*AX15 -> 508761.46 | BC16: =BC15+1 -> 13 | BD16: ='Forward Curve'!A14 -> 45577 | BE16: =BE15 -> 6550000 | BF16: ='Forward Curve'!B14 -> 0.0462 | BG16: =BG15 -> 0.019 | BH16: =BH15 -> 0.002 | BI16: 0.0006 | BJ16: =BJ15 -> 0.001 | BK16: =BF16+BG16+BH16+BI16+BJ16 -> 0.0688 | BL16: =BK16*(_xlfn.DAYS(BD17,BD16)/360)*BE16 -> 38805.111 | BM16: =BM15 -> 0.0411 | BN16: =BN15 -> 0.0637 | BO16: =BN16*(_xlfn.DAYS(BD17,BD16)/360)*BE16 -> 35928.569 | BP16: =NPV((1+BK16)^(BC16/12)-1,BL16:BL16) -> 36106.422 | BQ16: =NPV((1+BK16)^(BC16/12)-1,BO16) -> 33429.928 | CC16: Exit Value | CD16: =(CQ7*1.02)/CD15 -> 13617059 | CF16: IRR | CG16: =XIRR(CG15:CQ15,CG4:CQ4) -> 0.11420894 | DR16: Equity Multiple | DS16: ='Property CF'!BJ30 -> 1.2056384 | EE16: =EG16+NPV(0.07,EH16:EJ16) -> 0 | EF16: Broker | EG16: =DY15 -> 0 | EH16: 0 | EI16: 0 | EJ16: 0 | EK16: 0 | EL16: 0
AH17: 5 | AI17: 300 Post Road West | AJ17: 2001 | AK17: 28860 | AL17: 43831 | AM17: 20000 | AN17: 30 | AO17: 0.02 | AP17: Hartford Healthcare | AQ17: 10 | AR17: NNN | AT17: Interest Rate | AU17: Floating at SOFR + 235 bps | AW17: DSCR | AX17: =AX4/AX16 -> 1.3062777 | BC17: =BC16+1 -> 14 | BD17: ='Forward Curve'!A15 -> 45608 | BE17: =BE16 -> 6550000 | BF17: ='Forward Curve'!B15 -> 0.0462 | BG17: =BG16 -> 0.019 | BH17: =BH16 -> 0.002 | BI17: 0.0006 | BJ17: =BJ16 -> 0.001 | BK17: =BF17+BG17+BH17+BI17+BJ17 -> 0.0688 | BL17: =BK17*(_xlfn.DAYS(BD18,BD17)/360)*BE17 -> 37553.333 | BM17: =BM16 -> 0.0411 | BN17: =BN16 -> 0.0637 | BO17: =BN17*(_xlfn.DAYS(BD18,BD17)/360)*BE17 -> 34769.583 | BP17: =NPV((1+BK17)^(BC17/12)-1,BL17:BL17) -> 34748.493 | BQ17: =NPV((1+BK17)^(BC17/12)-1,BO17) -> 32172.66 | CC17: Cost of Sale | CD17: 0.025 | CF17: Equity Multiple | CG17: =SUMIF(CG15:CQ15,">0")/-(SUMIF(CG15:CQ15,"<0")) -> 2.3213034 | EE17: =SUM(EE14:EE16) -> 531991.98 | EF17: Total NPV
B18: Cash Flow After Debt Service | C18: =+C12-C15 -> 240394.84 | D18: =+C18/SF -> 12.818324 | E18: =+E12-E15 -> 193925.33 | F18: =+E18/SF -> 10.340478 | G18: =+G12-G15 -> 193925.33 | H18: =+G18/SF -> 10.340478 | AI18: Wesport, Connecticut | AT18: Origination Fee | AU18: 0.01 | BC18: =BC17+1 -> 15 | BD18: ='Forward Curve'!A16 -> 45638 | BE18: =BE17 -> 6550000 | BF18: ='Forward Curve'!B16 -> 0.0462 | BG18: =BG17 -> 0.019 | BH18: =BH17 -> 0.002 | BI18: 0.0006 | BJ18: =BJ17 -> 0.001 | BK18: =BF18+BG18+BH18+BI18+BJ18 -> 0.0688 | BL18: =BK18*(_xlfn.DAYS(BD19,BD18)/360)*BE18 -> 38805.111 | BM18: =BM17 -> 0.0411 | BN18: =BN17 -> 0.0637 | BO18: =BN18*(_xlfn.DAYS(BD19,BD18)/360)*BE18 -> 35928.569 | BP18: =NPV((1+BK18)^(BC18/12)-1,BL18:BL18) -> 35708.234 | BQ18: =NPV((1+BK18)^(BC18/12)-1,BO18) -> 33061.258 | CC18: Net Value | CD18: =CD16*(1-CD17) -> 13276632 | EE18: =EE17/SF -> 28.366854 | EF18: Total NPV/SF
AT19: Payments | AU19: Interest Only on the Drawn Amount | BC19: =BC18+1 -> 16 | BD19: ='Forward Curve'!A17 -> 45669 | BE19: =BE18 -> 6550000 | BF19: ='Forward Curve'!B17 -> 0.0462 | BG19: =BG18 -> 0.019 | BH19: =BH18 -> 0.002 | BI19: 0.0006 | BJ19: =BJ18 -> 0.001 | BK19: =BF19+BG19+BH19+BI19+BJ19 -> 0.0688 | BL19: =BK19*(_xlfn.DAYS(BD20,BD19)/360)*BE19 -> 38805.111 | BM19: =BM18 -> 0.0411 | BN19: =BN18 -> 0.0637 | BO19: =BN19*(_xlfn.DAYS(BD20,BD19)/360)*BE19 -> 35928.569 | BP19: =NPV((1+BK19)^(BC19/12)-1,BL19:BL19) -> 35510.79 | BQ19: =NPV((1+BK19)^(BC19/12)-1,BO19) -> 32878.45 | CC19: Net Debt | CD19: =CD18-CD12 -> 5079569.7 | CF19: Unlevered | CG19: =-CD9 -> -11710090 | CH19: =CH7 -> 692585.33 | CI19: =CI7 -> 706437.04 | CJ19: =CJ7 -> 720565.78 | CK19: =CK7 -> 734977.09 | CL19: =CL7 -> 749676.64 | CM19: =CM7 -> 764670.17 | CN19: =CN7 -> 779963.57 | CO19: =CO7 -> 795562.84 | CP19: =CP7 -> 811474.1 | CQ19: =CQ7+CQ13+CD18 -> 14104336 | EE19: =EE18/10 -> 2.8366854 | EF19: Total/NPV/SF/Year
B20: Non-Recoverables | AI20: Weighted Average | AK20: =+SUM(AK4:AK19)/AH17 -> 20599.8 | AM20: =+SUM(AM4:AM19)/AH17 -> 17627.8 | AN20: =+SUMPRODUCT(AM4:AM19,AN4:AN19)/SUM(AM4:AM19) -> 32.686192 | AO20: =SUMPRODUCT(AO5:AO17,AK5:AK17)/SUM(AK5:AK17) -> 0.021110011 | AQ20: =+SUMPRODUCT(AM4:AM19,AQ4:AQ19)/SUM(AM4:AM19) -> 12.878533 | AT20: Prepayment Fee | AU20: None | BC20: =BC19+1 -> 17 | BD20: ='Forward Curve'!A18 -> 45700 | BE20: =BE19 -> 6550000 | BF20: ='Forward Curve'!B18 -> 0.0462 | BG20: =BG19 -> 0.019 | BH20: =BH19 -> 0.002 | BI20: 0.0006 | BJ20: =BJ19 -> 0.001 | BK20: =BF20+BG20+BH20+BI20+BJ20 -> 0.0688 | BL20: =BK20*(_xlfn.DAYS(BD21,BD20)/360)*BE20 -> 35049.778 | BM20: =BM19 -> 0.0411 | BN20: =BN19 -> 0.0637 | BO20: =BN20*(_xlfn.DAYS(BD21,BD20)/360)*BE20 -> 32451.611 | BP20: =NPV((1+BK20)^(BC20/12)-1,BL20:BL20) -> 31896.912 | BQ20: =NPV((1+BK20)^(BC20/12)-1,BO20) -> 29532.461 | CF20: IRR | CG20: =XIRR(CG19:CQ19,CG4:CQ4) -> 0.075591156
B21: Asset Management Fee | C21: 0 | D21: =+C21/SF -> 0 | E21: 0 | F21: =+E21/SF -> 0 | G21: =E21 -> 0 | H21: =+G21/SF -> 0 | BC21: =BC20+1 -> 18 | BD21: ='Forward Curve'!A19 -> 45728 | BE21: =BE20 -> 6550000 | BF21: ='Forward Curve'!B19 -> 0.0462 | BG21: =BG20 -> 0.019 | BH21: =BH20 -> 0.002 | BI21: 0.0006 | BJ21: =BJ20 -> 0.001 | BK21: =BF21+BG21+BH21+BI21+BJ21 -> 0.0688 | BL21: =BK21*(_xlfn.DAYS(BD22,BD21)/360)*BE21 -> 38805.111 | BM21: =BM20 -> 0.0411 | BN21: =BN20 -> 0.0637 | BO21: =BN21*(_xlfn.DAYS(BD22,BD21)/360)*BE21 -> 35928.569 | BP21: =NPV((1+BK21)^(BC21/12)-1,BL21:BL21) -> 35119.172 | BQ21: =NPV((1+BK21)^(BC21/12)-1,BO21) -> 32515.861 | CC21: Interest Rate | CD21: 0.055 | CF21: Equity Multiple | CG21: =SUMIF(CG19:CQ19,">0")/-(SUMIF(CG19:CQ19,"<0")) -> 1.781391
B22: Non-Recoverables | C22: =+SUBTOTAL(9,C21:C21) -> 0 | D22: =+SUBTOTAL(9,D21:D21) -> 0 | E22: =+SUBTOTAL(9,E21:E21) -> 0 | F22: =+SUBTOTAL(9,F21:F21) -> 0 | G22: =+SUBTOTAL(9,G21:G21) -> 0 | H22: =+SUBTOTAL(9,H21:H21) -> 0 | AH22: 6 | AI22: 1500 Boston Post Road | AJ22: 1997 | AK22: =X10 -> 18754 | AL22: 35734 | AM22: =AK22 -> 18754 | AN22: =D6 -> 35.436907 | AO22: CPI | AP22: =AE10 -> Stamford Health | AQ22: =AF10 -> 5.0438356 | AR22: NNN | BC22: =BC21+1 -> 19 | BD22: ='Forward Curve'!A20 -> 45759 | BE22: =BE21 -> 6550000 | BF22: ='Forward Curve'!B20 -> 0.0417 | BG22: =BG21 -> 0.019 | BH22: =BH21 -> 0.002 | BI22: 0.0006 | BJ22: =BJ21 -> 0.001 | BK22: =BF22+BG22+BH22+BI22+BJ22 -> 0.0643 | BL22: =BK22*(_xlfn.DAYS(BD23,BD22)/360)*BE22 -> 35097.083 | BM22: =BM21 -> 0.0411 | BN22: =BN21 -> 0.0637 | BO22: =BN22*(_xlfn.DAYS(BD23,BD22)/360)*BE22 -> 34769.583 | BP22: =NPV((1+BK22)^(BC22/12)-1,BL22:BL22) -> 31799.449 | BQ22: =NPV((1+BK22)^(BC22/12)-1,BO22) -> 31502.72 | CC22: Loan Constant | CD22: =(CD21/12)/(1 - (1 / (1 + CD21/12))^360)*12 -> 0.06813468
AI23: Darien, CT | BC23: =BC22+1 -> 20 | BD23: ='Forward Curve'!A21 -> 45789 | BE23: =BE22 -> 6550000 | BF23: ='Forward Curve'!B21 -> 0.0413 | BG23: =BG22 -> 0.019 | BH23: =BH22 -> 0.002 | BI23: 0.0006 | BJ23: =BJ22 -> 0.001 | BK23: =BF23+BG23+BH23+BI23+BJ23 -> 0.0639 | BL23: =BK23*(_xlfn.DAYS(BD24,BD23)/360)*BE23 -> 36041.375 | BM23: =BM22 -> 0.0411 | BN23: =BN22 -> 0.0637 | BO23: =BN23*(_xlfn.DAYS(BD24,BD23)/360)*BE23 -> 35928.569 | BP23: =NPV((1+BK23)^(BC23/12)-1,BL23:BL23) -> 32506.235 | BQ23: =NPV((1+BK23)^(BC23/12)-1,BO23) -> 32404.494 | CC23: Debt Service | CD23: =CD22*CD12 -> 558504.25
B24: Cash Flow Available For Distribution | C24: =+C18-C22 -> 240394.84 | D24: =+C24/SF -> 12.818324 | E24: =+E18-E22 -> 193925.33 | F24: =+E24/SF -> 10.340478 | G24: =+G18-G22 -> 193925.33 | H24: =+G24/SF -> 10.340478 | BC24: =BC23+1 -> 21 | BD24: ='Forward Curve'!A22 -> 45820 | BE24: =BE23 -> 6550000 | BF24: ='Forward Curve'!B22 -> 0.0413 | BG24: =BG23 -> 0.019 | BH24: =BH23 -> 0.002 | BI24: 0.0006 | BJ24: =BJ23 -> 0.001 | BK24: =BF24+BG24+BH24+BI24+BJ24 -> 0.0639 | BL24: =BK24*(_xlfn.DAYS(BD25,BD24)/360)*BE24 -> 34878.75 | BM24: =BM23 -> 0.0411 | BN24: =BN23 -> 0.0637 | BO24: =BN24*(_xlfn.DAYS(BD25,BD24)/360)*BE24 -> 34769.583 | BP24: =NPV((1+BK24)^(BC24/12)-1,BL24:BL24) -> 31295.688 | BQ24: =NPV((1+BK24)^(BC24/12)-1,BO24) -> 31197.735 | CC24: DSCR | CD24: =CH7/CD23 -> 1.2400717
BC25: =BC24+1 -> 22 | BD25: ='Forward Curve'!A23 -> 45850 | BE25: =BE24 -> 6550000 | BF25: ='Forward Curve'!B23 -> 0.0413 | BG25: =BG24 -> 0.019 | BH25: =BH24 -> 0.002 | BI25: 0.0006 | BJ25: =BJ24 -> 0.001 | BK25: =BF25+BG25+BH25+BI25+BJ25 -> 0.0639 | BL25: =BK25*(_xlfn.DAYS(BD26,BD25)/360)*BE25 -> 36041.375 | BM25: =BM24 -> 0.0411 | BN25: =BN24 -> 0.0637 | BO25: =BN25*(_xlfn.DAYS(BD26,BD25)/360)*BE25 -> 35928.569 | BP25: =NPV((1+BK25)^(BC25/12)-1,BL25:BL25) -> 32172.381 | BQ25: =NPV((1+BK25)^(BC25/12)-1,BO25) -> 32071.685
B26: Equity Outstanding | C26: =-'Property CF'!T117 -> 3551440.2 | E26: =-'Property CF'!AF117 -> 3551440.2 | G26: =-'Property CF'!AL113 -> 3845210.2 | BC26: =BC25+1 -> 23 | BD26: ='Forward Curve'!A24 -> 45881 | BE26: =BE25 -> 6550000 | BF26: ='Forward Curve'!B24 -> 0.0413 | BG26: =BG25 -> 0.019 | BH26: =BH25 -> 0.002 | BI26: 0.0006 | BJ26: =BJ25 -> 0.001 | BK26: =BF26+BG26+BH26+BI26+BJ26 -> 0.0639 | BL26: =BK26*(_xlfn.DAYS(BD27,BD26)/360)*BE26 -> 36041.375 | BM26: =BM25 -> 0.0411 | BN26: =BN25 -> 0.0637 | BO26: =BN26*(_xlfn.DAYS(BD27,BD26)/360)*BE26 -> 35928.569 | BP26: =NPV((1+BK26)^(BC26/12)-1,BL26:BL26) -> 32006.742 | BQ26: =NPV((1+BK26)^(BC26/12)-1,BO26) -> 31906.564
B27: Cash-on-Cash | C27: =C24/C26 -> 0.067689396 | E27: =E24/E26 -> 0.054604699 | G27: =G24/G26 -> 0.050432958 | BC27: =BC26+1 -> 24 | BD27: ='Forward Curve'!A25 -> 45912 | BE27: =BE26 -> 6550000 | BF27: ='Forward Curve'!B25 -> 0.0413 | BG27: =BG26 -> 0.019 | BH27: =BH26 -> 0.002 | BI27: 0.0006 | BJ27: =BJ26 -> 0.001 | BK27: =BF27+BG27+BH27+BI27+BJ27 -> 0.0639 | BL27: =BK27*(_xlfn.DAYS(BD28,BD27)/360)*BE27 -> 34878.75 | BM27: =BM26 -> 0.0411 | BN27: =BN26 -> 0.0637 | BO27: =BN27*(_xlfn.DAYS(BD28,BD27)/360)*BE27 -> 34769.583 | BP27: =NPV((1+BK27)^(BC27/12)-1,BL27:BL27) -> 30814.796 | BQ27: =NPV((1+BK27)^(BC27/12)-1,BO27) -> 30718.349
BC28: =BC27+1 -> 25 | BD28: ='Forward Curve'!A26 -> 45942 | BE28: =BE27 -> 6550000 | BF28: ='Forward Curve'!B26 -> 0.0396 | BG28: =BG27 -> 0.019 | BH28: =BH27 -> 0.002 | BI28: 0.0006 | BJ28: =BJ27 -> 0.001 | BK28: =BF28+BG28+BH28+BI28+BJ28 -> 0.0622 | BL28: =BK28*(_xlfn.DAYS(BD29,BD28)/360)*BE28 -> 35082.528 | BM28: =BM27 -> 0.0411 | BN28: =BN27 -> 0.0637 | BO28: =BN28*(_xlfn.DAYS(BD29,BD28)/360)*BE28 -> 35928.569 | BP28: =NPV((1+BK28)^(BC28/12)-1,BL28:BL28) -> 30938.156 | BQ28: =NPV((1+BK28)^(BC28/12)-1,BO28) -> 31684.253
BC29: =BC28+1 -> 26 | BD29: ='Forward Curve'!A27 -> 45973 | BE29: =BE28 -> 6550000 | BF29: ='Forward Curve'!B27 -> 0.0393 | BG29: =BG28 -> 0.019 | BH29: =BH28 -> 0.002 | BI29: 0.0006 | BJ29: =BJ28 -> 0.001 | BK29: =BF29+BG29+BH29+BI29+BJ29 -> 0.0619 | BL29: =BK29*(_xlfn.DAYS(BD30,BD29)/360)*BE29 -> 33787.083 | BM29: =BM28 -> 0.0411 | BN29: =BN28 -> 0.0637 | BO29: =BN29*(_xlfn.DAYS(BD30,BD29)/360)*BE29 -> 34769.583 | BP29: =NPV((1+BK29)^(BC29/12)-1,BL29:BL29) -> 29664.443 | BQ29: =NPV((1+BK29)^(BC29/12)-1,BO29) -> 30527.06
BC30: =BC29+1 -> 27 | BD30: ='Forward Curve'!A28 -> 46003 | BE30: =BE29 -> 6550000 | BF30: 0.036124297 | BG30: =BG29 -> 0.019 | BH30: =BH29 -> 0.002 | BI30: 0.0006 | BJ30: =BJ29 -> 0.001 | BK30: =BF30+BG30+BH30+BI30+BJ30 -> 0.058724297 | BL30: =BK30*(_xlfn.DAYS(BD31,BD30)/360)*BE30 -> 33122.135 | BM30: =BM29 -> 0.0411 | BN30: =BN29 -> 0.0637 | BO30: =BN30*(_xlfn.DAYS(BD31,BD30)/360)*BE30 -> 35928.569 | BP30: =NPV((1+BK30)^(BC30/12)-1,BL30:BL30) -> 29131.097 | BQ30: =NPV((1+BK30)^(BC30/12)-1,BO30) -> 31599.372 | BS30: Sale Date
BC31: =BC30+1 -> 28 | BD31: ='Forward Curve'!A29 -> 46034 | BE31: =BE30 -> 6550000 | BF31: 0.035451383 | BG31: =BG30 -> 0.019 | BH31: =BH30 -> 0.002 | BI31: 0.0006 | BJ31: =BJ30 -> 0.001 | BK31: =BF31+BG31+BH31+BI31+BJ31 -> 0.058051383 | BL31: =BK31*(_xlfn.DAYS(BD32,BD31)/360)*BE31 -> 32742.593 | BM31: =BM30 -> 0.0411 | BN31: =BN30 -> 0.0637 | BO31: =BN31*(_xlfn.DAYS(BD32,BD31)/360)*BE31 -> 35928.569 | BP31: =NPV((1+BK31)^(BC31/12)-1,BL31:BL31) -> 28703.22 | BQ31: =NPV((1+BK31)^(BC31/12)-1,BO31) -> 31496.151
BC32: =BC31+1 -> 29 | BD32: ='Forward Curve'!A30 -> 46065 | BE32: =BE31 -> 6550000 | BF32: 0.034492229 | BG32: =BG31 -> 0.019 | BH32: =BH31 -> 0.002 | BI32: 0.0006 | BJ32: =BJ31 -> 0.001 | BK32: =BF32+BG32+BH32+BI32+BJ32 -> 0.057092229 | BL32: =BK32*(_xlfn.DAYS(BD33,BD32)/360)*BE32 -> 29085.319 | BM32: =BM31 -> 0.0411 | BN32: =BN31 -> 0.0637 | BO32: =BN32*(_xlfn.DAYS(BD33,BD32)/360)*BE32 -> 32451.611 | BP32: =NPV((1+BK32)^(BC32/12)-1,BL32:BL32) -> 25433.202 | BQ32: =NPV((1+BK32)^(BC32/12)-1,BO32) -> 28376.803
BC33: =BC32+1 -> 30 | BD33: ='Forward Curve'!A31 -> 46093 | BE33: =BE32 -> 6550000 | BF33: 0.03391507 | BG33: =BG32 -> 0.019 | BH33: =BH32 -> 0.002 | BI33: 0.0006 | BJ33: =BJ32 -> 0.001 | BK33: =BF33+BG33+BH33+BI33+BJ33 -> 0.05651507 | BL33: =BK33*(_xlfn.DAYS(BD34,BD33)/360)*BE33 -> 31876.069 | BM33: =BM32 -> 0.0411 | BN33: =BN32 -> 0.0637 | BO33: =BN33*(_xlfn.DAYS(BD34,BD33)/360)*BE33 -> 35928.569 | BP33: =NPV((1+BK33)^(BC33/12)-1,BL33:BL33) -> 27782.769 | BQ33: =NPV((1+BK33)^(BC33/12)-1,BO33) -> 31314.875
