Workbook
Name Aspect_Equity_Interest: Summary!$C$22
Name Asset_Management_Fee: Summary!$C$10
Name Capital_Reserves__RSF: Summary!$C$11
Name Cost_of_Sale__Transfer_Tax___Broker_Fee: 'Portfolio-Level CF'!$AC$52
Name Equity_Share_GP: 'JV Waterfall'!$C$8
Name Equity_Share_LP: 'JV Waterfall'!$C$9
Name Interest_Rate: Summary!$C$16
Name LTC: Summary!$C$15
Name Preferred_Return: 'JV Waterfall'!$E$14
Name Total_Equity: 'JV Waterfall'!$D$10
Name Welltower_Equity_Interest: Summary!$C$23

Sheet Summary
B1: Tucker017!
B2: Assumptions | E2: Purchase Price Summary
B3: Sale | E3: Property Address | F3: RSF | G3: % of RSF | H3: Year 1 NOI | I3: % of NOI | J3: Purchase Price | K3: % of Purchase | L3: Cap Rate
B4: Purchase Price | C4: =Summary!J10 -> 99250000 | E4: 131 Kent Road, New Milford, CT 06776 | F4: ='Rent Roll'!C17 -> 29341 | G4: =F4/$F$10 -> 0.14865009 | H4: ='Portfolio-Level CF'!AC16 -> 776823 | I4: =H4/$H$10 -> 0.152728 | J4: 13296853 | K4: =J4/$J$10 -> 0.13397333 | L4: =H4/J4 -> 0.058421568
B5: Earnouts | C5: =C39 -> 2284000 | E5: 164 Mount Pleasant Road, Newtown, CT 06470 | F5: ='Rent Roll'!C30 -> 25984 | G5: =F5/$F$10 -> 0.13164254 | H5: ='Portfolio-Level CF'!AC22 -> 421291 | I5: =H5/$H$10 -> 0.082828302 | J5: 10215862 | K5: =J5/$J$10 -> 0.1029306 | L5: =H5/J5 -> 0.041238909
B6: TI/LC | C6: =C56+C61 -> 1270966.5 | E6: 170 Mount Pleasant Road, Newtown, CT 06470 | F6: ='Rent Roll'!C42 -> 30000 | G6: =F6/$F$10 -> 0.15198877 | H6: ='Portfolio-Level CF'!AC28 -> 638299 | I6: =H6/$H$10 -> 0.12549336 | J6: 11049286 | K6: =J6/$J$10 -> 0.11132782 | L6: =H6/J6 -> 0.057768347
B7: Closing Costs | C7: =C49 -> 935471 | E7: 2 Riverview Drive, Danbury, CT 06810 | F7: ='Rent Roll'!C55 -> 43201 | G7: =F7/$F$10 -> 0.2188689 | H7: ='Portfolio-Level CF'!AC34 -> 1354228 | I7: =H7/$H$10 -> 0.26624923 | J7: 26594452 | K7: =J7/$J$10 -> 0.26795418 | L7: =H7/J7 -> 0.050921448
B8: Lease Legal Costs - DaVita | C8: =C66 -> 10000 | E8: 226 White Street, Danbury, CT 06810 | F8: ='Rent Roll'!C64 -> 26150 | G8: =F8/$F$10 -> 0.13248355 | H8: ='Portfolio-Level CF'!AC40 -> 584129 | I8: =H8/$H$10 -> 0.11484322 | J8: 11256765 | K8: =J8/$J$10 -> 0.11341829 | L8: =H8/J8 -> 0.051891374
B9: Total Development Cost | C9: =C4+SUM(C5:C8) -> 1.0375044e+08 | E9: 40 Old Ridgebury Road, Danbury, CT 06810 | F9: ='Rent Roll'!C75 -> 42707 | G9: =F9/$F$10 -> 0.21636615 | H9: ='Portfolio-Level CF'!AC46 -> 1311547 | I9: =H9/$H$10 -> 0.2578579 | J9: 26836782 | K9: =J9/$J$10 -> 0.27039579 | L9: =H9/J9 -> 0.048871247
B10: Asset Management Fee % | C10: 0.0025 | E10: Total | F10: =SUM(F4:F9) -> 197383 | G10: =SUM(G4:G9) -> 1 | H10: =SUM(H4:H9) -> 5086317 | I10: =SUM(I4:I9) -> 1 | J10: =SUM(J4:J9) -> 99250000 | K10: =SUM(K4:K9) -> 1 | L10: =H10/J10 -> 0.051247526
B11: Capital Reserves (RSF) | C11: 0.5 | J11: =J10+39700000+12000000+7000000 -> 157950000
B12: Portfolio Size (RSF) | C12: =Summary!F10 -> 197383 | E12: Total Development Cost Summary
E13: Property Address | F13: Pro-Rata Closing Costs | G13: Tenant Improvments | H13: Leasing Commissions | I13: Earnouts | J13: Total Cost | K13: % of Total Cost | L13: Cap Rate
B14: Debt | E14: 131 Kent Road, New Milford, CT 06776 | F14: =$C$7*(J4/$J$10) -> 125328.16 | G14: 0 | H14: 0 | I14: 0 | J14: =J4+SUM(F14:I14) -> 13422181 | K14: =J14/$J$20 -> 0.12936988 | L14: =H4/J14 -> 0.057876063
B15: LTC | C15: 0.65 | E15: 164 Mount Pleasant Road, Newtown, CT 06470 | F15: =$C$7*(J5/$J$10) -> 96288.59 | G15: =C54+C55 -> 565220 | H15: =C61 -> 74471.53 | I15: 0 | J15: =J5+SUM(F15:I15)+C8 -> 10961842 | K15: =J15/$J$20 -> 0.10565586 | L15: =H5/J15 -> 0.038432501
B16: Interest Rate | C16: =(4%*(365/360)) -> 0.040555556 | E16: 170 Mount Pleasant Road, Newtown, CT 06470 | F16: =$C$7*(J6/$J$10) -> 104143.95 | G16: =C52+C53 -> 631275 | H16: 0 | I16: =C39 -> 2284000 | J16: =J6+SUM(F16:I16) -> 14068705 | K16: =J16/$J$20 -> 0.1356014 | L16: =H6/J16 -> 0.045370132
B17: Loan Amount | C17: =C9*C15 -> 67437784 | E17: 2 Riverview Drive, Danbury, CT 06810 | F17: =$C$7*(J7/$J$10) -> 250663.36 | G17: 0 | H17: 0 | I17: 0 | J17: =J7+SUM(F17:I17) -> 26845115 | K17: =J17/$J$20 -> 0.25874701 | L17: =H7/J17 -> 0.050445974
B18: Annual Debt Service | C18: =C17*((C16/360)*365) -> 2772962.6 | E18: 226 White Street, Danbury, CT 06810 | F18: =$C$7*(J8/$J$10) -> 106099.52 | G18: 0 | H18: 0 | I18: 0 | J18: =J8+SUM(F18:I18) -> 11362865 | K18: =J18/$J$20 -> 0.10952112 | L18: =H8/J18 -> 0.051406844
E19: 40 Old Ridgebury Road, Danbury, CT 06810 | F19: =$C$7*(J9/$J$10) -> 252947.42 | G19: 0 | H19: 0 | I19: 0 | J19: =J9+SUM(F19:I19) -> 27089729 | K19: =J19/$J$20 -> 0.26110472 | L19: =H9/J19 -> 0.048414917
B20: Equity | E20: Total | F20: =SUM(F14:F19) -> 935471 | G20: =SUM(G14:G19) -> 1196495 | H20: =SUM(H14:H19) -> 74471.53 | I20: =SUM(I14:I19) -> 2284000 | J20: =SUM(J14:J19) -> 1.0375044e+08 | K20: =SUM(K14:K19) -> 1 | L20: =H10/J20 -> 0.049024535
B21: Required Initial Common Capital Contributions | C21: =C9-C17 -> 36312653
B22: Aspect Equity Interest % | C22: 0.05 | E22: Common Equity & Preferred Equity Splits
B23: Welltower Equity Interest % | C23: 0.95 | E23: Property Address | F23: Aspect Common Interest | G23: Welltower Common Interest | H23: Initial Common Capital | I23: Initial Preferred Capital | J23: Welltower Total Interest | K23: Aspect Total Interest | L23: Total Capital
E24: =E4 -> 131 Kent Road, New Milford, CT 06776 | F24: =H24*Summary!$C$22 -> 234888.17 | G24: =H24*Summary!$C$23 -> 4462875.2 | H24: =K14*Summary!$C$21 -> 4697763.4 | I24: =Summary!$C$17*K14 -> 8724417.8 | J24: =I24+G24 -> 13187293 | K24: =F24 -> 234888.17 | L24: =I24+H24 -> 13422181
B25: Aspect Equity Interest | C25: =Summary!F30 -> 1815632.7 | E25: =E5 -> 164 Mount Pleasant Road, Newtown, CT 06470 | F25: =H25*Summary!$C$22 -> 191832.23 | G25: =H25*Summary!$C$23 -> 3644812.5 | H25: =K15*Summary!$C$21 -> 3836644.7 | I25: =Summary!$C$17*K15 -> 7125197.3 | J25: =I25+G25 -> 10770010 | K25: =F25 -> 191832.23 | L25: =I25+H25 -> 10961842
B26: Welltower Equity Interest | C26: =Summary!G30 -> 34497020 | E26: =E6 -> 170 Mount Pleasant Road, Newtown, CT 06470 | F26: =H26*Summary!$C$22 -> 246202.34 | G26: =H26*Summary!$C$23 -> 4677844.4 | H26: =K16*Summary!$C$21 -> 4924046.8 | I26: =Summary!$C$17*K16 -> 9144658.3 | J26: =I26+G26 -> 13822503 | K26: =F26 -> 246202.34 | L26: =I26+H26 -> 14068705
B27: Total Equity Interest | C27: =C25+C26 -> 36312653 | E27: =E7 -> 2 Riverview Drive, Danbury, CT 06810 | F27: =H27*Summary!$C$22 -> 469789.52 | G27: =H27*Summary!$C$23 -> 8926000.9 | H27: =K17*Summary!$C$21 -> 9395790.4 | I27: =Summary!$C$17*K17 -> 17449325 | J27: =I27+G27 -> 26375326 | K27: =F27 -> 469789.52 | L27: =I27+H27 -> 26845115
E28: =E8 -> 226 White Street, Danbury, CT 06810 | F28: =H28*Summary!$C$22 -> 198850.13 | G28: =H28*Summary!$C$23 -> 3778152.5 | H28: =K18*Summary!$C$21 -> 3977002.6 | I28: =Summary!$C$17*K18 -> 7385861.9 | J28: =I28+G28 -> 11164014 | K28: =F28 -> 198850.13 | L28: =I28+H28 -> 11362865
B29: JV Ownership Interest | E29: =E9 -> 40 Old Ridgebury Road, Danbury, CT 06810 | F29: =H29*Summary!$C$22 -> 474070.26 | G29: =H29*Summary!$C$23 -> 9007335 | H29: =K19*Summary!$C$21 -> 9481405.3 | I29: =Summary!$C$17*K19 -> 17608324 | J29: =I29+G29 -> 26615659 | K29: =F29 -> 474070.26 | L29: =I29+H29 -> 27089729
B30: =B9 -> Total Development Cost | C30: =C9 -> 1.0375044e+08 | E30: Total | F30: =SUM(F24:F29) -> 1815632.7 | G30: =SUM(G24:G29) -> 34497020 | H30: =SUM(H24:H29) -> 36312653 | I30: =SUM(I24:I29) -> 67437784 | J30: =SUM(J24:J29) -> 1.019348e+08 | K30: =SUM(K24:K29) -> 1815632.7 | L30: =I30+H30 -> 1.0375044e+08
B31: Aspect Total Interest | C31: =Summary!F30/C30 -> 0.0175
B32: Welltower Total Interest | C32: =Summary!J30/C30 -> 0.9825 | E32: Property Valuation & Leveraged Returns by Property - Year 10 | N32: Leveraged Returns to Equity - Year 10 | R32: Leveraged Returns to Equity - Year 10
E33: Property Address | F33: Year 10 NOI | G33: Year 10 Net Sale Price | H33: Net Gain on Sale | I33: Levered IRR | J33: Equity Multiple | K33: Average Cash on Cash | L33: Cap Spread | N33: Leveraged Project Returns | O33: Amount | P33: $ PSF | R33: Aspect Health Inc. Returns | S33: Amount | T33: $ PSF
E34: =E24 -> 131 Kent Road, New Milford, CT 06776 | F34: ='Property-Level CF'!M10 -> 884835 | G34: =(F34/L4)*(1-'Portfolio-Level CF'!$AC$52) -> 14562582 | H34: =G34-J4 -> 1265728.7 | I34: ='Property-Level CF'!M44 -> 0.080202328 | J34: ='Property-Level CF'!M45 -> 1.8775317 | K34: ='Property-Level CF'!M42 -> 0.063477776 | L34: ='Property-Level CF'!M20 -> 0.0075017712 | N34: Total Proceeds | O34: =SUM('Portfolio-Level CF'!D39:M39) -> 81273719 | P34: =O34/$C$12 -> 411.75643 | R34: Total GP Distributions | S34: =SUM('Portfolio-Level CF'!D52:M52)+'Portfolio-Level CF'!M66-'Portfolio-Level CF'!M54 -> 4063685.9 | T34: =S34/$C$12 -> 20.587821
B35: Additional Development Costs | E35: =E25 -> 164 Mount Pleasant Road, Newtown, CT 06470 | F35: ='Property-Level CF'!AL10 -> 791022 | G35: =(F35/L5)*(1-'Portfolio-Level CF'!$AC$52) -> 18442962 | H35: =G35-J5 -> 8227100.6 | I35: ='Property-Level CF'!AL44 -> 0.13599865 | J35: ='Property-Level CF'!AL45 -> 2.8608086 | K35: ='Property-Level CF'!AL42 -> 0.097761736 | L35: ='Property-Level CF'!AL20 -> 0.019161412 | N35: Capital Contribution | O35: ='Portfolio-Level CF'!C39 -> -36312653 | P35: =-O35/$C$12 -> 183.97052 | R35: Total Asset Management Fee's | S35: =SUM('Portfolio-Level CF'!D53:M53) -> 907816.33 | T35: =S35/$C$12 -> 4.599263
B36: Earnouts | E36: =E26 -> 170 Mount Pleasant Road, Newtown, CT 06470 | F36: ='Property-Level CF'!BK10 -> 987095 | G36: =(F36/L6)*(1-'Portfolio-Level CF'!$AC$52) -> 16429271 | H36: =G36-J6 -> 5379985 | I36: ='Property-Level CF'!BK44 -> 0.13334286 | J36: ='Property-Level CF'!BK45 -> 2.7893739 | K36: ='Property-Level CF'!BK42 -> 0.1009794 | L36: ='Property-Level CF'!BK20 -> 0.017162463 | N36: Net Profit | O36: =O34+O35 -> 44961066 | P36: =O36/$C$12 -> 227.78591 | R36: Capital Contribution | S36: ='Portfolio-Level CF'!C54 -> -1815632.7 | T36: =-S36/$C$12 -> 9.198526
B37: Women's Health | C37: 1362000 | E37: =E27 -> 2 Riverview Drive, Danbury, CT 06810 | F37: ='Property-Level CF'!CJ10 -> 1584598 | G37: =(F37/L7)*(1-'Portfolio-Level CF'!$AC$52) -> 29920417 | H37: =G37-J7 -> 3325965.5 | I37: ='Property-Level CF'!CJ44 -> 0.094007475 | J37: ='Property-Level CF'!CJ45 -> 2.1008023 | K37: ='Property-Level CF'!CJ42 -> 0.077349589 | L37: ='Property-Level CF'!CJ20 -> 0.0081059759 | R37: Net GP Profit | S37: =S34+S35+S36 -> 3155869.6 | T37: =S37/$C$12 -> 15.988558
B38: AccessPT | C38: 922000 | E38: =E28 -> 226 White Street, Danbury, CT 06810 | F38: ='Property-Level CF'!DI10 -> 698088 | G38: =(F38/L8)*(1-'Portfolio-Level CF'!$AC$52) -> 12934936 | H38: =G38-J8 -> 1678171.3 | I38: ='Property-Level CF'!DI44 -> 0.10089337 | J38: ='Property-Level CF'!DI45 -> 2.2070377 | K38: ='Property-Level CF'!DI42 -> 0.081174707 | L38: ='Property-Level CF'!DI20 -> 0.0095445431 | N38: IRR | O38: ='Portfolio-Level CF'!M44 -> 0.10385787
B39: Total | C39: =SUM(C37:C38) -> 2284000 | E39: =E29 -> 40 Old Ridgebury Road, Danbury, CT 06810 | F39: ='Property-Level CF'!EH10 -> 1567320 | G39: =(F39/L9)*(1-'Portfolio-Level CF'!$AC$52) -> 30835681 | H39: =G39-J9 -> 3998899 | I39: ='Property-Level CF'!EH44 -> 0.093715507 | J39: ='Property-Level CF'!EH45 -> 2.1235596 | K39: ='Property-Level CF'!CJ42 -> 0.077349589 | L39: ='Property-Level CF'!EH20 -> 0.0089853664 | N39: Equity Multiple | O39: ='Portfolio-Level CF'!M45 -> 2.2381653 | R39: IRR | S39: ='Portfolio-Level CF'!M68 -> 0.14754039
E40: Total | F40: =SUM(F34:F39) -> 6512958 | G40: =F40/'Portfolio-Level CF'!M18*(1-'Portfolio-Level CF'!AC52) -> 1.2051134e+08 | H40: =G40-L30 -> 16760905 | I40: ='Portfolio-Level CF'!M44 -> 0.10385787 | J40: ='Portfolio-Level CF'!M45 -> 2.2381653 | K40: ='Portfolio-Level CF'!M42 -> 0.077659323 | L40: ='Portfolio-Level CF'!M20 -> 0.010811585 | N40: Avg Cash-on-Cash | O40: ='Portfolio-Level CF'!M42 -> 0.077659323 | R40: Equity Multiple | S40: ='Portfolio-Level CF'!M69 -> 2.2381653
B41: Closing Costs
B42: PCA | C42: 19050 | E42: Property Valuation & Leveraged Returns by Property - Year 5 | N42: Leveraged Returns to Equity - Year 5 | R42: Leveraged Returns to Equity - Year 5
B43: Phase 1 | C43: 28000 | E43: Property Address | F43: Year 5 NOI | G43: Year 5 Net Sale Price | H43: Net Gain on Sale | I43: Levered IRR | J43: Equity Multiple | K43: Average Cash on Cash | L43: Cap Spread | N43: Leveraged Project Returns | O43: Amount | P43: $ PSF | R43: Aspect Health Inc. Returns | S43: Amount | T43: $ PSF
B44: Survey | C44: 33470 | E44: =E34 -> 131 Kent Road, New Milford, CT 06776 | F44: ='Property-Level CF'!H10 -> 839376 | G44: =(F44/L4)*(1-'Portfolio-Level CF'!$AC$52) -> 13814419 | H44: =G44-J4 -> 517566.12 | I44: ='Property-Level CF'!H44 -> 0.0858378 | J44: ='Property-Level CF'!H45 -> 1.4522655 | K44: ='Property-Level CF'!H42 -> 0.073754177 | L44: ='Property-Level CF'!H20 -> 0.0041149148 | N44: Total Proceeds | O44: =SUM('Portfolio-Level CF'!T19:T23) -> 56387827 | P44: =O44/$C$12 -> 285.67722 | R44: Total GP Distributions | S44: =SUM('Portfolio-Level CF'!H57:H61) -> 3273299.5 | T44: =S44/$C$12 -> 16.583492
B45: Appraisal | C45: 30000 | E45: =E35 -> 164 Mount Pleasant Road, Newtown, CT 06470 | F45: ='Property-Level CF'!AG10 -> 762241 | G45: =(F45/L5)*(1-'Portfolio-Level CF'!$AC$52) -> 17771923 | H45: =G45-J5 -> 7556061.2 | I45: ='Property-Level CF'!AG44 -> 0.181736 | J45: ='Property-Level CF'!AG45 -> 2.1865479 | K45: ='Property-Level CF'!AG42 -> 0.087889411 | L45: ='Property-Level CF'!AG20 -> 0.01653585 | N45: Capital Contribution | O45: =O35 -> -36312653 | P45: =-O45/$C$12 -> 183.97052 | R45: Total Asset Management Fee's | S45: =SUM('Portfolio-Level CF'!D53:H53) -> 453908.16 | T45: =S45/$C$12 -> 2.2996315
B46: Contingency | C46: 30000 | E46: =E36 -> 170 Mount Pleasant Road, Newtown, CT 06470 | F46: ='Property-Level CF'!BF10 -> 891356 | G46: =(F46/L6)*(1-'Portfolio-Level CF'!$AC$52) -> 14835785 | H46: =G46-J6 -> 3786499.1 | I46: ='Property-Level CF'!BF44 -> 0.14465338 | J46: ='Property-Level CF'!BF45 -> 1.85962 | K46: ='Property-Level CF'!BF42 -> 0.086553641 | L46: ='Property-Level CF'!BF20 -> 0.010357359 | N46: Net Profit | O46: =O44+O45 -> 20075173 | P46: =O46/$C$12 -> 101.7067 | R46: Capital Contribution | S46: =S36 -> -1815632.7 | T46: =-S46/$C$12 -> 9.198526
B47: Title Costs | C47: 294951 | E47: =E37 -> 2 Riverview Drive, Danbury, CT 06810 | F47: ='Property-Level CF'!CE10 -> 1451191 | G47: =(F47/L7)*(1-'Portfolio-Level CF'!$AC$52) -> 27401423 | H47: =G47-J7 -> 806971.29 | I47: ='Property-Level CF'!CE44 -> 0.07783123 | J47: ='Property-Level CF'!CE45 -> 1.4121116 | K47: ='Property-Level CF'!CE42 -> 0.070580685 | L47: ='Property-Level CF'!CE20 -> 0.0031364685 | R47: Net GP Profit | S47: =S44+S45+S46 -> 1911575 | T47: =S47/$C$12 -> 9.684598
B48: Legal | C48: 500000 | E48: =E38 -> 226 White Street, Danbury, CT 06810 | F48: ='Property-Level CF'!DD10 -> 632280 | G48: =(F48/L8)*(1-'Portfolio-Level CF'!$AC$52) -> 11715574 | H48: =G48-J8 -> 458808.82 | I48: ='Property-Level CF'!DD44 -> 0.085187853 | J48: ='Property-Level CF'!DD45 -> 1.4547836 | K48: ='Property-Level CF'!DD42 -> 0.073219268 | L48: ='Property-Level CF'!DD20 -> 0.0037530457 | N48: IRR | O48: ='Portfolio-Level CF'!H44 -> 0.10227762
B49: Total | C49: =SUM(C42:C48) -> 935471 | E49: =E39 -> 40 Old Ridgebury Road, Danbury, CT 06810 | F49: ='Property-Level CF'!EC10 -> 1419623 | G49: =(F49/L9)*(1-'Portfolio-Level CF'!$AC$52) -> 27929869 | H49: =G49-J9 -> 1093086.8 | I49: ='Property-Level CF'!EC44 -> 0.077607943 | J49: ='Property-Level CF'!EC45 -> 1.4153903 | K49: ='Property-Level CF'!EC42 -> 0.065356226 | L49: ='Property-Level CF'!EC20 -> 0.0035332263 | N49: Equity Multiple | O49: ='Portfolio-Level CF'!H45 -> 1.5528424 | R49: IRR | S49: ='Portfolio-Level CF'!H68 -> 0.14899957
E50: Total | F50: =SUM(F44:F49) -> 5996067 | G50: =F50/'Portfolio-Level CF'!H18*(1-'Portfolio-Level CF'!AC52) -> 1.1086003e+08 | H50: =G50-L30 -> 7109593.1 | I50: ='Portfolio-Level CF'!H44 -> 0.10227762 | J50: ='Portfolio-Level CF'!H45 -> 1.5528424 | K50: ='Portfolio-Level CF'!H42 -> 0.071410813 | L50: ='Portfolio-Level CF'!H20 -> 0.0057886916 | N50: Avg Cash-on-Cash | O50: ='Portfolio-Level CF'!H42 -> 0.071410813 | R50: Equity Multiple | S50: ='Portfolio-Level CF'!H69 -> 1.5528424
B51: TI's
B52: AccessPT - $75 RSF @ 2,297 RSF | C52: =75*2297 -> 172275 | E52: Purchase Price Summary - Adjusted NOI Cap Rate Analysis
B53: Women's Health - $120 RSF @ 3,825 RSF | C53: =120*3825 -> 459000 | E53: Property Address | F53: Year 1 Unadjusted NOI | G53: Free Rent | H53: OpEx Leakage | I53: Year 1 Adjusted NOI | J53: NOI Variance | K53: Adjusted Cap Rate | L53: Cap Spread
B54: DaVita - Initial Premise - $20 @ 9,411 RSF | C54: =20*'Rent Roll'!C24 -> 188220 | E54: 131 Kent Road, New Milford, CT 06776 | F54: =H4 -> 776823 | G54: 0 | H54: ='Cash Flow Dump'!B44-'Cash Flow Dump'!B22 -> 6458 | I54: =F54+SUM(G54:H54) -> 783281 | J54: =I54-F54 -> 6458 | K54: =I54/J4 -> 0.058907247 | L54: =K54-L4 -> 0.00048567883
B55: DaVita - Expansion Premise - $100 @ 3,770 RSF | C55: =100*'Rent Roll'!C28 -> 377000 | E55: 164 Mount Pleasant Road, Newtown, CT 06470 | F55: =H5 -> 421291 | G55: =-'Cash Flow Dump'!P16 -> 67769 | H55: ='Cash Flow Dump'!P44-'Cash Flow Dump'!P22 -> 72422 | I55: =F55+SUM(G55:H55) -> 561482 | J55: =I55-F55 -> 140191 | K55: =I55/J5 -> 0.054961785 | L55: =K55-L5 -> 0.013722875
B56: Total | C56: =SUM(C52:C55) -> 1196495 | E56: 170 Mount Pleasant Road, Newtown, CT 06470 | F56: =H6 -> 638299 | G56: =-'Cash Flow Dump'!AD16 -> 82913 | H56: ='Cash Flow Dump'!AD46-'Cash Flow Dump'!AD22 -> 28810 | I56: =F56+SUM(G56:H56) -> 750022 | J56: =I56-F56 -> 111723 | K56: =I56/J6 -> 0.067879679 | L56: =K56-L6 -> 0.010111332
E57: 2 Riverview Drive, Danbury, CT 06810 | F57: =H7 -> 1354228 | G57: 0 | H57: ='Cash Flow Dump'!AR44-'Cash Flow Dump'!AR21 -> 0 | I57: =F57+SUM(G57:H57) -> 1354228 | J57: =I57-F57 -> 0 | K57: =I57/J7 -> 0.050921448 | L57: =K57-L7 -> 0
B58: LC's | E58: 226 White Street, Danbury, CT 06810 | F58: =H8 -> 584129 | G58: 0 | H58: ='Cash Flow Dump'!BF37-'Cash Flow Dump'!BF20 -> 0 | I58: =F58+SUM(G58:H58) -> 584129 | J58: =I58-F58 -> 0 | K58: =I58/J8 -> 0.051891374 | L58: =K58-L8 -> 0
B59: DaVita - Initial Premise | C59: ='Rent Roll'!M28 -> 53925.03 | E59: 40 Old Ridgebury Road, Danbury, CT 06810 | F59: =H9 -> 1311547 | G59: 0 | H59: ='Cash Flow Dump'!BT43-'Cash Flow Dump'!BT20 -> 0 | I59: =F59+SUM(G59:H59) -> 1311547 | J59: =I59-F59 -> 0 | K59: =I59/J9 -> 0.048871247 | L59: =K59-L9 -> 0
B60: DaVita - Expansion Premise | C60: ='Rent Roll'!M29 -> 20546.5 | E60: Total | F60: =SUM(F54:F59) -> 5086317 | G60: =SUM(G54:G59) -> 150682 | H60: =SUM(H54:H59) -> 107690 | I60: =SUM(I54:I59) -> 5344689 | J60: =I60-H10 -> 258372 | K60: =I60/J10 -> 0.053850771 | L60: =K60-L10 -> 0.0026032443
B61: Total | C61: =SUM(C59:C60) -> 74471.53
E62: Total Development Cost Summary - Adjusted NOI Cap Rate Analysis
B63: Legal | E63: Property Address | F63: Pro-Rata Closing Costs | G63: Tenant Improvments | H63: Leasing Commissions | I63: Earnouts | J63: Total Cost | K63: Adjusted Cap Rate | L63: Cap Spread
B64: DaVita - Initial Premise | C64: =C66*('Rent Roll'!C24)/('Rent Roll'!C24+'Rent Roll'!C28) -> 7139.8225 | E64: 131 Kent Road, New Milford, CT 06776 | F64: =Summary!F14 -> 125328.16 | G64: =Summary!G14 -> 0 | H64: =Summary!H14 -> 0 | I64: =Summary!I14 -> 0 | J64: =Summary!J14 -> 13422181 | K64: =I54/J64 -> 0.058357207 | L64: =K64-L14 -> 0.00048114386
B65: DaVita - Expansion Premise | C65: =C66*('Rent Roll'!C28)/('Rent Roll'!C24+'Rent Roll'!C28) -> 2860.1775 | E65: 164 Mount Pleasant Road, Newtown, CT 06470 | F65: =Summary!F15 -> 96288.59 | G65: =Summary!G15 -> 565220 | H65: =Summary!H15 -> 74471.53 | I65: =Summary!I15 -> 0 | J65: =Summary!J15 -> 10961842 | K65: =I55/J65 -> 0.051221501 | L65: =K65-L15 -> 0.012789
B66: Total | C66: 10000 | E66: 170 Mount Pleasant Road, Newtown, CT 06470 | F66: =Summary!F16 -> 104143.95 | G66: =Summary!G16 -> 631275 | H66: =Summary!H16 -> 0 | I66: =Summary!I16 -> 2284000 | J66: =Summary!J16 -> 14068705 | K66: =I56/J66 -> 0.053311374 | L66: =K66-L16 -> 0.0079412426
E67: 2 Riverview Drive, Danbury, CT 06810 | F67: =Summary!F17 -> 250663.36 | G67: =Summary!G17 -> 0 | H67: =Summary!H17 -> 0 | I67: =Summary!I17 -> 0 | J67: =Summary!J17 -> 26845115 | K67: =I57/J67 -> 0.050445974 | L67: =K67-L17 -> 0
E68: 226 White Street, Danbury, CT 06810 | F68: =Summary!F18 -> 106099.52 | G68: =Summary!G18 -> 0 | H68: =Summary!H18 -> 0 | I68: =Summary!I18 -> 0 | J68: =Summary!J18 -> 11362865 | K68: =I58/J68 -> 0.051406844 | L68: =K68-L18 -> 0
E69: 40 Old Ridgebury Road, Danbury, CT 06810 | F69: =Summary!F19 -> 252947.42 | G69: =Summary!G19 -> 0 | H69: =Summary!H19 -> 0 | I69: =Summary!I19 -> 0 | J69: =Summary!J19 -> 27089729 | K69: =I59/J69 -> 0.048414917 | L69: =K69-L19 -> 0
E70: Total | F70: =SUM(F64:F69) -> 935471 | G70: =SUM(G64:G69) -> 1196495 | H70: =SUM(H64:H69) -> 74471.53 | I70: =SUM(I64:I69) -> 2284000 | J70: =SUM(J64:J69) -> 1.0375044e+08 | K70: =I60/J70 -> 0.051514857 | L70: =K70-L20 -> 0.002490322

Sheet Portfolio-Level CF
B2: CASH FLOW | O2: Year | P2: =D5 -> Year 1 | Q2: =E5 -> Year 2 | R2: =F5 -> Year 3 | S2: =G5 -> Year 4 | T2: =H5 -> Year 5 | U2: =I5 -> Year 6 | V2: =J5 -> Year 7 | W2: =K5 -> Year 8 | ... Y2: =M5 -> Year 10 | AA2: CASH FLOW
B3: Portfolio-Level Cash Flow Roll-Up | O3: Unlevered IRR | P3: =IRR(P4:P15) -> 0.0095634648 | Q3: =IRR(Q4:Q15) -> 0.036675356 | R3: =IRR(R4:R15) -> 0.060475501 | S3: =IRR(S4:S15) -> 0.061822143 | T3: =IRR(T4:T15) -> 0.0644085 | U3: =IRR(U4:U15) -> 0.063805188 | V3: =IRR(V4:V15) -> 0.065162092 | W3: =IRR(W4:W15) -> 0.066281943 | ... Y3: =IRR(Y4:Y15) -> 0.066186186 | AA3: Property-Level Cash Flow
G4: =(H10-'Rent Roll'!K12) -> 5779833.2 | H4: =G4/99100000 -> 0.058323241 | O4: 0 | P4: =C16 -> -1.0375044e+08 | Q4: =P4 -> -1.0375044e+08 | R4: =Q4 -> -1.0375044e+08 | S4: =R4 -> -1.0375044e+08 | T4: =S4 -> -1.0375044e+08 | U4: =T4 -> -1.0375044e+08 | V4: =U4 -> -1.0375044e+08 | W4: =V4 -> -1.0375044e+08 | X4: =W4 -> -1.0375044e+08 | Y4: =X4 -> -1.0375044e+08
C5: Year 0 | D5: Year 1 | E5: Year 2 | F5: Year 3 | G5: Year 4 | H5: Year 5 | I5: Year 6 | J5: Year 7 | K5: Year 8 | L5: Year 9 | M5: Year 10 | O5: =O4+1 -> 1 | P5: =D23+D14 -> 1.0474265e+08 | Q5: =D14 -> 4986605.5 | R5: =Q5 -> 4986605.5 | S5: =R5 -> 4986605.5 | T5: =S5 -> 4986605.5 | U5: =T5 -> 4986605.5 | V5: =U5 -> 4986605.5 | W5: =V5 -> 4986605.5 | X5: =W5 -> 4986605.5 | Y5: =X5 -> 4986605.5 | AC5: ='Portfolio-Level CF'!D5 -> Year 1 | AD5: ='Portfolio-Level CF'!E5 -> Year 2 | AE5: ='Portfolio-Level CF'!F5 -> Year 3 | AF5: ='Portfolio-Level CF'!G5 -> Year 4 | AG5: ='Portfolio-Level CF'!H5 -> Year 5 | AH5: ='Portfolio-Level CF'!I5 -> Year 6 | AI5: ='Portfolio-Level CF'!J5 -> Year 7 | AJ5: ='Portfolio-Level CF'!K5 -> Year 8 | ... AL5: ='Portfolio-Level CF'!M5 -> Year 10
B6: Year Ending | C6: 44377 | D6: 44742 | E6: 45107 | F6: 45473 | G6: 45838 | H6: 46203 | I6: 46568 | J6: 46934 | K6: 47299 | L6: 47664 | M6: 48029 | O6: =O5+1 -> 2 | Q6: =E23+E14 -> 1.0633067e+08 | R6: =E14 -> 5314553.5 | S6: =R6 -> 5314553.5 | T6: =S6 -> 5314553.5 | U6: =T6 -> 5314553.5 | V6: =U6 -> 5314553.5 | W6: =V6 -> 5314553.5 | X6: =W6 -> 5314553.5 | Y6: =X6 -> 5314553.5 | AA6: # | AB6: Year Ending | AC6: ='Portfolio-Level CF'!D6 -> 44742 | AD6: ='Portfolio-Level CF'!E6 -> 45107 | AE6: ='Portfolio-Level CF'!F6 -> 45473 | AF6: ='Portfolio-Level CF'!G6 -> 45838 | AG6: ='Portfolio-Level CF'!H6 -> 46203 | AH6: ='Portfolio-Level CF'!I6 -> 46568 | AI6: ='Portfolio-Level CF'!J6 -> 46934 | AJ6: ='Portfolio-Level CF'!K6 -> 47299 | ... AL6: ='Portfolio-Level CF'!M6 -> 48029
B7: Average Occupancy % | D7: ='Occupancy Report'!D24 -> 0.95533979 | E7: ='Occupancy Report'!H24 -> 1 | F7: ='Occupancy Report'!L24 -> 0.99949042 | G7: ='Occupancy Report'!P24 -> 0.99694165 | H7: ='Occupancy Report'!T24 -> 1 | I7: ='Occupancy Report'!X24 -> 0.99211685 | J7: ='Occupancy Report'!AB24 -> 0.99582284 | K7: ='Occupancy Report'!AF24 -> 0.99945537 | L7: ='Occupancy Report'!AJ24 -> 0.9959533 | M7: ='Occupancy Report'!AN24 -> 0.99590812 | O7: =O6+1 -> 3 | R7: =F23+F14 -> 1.1249087e+08 | S7: =F14 -> 5626184.5 | T7: =S7 -> 5626184.5 | U7: =T7 -> 5626184.5 | V7: =U7 -> 5626184.5 | W7: =V7 -> 5626184.5 | X7: =W7 -> 5626184.5 | Y7: =X7 -> 5626184.5 | AA7: - | AB7: Portfolio Wrap-up
O8: =O7+1 -> 4 | S8: =G23+G14 -> 1.139497e+08 | T8: =G14 -> 5459582.5 | U8: =T8 -> 5459582.5 | V8: =U8 -> 5459582.5 | W8: =V8 -> 5459582.5 | X8: =W8 -> 5459582.5 | Y8: =X8 -> 5459582.5 | AB8: EGR | AC8: =SUMIF($AB$14:$AB$145,$AB8,AC14:AC145) -> 7185904 | AD8: =SUMIF($AB$14:$AB$145,$AB8,AD14:AD145) -> 7620803 | AE8: =SUMIF($AB$14:$AB$145,$AB8,AE14:AE145) -> 8000831 | AF8: =SUMIF($AB$14:$AB$145,$AB8,AF14:AF145) -> 8140118 | AG8: =SUMIF($AB$14:$AB$145,$AB8,AG14:AG145) -> 8327368 | AH8: =SUMIF($AB$14:$AB$145,$AB8,AH14:AH145) -> 8415129 | AI8: =SUMIF($AB$14:$AB$145,$AB8,AI14:AI145) -> 8623077 | AJ8: =SUMIF($AB$14:$AB$145,$AB8,AJ14:AJ145) -> 8819545 | ... AL8: =SUMIF($AB$14:$AB$145,$AB8,AL14:AL145) -> 9141460
B9: Effective Gross Rent | D9: ='Portfolio-Level CF'!AC8 -> 7185904 | E9: ='Portfolio-Level CF'!AD8 -> 7620803 | F9: ='Portfolio-Level CF'!AE8 -> 8000831 | G9: ='Portfolio-Level CF'!AF8 -> 8140118 | H9: ='Portfolio-Level CF'!AG8 -> 8327368 | I9: ='Portfolio-Level CF'!AH8 -> 8415129 | J9: ='Portfolio-Level CF'!AI8 -> 8623077 | K9: ='Portfolio-Level CF'!AJ8 -> 8819545 | ... M9: ='Portfolio-Level CF'!AL8 -> 9141460 | O9: =O8+1 -> 5 | T9: =H23+H14 -> 1.1675741e+08 | U9: =H14 -> 5897375.5 | V9: =U9 -> 5897375.5 | W9: =V9 -> 5897375.5 | X9: =W9 -> 5897375.5 | Y9: =X9 -> 5897375.5 | AB9: NOI | AC9: =IF(AC$5="","",SUMIF($AB$14:$AB$145,$AB$9,AC14:AC145)) -> 5086317 | AD9: =IF(AD$5="","",SUMIF($AB$14:$AB$145,$AB$9,AD14:AD145)) -> 5459796 | AE9: =IF(AE$5="","",SUMIF($AB$14:$AB$145,$AB$9,AE14:AE145)) -> 5779539 | AF9: =IF(AF$5="","",SUMIF($AB$14:$AB$145,$AB$9,AF14:AF145)) -> 5865233 | AG9: =IF(AG$5="","",SUMIF($AB$14:$AB$145,$AB$9,AG14:AG145)) -> 5996067 | AH9: =IF(AH$5="","",SUMIF($AB$14:$AB$145,$AB$9,AH14:AH145)) -> 6029402 | AI9: =IF(AI$5="","",SUMIF($AB$14:$AB$145,$AB$9,AI14:AI145)) -> 6177842 | AJ9: =IF(AJ$5="","",SUMIF($AB$14:$AB$145,$AB$9,AJ14:AJ145)) -> 6313834 | ... AL9: =IF(AL$5="","",SUMIF($AB$14:$AB$145,$AB$9,AL14:AL145)) -> 6512958
B10: Net Operating Income | D10: ='Portfolio-Level CF'!AC9 -> 5086317 | E10: ='Portfolio-Level CF'!AD9 -> 5459796 | F10: ='Portfolio-Level CF'!AE9 -> 5779539 | G10: ='Portfolio-Level CF'!AF9 -> 5865233 | H10: ='Portfolio-Level CF'!AG9 -> 5996067 | I10: ='Portfolio-Level CF'!AH9 -> 6029402 | J10: ='Portfolio-Level CF'!AI9 -> 6177842 | K10: ='Portfolio-Level CF'!AJ9 -> 6313834 | ... M10: ='Portfolio-Level CF'!AL9 -> 6512958 | O10: =O9+1 -> 6 | U10: =I23+I14 -> 1.175448e+08 | V10: =I14 -> 5930710.5 | W10: =V10 -> 5930710.5 | X10: =W10 -> 5930710.5 | Y10: =X10 -> 5930710.5 | AB10: NCF before DS | AC10: =SUMIF($AB$14:$AB$145,$AB$10,AC14:AC145) -> 4986605.5 | AD10: =SUMIF($AB$14:$AB$145,$AB$10,AD14:AD145) -> 5314553.5 | AE10: =SUMIF($AB$14:$AB$145,$AB$10,AE14:AE145) -> 5626184.5 | AF10: =SUMIF($AB$14:$AB$145,$AB$10,AF14:AF145) -> 5459582.5 | AG10: =SUMIF($AB$14:$AB$145,$AB$10,AG14:AG145) -> 5897375.5 | AH10: =SUMIF($AB$14:$AB$145,$AB$10,AH14:AH145) -> 5930710.5 | AI10: =SUMIF($AB$14:$AB$145,$AB$10,AI14:AI145) -> 5631357.5 | AJ10: =SUMIF($AB$14:$AB$145,$AB$10,AJ14:AJ145) -> 6215142.5 | ... AL10: =SUMIF($AB$14:$AB$145,$AB$10,AL14:AL145) -> 5967977.5
B11: Tenant Improvement | D11: ='Property-Level CF'!CA11+'Property-Level CF'!DY11+'Property-Level CF'!CZ11+'Property-Level CF'!D11+'Property-Level CF'!AC11+'Property-Level CF'!BB11 -> 0 | E11: ='Property-Level CF'!CB11+'Property-Level CF'!DZ11+'Property-Level CF'!DA11+'Property-Level CF'!E11+'Property-Level CF'!AD11+'Property-Level CF'!BC11 -> 41850 | F11: ='Property-Level CF'!CC11+'Property-Level CF'!EA11+'Property-Level CF'!DB11+'Property-Level CF'!F11+'Property-Level CF'!AE11+'Property-Level CF'!BD11 -> 45149 | G11: ='Property-Level CF'!CD11+'Property-Level CF'!EB11+'Property-Level CF'!DC11+'Property-Level CF'!G11+'Property-Level CF'!AF11+'Property-Level CF'!BE11 -> 253532 | H11: ='Property-Level CF'!CE11+'Property-Level CF'!EC11+'Property-Level CF'!DD11+'Property-Level CF'!H11+'Property-Level CF'!AG11+'Property-Level CF'!BF11 -> 0 | I11: ='Property-Level CF'!CF11+'Property-Level CF'!ED11+'Property-Level CF'!DE11+'Property-Level CF'!I11+'Property-Level CF'!AH11+'Property-Level CF'!BG11 -> 0 | J11: ='Property-Level CF'!CG11+'Property-Level CF'!EE11+'Property-Level CF'!DF11+'Property-Level CF'!J11+'Property-Level CF'!AI11+'Property-Level CF'!BH11 -> 427040 | K11: ='Property-Level CF'!CH11+'Property-Level CF'!EF11+'Property-Level CF'!DG11+'Property-Level CF'!K11+'Property-Level CF'!AJ11+'Property-Level CF'!BI11 -> 0 | ... M11: ='Property-Level CF'!CJ11+'Property-Level CF'!EH11+'Property-Level CF'!DI11+'Property-Level CF'!M11+'Property-Level CF'!AL11+'Property-Level CF'!BK11 -> 403214 | O11: =O10+1 -> 7 | V11: =J23+J14 -> 1.199805e+08 | W11: =J14 -> 5631357.5 | X11: =W11 -> 5631357.5 | Y11: =X11 -> 5631357.5 | AB11: DS | AC11: =SUMIF($AB$14:$AB$145,$AB$10,AC15:AC146) -> 2772962.6 | AD11: =SUMIF($AB$14:$AB$145,$AB$10,AD15:AD146) -> 2772962.6 | AE11: =SUMIF($AB$14:$AB$145,$AB$10,AE15:AE146) -> 2772962.6 | AF11: =SUMIF($AB$14:$AB$145,$AB$10,AF15:AF146) -> 2772962.6 | AG11: =SUMIF($AB$14:$AB$145,$AB$10,AG15:AG146) -> 2772962.6 | AH11: =SUMIF($AB$14:$AB$145,$AB$10,AH15:AH146) -> 2772962.6 | AI11: =SUMIF($AB$14:$AB$145,$AB$10,AI15:AI146) -> 2772962.6 | AJ11: =SUMIF($AB$14:$AB$145,$AB$10,AJ15:AJ146) -> 2772962.6 | ... AL11: =SUMIF($AB$14:$AB$145,$AB$10,AL15:AL146) -> 2772962.6
B12: Leasing Commissions | D12: ='Property-Level CF'!CA12+'Property-Level CF'!DY12+'Property-Level CF'!CZ12+'Property-Level CF'!D12+'Property-Level CF'!AC12+'Property-Level CF'!BB12 -> 1020 | E12: ='Property-Level CF'!CB12+'Property-Level CF'!DZ12+'Property-Level CF'!DA12+'Property-Level CF'!E12+'Property-Level CF'!AD12+'Property-Level CF'!BC12 -> 4701 | F12: ='Property-Level CF'!CC12+'Property-Level CF'!EA12+'Property-Level CF'!DB12+'Property-Level CF'!F12+'Property-Level CF'!AE12+'Property-Level CF'!BD12 -> 9514 | G12: ='Property-Level CF'!CD12+'Property-Level CF'!EB12+'Property-Level CF'!DC12+'Property-Level CF'!G12+'Property-Level CF'!AF12+'Property-Level CF'!BE12 -> 53427 | H12: ='Property-Level CF'!CE12+'Property-Level CF'!EC12+'Property-Level CF'!DD12+'Property-Level CF'!H12+'Property-Level CF'!AG12+'Property-Level CF'!BF12 -> 0 | I12: ='Property-Level CF'!CF12+'Property-Level CF'!ED12+'Property-Level CF'!DE12+'Property-Level CF'!I12+'Property-Level CF'!AH12+'Property-Level CF'!BG12 -> 0 | J12: ='Property-Level CF'!CG12+'Property-Level CF'!EE12+'Property-Level CF'!DF12+'Property-Level CF'!J12+'Property-Level CF'!AI12+'Property-Level CF'!BH12 -> 20753 | K12: ='Property-Level CF'!CH12+'Property-Level CF'!EF12+'Property-Level CF'!DG12+'Property-Level CF'!K12+'Property-Level CF'!AJ12+'Property-Level CF'!BI12 -> 0 | ... M12: ='Property-Level CF'!CJ12+'Property-Level CF'!EH12+'Property-Level CF'!DI12+'Property-Level CF'!M12+'Property-Level CF'!AL12+'Property-Level CF'!BK12 -> 43075 | O12: =O11+1 -> 8 | W12: =K23+K14 -> 1.2303209e+08 | X12: =K14 -> 6215142.5 | Y12: =X12 -> 6215142.5 | AB12: NCF after DS | AC12: =AC10-AC11 -> 2213642.9 | AD12: =AD10-AD11 -> 2541590.9 | AE12: =AE10-AE11 -> 2853221.9 | AF12: =AF10-AF11 -> 2686619.9 | AG12: =AG10-AG11 -> 3124412.9 | AH12: =AH10-AH11 -> 3157747.9 | AI12: =AI10-AI11 -> 2858394.9 | AJ12: =AJ10-AJ11 -> 3442179.9 | ... AL12: =AL10-AL11 -> 3195014.9
B13: Capital Reserves | D13: =Summary!C12*Summary!$C$11 -> 98691.5 | E13: =D13 -> 98691.5 | F13: =E13 -> 98691.5 | G13: =F13 -> 98691.5 | H13: =G13 -> 98691.5 | I13: =H13 -> 98691.5 | J13: =I13 -> 98691.5 | K13: =J13 -> 98691.5 | L13: =K13 -> 98691.5 | M13: =L13 -> 98691.5 | O13: =O12+1 -> 9 | X13: =L23+L14 -> 1.2400989e+08 | Y13: =L14 -> 5808113.5
B14: Net Cash Flow Before Debt Service | D14: =D10-SUM(D11:D13) -> 4986605.5 | E14: =E10-SUM(E11:E13) -> 5314553.5 | F14: =F10-SUM(F11:F13) -> 5626184.5 | G14: =G10-SUM(G11:G13) -> 5459582.5 | H14: =H10-SUM(H11:H13) -> 5897375.5 | I14: =I10-SUM(I11:I13) -> 5930710.5 | J14: =J10-SUM(J11:J13) -> 5631357.5 | K14: =K10-SUM(K11:K13) -> 6215142.5 | ... M14: =M10-SUM(M11:M13) -> 5967977.5 | O14: =O13+1 -> 10 | Y14: =M15+M14 -> 1.2647932e+08 | AA14: 1 | AB14: 131 Kent
B15: Sale (Unlevered) | M15: =M23 -> 1.2051134e+08 | O15: =O14+1 -> 11 | AA15: =AB14&AB15 -> 131 KentEGR | AB15: =IF(AB14="","","EGR") -> EGR | AC15: ='Property-Level CF'!D9 -> 1080474 | AD15: ='Property-Level CF'!E9 -> 1104382 | AE15: ='Property-Level CF'!F9 -> 1120725 | AF15: ='Property-Level CF'!G9 -> 1124325 | AG15: ='Property-Level CF'!H9 -> 1174564 | AH15: ='Property-Level CF'!I9 -> 1131939 | AI15: ='Property-Level CF'!J9 -> 1155752 | AJ15: ='Property-Level CF'!K9 -> 1206302 | ... AL15: ='Property-Level CF'!M9 -> 1261766
B16: Unlevered Cash Flow | C16: =-Summary!J20 -> -1.0375044e+08 | D16: =D14+D15 -> 4986605.5 | E16: =E14+E15 -> 5314553.5 | F16: =F14+F15 -> 5626184.5 | G16: =G14+G15 -> 5459582.5 | H16: =H14+H15 -> 5897375.5 | I16: =I14+I15 -> 5930710.5 | J16: =J14+J15 -> 5631357.5 | K16: =K14+K15 -> 6215142.5 | ... M16: =M14+M15 -> 1.2647932e+08 | O16: Year | P16: =P2 -> Year 1 | Q16: =Q2 -> Year 2 | R16: =R2 -> Year 3 | S16: =S2 -> Year 4 | T16: =T2 -> Year 5 | U16: =U2 -> Year 6 | V16: =V2 -> Year 7 | W16: =W2 -> Year 8 | ... Y16: =Y2 -> Year 10 | AA16: =AB14&AB16 -> 131 KentNOI | AB16: =IF(AB14="","","NOI") -> NOI | AC16: ='Property-Level CF'!D10 -> 776823 | AD16: ='Property-Level CF'!E10 -> 792690 | AE16: ='Property-Level CF'!F10 -> 801674 | AF16: ='Property-Level CF'!G10 -> 798070 | AG16: ='Property-Level CF'!H10 -> 839376 | AH16: ='Property-Level CF'!I10 -> 790672 | AI16: ='Property-Level CF'!J10 -> 806147 | AJ16: ='Property-Level CF'!K10 -> 847300 | ... AL16: ='Property-Level CF'!M10 -> 884835
O17: Levered IRR | P17: =IRR(P18:P29) -> -0.051539351 | Q17: =IRR(Q18:Q29) -> 0.025747677 | R17: =IRR(R18:R29) -> 0.092909389 | S17: =IRR(S18:S29) -> 0.096104457 | T17: =IRR(T18:T29) -> 0.10227762 | U17: =IRR(U18:U29) -> 0.10024719 | V17: =IRR(V18:V29) -> 0.10306125 | W17: =IRR(W18:W29) -> 0.1051344 | ... Y17: =IRR(Y18:Y29) -> 0.10385787 | AA17: =AB14&AB17 -> 131 KentNCF before DS | AB17: NCF before DS | AC17: ='Property-Level CF'!D14 -> 761132.5 | AD17: ='Property-Level CF'!E14 -> 731468.5 | AE17: ='Property-Level CF'!F14 -> 732340.5 | AF17: ='Property-Level CF'!G14 -> 476440.5 | AG17: ='Property-Level CF'!H14 -> 824705.5 | AH17: ='Property-Level CF'!I14 -> 776001.5 | AI17: ='Property-Level CF'!J14 -> 343683.5 | AJ17: ='Property-Level CF'!K14 -> 832629.5 | ... AL17: ='Property-Level CF'!M14 -> 638163.5
B18: Cap Rate at Sale | D18: =Summary!L20 -> 0.049024535 | E18: =E10/(E23/(1-'Portfolio-Level CF'!$AC$52)) -> 0.051967885 | F18: =F10/(F23/(1-'Portfolio-Level CF'!$AC$52)) -> 0.052000592 | G18: =G10/(G23/(1-'Portfolio-Level CF'!$AC$52)) -> 0.051980968 | H18: =H10/(H23/(1-'Portfolio-Level CF'!$AC$52)) -> 0.052004482 | I18: =I10/(I23/(1-'Portfolio-Level CF'!$AC$52)) -> 0.051940308 | J18: =J10/(J23/(1-'Portfolio-Level CF'!$AC$52)) -> 0.051946125 | K18: =K10/(K23/(1-'Portfolio-Level CF'!$AC$52)) -> 0.051968073 | L18: =L10/(L23/(1-'Portfolio-Level CF'!$AC$52)) -> 0.051943476 | M18: =M10/(M23/(1-'Portfolio-Level CF'!$AC$52)) -> 0.051963649 | O18: 0 | P18: =P4+Summary!I30 -> -36312653 | Q18: =P18 -> -36312653 | R18: =Q18 -> -36312653 | S18: =R18 -> -36312653 | T18: =S18 -> -36312653 | U18: =T18 -> -36312653 | V18: =U18 -> -36312653 | W18: =V18 -> -36312653 | X18: =W18 -> -36312653 | Y18: =X18 -> -36312653 | AB18: DS | AC18: ='Property-Level CF'!D30 -> 358737.83 | AD18: ='Property-Level CF'!E30 -> 358737.83 | AE18: ='Property-Level CF'!F30 -> 358737.83 | AF18: ='Property-Level CF'!G30 -> 358737.83 | AG18: ='Property-Level CF'!H30 -> 358737.83 | AH18: ='Property-Level CF'!I30 -> 358737.83 | AI18: ='Property-Level CF'!J30 -> 358737.83 | AJ18: ='Property-Level CF'!K30 -> 358737.83 | ... AL18: ='Property-Level CF'!M30 -> 358737.83
B19: Implied Exit Cap Rate | D19: =(D10/$D$23)*(1-'Portfolio-Level CF'!$AC$52) -> 0.049024535 | E19: =(E10/$D$23)*(1-'Portfolio-Level CF'!$AC$52) -> 0.052624318 | F19: =(F10/$D$23)*(1-'Portfolio-Level CF'!$AC$52) -> 0.055706165 | G19: =(G10/$D$23)*(1-'Portfolio-Level CF'!$AC$52) -> 0.056532128 | H19: =(H10/$D$23)*(1-'Portfolio-Level CF'!$AC$52) -> 0.057793173 | I19: =(I10/$D$23)*(1-'Portfolio-Level CF'!$AC$52) -> 0.058114473 | J19: =(J10/$D$23)*(1-'Portfolio-Level CF'!$AC$52) -> 0.059545214 | K19: =(K10/$D$23)*(1-'Portfolio-Level CF'!$AC$52) -> 0.060855975 | ... M19: =(M10/$D$23)*(1-'Portfolio-Level CF'!$AC$52) -> 0.062775234 | O19: =O18+1 -> 1 | P19: =D33+D39 -> 34441123 | Q19: =D39 -> 2122861.3 | R19: =Q19 -> 2122861.3 | S19: =R19 -> 2122861.3 | T19: =S19 -> 2122861.3 | U19: =T19 -> 2122861.3 | V19: =U19 -> 2122861.3 | W19: =V19 -> 2122861.3 | X19: =W19 -> 2122861.3 | Y19: =X19 -> 2122861.3 | AB19: NCF after DS | AC19: =AC17-AC18 -> 402394.67 | AD19: =AD17-AD18 -> 372730.67 | AE19: =AE17-AE18 -> 373602.67 | AF19: =AF17-AF18 -> 117702.67 | AG19: =AG17-AG18 -> 465967.67 | AH19: =AH17-AH18 -> 417263.67 | AI19: =AI17-AI18 -> -15054.326 | AJ19: =AJ17-AJ18 -> 473891.67 | ... AL19: =AL17-AL18 -> 279425.67
B20: Accretive (Dilutive) Cap Spread | D20: =D19-D18 -> 0 | E20: =E19-E18 -> 0.00065643245 | F20: =F19-F18 -> 0.0037055733 | G20: =G19-G18 -> 0.0045511601 | H20: =H19-H18 -> 0.0057886916 | I20: =I19-I18 -> 0.0061741648 | J20: =J19-J18 -> 0.0075990892 | K20: =K19-K18 -> 0.0088879018 | ... M20: =M19-M18 -> 0.010811585 | O20: =O19+1 -> 2 | Q20: =E33+E39 -> 36029139 | R20: =E39 -> 2450809.3 | S20: =R20 -> 2450809.3 | T20: =S20 -> 2450809.3 | U20: =T20 -> 2450809.3 | V20: =U20 -> 2450809.3 | W20: =V20 -> 2450809.3 | X20: =W20 -> 2450809.3 | Y20: =X20 -> 2450809.3 | AA20: 2 | AB20: 164 Mount Pleasant
B21: REIT GAAP Accounting Cap Rate Average | D21: =AVERAGE($D$19:D19) -> 0.049024535 | E21: =AVERAGE($D$19:E19) -> 0.050824427 | F21: =AVERAGE($D$19:F19) -> 0.052451673 | G21: =AVERAGE($D$19:G19) -> 0.053471787 | H21: =AVERAGE($D$19:H19) -> 0.054336064 | I21: =AVERAGE($D$19:I19) -> 0.054965799 | J21: =AVERAGE($D$19:J19) -> 0.055620001 | K21: =AVERAGE($D$19:K19) -> 0.056274498 | ... M21: =AVERAGE($D$19:M19) -> 0.057451948 | O21: =O20+1 -> 3 | R21: =F33+F39 -> 42189339 | S21: =F39 -> 2762440.3 | T21: =S21 -> 2762440.3 | U21: =T21 -> 2762440.3 | V21: =U21 -> 2762440.3 | W21: =V21 -> 2762440.3 | X21: =W21 -> 2762440.3 | Y21: =X21 -> 2762440.3 | AA21: =AB20&AB21 -> 164 Mount Pleasant EGR | AB21: EGR | AC21: ='Property-Level CF'!AC9 -> 753930 | AD21: ='Property-Level CF'!AD9 -> 906249 | AE21: ='Property-Level CF'!AE9 -> 1085628 | AF21: ='Property-Level CF'!AF9 -> 1112856 | AG21: ='Property-Level CF'!AG9 -> 1139458 | AH21: ='Property-Level CF'!AH9 -> 1156756 | AI21: ='Property-Level CF'!AI9 -> 1174243 | AJ21: ='Property-Level CF'!AJ9 -> 1192002 | ... AL21: ='Property-Level CF'!AL9 -> 1215445
O22: =O21+1 -> 4 | S22: =G33+G39 -> 43648176 | T22: =G39 -> 2595838.3 | U22: =T22 -> 2595838.3 | V22: =U22 -> 2595838.3 | W22: =V22 -> 2595838.3 | X22: =W22 -> 2595838.3 | Y22: =X22 -> 2595838.3 | AA22: =AB20&AB22 -> 164 Mount Pleasant NOI | AB22: NOI | AC22: ='Property-Level CF'!AC10 -> 421291 | AD22: ='Property-Level CF'!AD10 -> 560979 | AE22: ='Property-Level CF'!AE10 -> 726550 | AF22: ='Property-Level CF'!AF10 -> 744800 | AG22: ='Property-Level CF'!AG10 -> 762241 | AH22: ='Property-Level CF'!AH10 -> 770468 | AI22: ='Property-Level CF'!AI10 -> 778664 | AJ22: ='Property-Level CF'!AJ10 -> 786906 | ... AL22: ='Property-Level CF'!AL10 -> 791022
B23: Net Sale Price | D23: ='Property-Level CF'!CA23+'Property-Level CF'!DY23+'Property-Level CF'!CZ23+'Property-Level CF'!D23+'Property-Level CF'!AC23+'Property-Level CF'!BB23 -> 99756046 | E23: ='Property-Level CF'!CB23+'Property-Level CF'!DZ23+'Property-Level CF'!DA23+'Property-Level CF'!E23+'Property-Level CF'!AD23+'Property-Level CF'!BC23 -> 1.0101611e+08 | F23: ='Property-Level CF'!CC23+'Property-Level CF'!EA23+'Property-Level CF'!DB23+'Property-Level CF'!F23+'Property-Level CF'!AE23+'Property-Level CF'!BD23 -> 1.0686468e+08 | G23: ='Property-Level CF'!CD23+'Property-Level CF'!EB23+'Property-Level CF'!DC23+'Property-Level CF'!G23+'Property-Level CF'!AF23+'Property-Level CF'!BE23 -> 1.0849012e+08 | H23: ='Property-Level CF'!CE23+'Property-Level CF'!EC23+'Property-Level CF'!DD23+'Property-Level CF'!H23+'Property-Level CF'!AG23+'Property-Level CF'!BF23 -> 1.1086003e+08 | I23: ='Property-Level CF'!CF23+'Property-Level CF'!ED23+'Property-Level CF'!DE23+'Property-Level CF'!I23+'Property-Level CF'!AH23+'Property-Level CF'!BG23 -> 1.1161409e+08 | J23: ='Property-Level CF'!CG23+'Property-Level CF'!EE23+'Property-Level CF'!DF23+'Property-Level CF'!J23+'Property-Level CF'!AI23+'Property-Level CF'!BH23 -> 1.1434915e+08 | K23: ='Property-Level CF'!CH23+'Property-Level CF'!EF23+'Property-Level CF'!DG23+'Property-Level CF'!K23+'Property-Level CF'!AJ23+'Property-Level CF'!BI23 -> 1.1681694e+08 | ... M23: ='Property-Level CF'!CJ23+'Property-Level CF'!EH23+'Property-Level CF'!DI23+'Property-Level CF'!M23+'Property-Level CF'!AL23+'Property-Level CF'!BK23 -> 1.2051134e+08 | O23: =O22+1 -> 5 | T23: =H33+H39 -> 46455877 | U23: =H39 -> 3033631.3 | V23: =U23 -> 3033631.3 | W23: =V23 -> 3033631.3 | X23: =W23 -> 3033631.3 | Y23: =X23 -> 3033631.3 | AA23: =AB20&AB23 -> 164 Mount Pleasant NCF before DS | AB23: NCF before DS | AC23: ='Property-Level CF'!AC14 -> 408299 | AD23: ='Property-Level CF'!AD14 -> 547987 | AE23: ='Property-Level CF'!AE14 -> 713558 | AF23: ='Property-Level CF'!AF14 -> 731808 | AG23: ='Property-Level CF'!AG14 -> 749249 | AH23: ='Property-Level CF'!AH14 -> 757476 | AI23: ='Property-Level CF'!AI14 -> 765672 | AJ23: ='Property-Level CF'!AJ14 -> 773914 | ... AL23: ='Property-Level CF'!AL14 -> 563742
B24: Net Sale Price PSF | D24: =D23/Summary!$C$12 -> 505.3933 | E24: =E23/Summary!$C$12 -> 511.77718 | F24: =F23/Summary!$C$12 -> 541.40773 | G24: =G23/Summary!$C$12 -> 549.64268 | H24: =H23/Summary!$C$12 -> 561.64933 | I24: =I23/Summary!$C$12 -> 565.4696 | J24: =J23/Summary!$C$12 -> 579.32622 | K24: =K23/Summary!$C$12 -> 591.82879 | ... M24: =M23/Summary!$C$12 -> 610.5457 | O24: =O23+1 -> 6 | U24: =I33+I39 -> 47243268 | V24: =I39 -> 3066966.3 | W24: =V24 -> 3066966.3 | X24: =W24 -> 3066966.3 | Y24: =X24 -> 3066966.3 | AB24: DS | AC24: ='Property-Level CF'!AC30 -> 292979.76 | AD24: ='Property-Level CF'!AD30 -> 292979.76 | AE24: ='Property-Level CF'!AE30 -> 292979.76 | AF24: ='Property-Level CF'!AF30 -> 292979.76 | AG24: ='Property-Level CF'!AG30 -> 292979.76 | AH24: ='Property-Level CF'!AH30 -> 292979.76 | AI24: ='Property-Level CF'!AI30 -> 292979.76 | AJ24: ='Property-Level CF'!AJ30 -> 292979.76 | ... AL24: ='Property-Level CF'!AL30 -> 292979.76
O25: =O24+1 -> 7 | V25: =J33+J39 -> 49678976 | W25: =J39 -> 2767613.3 | X25: =W25 -> 2767613.3 | Y25: =X25 -> 2767613.3 | AB25: NCF after DS | AC25: =AC23-AC24 -> 115319.24 | AD25: =AD23-AD24 -> 255007.24 | AE25: =AE23-AE24 -> 420578.24 | AF25: =AF23-AF24 -> 438828.24 | AG25: =AG23-AG24 -> 456269.24 | AH25: =AH23-AH24 -> 464496.24 | AI25: =AI23-AI24 -> 472692.24 | AJ25: =AJ23-AJ24 -> 480934.24 | ... AL25: =AL23-AL24 -> 270762.24
B26: Unlevered IRR | D26: =P3 -> 0.0095634648 | E26: =Q3 -> 0.036675356 | F26: =R3 -> 0.060475501 | G26: =S3 -> 0.061822143 | H26: =T3 -> 0.0644085 | I26: =U3 -> 0.063805188 | J26: =V3 -> 0.065162092 | K26: =W3 -> 0.066281943 | ... M26: =Y3 -> 0.066186186 | O26: =O25+1 -> 8 | W26: =K33+K39 -> 52730557 | X26: =K39 -> 3351398.3 | Y26: =X26 -> 3351398.3 | AA26: 3 | AB26: 170 Mount Pleasant
B27: Unlevered Equity Multiple | D27: =(SUM($D$14:D14)+D23)/-P4 -> 1.0095635 | E27: =(SUM($D$14:E14)+E23)/-Q4 -> 1.0729331 | F27: =(SUM($D$14:F14)+F23)/-R4 -> 1.1835326 | G27: =(SUM($D$14:G14)+G23)/-S4 -> 1.2518217 | H27: =(SUM($D$14:H14)+H23)/-T4 -> 1.331506 | I27: =(SUM($D$14:I14)+I23)/-U4 -> 1.3959372 | J27: =(SUM($D$14:J14)+J23)/-V4 -> 1.4765771 | K27: =(SUM($D$14:K14)+K23)/-W4 -> 1.5602677 | ... M27: =(SUM($D$14:M14)+M23)/-Y4 -> 1.7093802 | O27: =O26+1 -> 9 | X27: =L33+L39 -> 53708361 | Y27: =L39 -> 2944369.3 | AA27: =AB26&AB27 -> 170 Mount Pleasant EGR | AB27: EGR | AC27: ='Property-Level CF'!BB9 -> 955031 | AD27: ='Property-Level CF'!BC9 -> 1124079 | AE27: ='Property-Level CF'!BD9 -> 1217274 | AF27: ='Property-Level CF'!BE9 -> 1232295 | AG27: ='Property-Level CF'!BF9 -> 1247438 | AH27: ='Property-Level CF'!BG9 -> 1263167 | AI27: ='Property-Level CF'!BH9 -> 1330801 | AJ27: ='Property-Level CF'!BI9 -> 1357587 | ... AL27: ='Property-Level CF'!BK9 -> 1389233
O28: =O27+1 -> 10 | Y28: =M33+M36+M38 -> 56177792 | AA28: =AB26&AB28 -> 170 Mount Pleasant NOI | AB28: NOI | AC28: ='Property-Level CF'!BB10 -> 638299 | AD28: ='Property-Level CF'!BC10 -> 794615 | AE28: ='Property-Level CF'!BD10 -> 877384 | AF28: ='Property-Level CF'!BE10 -> 884405 | AG28: ='Property-Level CF'!BF10 -> 891356 | AH28: ='Property-Level CF'!BG10 -> 898681 | AI28: ='Property-Level CF'!BH10 -> 956057 | AJ28: ='Property-Level CF'!BI10 -> 973687 | ... AL28: ='Property-Level CF'!BK10 -> 987095
B29: Loan Balance | D29: =Summary!$C$17 -> 67437784 | E29: =D29 -> 67437784 | F29: =E29 -> 67437784 | G29: =F29 -> 67437784 | H29: =G29 -> 67437784 | I29: =H29 -> 67437784 | J29: =I29 -> 67437784 | K29: =J29 -> 67437784 | L29: =K29 -> 67437784 | M29: =L29 -> 67437784 | O29: =O28+1 -> 11 | AA29: =AB26&AB29 -> 170 Mount Pleasant NCF before DS | AB29: NCF before DS | AC29: ='Property-Level CF'!BB14 -> 623299 | AD29: ='Property-Level CF'!BC14 -> 779615 | AE29: ='Property-Level CF'!BD14 -> 862384 | AF29: ='Property-Level CF'!BE14 -> 869405 | AG29: ='Property-Level CF'!BF14 -> 876356 | AH29: ='Property-Level CF'!BG14 -> 883681 | AI29: ='Property-Level CF'!BH14 -> 941057 | AJ29: ='Property-Level CF'!BI14 -> 958687 | ... AL29: ='Property-Level CF'!BK14 -> 972095
B30: Debt Service | D30: ='Portfolio-Level CF'!AC11 -> 2772962.6 | E30: ='Portfolio-Level CF'!AD11 -> 2772962.6 | F30: ='Portfolio-Level CF'!AE11 -> 2772962.6 | G30: ='Portfolio-Level CF'!AF11 -> 2772962.6 | H30: ='Portfolio-Level CF'!AG11 -> 2772962.6 | I30: ='Portfolio-Level CF'!AH11 -> 2772962.6 | J30: ='Portfolio-Level CF'!AI11 -> 2772962.6 | K30: ='Portfolio-Level CF'!AJ11 -> 2772962.6 | ... M30: ='Portfolio-Level CF'!AL11 -> 2772962.6 | AB30: DS | AC30: ='Property-Level CF'!BB30 -> 376017.62 | AD30: ='Property-Level CF'!BC30 -> 376017.62 | AE30: ='Property-Level CF'!BD30 -> 376017.62 | AF30: ='Property-Level CF'!BE30 -> 376017.62 | AG30: ='Property-Level CF'!BF30 -> 376017.62 | AH30: ='Property-Level CF'!BG30 -> 376017.62 | AI30: ='Property-Level CF'!BH30 -> 376017.62 | AJ30: ='Property-Level CF'!BI30 -> 376017.62 | ... AL30: ='Property-Level CF'!BK30 -> 376017.62
B31: Debt Coverage Ratio | D31: =D10/D30 -> 1.8342537 | E31: =E10/E30 -> 1.9689396 | F31: =F10/F30 -> 2.084247 | G31: =G10/G30 -> 2.1151504 | H31: =H10/H30 -> 2.1623324 | I31: =I10/I30 -> 2.1743539 | J31: =J10/J30 -> 2.2278851 | K31: =K10/K30 -> 2.2769272 | ... M31: =M10/M30 -> 2.3487363 | O31: Portfolio Sale Price by Cap Rate by Exit Year | AB31: NCF after DS | AC31: =AC29-AC30 -> 247281.38 | AD31: =AD29-AD30 -> 403597.38 | AE31: =AE29-AE30 -> 486366.38 | AF31: =AF29-AF30 -> 493387.38 | AG31: =AG29-AG30 -> 500338.38 | AH31: =AH29-AH30 -> 507663.38 | AI31: =AI29-AI30 -> 565039.38 | AJ31: =AJ29-AJ30 -> 582669.38 | ... AL31: =AL29-AL30 -> 596077.38
O32: Cap Rate | P32: =P16 -> Year 1 | Q32: =Q16 -> Year 2 | R32: =R16 -> Year 3 | S32: =S16 -> Year 4 | T32: =T16 -> Year 5 | U32: =U16 -> Year 6 | V32: =V16 -> Year 7 | W32: =W16 -> Year 8 | ... Y32: =Y16 -> Year 10 | AA32: 4 | AB32: 2 Riverview
B33: Net Cash on Sale | D33: =D23-D29 -> 32318261 | E33: =E23-E29 -> 33578330 | F33: =F23-F29 -> 39426898 | G33: =G23-G29 -> 41052337 | H33: =H23-H29 -> 43422246 | I33: =I23-I29 -> 44176302 | J33: =J23-J29 -> 46911363 | K33: =K23-K29 -> 49379158 | L33: =L23-L29 -> 50763991 | M33: =M15-M29 -> 53073558 | O33: 0.05 | P33: =('Portfolio-Level CF'!D10/$O33)*(1-'Portfolio-Level CF'!$AC$52) -> 97809876 | Q33: =('Portfolio-Level CF'!E10/$O33)*(1-'Portfolio-Level CF'!$AC$52) -> 1.0499188e+08 | R33: =('Portfolio-Level CF'!F10/$O33)*(1-'Portfolio-Level CF'!$AC$52) -> 1.1114053e+08 | S33: =('Portfolio-Level CF'!G10/$O33)*(1-'Portfolio-Level CF'!$AC$52) -> 1.1278843e+08 | T33: =('Portfolio-Level CF'!H10/$O33)*(1-'Portfolio-Level CF'!$AC$52) -> 1.1530437e+08 | U33: =('Portfolio-Level CF'!I10/$O33)*(1-'Portfolio-Level CF'!$AC$52) -> 1.159454e+08 | V33: =('Portfolio-Level CF'!J10/$O33)*(1-'Portfolio-Level CF'!$AC$52) -> 1.187999e+08 | W33: =('Portfolio-Level CF'!K10/$O33)*(1-'Portfolio-Level CF'!$AC$52) -> 1.2141503e+08 | ... Y33: =('Portfolio-Level CF'!M10/$O33)*(1-'Portfolio-Level CF'!$AC$52) -> 1.2524418e+08 | AA33: =AB32&AB33 -> 2 Riverview EGR | AB33: EGR | AC33: ='Property-Level CF'!CA9 -> 1885346 | AD33: ='Property-Level CF'!CB9 -> 1921877 | AE33: ='Property-Level CF'!CC9 -> 1959053 | AF33: ='Property-Level CF'!CD9 -> 1997206 | AG33: ='Property-Level CF'!CE9 -> 2036006 | AH33: ='Property-Level CF'!CF9 -> 2075650 | AI33: ='Property-Level CF'!CG9 -> 2115923 | AJ33: ='Property-Level CF'!CH9 -> 2156964 | ... AL33: ='Property-Level CF'!CJ9 -> 2244371
B34: Net Gain | D34: =D33+$C$39 -> -3994391.8 | E34: =E33+$C$39 -> -2734323.1 | F34: =F33+$C$39 -> 3114245.3 | G34: =G33+$C$39 -> 4739684.4 | H34: =H33+$C$39 -> 7109593.1 | I34: =I33+$C$39 -> 7863648.5 | J34: =J33+$C$39 -> 10598710 | K34: =K33+$C$39 -> 13066505 | ... M34: =M33+$C$39 -> 16760905 | O34: =Summary!L10 -> 0.051247526 | P34: =('Portfolio-Level CF'!D10/$O34)*(1-'Portfolio-Level CF'!$AC$52) -> 95428875 | Q34: =('Portfolio-Level CF'!E10/$O34)*(1-'Portfolio-Level CF'!$AC$52) -> 1.0243604e+08 | R34: =('Portfolio-Level CF'!F10/$O34)*(1-'Portfolio-Level CF'!$AC$52) -> 1.0843502e+08 | S34: =('Portfolio-Level CF'!G10/$O34)*(1-'Portfolio-Level CF'!$AC$52) -> 1.100428e+08 | T34: =('Portfolio-Level CF'!H10/$O34)*(1-'Portfolio-Level CF'!$AC$52) -> 1.124975e+08 | U34: =('Portfolio-Level CF'!I10/$O34)*(1-'Portfolio-Level CF'!$AC$52) -> 1.1312292e+08 | V34: =('Portfolio-Level CF'!J10/$O34)*(1-'Portfolio-Level CF'!$AC$52) -> 1.1590794e+08 | W34: =('Portfolio-Level CF'!K10/$O34)*(1-'Portfolio-Level CF'!$AC$52) -> 1.184594e+08 | ... Y34: =('Portfolio-Level CF'!M10/$O34)*(1-'Portfolio-Level CF'!$AC$52) -> 1.2219534e+08 | AA34: =AB32&AB34 -> 2 Riverview NOI | AB34: NOI | AC34: ='Property-Level CF'!CA10 -> 1354228 | AD34: ='Property-Level CF'!CB10 -> 1377820 | AE34: ='Property-Level CF'!CC10 -> 1401741 | AF34: ='Property-Level CF'!CD10 -> 1426308 | AG34: ='Property-Level CF'!CE10 -> 1451191 | AH34: ='Property-Level CF'!CF10 -> 1476575 | AI34: ='Property-Level CF'!CG10 -> 1502242 | AJ34: ='Property-Level CF'!CH10 -> 1528321 | ... AL34: ='Property-Level CF'!CJ10 -> 1584598
O35: 0.055 | P35: =('Portfolio-Level CF'!D10/$O35)*(1-'Portfolio-Level CF'!$AC$52) -> 88918069 | Q35: =('Portfolio-Level CF'!E10/$O35)*(1-'Portfolio-Level CF'!$AC$52) -> 95447161 | R35: =('Portfolio-Level CF'!F10/$O35)*(1-'Portfolio-Level CF'!$AC$52) -> 1.0103685e+08 | S35: =('Portfolio-Level CF'!G10/$O35)*(1-'Portfolio-Level CF'!$AC$52) -> 1.0253494e+08 | T35: =('Portfolio-Level CF'!H10/$O35)*(1-'Portfolio-Level CF'!$AC$52) -> 1.0482215e+08 | U35: =('Portfolio-Level CF'!I10/$O35)*(1-'Portfolio-Level CF'!$AC$52) -> 1.0540491e+08 | V35: =('Portfolio-Level CF'!J10/$O35)*(1-'Portfolio-Level CF'!$AC$52) -> 1.0799991e+08 | W35: =('Portfolio-Level CF'!K10/$O35)*(1-'Portfolio-Level CF'!$AC$52) -> 1.103773e+08 | ... Y35: =('Portfolio-Level CF'!M10/$O35)*(1-'Portfolio-Level CF'!$AC$52) -> 1.1385835e+08 | AA35: =AB32&AB35 -> 2 Riverview NCF before DS | AB35: NCF before DS | AC35: ='Property-Level CF'!CA14 -> 1332627.5 | AD35: ='Property-Level CF'!CB14 -> 1356219.5 | AE35: ='Property-Level CF'!CC14 -> 1380140.5 | AF35: ='Property-Level CF'!CD14 -> 1404707.5 | AG35: ='Property-Level CF'!CE14 -> 1429590.5 | AH35: ='Property-Level CF'!CF14 -> 1454974.5 | AI35: ='Property-Level CF'!CG14 -> 1480641.5 | AJ35: ='Property-Level CF'!CH14 -> 1506720.5 | ... AL35: ='Property-Level CF'!CJ14 -> 1562997.5
B36: Net Cash Flow after Debt Service | D36: =D16-D30 -> 2213642.9 | E36: =E16-E30 -> 2541590.9 | F36: =F16-F30 -> 2853221.9 | G36: =G16-G30 -> 2686619.9 | H36: =H16-H30 -> 3124412.9 | I36: =I16-I30 -> 3157747.9 | J36: =J16-J30 -> 2858394.9 | K36: =K16-K30 -> 3442179.9 | L36: =L16-L30 -> 3035150.9 | M36: =M14-M30 -> 3195014.9 | O36: 0.0575 | P36: =('Portfolio-Level CF'!D10/$O36)*(1-'Portfolio-Level CF'!$AC$52) -> 85052066 | Q36: =('Portfolio-Level CF'!E10/$O36)*(1-'Portfolio-Level CF'!$AC$52) -> 91297284 | R36: =('Portfolio-Level CF'!F10/$O36)*(1-'Portfolio-Level CF'!$AC$52) -> 96643943 | S36: =('Portfolio-Level CF'!G10/$O36)*(1-'Portfolio-Level CF'!$AC$52) -> 98076896 | T36: =('Portfolio-Level CF'!H10/$O36)*(1-'Portfolio-Level CF'!$AC$52) -> 1.0026467e+08 | U36: =('Portfolio-Level CF'!I10/$O36)*(1-'Portfolio-Level CF'!$AC$52) -> 1.0082209e+08 | V36: =('Portfolio-Level CF'!J10/$O36)*(1-'Portfolio-Level CF'!$AC$52) -> 1.0330426e+08 | W36: =('Portfolio-Level CF'!K10/$O36)*(1-'Portfolio-Level CF'!$AC$52) -> 1.0557829e+08 | ... Y36: =('Portfolio-Level CF'!M10/$O36)*(1-'Portfolio-Level CF'!$AC$52) -> 1.0890798e+08 | AB36: DS | AC36: ='Property-Level CF'!CA30 -> 717495.78 | AD36: =AC36 -> 717495.78 | AE36: =AD36 -> 717495.78 | AF36: =AE36 -> 717495.78 | AG36: =AF36 -> 717495.78 | AH36: =AG36 -> 717495.78 | AI36: =AH36 -> 717495.78 | AJ36: =AI36 -> 717495.78 | AK36: =AJ36 -> 717495.78 | AL36: =AK36 -> 717495.78
B37: Sale (Levered) | M37: =M15-M29 -> 53073558 | O37: 0.06 | P37: =('Portfolio-Level CF'!D10/$O37)*(1-'Portfolio-Level CF'!$AC$52) -> 81508230 | Q37: =('Portfolio-Level CF'!E10/$O37)*(1-'Portfolio-Level CF'!$AC$52) -> 87493231 | R37: =('Portfolio-Level CF'!F10/$O37)*(1-'Portfolio-Level CF'!$AC$52) -> 92617112 | S37: =('Portfolio-Level CF'!G10/$O37)*(1-'Portfolio-Level CF'!$AC$52) -> 93990359 | T37: =('Portfolio-Level CF'!H10/$O37)*(1-'Portfolio-Level CF'!$AC$52) -> 96086974 | U37: =('Portfolio-Level CF'!I10/$O37)*(1-'Portfolio-Level CF'!$AC$52) -> 96621167 | V37: =('Portfolio-Level CF'!J10/$O37)*(1-'Portfolio-Level CF'!$AC$52) -> 98999918 | W37: =('Portfolio-Level CF'!K10/$O37)*(1-'Portfolio-Level CF'!$AC$52) -> 1.0117919e+08 | ... Y37: =('Portfolio-Level CF'!M10/$O37)*(1-'Portfolio-Level CF'!$AC$52) -> 1.0437015e+08 | AB37: NCF after DS | AC37: =AC35-AC36 -> 615131.72 | AD37: =AD35-AD36 -> 638723.72 | AE37: =AE35-AE36 -> 662644.72 | AF37: =AF35-AF36 -> 687211.72 | AG37: =AG35-AG36 -> 712094.72 | AH37: =AH35-AH36 -> 737478.72 | AI37: =AI35-AI36 -> 763145.72 | AJ37: =AJ35-AJ36 -> 789224.72 | ... AL37: =AL35-AL36 -> 845501.72
B38: Asset Management Fees | D38: =C39*Summary!C10 -> -90781.633 | E38: =D38 -> -90781.633 | F38: =E38 -> -90781.633 | G38: =F38 -> -90781.633 | H38: =G38 -> -90781.633 | I38: =H38 -> -90781.633 | J38: =I38 -> -90781.633 | K38: =J38 -> -90781.633 | L38: =K38 -> -90781.633 | M38: =L38 -> -90781.633 | AA38: 5 | AB38: 226 White St
B39: Levered Cash Flow | C39: =(C16*(1-Summary!C15)) -> -36312653 | D39: =D36+D37+D38 -> 2122861.3 | E39: =E36+E37+E38 -> 2450809.3 | F39: =F36+F37+F38 -> 2762440.3 | G39: =G36+G37+G38 -> 2595838.3 | H39: =H36+H37+H38 -> 3033631.3 | I39: =I36+I37+I38 -> 3066966.3 | J39: =J36+J37+J38 -> 2767613.3 | K39: =K36+K37+K38 -> 3351398.3 | ... M39: =M36+M37+M38 -> 56177792 | O39: Portfolio Final Year Cash Flow by Cap Rate by Exit Year | AA39: =AB38&AB39 -> 226 White StEGR | AB39: EGR | AC39: ='Property-Level CF'!CZ9 -> 810031 | AD39: ='Property-Level CF'!DA9 -> 827265 | AE39: ='Property-Level CF'!DB9 -> 844869 | AF39: ='Property-Level CF'!DC9 -> 862852 | AG39: ='Property-Level CF'!DD9 -> 881222 | AH39: ='Property-Level CF'!DE9 -> 899987 | AI39: ='Property-Level CF'!DF9 -> 919155 | AJ39: ='Property-Level CF'!DG9 -> 938737 | ... AL39: ='Property-Level CF'!DI9 -> 979173
O40: Cap Rate | P40: =P32 -> Year 1 | Q40: =Q32 -> Year 2 | R40: =R32 -> Year 3 | S40: =S32 -> Year 4 | T40: =T32 -> Year 5 | U40: =U32 -> Year 6 | V40: =V32 -> Year 7 | W40: =W32 -> Year 8 | ... Y40: =Y32 -> Year 10 | AA40: =AB38&AB40 -> 226 White StNOI | AB40: NOI | AC40: ='Property-Level CF'!CZ10 -> 584129 | AD40: ='Property-Level CF'!DA10 -> 595812 | AE40: ='Property-Level CF'!DB10 -> 607728 | AF40: ='Property-Level CF'!DC10 -> 619882 | AG40: ='Property-Level CF'!DD10 -> 632280 | AH40: ='Property-Level CF'!DE10 -> 644926 | AI40: ='Property-Level CF'!DF10 -> 657824 | AJ40: ='Property-Level CF'!DG10 -> 670981 | ... AL40: ='Property-Level CF'!DI10 -> 698088
B41: Cash on Cash Return | D41: =(D14-D30+D38)/-$C$39 -> 0.058460649 | E41: =(E14-E30+E38)/-$C$39 -> 0.067491881 | F41: =(F14-F30+F38)/-$C$39 -> 0.076073766 | G41: =(G14-G30+G38)/-$C$39 -> 0.071485778 | H41: =(H14-H30+H38)/-$C$39 -> 0.083541989 | I41: =(I14-I30+I38)/-$C$39 -> 0.084459989 | J41: =(J14-J30+J38)/-$C$39 -> 0.076216223 | K41: =(K14-K30+K38)/-$C$39 -> 0.09229285 | ... M41: =(M14-M30+M38)/-$C$39 -> 0.08548627 | O41: =O33 -> 0.05 | P41: =((P33-Summary!$C$17)+D39) -> 32494953 | Q41: =((Q33-Summary!$C$17)+E39) -> 40004902 | R41: =((R33-Summary!$C$17)+F39) -> 46465191 | S41: =((S33-Summary!$C$17)+G39) -> 47946484 | T41: =((T33-Summary!$C$17)+H39) -> 50900215 | U41: =((U33-Summary!$C$17)+I39) -> 51574582 | V41: =((V33-Summary!$C$17)+J39) -> 54129731 | W41: =((W33-Summary!$C$17)+K39) -> 57328642 | X41: =((X33-Summary!$C$17)+L39) -> 58302807 | Y41: =((Y33-Summary!$C$17))+$M$39-$M$37 -> 60910631 | AA41: =AB38&AB41 -> 226 White StNCF before DS | AB41: NCF before DS | AC41: ='Property-Level CF'!CZ14 -> 571054 | AD41: ='Property-Level CF'!DA14 -> 582737 | AE41: ='Property-Level CF'!DB14 -> 594653 | AF41: ='Property-Level CF'!DC14 -> 606807 | AG41: ='Property-Level CF'!DD14 -> 619205 | AH41: ='Property-Level CF'!DE14 -> 631851 | AI41: ='Property-Level CF'!DF14 -> 644749 | AJ41: ='Property-Level CF'!DG14 -> 657906 | ... AL41: ='Property-Level CF'!DI14 -> 685013
B42: Average Cash on Cash | D42: =AVERAGE($D$41:D41) -> 0.058460649 | E42: =AVERAGE($D$41:E41) -> 0.062976265 | F42: =AVERAGE($D$41:F41) -> 0.067342099 | G42: =AVERAGE($D$41:G41) -> 0.068378018 | H42: =AVERAGE($D$41:H41) -> 0.071410813 | I42: =AVERAGE($D$41:I41) -> 0.073585675 | J42: =AVERAGE($D$41:J41) -> 0.073961468 | K42: =AVERAGE($D$41:K41) -> 0.076252891 | ... M42: =AVERAGE($D$41:M41) -> 0.077659323 | O42: =O34 -> 0.051247526 | P42: =((P34-Summary!$C$17)+D39) -> 30113952 | Q42: =((Q34-Summary!$C$17)+E39) -> 37449068 | R42: =((R34-Summary!$C$17)+F39) -> 43759680 | S42: =((S34-Summary!$C$17)+G39) -> 45200858 | T42: =((T34-Summary!$C$17)+H39) -> 48093343 | U42: =((U34-Summary!$C$17)+I39) -> 48752106 | V42: =((V34-Summary!$C$17)+J39) -> 51237766 | W42: =((W34-Summary!$C$17)+K39) -> 54373017 | X42: =((X34-Summary!$C$17)+L39) -> 55313560 | Y42: =((Y34-Summary!$C$17))+$M$39-$M$37 -> 57861793 | AB42: DS | AC42: ='Property-Level CF'!CZ30 -> 303697.98 | AD42: =AC42 -> 303697.98 | AE42: =AD42 -> 303697.98 | AF42: =AE42 -> 303697.98 | AG42: =AF42 -> 303697.98 | AH42: =AG42 -> 303697.98 | AI42: =AH42 -> 303697.98 | AJ42: =AI42 -> 303697.98 | AK42: =AJ42 -> 303697.98 | AL42: =AK42 -> 303697.98
O43: =O35 -> 0.055 | P43: =((P35-Summary!$C$17)+D39) -> 23603146 | Q43: =((Q35-Summary!$C$17)+E39) -> 30460186 | R43: =((R35-Summary!$C$17)+F39) -> 36361506 | S43: =((S35-Summary!$C$17)+G39) -> 37692991 | T43: =((T35-Summary!$C$17)+H39) -> 40418000 | U43: =((U35-Summary!$C$17)+I39) -> 41034091 | V43: =((V35-Summary!$C$17)+J39) -> 43329739 | W43: =((W35-Summary!$C$17)+K39) -> 46290912 | X43: =((X35-Summary!$C$17)+L39) -> 47139514 | Y43: =((Y35-Summary!$C$17))+$M$39-$M$37 -> 49524796 | AB43: NCF after DS | AC43: =AC41-AC42 -> 267356.02 | AD43: =AD41-AD42 -> 279039.02 | AE43: =AE41-AE42 -> 290955.02 | AF43: =AF41-AF42 -> 303109.02 | AG43: =AG41-AG42 -> 315507.02 | AH43: =AH41-AH42 -> 328153.02 | AI43: =AI41-AI42 -> 341051.02 | AJ43: =AJ41-AJ42 -> 354208.02 | ... AL43: =AL41-AL42 -> 381315.02
B44: Levered IRR | D44: =P17 -> -0.051539351 | E44: =Q17 -> 0.025747677 | F44: =R17 -> 0.092909389 | G44: =S17 -> 0.096104457 | H44: =T17 -> 0.10227762 | I44: =U17 -> 0.10024719 | J44: =V17 -> 0.10306125 | K44: =W17 -> 0.1051344 | ... M44: =Y17 -> 0.10385787 | O44: =O36 -> 0.0575 | P44: =((P36-Summary!$C$17)+D39) -> 19737143 | Q44: =((Q36-Summary!$C$17)+E39) -> 26310309 | R44: =((R36-Summary!$C$17)+F39) -> 31968599 | S44: =((S36-Summary!$C$17)+G39) -> 33234950 | T44: =((T36-Summary!$C$17)+H39) -> 35860515 | U44: =((U36-Summary!$C$17)+I39) -> 36451269 | V44: =((V36-Summary!$C$17)+J39) -> 38634091 | W44: =((W36-Summary!$C$17)+K39) -> 41491899 | X44: =((X36-Summary!$C$17)+L39) -> 42285909 | Y44: =((Y36-Summary!$C$17))+$M$39-$M$37 -> 44574434 | AA44: 6 | AB44: 40 ORR
B45: Levered Equity Multiple | D45: =((SUM($D$39:D39)+(D23-Summary!$I$30))/-P18) -> 0.94846065 | E45: =((SUM($D$39:E39)+(E23-Summary!$I$30))/-Q18) -> 1.0506531 | F45: =((SUM($D$39:F39)+(F23-Summary!$I$30))/-R18) -> 1.2877883 | G45: =((SUM($D$39:G39)+(G23-Summary!$I$30))/-S18) -> 1.4040364 | H45: =((SUM($D$39:H39)+(H23-Summary!$I$30))/-T18) -> 1.5528424 | I45: =((SUM($D$39:I39)+(I23-Summary!$I$30))/-U18) -> 1.658068 | J45: =((SUM($D$39:J39)+(J23-Summary!$I$30))/-V18) -> 1.809604 | K45: =((SUM($D$39:K39)+(K23-Summary!$I$30))/-W18) -> 1.9698565 | L45: =((SUM($D$39:L39)+(L23-Summary!$I$30))/-X18) -> 2.0890767 | M45: =((SUM($D$39:M39)-(M37)+(M15-Summary!$I$30))/-Y18) -> 2.2381653 | O45: =O37 -> 0.06 | P45: =((P37-Summary!$C$17)+D39) -> 16193307 | Q45: =((Q37-Summary!$C$17)+E39) -> 22506256 | R45: =((R37-Summary!$C$17)+F39) -> 27941768 | S45: =((S37-Summary!$C$17)+G39) -> 29148413 | T45: =((T37-Summary!$C$17)+H39) -> 31682821 | U45: =((U37-Summary!$C$17)+I39) -> 32250349 | V45: =((V37-Summary!$C$17)+J39) -> 34329747 | W45: =((W37-Summary!$C$17)+K39) -> 37092804 | X45: =((X37-Summary!$C$17)+L39) -> 37836770 | Y45: =((Y37-Summary!$C$17))+$M$39-$M$37 -> 40036601 | AA45: =AB44&AB45 -> 40 ORREGR | AB45: EGR | AC45: ='Property-Level CF'!DY9 -> 1701092 | AD45: ='Property-Level CF'!DZ9 -> 1736951 | AE45: ='Property-Level CF'!EA9 -> 1773282 | AF45: ='Property-Level CF'!EB9 -> 1810584 | AG45: ='Property-Level CF'!EC9 -> 1848680 | AH45: ='Property-Level CF'!ED9 -> 1887630 | AI45: ='Property-Level CF'!EE9 -> 1927203 | AJ45: ='Property-Level CF'!EF9 -> 1967953 | ... AL45: ='Property-Level CF'!EH9 -> 2051472
AA46: =AB44&AB46 -> 40 ORRNOI | AB46: NOI | AC46: ='Property-Level CF'!DY10 -> 1311547 | AD46: ='Property-Level CF'!DZ10 -> 1337880 | AE46: ='Property-Level CF'!EA10 -> 1364462 | AF46: ='Property-Level CF'!EB10 -> 1391768 | AG46: ='Property-Level CF'!EC10 -> 1419623 | AH46: ='Property-Level CF'!ED10 -> 1448080 | AI46: ='Property-Level CF'!EE10 -> 1476908 | AJ46: ='Property-Level CF'!EF10 -> 1506639 | ... AL46: ='Property-Level CF'!EH10 -> 1567320
B47: CASH FLOW | O47: Portfolio IRR by Cap Rate by Exit Year | AA47: =AB44&AB47 -> 40 ORRNCF before DS | AB47: NCF before DS | AC47: ='Property-Level CF'!DY14 -> 1290193.5 | AD47: ='Property-Level CF'!DZ14 -> 1316526.5 | AE47: ='Property-Level CF'!EA14 -> 1343108.5 | AF47: ='Property-Level CF'!EB14 -> 1370414.5 | AG47: ='Property-Level CF'!EC14 -> 1398269.5 | AH47: ='Property-Level CF'!ED14 -> 1426726.5 | AI47: ='Property-Level CF'!EE14 -> 1455554.5 | AJ47: ='Property-Level CF'!EF14 -> 1485285.5 | ... AL47: ='Property-Level CF'!EH14 -> 1545966.5
B48: Aspect GP Portfolio Returns by Year | O48: Cap Rate | P48: =P40 -> Year 1 | Q48: =Q40 -> Year 2 | R48: =R40 -> Year 3 | S48: =S40 -> Year 4 | T48: =T40 -> Year 5 | U48: =U40 -> Year 6 | V48: =V40 -> Year 7 | W48: =W40 -> Year 8 | ... Y48: =Y40 -> Year 10 | AB48: DS | AC48: ='Property-Level CF'!DY30 -> 724033.64 | AD48: =AC48 -> 724033.64 | AE48: =AD48 -> 724033.64 | AF48: =AE48 -> 724033.64 | AG48: =AF48 -> 724033.64 | AH48: =AG48 -> 724033.64 | AI48: =AH48 -> 724033.64 | AJ48: =AI48 -> 724033.64 | AK48: =AJ48 -> 724033.64 | AL48: =AK48 -> 724033.64
C49: =C5 -> Year 0 | D49: =D5 -> Year 1 | E49: =E5 -> Year 2 | F49: =F5 -> Year 3 | G49: =G5 -> Year 4 | H49: =H5 -> Year 5 | I49: =I5 -> Year 6 | J49: =J5 -> Year 7 | ... M49: =M5 -> Year 10 | O49: =O41 -> 0.05 | P49: =IRR(($C$39:C39,P41)) -> -0.10513416 | Q49: =IRR(($C39:D39,Q41)) -> 0.079246426 | R49: =IRR(($C39:E39,R41)) -> 0.1265754 | S49: =IRR(($C39:F39,S41)) -> 0.11977907 | T49: =IRR(($C39:G39,T41)) -> 0.12023852 | U49: =IRR(($C39:H39,U41)) -> 0.11402895 | V49: =IRR(($C39:I39,V41)) -> 0.11425016 | W49: =IRR(($C39:J39,W41)) -> 0.11444326 | X49: =IRR(($C39:K39,X41)) -> 0.11143173 | Y49: =IRR(($C39:L39,Y41)) -> 0.11058477 | AB49: NCF after DS | AC49: =AC47-AC48 -> 566159.86 | AD49: =AD47-AD48 -> 592492.86 | AE49: =AE47-AE48 -> 619074.86 | AF49: =AF47-AF48 -> 646380.86 | AG49: =AG47-AG48 -> 674235.86 | AH49: =AH47-AH48 -> 702692.86 | AI49: =AI47-AI48 -> 731520.86 | AJ49: =AJ47-AJ48 -> 761251.86 | ... AL49: =AL47-AL48 -> 821932.86
B50: Year Ending | C50: =C6 -> 44377 | D50: =D6 -> 44742 | E50: =E6 -> 45107 | F50: =F6 -> 45473 | G50: =G6 -> 45838 | H50: =H6 -> 46203 | I50: =I6 -> 46568 | J50: =J6 -> 46934 | ... M50: =M6 -> 48029 | O50: =O42 -> 0.051247526 | P50: =IRR(($C$39:C39,P42)) -> -0.17070362 | Q50: =IRR(($C$39:D39,Q42)) -> 0.045178016 | R50: =IRR(($C$39:E39,R42)) -> 0.10552149 | S50: =IRR(($C$39:F39,S42)) -> 0.10484153 | T50: =IRR(($C$39:G39,T42)) -> 0.10903916 | U50: =IRR(($C$39:H39,U42)) -> 0.10515315 | V50: =IRR(($C$39:I39,V42)) -> 0.10706389 | W50: =IRR(($C$39:J39,W42)) -> 0.10852845 | ... Y50: =IRR(($C$39:L39,Y42)) -> 0.10629852
O51: =O43 -> 0.055 | P51: =IRR(($C$39:C39,P43)) -> -0.35000217 | Q51: =IRR(($C$39:D39,Q43)) -> -0.054426074 | R51: =IRR(($C$39:E39,R43)) -> 0.043230654 | S51: =IRR(($C$39:F39,S43)) -> 0.060375896 | T51: =IRR(($C$39:G39,T43)) -> 0.075692468 | U51: =IRR(($C$39:H39,U43)) -> 0.078715837 | V51: =IRR(($C$39:I39,V43)) -> 0.085700552 | W51: =IRR(($C$39:J39,W43)) -> 0.090996739 | ... Y51: =IRR(($C$39:L39,Y43)) -> 0.093647045
B52: Aspect GP Returns | D52: =(D36+D38)*Summary!$C$22 -> 106143.06 | E52: =(E36+E38)*Summary!$C$22 -> 122540.46 | F52: =(F36+F38)*Summary!$C$22 -> 138122.01 | G52: =(G36+G38)*Summary!$C$22 -> 129791.91 | H52: =(H36+H38)*Summary!$C$22 -> 151681.56 | I52: =(I36+I38)*Summary!$C$22 -> 153348.31 | J52: =(J36+J38)*Summary!$C$22 -> 138380.66 | K52: =(K36+K38)*Summary!$C$22 -> 167569.91 | ... M52: =(M36+M38)*Summary!$C$22 -> 155211.66 | O52: =O44 -> 0.0575 | P52: =IRR(($C$39:C39,P44)) -> -0.45646652 | Q52: =IRR(($C$39:D39,Q44)) -> -0.11906329 | R52: =IRR(($C$39:E39,R44)) -> 0.0022405798 | S52: =IRR(($C$39:F39,S44)) -> 0.030899359 | T52: =IRR(($C$39:G39,T44)) -> 0.053595927 | U52: =IRR(($C$39:H39,U44)) -> 0.061196769 | V52: =IRR(($C$39:I39,V44)) -> 0.071586413 | W52: =IRR(($C$39:J39,W44)) -> 0.079463605 | ... Y52: =IRR(($C$39:L39,Y44)) -> 0.085373772 | AB52: Cost of Sale (Transfer Tax, Closing Costs, Broker Fee) | AC52: =2.25%+0.75%+0.85% -> 0.0385
B53: Asset Mangement Fee | D53: =-D38 -> 90781.633 | E53: =-E38 -> 90781.633 | F53: =-F38 -> 90781.633 | G53: =-G38 -> 90781.633 | H53: =-H38 -> 90781.633 | I53: =-I38 -> 90781.633 | J53: =-J38 -> 90781.633 | K53: =-K38 -> 90781.633 | ... M53: =-M38 -> 90781.633 | O53: =O45 -> 0.06 | P53: =IRR(($C$39:C39,P45)) -> -0.55405884 | Q53: =IRR(($C$39:D39,Q45)) -> -0.18295915 | R53: =IRR(($C$39:E39,R45)) -> -0.03868239 | S53: =IRR(($C$39:F39,S45)) -> 0.0013070837 | T53: =IRR(($C$39:G39,T45)) -> 0.031438558 | U53: =IRR(($C$39:H39,U45)) -> 0.043636134 | V53: =IRR(($C$39:I39,V45)) -> 0.057481701 | W53: =IRR(($C$39:J39,W45)) -> 0.067984941 | ... Y53: =IRR(($C$39:L39,Y45)) -> 0.077184684
B54: Total Yearly GP Returns | C54: =C39*Summary!C22 -> -1815632.7 | D54: =SUM(D52:D53) -> 196924.7 | E54: =SUM(E52:E53) -> 213322.1 | F54: =SUM(F52:F53) -> 228903.65 | G54: =SUM(G52:G53) -> 220573.55 | H54: =SUM(H52:H53) -> 242463.2 | I54: =SUM(I52:I53) -> 244129.95 | J54: =SUM(J52:J53) -> 229162.3 | K54: =SUM(K52:K53) -> 258351.55 | ... M54: =SUM(M52:M53) -> 245993.3
O55: Aspect GP Portfolio Returns - Final Year Cash Flow by Cap Rate by Exit Year
D56: =C54 -> -1815632.7 | E56: =C54 -> -1815632.7 | F56: =E56 -> -1815632.7 | G56: =F56 -> -1815632.7 | H56: =G56 -> -1815632.7 | I56: =H56 -> -1815632.7 | J56: =I56 -> -1815632.7 | K56: =J56 -> -1815632.7 | L56: =K56 -> -1815632.7 | M56: =L56 -> -1815632.7 | O56: Cap Rate | P56: =P48 -> Year 1 | Q56: =Q48 -> Year 2 | R56: =R48 -> Year 3 | S56: =S48 -> Year 4 | T56: =T48 -> Year 5 | U56: =U48 -> Year 6 | V56: =V48 -> Year 7 | W56: =W48 -> Year 8 | ... Y56: =Y48 -> Year 10
D57: =D54+(D33*Summary!C22) -> 1812837.8 | E57: =D54 -> 196924.7 | F57: =E57 -> 196924.7 | G57: =F57 -> 196924.7 | H57: =G57 -> 196924.7 | I57: =H57 -> 196924.7 | J57: =I57 -> 196924.7 | K57: =J57 -> 196924.7 | L57: =K57 -> 196924.7 | M57: =L57 -> 196924.7 | O57: =O33 -> 0.05 | P57: =((P33-Summary!$C$17)*Summary!$C$22)+D$54 -> 1715529.3 | Q57: =((Q33-Summary!$C$17)*Summary!$C$22)+E$54 -> 2091026.7 | R57: =((R33-Summary!$C$17)*Summary!$C$22)+F$54 -> 2414041.2 | S57: =((S33-Summary!$C$17)*Summary!$C$22)+G$54 -> 2488105.9 | T57: =((T33-Summary!$C$17)*Summary!$C$22)+H$54 -> 2635792.4 | U57: =((U33-Summary!$C$17)*Summary!$C$22)+I$54 -> 2669510.7 | V57: =((V33-Summary!$C$17)*Summary!$C$22)+J$54 -> 2797268.2 | W57: =((W33-Summary!$C$17)*Summary!$C$22)+K$54 -> 2957213.7 | ... Y57: =((Y33-Summary!$C$17)*Summary!$C$22)+M$54 -> 3136313.2
E58: =E54+(E33*Summary!C22) -> 1892238.6 | F58: =E54 -> 213322.1 | G58: =F58 -> 213322.1 | H58: =G58 -> 213322.1 | I58: =H58 -> 213322.1 | J58: =I58 -> 213322.1 | K58: =J58 -> 213322.1 | L58: =K58 -> 213322.1 | M58: =L58 -> 213322.1 | O58: =O34 -> 0.051247526 | P58: =(P34-Summary!$C$17)*Summary!$C$22+D$54 -> 1596479.2 | Q58: =(Q34-Summary!$C$17)*Summary!$C$22+E$54 -> 1963235.1 | R58: =(R34-Summary!$C$17)*Summary!$C$22+F$54 -> 2278765.6 | S58: =(S34-Summary!$C$17)*Summary!$C$22+G$54 -> 2350824.5 | T58: =(T34-Summary!$C$17)*Summary!$C$22+H$54 -> 2495448.8 | U58: =(U34-Summary!$C$17)*Summary!$C$22+I$54 -> 2528386.9 | V58: =(V34-Summary!$C$17)*Summary!$C$22+J$54 -> 2652669.9 | W58: =(W34-Summary!$C$17)*Summary!$C$22+K$54 -> 2809432.5 | ... Y58: =(Y34-Summary!$C$17)*Summary!$C$22+M$54 -> 2983871.3
F59: =F54+(F33*Summary!C22) -> 2200248.6 | G59: =F54 -> 228903.65 | H59: =G59 -> 228903.65 | I59: =H59 -> 228903.65 | J59: =I59 -> 228903.65 | K59: =J59 -> 228903.65 | L59: =K59 -> 228903.65 | M59: =L59 -> 228903.65 | O59: =O35 -> 0.055 | P59: =(P35-Summary!$C$17)*Summary!$C$22+D$54 -> 1270938.9 | Q59: =(Q35-Summary!$C$17)*Summary!$C$22+E$54 -> 1613790.9 | R59: =(R35-Summary!$C$17)*Summary!$C$22+F$54 -> 1908856.9 | S59: =(S35-Summary!$C$17)*Summary!$C$22+G$54 -> 1975431.2 | T59: =(T35-Summary!$C$17)*Summary!$C$22+H$54 -> 2111681.6 | U59: =(U35-Summary!$C$17)*Summary!$C$22+I$54 -> 2142486.2 | V59: =(V35-Summary!$C$17)*Summary!$C$22+J$54 -> 2257268.6 | W59: =(W35-Summary!$C$17)*Summary!$C$22+K$54 -> 2405327.2 | ... Y59: =(Y35-Summary!$C$17)*Summary!$C$22+M$54 -> 2567021.5
G60: =G54+(G33*Summary!C22) -> 2273190.4 | H60: =G54 -> 220573.55 | I60: =H60 -> 220573.55 | J60: =I60 -> 220573.55 | K60: =J60 -> 220573.55 | L60: =K60 -> 220573.55 | M60: =L60 -> 220573.55 | O60: =O36 -> 0.0575 | P60: =(P36-Summary!$C$17)*Summary!$C$22+D$54 -> 1077638.8 | Q60: =(Q36-Summary!$C$17)*Summary!$C$22+E$54 -> 1406297.1 | R60: =(R36-Summary!$C$17)*Summary!$C$22+F$54 -> 1689211.6 | S60: =(S36-Summary!$C$17)*Summary!$C$22+G$54 -> 1752529.1 | T60: =(T36-Summary!$C$17)*Summary!$C$22+H$54 -> 1883807.4 | U60: =(U36-Summary!$C$17)*Summary!$C$22+I$54 -> 1913345.1 | V60: =(V36-Summary!$C$17)*Summary!$C$22+J$54 -> 2022486.2 | W60: =(W36-Summary!$C$17)*Summary!$C$22+K$54 -> 2165376.6 | ... Y60: =(Y36-Summary!$C$17)*Summary!$C$22+M$54 -> 2319503.3
H61: =H54+(H33*Summary!C22) -> 2413575.5 | I61: =H54 -> 242463.2 | J61: =I61 -> 242463.2 | K61: =J61 -> 242463.2 | L61: =K61 -> 242463.2 | M61: =L61 -> 242463.2 | O61: =O37 -> 0.06 | P61: =(P37-Summary!$C$17)*Summary!$C$22+D$54 -> 900446.97 | Q61: =(Q37-Summary!$C$17)*Summary!$C$22+E$54 -> 1216094.4 | R61: =(R37-Summary!$C$17)*Summary!$C$22+F$54 -> 1487870.1 | S61: =(S37-Summary!$C$17)*Summary!$C$22+G$54 -> 1548202.3 | T61: =(T37-Summary!$C$17)*Summary!$C$22+H$54 -> 1674922.7 | U61: =(U37-Summary!$C$17)*Summary!$C$22+I$54 -> 1703299.1 | V61: =(V37-Summary!$C$17)*Summary!$C$22+J$54 -> 1807269 | W61: =(W37-Summary!$C$17)*Summary!$C$22+K$54 -> 1945421.8 | ... Y61: =(Y37-Summary!$C$17)*Summary!$C$22+M$54 -> 2092611.7
I62: =I54+(I33*Summary!C22) -> 2452945 | J62: =I54 -> 244129.95 | K62: =J62 -> 244129.95 | L62: =K62 -> 244129.95 | M62: =L62 -> 244129.95
J63: =J54+(J33*Summary!C22) -> 2574730.4 | K63: =J54 -> 229162.3 | L63: =J54 -> 229162.3 | M63: =L63 -> 229162.3 | O63: Aspect GP Portfolio Returns - IRR by Cap Rate by Exit Year
K64: =K54+(K33*Summary!C22) -> 2727309.5 | L64: =K54 -> 258351.55 | M64: =L64 -> 258351.55 | O64: Cap Rate | P64: =P56 -> Year 1 | Q64: =Q56 -> Year 2 | R64: =R56 -> Year 3 | S64: =S56 -> Year 4 | T64: =T56 -> Year 5 | U64: =U56 -> Year 6 | V64: =V56 -> Year 7 | W64: =W56 -> Year 8 | ... Y64: =Y56 -> Year 10
L65: =L54+(L33*Summary!C22) -> 2776199.7 | M65: =L54 -> 238000.1 | O65: =O33 -> 0.05 | P65: =IRR(($C54:C54,P57)) -> -0.055134162 | Q65: =IRR(($C54:D54,Q57)) -> 0.12876293 | R65: =IRR(($C54:E54,R57)) -> 0.17371155 | S65: =IRR(($C54:F54,S57)) -> 0.16612042 | T65: =IRR(($C54:G54,T57)) -> 0.16551431 | U65: =IRR(($C54:H54,U57)) -> 0.15895382 | V65: =IRR(($C54:I54,V57)) -> 0.15836714 | W65: =IRR(($C54:J54,W57)) -> 0.15776833 | ... Y65: =IRR(($C54:L54,Y57)) -> 0.15313074
M66: =M54+(M33*Summary!C22) -> 2899671.2 | O66: =O34 -> 0.051247526 | P66: =IRR(($C54:C54,P58)) -> -0.12070362 | Q66: =IRR(($C54:D54,Q58)) -> 0.09549697 | R66: =IRR(($C54:E54,R58)) -> 0.15353249 | S66: =IRR(($C54:F54,S58)) -> 0.15210249 | T66: =IRR(($C54:G54,T58)) -> 0.15520568 | U66: =IRR(($C54:H54,U58)) -> 0.15095988 | V66: =IRR(($C54:I54,V58)) -> 0.15201823 | W66: =IRR(($C54:J54,W58)) -> 0.15263831 | ... Y66: =IRR(($C54:L54,Y58)) -> 0.14956279
O67: =O35 -> 0.055 | P67: =IRR(($C54:C54,P59)) -> -0.30000217 | Q67: =IRR(($C54:D54,Q59)) -> -0.0014328114 | R67: =IRR(($C54:E54,R59)) -> 0.094108923 | S67: =IRR(($C54:F54,S59)) -> 0.11063577 | T67: =IRR(($C54:G54,T59)) -> 0.12473655 | U67: =IRR(($C54:H54,U59)) -> 0.12735607 | V67: =IRR(($C54:I54,V59)) -> 0.13332444 | W67: =IRR(($C54:J54,W59)) -> 0.13758733 | ... Y67: =IRR(($C54:L54,Y59)) -> 0.13915542
B68: Levered IRR | D68: =IRR(D56:D66) -> -0.0015393511 | E68: =IRR(E56:E66) -> 0.076547961 | F68: =IRR(F56:F66) -> 0.14146599 | G68: =IRR(G56:G66) -> 0.1439228 | H68: =IRR(H56:H66) -> 0.14899957 | I68: =IRR(I56:I66) -> 0.14655575 | J68: =IRR(J56:J66) -> 0.14849476 | K68: =IRR(K56:K66) -> 0.1497061 | ... M68: =IRR(M56:M66) -> 0.14754039 | O68: =O36 -> 0.0575 | P68: =IRR(($C54:C54,P60)) -> -0.40646652 | Q68: =IRR(($C54:D54,Q60)) -> -0.064015583 | R68: =IRR(($C54:E54,R60)) -> 0.055268166 | S68: =IRR(($C54:F54,S60)) -> 0.083390962 | T68: =IRR(($C54:G54,T60)) -> 0.10475331 | U68: =IRR(($C54:H54,U60)) -> 0.11190232 | V68: =IRR(($C54:I54,V60)) -> 0.12113528 | W68: =IRR(($C54:J54,W60)) -> 0.12782244 | ... Y68: =IRR(($C54:L54,Y60)) -> 0.13245663
B69: Levered Equity Multiple | D69: =(SUM(D57:D66)-SUM($D$53:D53))/-D56 -> 0.94846065 | E69: =(SUM(E57:E66)-SUM($D$53:E53))/-E56 -> 1.0506531 | F69: =(SUM(F57:F66)-SUM($D$53:F53))/-F56 -> 1.2877883 | G69: =(SUM(G57:G66)-SUM($D$53:G53))/-G56 -> 1.4040364 | H69: =(SUM(H57:H66)-SUM($D$53:H53))/-H56 -> 1.5528424 | I69: =(SUM(I57:I66)-SUM($D$53:I53))/-I56 -> 1.658068 | J69: =(SUM(J57:J66)-SUM($D$53:J53))/-J56 -> 1.809604 | K69: =(SUM(K57:K66)-SUM($D$53:K53))/-K56 -> 1.9698565 | ... M69: =(SUM(M57:M66)-SUM($D$53:M53))/-M56 -> 2.2381653 | O69: =O37 -> 0.06 | P69: =IRR(($C54:C54,P61)) -> -0.50405884 | Q69: =IRR(($C54:D54,Q61)) -> -0.1255673 | R69: =IRR(($C54:E54,R61)) -> 0.0167375 | S69: =IRR(($C54:F54,S61)) -> 0.056264982 | T69: =IRR(($C54:G54,T61)) -> 0.084902166 | U69: =IRR(($C54:H54,U61)) -> 0.09657973 | V69: =IRR(($C54:I54,V61)) -> 0.10909598 | W69: =IRR(($C54:J54,W61)) -> 0.11822119 | ... Y69: =IRR(($C54:L54,Y61)) -> 0.12591591

Sheet Property-Level CF
B2: CASH FLOW | O2: Year | P2: =D5 -> Year 1 | Q2: =E5 -> Year 2 | R2: =F5 -> Year 3 | S2: =G5 -> Year 4 | T2: =H5 -> Year 5 | U2: =I5 -> Year 6 | V2: =J5 -> Year 7 | W2: =K5 -> Year 8 | ... Y2: =M5 -> Year 10 | AA2: CASH FLOW | AN2: Year | AO2: ='Property-Level CF'!AC5 -> Year 1 | AP2: ='Property-Level CF'!AD5 -> Year 2 | AQ2: ='Property-Level CF'!AE5 -> Year 3 | AR2: ='Property-Level CF'!AF5 -> Year 4 | AS2: ='Property-Level CF'!AG5 -> Year 5 | AT2: ='Property-Level CF'!AH5 -> Year 6 | AU2: ='Property-Level CF'!AI5 -> Year 7 | AV2: ='Property-Level CF'!AJ5 -> Year 8 | ... AX2: ='Property-Level CF'!AL5 -> Year 10 | AZ2: CASH FLOW | BM2: Year | BN2: ='Property-Level CF'!BB5 -> Year 1 | BO2: ='Property-Level CF'!BC5 -> Year 2 | BP2: ='Property-Level CF'!BD5 -> Year 3 | BQ2: ='Property-Level CF'!BE5 -> Year 4 | BR2: ='Property-Level CF'!BF5 -> Year 5 | BS2: ='Property-Level CF'!BG5 -> Year 6 | BT2: ='Property-Level CF'!BH5 -> Year 7 | BU2: ='Property-Level CF'!BI5 -> Year 8 | ... BW2: ='Property-Level CF'!BK5 -> Year 10 | BY2: CASH FLOW | CL2: Year | CM2: ='Property-Level CF'!CA5 -> Year 1 | CN2: ='Property-Level CF'!CB5 -> Year 2 | CO2: ='Property-Level CF'!CC5 -> Year 3 | CP2: ='Property-Level CF'!CD5 -> Year 4 | CQ2: ='Property-Level CF'!CE5 -> Year 5 | CR2: ='Property-Level CF'!CF5 -> Year 6 | CS2: ='Property-Level CF'!CG5 -> Year 7 | CT2: ='Property-Level CF'!CH5 -> Year 8 | ... CV2: ='Property-Level CF'!CJ5 -> Year 10 | CX2: CASH FLOW | DK2: Year | DL2: ='Property-Level CF'!CZ5 -> Year 1 | DM2: ='Property-Level CF'!DA5 -> Year 2 | DN2: ='Property-Level CF'!DB5 -> Year 3 | DO2: ='Property-Level CF'!DC5 -> Year 4 | DP2: ='Property-Level CF'!DD5 -> Year 5 | DQ2: ='Property-Level CF'!DE5 -> Year 6 | DR2: ='Property-Level CF'!DF5 -> Year 7 | DS2: ='Property-Level CF'!DG5 -> Year 8 | ... DU2: ='Property-Level CF'!DI5 -> Year 10 | DW2: CASH FLOW | EJ2: Year | EK2: ='Property-Level CF'!DY5 -> Year 1 | EL2: ='Property-Level CF'!DZ5 -> Year 2 | EM2: ='Property-Level CF'!EA5 -> Year 3 | EN2: ='Property-Level CF'!EB5 -> Year 4 | EO2: ='Property-Level CF'!EC5 -> Year 5 | EP2: ='Property-Level CF'!ED5 -> Year 6 | EQ2: ='Property-Level CF'!EE5 -> Year 7 | ER2: ='Property-Level CF'!EF5 -> Year 8 | ... ET2: ='Property-Level CF'!EH5 -> Year 10
B3: =Summary!E4 -> 131 Kent Road, New Milford, CT 06776 | O3: Unlevered IRR | P3: =IRR(P4:P15) -> 0.018207065 | Q3: =IRR(Q4:Q15) -> 0.041901141 | R3: =IRR(R4:R15) -> 0.049895376 | S3: =IRR(S4:S15) -> 0.045662949 | T3: =IRR(T4:T15) -> 0.057865901 | U3: =IRR(U4:U15) -> 0.048907337 | V3: =IRR(V4:V15) -> 0.048552772 | W3: =IRR(W4:W15) -> 0.055276831 | ... Y3: =IRR(Y4:Y15) -> 0.056123945 | AA3: =Summary!E5 -> 164 Mount Pleasant Road, Newtown, CT 06470 | AN3: Unlevered IRR | AO3: =IRR(AO4:AO15) -> -0.0012527016 | AP3: =IRR(AP4:AP15) -> 0.0079366159 | AQ3: =IRR(AQ4:AQ15) -> 0.11035437 | AR3: =IRR(AR4:AR15) -> 0.10336455 | AS3: =IRR(AS4:AS15) -> 0.098897827 | AT3: =IRR(AT4:AT15) -> 0.093966435 | AU3: =IRR(AU4:AU15) -> 0.090460677 | AV3: =IRR(AV4:AV15) -> 0.087849783 | ... AX3: =IRR(AX4:AX15) -> 0.081037425 | AZ3: =Summary!E6 -> 170 Mount Pleasant Road, Newtown, CT 06470 | BM3: Unlevered IRR | BN3: =IRR(BN4:BN15) -> 0.0058039353 | BO3: =IRR(BO4:BO15) -> 0.061650282 | BP3: =IRR(BP4:BP15) -> 0.09312356 | BQ3: =IRR(BQ4:BQ15) -> 0.085985009 | BR3: =IRR(BR4:BR15) -> 0.081719594 | BS3: =IRR(BS4:BS15) -> 0.078954769 | BT3: =IRR(BT4:BT15) -> 0.084043199 | BU3: =IRR(BU4:BU15) -> 0.08297021 | ... BW3: =IRR(BW4:BW15) -> 0.079510418 | BY3: =Summary!E7 -> 2 Riverview Drive, Danbury, CT 06810 | CL3: Unlevered IRR | CM3: =IRR(CM4:CM15) -> 0.01114134 | CN3: =IRR(CN4:CN15) -> 0.034896017 | CO3: =IRR(CO4:CO15) -> 0.046020665 | CP3: =IRR(CP4:CP15) -> 0.051663947 | CQ3: =IRR(CQ4:CQ15) -> 0.055046562 | CR3: =IRR(CR4:CR15) -> 0.057312169 | CS3: =IRR(CS4:CS15) -> 0.058917249 | CT3: =IRR(CT4:CT15) -> 0.060118142 | ... CV3: =IRR(CV4:CV15) -> 0.061945 | CX3: =Summary!E8 -> 226 White Street, Danbury, CT 06810 | DK3: Unlevered IRR | DL3: =IRR(DL4:DL15) -> 0.011756166 | DM3: =IRR(DM4:DM15) -> 0.036804407 | DN3: =IRR(DN4:DN15) -> 0.048400461 | DO3: =IRR(DO4:DO15) -> 0.054245238 | DP3: =IRR(DP4:DP15) -> 0.057766297 | DQ3: =IRR(DQ4:DQ15) -> 0.060118578 | DR3: =IRR(DR4:DR15) -> 0.061800261 | DS3: =IRR(DS4:DS15) -> 0.063061998 | ... DU3: =IRR(DU4:DU15) -> 0.064826948 | DW3: =Summary!E9 -> 40 Old Ridgebury Road, Danbury, CT 06810 | EJ3: Unlevered IRR | EK3: =IRR(EK4:EK15) -> 0.0091266662 | EL3: =IRR(EL4:EL15) -> 0.034165979 | EM3: =IRR(EM4:EM15) -> 0.045690436 | EN3: =IRR(EN4:EN15) -> 0.051532587 | EO3: =IRR(EO4:EO15) -> 0.055051513 | EP3: =IRR(EP4:EP15) -> 0.057406682 | EQ3: =IRR(EQ4:EQ15) -> 0.059072596 | ER3: =IRR(ER4:ER15) -> 0.060346407 | ... ET3: =IRR(ET4:ET15) -> 0.062094976
O4: 0 | P4: ='Property-Level CF'!C16 -> -13422181 | Q4: =P4 -> -13422181 | R4: =Q4 -> -13422181 | S4: =R4 -> -13422181 | T4: =S4 -> -13422181 | U4: =T4 -> -13422181 | V4: =U4 -> -13422181 | W4: =V4 -> -13422181 | X4: =W4 -> -13422181 | Y4: =X4 -> -13422181 | AN4: 0 | AO4: ='Property-Level CF'!AB16 -> -10961842 | AP4: =AO4 -> -10961842 | AQ4: =AP4 -> -10961842 | AR4: =AQ4 -> -10961842 | AS4: =AR4 -> -10961842 | AT4: =AS4 -> -10961842 | AU4: =AT4 -> -10961842 | AV4: =AU4 -> -10961842 | AW4: =AV4 -> -10961842 | AX4: =AW4 -> -10961842 | BM4: 0 | BN4: ='Property-Level CF'!BA16 -> -14068705 | BO4: =BN4 -> -14068705 | BP4: =BO4 -> -14068705 | BQ4: =BP4 -> -14068705 | BR4: =BQ4 -> -14068705 | BS4: =BR4 -> -14068705 | BT4: =BS4 -> -14068705 | BU4: =BT4 -> -14068705 | BV4: =BU4 -> -14068705 | BW4: =BV4 -> -14068705 | CL4: 0 | CM4: ='Property-Level CF'!BZ16 -> -26845115 | CN4: =CM4 -> -26845115 | CO4: =CN4 -> -26845115 | CP4: =CO4 -> -26845115 | CQ4: =CP4 -> -26845115 | CR4: =CQ4 -> -26845115 | CS4: =CR4 -> -26845115 | CT4: =CS4 -> -26845115 | CU4: =CT4 -> -26845115 | CV4: =CU4 -> -26845115 | DK4: 0 | DL4: ='Property-Level CF'!CY16 -> -11362865 | DM4: =DL4 -> -11362865 | DN4: =DM4 -> -11362865 | DO4: =DN4 -> -11362865 | DP4: =DO4 -> -11362865 | DQ4: =DP4 -> -11362865 | DR4: =DQ4 -> -11362865 | DS4: =DR4 -> -11362865 | DT4: =DS4 -> -11362865 | DU4: =DT4 -> -11362865 | EJ4: 0 | EK4: ='Property-Level CF'!DX16 -> -27089729 | EL4: =EK4 -> -27089729 | EM4: =EL4 -> -27089729 | EN4: =EM4 -> -27089729 | EO4: =EN4 -> -27089729 | EP4: =EO4 -> -27089729 | EQ4: =EP4 -> -27089729 | ER4: =EQ4 -> -27089729 | ES4: =ER4 -> -27089729 | ET4: =ES4 -> -27089729
C5: ='Portfolio-Level CF'!C5 -> Year 0 | D5: ='Portfolio-Level CF'!D5 -> Year 1 | E5: ='Portfolio-Level CF'!E5 -> Year 2 | F5: ='Portfolio-Level CF'!F5 -> Year 3 | G5: ='Portfolio-Level CF'!G5 -> Year 4 | H5: ='Portfolio-Level CF'!H5 -> Year 5 | I5: ='Portfolio-Level CF'!I5 -> Year 6 | J5: ='Portfolio-Level CF'!J5 -> Year 7 | ... M5: ='Portfolio-Level CF'!M5 -> Year 10 | O5: =O4+1 -> 1 | P5: ='Property-Level CF'!D23+'Property-Level CF'!D14 -> 13666560 | Q5: ='Property-Level CF'!D14 -> 761132.5 | R5: =Q5 -> 761132.5 | S5: =R5 -> 761132.5 | T5: =S5 -> 761132.5 | U5: =T5 -> 761132.5 | V5: =U5 -> 761132.5 | W5: =V5 -> 761132.5 | X5: =W5 -> 761132.5 | Y5: =X5 -> 761132.5 | AB5: ='Property-Level CF'!C5 -> Year 0 | AC5: ='Property-Level CF'!D5 -> Year 1 | AD5: ='Property-Level CF'!E5 -> Year 2 | AE5: ='Property-Level CF'!F5 -> Year 3 | AF5: ='Property-Level CF'!G5 -> Year 4 | AG5: ='Property-Level CF'!H5 -> Year 5 | AH5: ='Property-Level CF'!I5 -> Year 6 | AI5: ='Property-Level CF'!J5 -> Year 7 | ... AL5: ='Property-Level CF'!M5 -> Year 10 | AN5: =AN4+1 -> 1 | AO5: ='Property-Level CF'!AC23+'Property-Level CF'!AC14 -> 10948110 | AP5: ='Property-Level CF'!AC14 -> 408299 | AQ5: =AP5 -> 408299 | AR5: =AQ5 -> 408299 | AS5: =AR5 -> 408299 | AT5: =AS5 -> 408299 | AU5: =AT5 -> 408299 | AV5: =AU5 -> 408299 | AW5: =AV5 -> 408299 | AX5: =AW5 -> 408299 | BA5: ='Property-Level CF'!AB5 -> Year 0 | BB5: ='Property-Level CF'!AC5 -> Year 1 | BC5: ='Property-Level CF'!AD5 -> Year 2 | BD5: ='Property-Level CF'!AE5 -> Year 3 | BE5: ='Property-Level CF'!AF5 -> Year 4 | BF5: ='Property-Level CF'!AG5 -> Year 5 | BG5: ='Property-Level CF'!AH5 -> Year 6 | BH5: ='Property-Level CF'!AI5 -> Year 7 | ... BK5: ='Property-Level CF'!AL5 -> Year 10 | BM5: =BM4+1 -> 1 | BN5: ='Property-Level CF'!BB23+'Property-Level CF'!BB14 -> 14150359 | BO5: ='Property-Level CF'!BB14 -> 623299 | BP5: =BO5 -> 623299 | BQ5: =BP5 -> 623299 | BR5: =BQ5 -> 623299 | BS5: =BR5 -> 623299 | BT5: =BS5 -> 623299 | BU5: =BT5 -> 623299 | BV5: =BU5 -> 623299 | BW5: =BV5 -> 623299 | BZ5: ='Portfolio-Level CF'!C5 -> Year 0 | CA5: ='Portfolio-Level CF'!D5 -> Year 1 | CB5: ='Portfolio-Level CF'!E5 -> Year 2 | CC5: ='Portfolio-Level CF'!F5 -> Year 3 | CD5: ='Portfolio-Level CF'!G5 -> Year 4 | CE5: ='Portfolio-Level CF'!H5 -> Year 5 | CF5: ='Portfolio-Level CF'!I5 -> Year 6 | CG5: ='Portfolio-Level CF'!J5 -> Year 7 | ... CJ5: ='Portfolio-Level CF'!M5 -> Year 10 | CL5: =CL4+1 -> 1 | CM5: ='Property-Level CF'!CA23+'Property-Level CF'!CA14 -> 27144206 | CN5: ='Property-Level CF'!CA14 -> 1332627.5 | CO5: =CN5 -> 1332627.5 | CP5: =CO5 -> 1332627.5 | CQ5: =CP5 -> 1332627.5 | CR5: =CQ5 -> 1332627.5 | CS5: =CR5 -> 1332627.5 | CT5: =CS5 -> 1332627.5 | CU5: =CT5 -> 1332627.5 | CV5: =CU5 -> 1332627.5 | CY5: ='Property-Level CF'!DX5 -> Year 0 | CZ5: ='Property-Level CF'!DY5 -> Year 1 | DA5: ='Property-Level CF'!DZ5 -> Year 2 | DB5: ='Property-Level CF'!EA5 -> Year 3 | DC5: ='Property-Level CF'!EB5 -> Year 4 | DD5: ='Property-Level CF'!EC5 -> Year 5 | DE5: ='Property-Level CF'!ED5 -> Year 6 | DF5: ='Property-Level CF'!EE5 -> Year 7 | ... DI5: ='Property-Level CF'!EH5 -> Year 10 | DK5: =DK4+1 -> 1 | DL5: ='Property-Level CF'!CZ23+'Property-Level CF'!CZ14 -> 11496448 | DM5: ='Property-Level CF'!CZ14 -> 571054 | DN5: =DM5 -> 571054 | DO5: =DN5 -> 571054 | DP5: =DO5 -> 571054 | DQ5: =DP5 -> 571054 | DR5: =DQ5 -> 571054 | DS5: =DR5 -> 571054 | DT5: =DS5 -> 571054 | DU5: =DT5 -> 571054 | DX5: ='Property-Level CF'!BZ5 -> Year 0 | DY5: ='Property-Level CF'!CA5 -> Year 1 | DZ5: ='Property-Level CF'!CB5 -> Year 2 | EA5: ='Property-Level CF'!CC5 -> Year 3 | EB5: ='Property-Level CF'!CD5 -> Year 4 | EC5: ='Property-Level CF'!CE5 -> Year 5 | ED5: ='Property-Level CF'!CF5 -> Year 6 | EE5: ='Property-Level CF'!CG5 -> Year 7 | ... EH5: ='Property-Level CF'!CJ5 -> Year 10 | EJ5: =EJ4+1 -> 1 | EK5: ='Property-Level CF'!DY23+'Property-Level CF'!DY14 -> 27336968 | EL5: ='Property-Level CF'!DY14 -> 1290193.5 | EM5: =EL5 -> 1290193.5 | EN5: =EM5 -> 1290193.5 | EO5: =EN5 -> 1290193.5 | EP5: =EO5 -> 1290193.5 | EQ5: =EP5 -> 1290193.5 | ER5: =EQ5 -> 1290193.5 | ES5: =ER5 -> 1290193.5 | ET5: =ES5 -> 1290193.5
B6: Year Ending | C6: ='Portfolio-Level CF'!C6 -> 44377 | D6: ='Portfolio-Level CF'!D6 -> 44742 | E6: ='Portfolio-Level CF'!E6 -> 45107 | F6: ='Portfolio-Level CF'!F6 -> 45473 | G6: ='Portfolio-Level CF'!G6 -> 45838 | H6: ='Portfolio-Level CF'!H6 -> 46203 | I6: ='Portfolio-Level CF'!I6 -> 46568 | J6: ='Portfolio-Level CF'!J6 -> 46934 | ... M6: ='Portfolio-Level CF'!M6 -> 48029 | O6: =O5+1 -> 2 | Q6: ='Property-Level CF'!E23+'Property-Level CF'!E14 -> 13777531 | R6: ='Property-Level CF'!E14 -> 731468.5 | S6: =R6 -> 731468.5 | T6: =S6 -> 731468.5 | U6: =T6 -> 731468.5 | V6: =U6 -> 731468.5 | W6: =V6 -> 731468.5 | X6: =W6 -> 731468.5 | Y6: =X6 -> 731468.5 | AA6: Year Ending | AB6: ='Property-Level CF'!C6 -> 44377 | AC6: ='Property-Level CF'!D6 -> 44742 | AD6: ='Property-Level CF'!E6 -> 45107 | AE6: ='Property-Level CF'!F6 -> 45473 | AF6: ='Property-Level CF'!G6 -> 45838 | AG6: ='Property-Level CF'!H6 -> 46203 | AH6: ='Property-Level CF'!I6 -> 46568 | AI6: ='Property-Level CF'!J6 -> 46934 | ... AL6: ='Property-Level CF'!M6 -> 48029 | AN6: =AN5+1 -> 2 | AP6: ='Property-Level CF'!AD23+'Property-Level CF'!AD14 -> 10724993 | AQ6: ='Property-Level CF'!AD14 -> 547987 | AR6: =AQ6 -> 547987 | AS6: =AR6 -> 547987 | AT6: =AS6 -> 547987 | AU6: =AT6 -> 547987 | AV6: =AU6 -> 547987 | AW6: =AV6 -> 547987 | AX6: =AW6 -> 547987 | AZ6: Year Ending | BA6: ='Property-Level CF'!AB6 -> 44377 | BB6: ='Property-Level CF'!AC6 -> 44742 | BC6: ='Property-Level CF'!AD6 -> 45107 | BD6: ='Property-Level CF'!AE6 -> 45473 | BE6: ='Property-Level CF'!AF6 -> 45838 | BF6: ='Property-Level CF'!AG6 -> 46203 | BG6: ='Property-Level CF'!AH6 -> 46568 | BH6: ='Property-Level CF'!AI6 -> 46934 | ... BK6: ='Property-Level CF'!AL6 -> 48029 | BM6: =BM5+1 -> 2 | BO6: ='Property-Level CF'!BC23+'Property-Level CF'!BC14 -> 15195131 | BP6: ='Property-Level CF'!BC14 -> 779615 | BQ6: =BP6 -> 779615 | BR6: =BQ6 -> 779615 | BS6: =BR6 -> 779615 | BT6: =BS6 -> 779615 | BU6: =BT6 -> 779615 | BV6: =BU6 -> 779615 | BW6: =BV6 -> 779615 | BY6: Year Ending | BZ6: ='Portfolio-Level CF'!C6 -> 44377 | CA6: ='Portfolio-Level CF'!D6 -> 44742 | CB6: ='Portfolio-Level CF'!E6 -> 45107 | CC6: ='Portfolio-Level CF'!F6 -> 45473 | CD6: ='Portfolio-Level CF'!G6 -> 45838 | CE6: ='Portfolio-Level CF'!H6 -> 46203 | CF6: ='Portfolio-Level CF'!I6 -> 46568 | CG6: ='Portfolio-Level CF'!J6 -> 46934 | ... CJ6: ='Portfolio-Level CF'!M6 -> 48029 | CL6: =CL5+1 -> 2 | CN6: ='Property-Level CF'!CB23+'Property-Level CF'!CB14 -> 27372250 | CO6: ='Property-Level CF'!CB14 -> 1356219.5 | CP6: =CO6 -> 1356219.5 | CQ6: =CP6 -> 1356219.5 | CR6: =CQ6 -> 1356219.5 | CS6: =CR6 -> 1356219.5 | CT6: =CS6 -> 1356219.5 | CU6: =CT6 -> 1356219.5 | CV6: =CU6 -> 1356219.5 | CX6: Year Ending | CY6: ='Property-Level CF'!DX6 -> 44377 | CZ6: ='Property-Level CF'!DY6 -> 44742 | DA6: ='Property-Level CF'!DZ6 -> 45107 | DB6: ='Property-Level CF'!EA6 -> 45473 | DC6: ='Property-Level CF'!EB6 -> 45838 | DD6: ='Property-Level CF'!EC6 -> 46203 | DE6: ='Property-Level CF'!ED6 -> 46568 | DF6: ='Property-Level CF'!EE6 -> 46934 | ... DI6: ='Property-Level CF'!EH6 -> 48029 | DK6: =DK5+1 -> 2 | DM6: ='Property-Level CF'!DA23+'Property-Level CF'!DA14 -> 11622592 | DN6: ='Property-Level CF'!DA14 -> 582737 | DO6: =DN6 -> 582737 | DP6: =DO6 -> 582737 | DQ6: =DP6 -> 582737 | DR6: =DQ6 -> 582737 | DS6: =DR6 -> 582737 | DT6: =DS6 -> 582737 | DU6: =DT6 -> 582737 | DW6: Year Ending | DX6: ='Property-Level CF'!BZ6 -> 44377 | DY6: ='Property-Level CF'!CA6 -> 44742 | DZ6: ='Property-Level CF'!CB6 -> 45107 | EA6: ='Property-Level CF'!CC6 -> 45473 | EB6: ='Property-Level CF'!CD6 -> 45838 | EC6: ='Property-Level CF'!CE6 -> 46203 | ED6: ='Property-Level CF'!CF6 -> 46568 | EE6: ='Property-Level CF'!CG6 -> 46934 | ... EH6: ='Property-Level CF'!CJ6 -> 48029 | EJ6: =EJ5+1 -> 2 | EL6: ='Property-Level CF'!DZ23+'Property-Level CF'!DZ14 -> 27638172 | EM6: ='Property-Level CF'!DZ14 -> 1316526.5 | EN6: =EM6 -> 1316526.5 | EO6: =EN6 -> 1316526.5 | EP6: =EO6 -> 1316526.5 | EQ6: =EP6 -> 1316526.5 | ER6: =EQ6 -> 1316526.5 | ES6: =ER6 -> 1316526.5 | ET6: =ES6 -> 1316526.5
B7: Average Occupancy % | D7: ='Occupancy Report'!D49 -> 0.97895152 | E7: ='Occupancy Report'!H49 -> 1 | F7: ='Occupancy Report'!L49 -> 0.99657192 | G7: ='Occupancy Report'!P49 -> 0.97942583 | H7: ='Occupancy Report'!T49 -> 1 | I7: ='Occupancy Report'!X49 -> 0.94696841 | J7: ='Occupancy Report'!AB49 -> 0.97189939 | K7: ='Occupancy Report'!AF49 -> 0.99633618 | L7: ='Occupancy Report'!AJ49 -> 0.97942583 | M7: ='Occupancy Report'!AN49 -> 0.98567136 | O7: =O6+1 -> 3 | R7: ='Property-Level CF'!F23+'Property-Level CF'!F14 -> 13926261 | S7: ='Property-Level CF'!F14 -> 732340.5 | T7: =S7 -> 732340.5 | U7: =T7 -> 732340.5 | V7: =U7 -> 732340.5 | W7: =V7 -> 732340.5 | X7: =W7 -> 732340.5 | Y7: =X7 -> 732340.5 | AA7: Average Occupancy % | AC7: ='Occupancy Report'!D74 -> 0.79248448 | AD7: ='Occupancy Report'!H74 -> 1 | AE7: ='Occupancy Report'!L74 -> 1 | AF7: ='Occupancy Report'!P74 -> 1 | AG7: ='Occupancy Report'!T74 -> 1 | AH7: ='Occupancy Report'!X74 -> 1 | AI7: ='Occupancy Report'!AB74 -> 1 | AJ7: ='Occupancy Report'!AF74 -> 1 | AK7: ='Occupancy Report'!AJ74 -> 0.99249217 | AL7: ='Occupancy Report'!AN74 -> 0.9850966 | AN7: =AN6+1 -> 3 | AQ7: ='Property-Level CF'!AE23+'Property-Level CF'!AE14 -> 13894272 | AR7: ='Property-Level CF'!AE14 -> 713558 | AS7: =AR7 -> 713558 | AT7: =AS7 -> 713558 | AU7: =AT7 -> 713558 | AV7: =AU7 -> 713558 | AW7: =AV7 -> 713558 | AX7: =AW7 -> 713558 | AZ7: Average Occupancy % | BB7: ='Occupancy Report'!D99 -> 0.90648333 | BC7: ='Occupancy Report'!H99 -> 1 | BD7: ='Occupancy Report'!L99 -> 1 | BE7: ='Occupancy Report'!P99 -> 1 | BF7: ='Occupancy Report'!T99 -> 1 | BG7: ='Occupancy Report'!X99 -> 1 | BH7: ='Occupancy Report'!AB99 -> 1 | BI7: ='Occupancy Report'!AF99 -> 1 | BJ7: ='Occupancy Report'!AJ99 -> 1 | BK7: ='Occupancy Report'!AN99 -> 1 | BM7: =BM6+1 -> 3 | BP7: ='Property-Level CF'!BD23+'Property-Level CF'!BD14 -> 16779454 | BQ7: ='Property-Level CF'!BD14 -> 862384 | BR7: =BQ7 -> 862384 | BS7: =BR7 -> 862384 | BT7: =BS7 -> 862384 | BU7: =BT7 -> 862384 | BV7: =BU7 -> 862384 | BW7: =BV7 -> 862384 | BY7: Average Occupancy % | CA7: ='Occupancy Report'!D124 -> 1 | CB7: ='Occupancy Report'!H124 -> 1 | CC7: ='Occupancy Report'!L124 -> 1 | CD7: ='Occupancy Report'!P124 -> 1 | CE7: ='Occupancy Report'!T124 -> 1 | CF7: ='Occupancy Report'!X124 -> 1 | CG7: ='Occupancy Report'!AB124 -> 1 | CH7: ='Occupancy Report'!AF124 -> 1 | CI7: ='Occupancy Report'!AJ124 -> 1 | CJ7: ='Occupancy Report'!AN124 -> 1 | CL7: =CL6+1 -> 3 | CO7: ='Property-Level CF'!CC23+'Property-Level CF'!CC14 -> 27847848 | CP7: ='Property-Level CF'!CC14 -> 1380140.5 | CQ7: =CP7 -> 1380140.5 | CR7: =CQ7 -> 1380140.5 | CS7: =CR7 -> 1380140.5 | CT7: =CS7 -> 1380140.5 | CU7: =CT7 -> 1380140.5 | CV7: =CU7 -> 1380140.5 | CX7: Average Occupancy % | CZ7: ='Occupancy Report'!D149 -> 1 | DA7: ='Occupancy Report'!H149 -> 1 | DB7: ='Occupancy Report'!L149 -> 1 | DC7: ='Occupancy Report'!P149 -> 1 | DD7: ='Occupancy Report'!T149 -> 1 | DE7: ='Occupancy Report'!X149 -> 1 | DF7: ='Occupancy Report'!AB149 -> 1 | DG7: ='Occupancy Report'!AF149 -> 1 | DH7: ='Occupancy Report'!AJ149 -> 1 | DI7: ='Occupancy Report'!AN149 -> 1 | DK7: =DK6+1 -> 3 | DN7: ='Property-Level CF'!DB23+'Property-Level CF'!DB14 -> 11855301 | DO7: ='Property-Level CF'!DB14 -> 594653 | DP7: =DO7 -> 594653 | DQ7: =DP7 -> 594653 | DR7: =DQ7 -> 594653 | DS7: =DR7 -> 594653 | DT7: =DS7 -> 594653 | DU7: =DT7 -> 594653 | DW7: Average Occupancy % | DY7: ='Occupancy Report'!D174 -> 1 | DZ7: ='Occupancy Report'!H174 -> 1 | EA7: ='Occupancy Report'!L174 -> 1 | EB7: ='Occupancy Report'!P174 -> 1 | EC7: ='Occupancy Report'!T174 -> 1 | ED7: ='Occupancy Report'!X174 -> 1 | EE7: ='Occupancy Report'!AB174 -> 1 | EF7: ='Occupancy Report'!AF174 -> 1 | EG7: ='Occupancy Report'!AJ174 -> 1 | EH7: ='Occupancy Report'!AN174 -> 1 | EJ7: =EJ6+1 -> 3 | EM7: ='Property-Level CF'!EA23+'Property-Level CF'!EA14 -> 28187732 | EN7: ='Property-Level CF'!EA14 -> 1343108.5 | EO7: =EN7 -> 1343108.5 | EP7: =EO7 -> 1343108.5 | EQ7: =EP7 -> 1343108.5 | ER7: =EQ7 -> 1343108.5 | ES7: =ER7 -> 1343108.5 | ET7: =ES7 -> 1343108.5
O8: =O7+1 -> 4 | S8: ='Property-Level CF'!G23+'Property-Level CF'!G14 -> 13611047 | T8: ='Property-Level CF'!G14 -> 476440.5 | U8: =T8 -> 476440.5 | V8: =U8 -> 476440.5 | W8: =V8 -> 476440.5 | X8: =W8 -> 476440.5 | Y8: =X8 -> 476440.5 | AN8: =AN7+1 -> 4 | AR8: ='Property-Level CF'!AF23+'Property-Level CF'!AF14 -> 14243604 | AS8: ='Property-Level CF'!AF14 -> 731808 | AT8: =AS8 -> 731808 | AU8: =AT8 -> 731808 | AV8: =AU8 -> 731808 | AW8: =AV8 -> 731808 | AX8: =AW8 -> 731808 | BM8: =BM7+1 -> 4 | BQ8: ='Property-Level CF'!BE23+'Property-Level CF'!BE14 -> 16913847 | BR8: ='Property-Level CF'!BE14 -> 869405 | BS8: =BR8 -> 869405 | BT8: =BS8 -> 869405 | BU8: =BT8 -> 869405 | BV8: =BU8 -> 869405 | BW8: =BV8 -> 869405 | CL8: =CL7+1 -> 4 | CP8: ='Property-Level CF'!CD23+'Property-Level CF'!CD14 -> 28336289 | CQ8: ='Property-Level CF'!CD14 -> 1404707.5 | CR8: =CQ8 -> 1404707.5 | CS8: =CR8 -> 1404707.5 | CT8: =CS8 -> 1404707.5 | CU8: =CT8 -> 1404707.5 | CV8: =CU8 -> 1404707.5 | DK8: =DK7+1 -> 4 | DO8: ='Property-Level CF'!DC23+'Property-Level CF'!DC14 -> 12092657 | DP8: ='Property-Level CF'!DC14 -> 606807 | DQ8: =DP8 -> 606807 | DR8: =DQ8 -> 606807 | DS8: =DR8 -> 606807 | DT8: =DS8 -> 606807 | DU8: =DT8 -> 606807 | EJ8: =EJ7+1 -> 4 | EN8: ='Property-Level CF'!EB23+'Property-Level CF'!EB14 -> 28752260 | EO8: ='Property-Level CF'!EB14 -> 1370414.5 | EP8: =EO8 -> 1370414.5 | EQ8: =EP8 -> 1370414.5 | ER8: =EQ8 -> 1370414.5 | ES8: =ER8 -> 1370414.5 | ET8: =ES8 -> 1370414.5
B9: Effective Gross Rent | D9: ='Cash Flow Dump'!B32 -> 1080474 | E9: ='Cash Flow Dump'!C32 -> 1104382 | F9: ='Cash Flow Dump'!D32 -> 1120725 | G9: ='Cash Flow Dump'!E32 -> 1124325 | H9: ='Cash Flow Dump'!F32 -> 1174564 | I9: ='Cash Flow Dump'!G32 -> 1131939 | J9: ='Cash Flow Dump'!H32 -> 1155752 | K9: ='Cash Flow Dump'!I32 -> 1206302 | ... M9: ='Cash Flow Dump'!K32 -> 1261766 | O9: =O8+1 -> 5 | T9: ='Property-Level CF'!H23+'Property-Level CF'!H14 -> 14639125 | U9: ='Property-Level CF'!H14 -> 824705.5 | V9: =U9 -> 824705.5 | W9: =V9 -> 824705.5 | X9: =W9 -> 824705.5 | Y9: =X9 -> 824705.5 | AA9: Effective Gross Rent | AC9: ='Cash Flow Dump'!P32 -> 753930 | AD9: ='Cash Flow Dump'!Q32 -> 906249 | AE9: ='Cash Flow Dump'!R32 -> 1085628 | AF9: ='Cash Flow Dump'!S32 -> 1112856 | AG9: ='Cash Flow Dump'!T32 -> 1139458 | AH9: ='Cash Flow Dump'!U32 -> 1156756 | AI9: ='Cash Flow Dump'!V32 -> 1174243 | AJ9: ='Cash Flow Dump'!W32 -> 1192002 | ... AL9: ='Cash Flow Dump'!Y32 -> 1215445 | AN9: =AN8+1 -> 5 | AS9: ='Property-Level CF'!AG23+'Property-Level CF'!AG14 -> 14577451 | AT9: ='Property-Level CF'!AG14 -> 749249 | AU9: =AT9 -> 749249 | AV9: =AU9 -> 749249 | AW9: =AV9 -> 749249 | AX9: =AW9 -> 749249 | AZ9: Effective Gross Rent | BB9: ='Cash Flow Dump'!AD32 -> 955031 | BC9: ='Cash Flow Dump'!AE32 -> 1124079 | BD9: ='Cash Flow Dump'!AF32 -> 1217274 | BE9: ='Cash Flow Dump'!AG32 -> 1232295 | BF9: ='Cash Flow Dump'!AH32 -> 1247438 | BG9: ='Cash Flow Dump'!AI32 -> 1263167 | BH9: ='Cash Flow Dump'!AJ32 -> 1330801 | BI9: ='Cash Flow Dump'!AK32 -> 1357587 | ... BK9: ='Cash Flow Dump'!AM32 -> 1389233 | BM9: =BM8+1 -> 5 | BR9: ='Property-Level CF'!BF23+'Property-Level CF'!BF14 -> 17046899 | BS9: ='Property-Level CF'!BF14 -> 876356 | BT9: =BS9 -> 876356 | BU9: =BT9 -> 876356 | BV9: =BU9 -> 876356 | BW9: =BV9 -> 876356 | BY9: Effective Gross Rent | CA9: ='Cash Flow Dump'!AR31 -> 1885346 | CB9: ='Cash Flow Dump'!AS31 -> 1921877 | CC9: ='Cash Flow Dump'!AT31 -> 1959053 | CD9: ='Cash Flow Dump'!AU31 -> 1997206 | CE9: ='Cash Flow Dump'!AV31 -> 2036006 | CF9: ='Cash Flow Dump'!AW31 -> 2075650 | CG9: ='Cash Flow Dump'!AX31 -> 2115923 | CH9: ='Cash Flow Dump'!AY31 -> 2156964 | ... CJ9: ='Cash Flow Dump'!BA31 -> 2244371 | CL9: =CL8+1 -> 5 | CQ9: ='Property-Level CF'!CE23+'Property-Level CF'!CE14 -> 28831014 | CR9: ='Property-Level CF'!CE14 -> 1429590.5 | CS9: =CR9 -> 1429590.5 | CT9: =CS9 -> 1429590.5 | CU9: =CT9 -> 1429590.5 | CV9: =CU9 -> 1429590.5 | CX9: Effective Gross Rent | CZ9: ='Cash Flow Dump'!BF26 -> 810031 | DA9: ='Cash Flow Dump'!BG26 -> 827265 | DB9: ='Cash Flow Dump'!BH26 -> 844869 | DC9: ='Cash Flow Dump'!BI26 -> 862852 | DD9: ='Cash Flow Dump'!BJ26 -> 881222 | DE9: ='Cash Flow Dump'!BK26 -> 899987 | DF9: ='Cash Flow Dump'!BL26 -> 919155 | DG9: ='Cash Flow Dump'!BM26 -> 938737 | ... DI9: ='Cash Flow Dump'!BO26 -> 979173 | DK9: =DK8+1 -> 5 | DP9: ='Property-Level CF'!DD23+'Property-Level CF'!DD14 -> 12334779 | DQ9: ='Property-Level CF'!DD14 -> 619205 | DR9: =DQ9 -> 619205 | DS9: =DR9 -> 619205 | DT9: =DS9 -> 619205 | DU9: =DT9 -> 619205 | DW9: Effective Gross Rent | DY9: ='Cash Flow Dump'!BT30 -> 1701092 | DZ9: ='Cash Flow Dump'!BU30 -> 1736951 | EA9: ='Cash Flow Dump'!BV30 -> 1773282 | EB9: ='Cash Flow Dump'!BW30 -> 1810584 | EC9: ='Cash Flow Dump'!BX30 -> 1848680 | ED9: ='Cash Flow Dump'!BY30 -> 1887630 | EE9: ='Cash Flow Dump'!BZ30 -> 1927203 | EF9: ='Cash Flow Dump'!CA30 -> 1967953 | ... EH9: ='Cash Flow Dump'!CC30 -> 2051472 | EJ9: =EJ8+1 -> 5 | EO9: ='Property-Level CF'!EC23+'Property-Level CF'!EC14 -> 29328138 | EP9: ='Property-Level CF'!EC14 -> 1398269.5 | EQ9: =EP9 -> 1398269.5 | ER9: =EQ9 -> 1398269.5 | ES9: =ER9 -> 1398269.5 | ET9: =ES9 -> 1398269.5
B10: Net Operating Income | D10: ='Cash Flow Dump'!B46 -> 776823 | E10: ='Cash Flow Dump'!C46 -> 792690 | F10: ='Cash Flow Dump'!D46 -> 801674 | G10: ='Cash Flow Dump'!E46 -> 798070 | H10: ='Cash Flow Dump'!F46 -> 839376 | I10: ='Cash Flow Dump'!G46 -> 790672 | J10: ='Cash Flow Dump'!H46 -> 806147 | K10: ='Cash Flow Dump'!I46 -> 847300 | ... M10: ='Cash Flow Dump'!K46 -> 884835 | O10: =O9+1 -> 6 | U10: ='Property-Level CF'!I23+'Property-Level CF'!I14 -> 13788852 | V10: ='Property-Level CF'!I14 -> 776001.5 | W10: =V10 -> 776001.5 | X10: =W10 -> 776001.5 | Y10: =X10 -> 776001.5 | AA10: Net Operating Income | AC10: ='Cash Flow Dump'!P46 -> 421291 | AD10: ='Cash Flow Dump'!Q46 -> 560979 | AE10: ='Cash Flow Dump'!R46 -> 726550 | AF10: ='Cash Flow Dump'!S46 -> 744800 | AG10: ='Cash Flow Dump'!T46 -> 762241 | AH10: ='Cash Flow Dump'!U46 -> 770468 | AI10: ='Cash Flow Dump'!V46 -> 778664 | AJ10: ='Cash Flow Dump'!W46 -> 786906 | ... AL10: ='Cash Flow Dump'!Y46 -> 791022 | AN10: =AN9+1 -> 6 | AT10: ='Property-Level CF'!AH23+'Property-Level CF'!AH14 -> 14734928 | AU10: ='Property-Level CF'!AH14 -> 757476 | AV10: =AU10 -> 757476 | AW10: =AV10 -> 757476 | AX10: =AW10 -> 757476 | AZ10: Net Operating Income | BB10: ='Cash Flow Dump'!AD48 -> 638299 | BC10: ='Cash Flow Dump'!AE48 -> 794615 | BD10: ='Cash Flow Dump'!AF48 -> 877384 | BE10: ='Cash Flow Dump'!AG48 -> 884405 | BF10: ='Cash Flow Dump'!AH48 -> 891356 | BG10: ='Cash Flow Dump'!AI48 -> 898681 | BH10: ='Cash Flow Dump'!AJ48 -> 956057 | BI10: ='Cash Flow Dump'!AK48 -> 973687 | ... BK10: ='Cash Flow Dump'!AM48 -> 987095 | BM10: =BM9+1 -> 6 | BS10: ='Property-Level CF'!BG23+'Property-Level CF'!BG14 -> 17187111 | BT10: ='Property-Level CF'!BG14 -> 883681 | BU10: =BT10 -> 883681 | BV10: =BU10 -> 883681 | BW10: =BV10 -> 883681 | BY10: Net Operating Income | CA10: ='Cash Flow Dump'!AR46 -> 1354228 | CB10: ='Cash Flow Dump'!AS46 -> 1377820 | CC10: ='Cash Flow Dump'!AT46 -> 1401741 | CD10: ='Cash Flow Dump'!AU46 -> 1426308 | CE10: ='Cash Flow Dump'!AV46 -> 1451191 | CF10: ='Cash Flow Dump'!AW46 -> 1476575 | CG10: ='Cash Flow Dump'!AX46 -> 1502242 | CH10: ='Cash Flow Dump'!AY46 -> 1528321 | ... CJ10: ='Cash Flow Dump'!BA46 -> 1584598 | CL10: =CL9+1 -> 6 | CR10: ='Property-Level CF'!CF23+'Property-Level CF'!CF14 -> 29335699 | CS10: ='Property-Level CF'!CF14 -> 1454974.5 | CT10: =CS10 -> 1454974.5 | CU10: =CT10 -> 1454974.5 | CV10: =CU10 -> 1454974.5 | CX10: Net Operating Income | CZ10: ='Cash Flow Dump'!BF39 -> 584129 | DA10: ='Cash Flow Dump'!BG39 -> 595812 | DB10: ='Cash Flow Dump'!BH39 -> 607728 | DC10: ='Cash Flow Dump'!BI39 -> 619882 | DD10: ='Cash Flow Dump'!BJ39 -> 632280 | DE10: ='Cash Flow Dump'!BK39 -> 644926 | DF10: ='Cash Flow Dump'!BL39 -> 657824 | DG10: ='Cash Flow Dump'!BM39 -> 670981 | ... DI10: ='Cash Flow Dump'!BO39 -> 698088 | DK10: =DK9+1 -> 6 | DQ10: ='Property-Level CF'!DE23+'Property-Level CF'!DE14 -> 12581744 | DR10: ='Property-Level CF'!DE14 -> 631851 | DS10: =DR10 -> 631851 | DT10: =DS10 -> 631851 | DU10: =DT10 -> 631851 | DW10: Net Operating Income | DY10: ='Cash Flow Dump'!BT45 -> 1311547 | DZ10: ='Cash Flow Dump'!BU45 -> 1337880 | EA10: ='Cash Flow Dump'!BV45 -> 1364462 | EB10: ='Cash Flow Dump'!BW45 -> 1391768 | EC10: ='Cash Flow Dump'!BX45 -> 1419623 | ED10: ='Cash Flow Dump'!BY45 -> 1448080 | EE10: ='Cash Flow Dump'!BZ45 -> 1476908 | EF10: ='Cash Flow Dump'!CA45 -> 1506639 | ... EH10: ='Cash Flow Dump'!CC45 -> 1567320 | EJ10: =EJ9+1 -> 6 | EP10: ='Property-Level CF'!ED23+'Property-Level CF'!ED14 -> 29916462 | EQ10: ='Property-Level CF'!ED14 -> 1426726.5 | ER10: =EQ10 -> 1426726.5 | ES10: =ER10 -> 1426726.5 | ET10: =ES10 -> 1426726.5
B11: Tenant Improvement | D11: ='Cash Flow Dump'!B49 -> 0 | E11: ='Cash Flow Dump'!C49 -> 41850 | F11: ='Cash Flow Dump'!D49 -> 45149 | G11: ='Cash Flow Dump'!E49 -> 253532 | H11: ='Cash Flow Dump'!F49 -> 0 | I11: ='Cash Flow Dump'!G49 -> 0 | J11: ='Cash Flow Dump'!H49 -> 427040 | K11: ='Cash Flow Dump'!I49 -> 0 | ... M11: ='Cash Flow Dump'!K49 -> 209886 | O11: =O10+1 -> 7 | V11: ='Property-Level CF'!J23+'Property-Level CF'!J14 -> 13611221 | W11: ='Property-Level CF'!J14 -> 343683.5 | X11: =W11 -> 343683.5 | Y11: =X11 -> 343683.5 | AA11: Tenant Improvement | AC11: ='Cash Flow Dump'!P49 -> 0 | AD11: ='Cash Flow Dump'!Q49 -> 0 | AE11: ='Cash Flow Dump'!R49 -> 0 | AF11: ='Cash Flow Dump'!S49 -> 0 | AG11: ='Cash Flow Dump'!T49 -> 0 | AH11: ='Cash Flow Dump'!U49 -> 0 | AI11: ='Cash Flow Dump'!V49 -> 0 | AJ11: ='Cash Flow Dump'!W49 -> 0 | ... AL11: ='Cash Flow Dump'!Y49 -> 193328 | AN11: =AN10+1 -> 7 | AU11: ='Property-Level CF'!AI23+'Property-Level CF'!AI14 -> 14891812 | AV11: ='Property-Level CF'!AI14 -> 765672 | AW11: =AV11 -> 765672 | AX11: =AW11 -> 765672 | AZ11: Tenant Improvement | BB11: ='Cash Flow Dump'!AD51 -> 0 | BC11: ='Cash Flow Dump'!AE51 -> 0 | BD11: ='Cash Flow Dump'!AF51 -> 0 | BE11: ='Cash Flow Dump'!AG51 -> 0 | BF11: ='Cash Flow Dump'!AH51 -> 0 | BG11: ='Cash Flow Dump'!AI51 -> 0 | BH11: ='Cash Flow Dump'!AJ51 -> 0 | BI11: ='Cash Flow Dump'!AK51 -> 0 | ... BK11: ='Cash Flow Dump'!AM51 -> 0 | BM11: =BM10+1 -> 7 | BT11: ='Property-Level CF'!BH23+'Property-Level CF'!BH14 -> 18285374 | BU11: ='Property-Level CF'!BH14 -> 941057 | BV11: =BU11 -> 941057 | BW11: =BV11 -> 941057 | BY11: Tenant Improvement | CA11: ='Cash Flow Dump'!AR49 -> 0 | CB11: ='Cash Flow Dump'!AS49 -> 0 | CC11: ='Cash Flow Dump'!AT49 -> 0 | CD11: ='Cash Flow Dump'!AU49 -> 0 | CE11: ='Cash Flow Dump'!AV49 -> 0 | CF11: ='Cash Flow Dump'!AW49 -> 0 | CG11: ='Cash Flow Dump'!AX49 -> 0 | CH11: ='Cash Flow Dump'!AY49 -> 0 | ... CJ11: ='Cash Flow Dump'!BA49 -> 0 | CL11: =CL10+1 -> 7 | CS11: ='Property-Level CF'!CG23+'Property-Level CF'!CG14 -> 29846011 | CT11: ='Property-Level CF'!CG14 -> 1480641.5 | CU11: =CT11 -> 1480641.5 | CV11: =CU11 -> 1480641.5 | CX11: Tenant Improvement | CZ11: ='Cash Flow Dump'!BF42 -> 0 | DA11: ='Cash Flow Dump'!BG42 -> 0 | DB11: ='Cash Flow Dump'!BH42 -> 0 | DC11: ='Cash Flow Dump'!BI42 -> 0 | DD11: ='Cash Flow Dump'!BJ42 -> 0 | DE11: ='Cash Flow Dump'!BK42 -> 0 | DF11: ='Cash Flow Dump'!BL42 -> 0 | DG11: ='Cash Flow Dump'!BM42 -> 0 | ... DI11: ='Cash Flow Dump'!BO42 -> 0 | DK11: =DK10+1 -> 7 | DR11: ='Property-Level CF'!DF23+'Property-Level CF'!DF14 -> 12833630 | DS11: ='Property-Level CF'!DF14 -> 644749 | DT11: =DS11 -> 644749 | DU11: =DT11 -> 644749 | DW11: Tenant Improvement | DY11: ='Cash Flow Dump'!BT48 -> 0 | DZ11: ='Cash Flow Dump'!BU48 -> 0 | EA11: ='Cash Flow Dump'!BV48 -> 0 | EB11: ='Cash Flow Dump'!BW48 -> 0 | EC11: ='Cash Flow Dump'!BX48 -> 0 | ED11: ='Cash Flow Dump'!BY48 -> 0 | EE11: ='Cash Flow Dump'!BZ48 -> 0 | EF11: ='Cash Flow Dump'!CA48 -> 0 | ... EH11: ='Cash Flow Dump'!CC48 -> 0 | EJ11: =EJ10+1 -> 7 | EQ11: ='Property-Level CF'!EE23+'Property-Level CF'!EE14 -> 30512457 | ER11: ='Property-Level CF'!EE14 -> 1455554.5 | ES11: =ER11 -> 1455554.5 | ET11: =ES11 -> 1455554.5
B12: Leasing Commissions | D12: ='Cash Flow Dump'!B50 -> 1020 | E12: ='Cash Flow Dump'!C50 -> 4701 | F12: ='Cash Flow Dump'!D50 -> 9514 | G12: ='Cash Flow Dump'!E50 -> 53427 | H12: ='Cash Flow Dump'!F50 -> 0 | I12: ='Cash Flow Dump'!G50 -> 0 | J12: ='Cash Flow Dump'!H50 -> 20753 | K12: ='Cash Flow Dump'!I50 -> 0 | ... M12: ='Cash Flow Dump'!K50 -> 22115 | O12: =O11+1 -> 8 | W12: ='Property-Level CF'!K23+'Property-Level CF'!K14 -> 14777462 | X12: ='Property-Level CF'!K14 -> 832629.5 | Y12: =X12 -> 832629.5 | AA12: Leasing Commissions | AC12: ='Cash Flow Dump'!P50 -> 0 | AD12: ='Cash Flow Dump'!Q50 -> 0 | AE12: ='Cash Flow Dump'!R50 -> 0 | AF12: ='Cash Flow Dump'!S50 -> 0 | AG12: ='Cash Flow Dump'!T50 -> 0 | AH12: ='Cash Flow Dump'!U50 -> 0 | AI12: ='Cash Flow Dump'!V50 -> 0 | AJ12: ='Cash Flow Dump'!W50 -> 0 | ... AL12: ='Cash Flow Dump'!Y50 -> 20960 | AN12: =AN11+1 -> 8 | AV12: ='Property-Level CF'!AJ23+'Property-Level CF'!AJ14 -> 15049577 | AW12: ='Property-Level CF'!AJ14 -> 773914 | AX12: =AW12 -> 773914 | AZ12: Leasing Commissions | BB12: ='Cash Flow Dump'!AD52 -> 0 | BC12: ='Cash Flow Dump'!AE52 -> 0 | BD12: ='Cash Flow Dump'!AF52 -> 0 | BE12: ='Cash Flow Dump'!AG52 -> 0 | BF12: ='Cash Flow Dump'!AH52 -> 0 | BG12: ='Cash Flow Dump'!AI52 -> 0 | BH12: ='Cash Flow Dump'!AJ52 -> 0 | BI12: ='Cash Flow Dump'!AK52 -> 0 | ... BK12: ='Cash Flow Dump'!AM52 -> 0 | BM12: =BM11+1 -> 8 | BU12: ='Property-Level CF'!BI23+'Property-Level CF'!BI14 -> 18622839 | BV12: ='Property-Level CF'!BI14 -> 958687 | BW12: =BV12 -> 958687 | BY12: Leasing Commissions | CA12: ='Cash Flow Dump'!AR50 -> 0 | CB12: ='Cash Flow Dump'!AS50 -> 0 | CC12: ='Cash Flow Dump'!AT50 -> 0 | CD12: ='Cash Flow Dump'!AU50 -> 0 | CE12: ='Cash Flow Dump'!AV50 -> 0 | CF12: ='Cash Flow Dump'!AW50 -> 0 | CG12: ='Cash Flow Dump'!AX50 -> 0 | CH12: ='Cash Flow Dump'!AY50 -> 0 | ... CJ12: ='Cash Flow Dump'!BA50 -> 0 | CL12: =CL11+1 -> 8 | CT12: ='Property-Level CF'!CH23+'Property-Level CF'!CH14 -> 30364514 | CU12: ='Property-Level CF'!CH14 -> 1506720.5 | CV12: =CU12 -> 1506720.5 | CX12: Leasing Commissions | CZ12: ='Cash Flow Dump'!BF43 -> 0 | DA12: ='Cash Flow Dump'!BG43 -> 0 | DB12: ='Cash Flow Dump'!BH43 -> 0 | DC12: ='Cash Flow Dump'!BI43 -> 0 | DD12: ='Cash Flow Dump'!BJ43 -> 0 | DE12: ='Cash Flow Dump'!BK43 -> 0 | DF12: ='Cash Flow Dump'!BL43 -> 0 | DG12: ='Cash Flow Dump'!BM43 -> 0 | ... DI12: ='Cash Flow Dump'!BO43 -> 0 | DK12: =DK11+1 -> 8 | DS12: ='Property-Level CF'!DG23+'Property-Level CF'!DG14 -> 13090574 | DT12: ='Property-Level CF'!DG14 -> 657906 | DU12: =DT12 -> 657906 | DW12: Leasing Commissions | DY12: ='Cash Flow Dump'!BT49 -> 0 | DZ12: ='Cash Flow Dump'!BU49 -> 0 | EA12: ='Cash Flow Dump'!BV49 -> 0 | EB12: ='Cash Flow Dump'!BW49 -> 0 | EC12: ='Cash Flow Dump'!BX49 -> 0 | ED12: ='Cash Flow Dump'!BY49 -> 0 | EE12: ='Cash Flow Dump'!BZ49 -> 0 | EF12: ='Cash Flow Dump'!CA49 -> 0 | ... EH12: ='Cash Flow Dump'!CC49 -> 0 | EJ12: =EJ11+1 -> 8 | ER12: ='Property-Level CF'!EF23+'Property-Level CF'!EF14 -> 31127120 | ES12: ='Property-Level CF'!EF14 -> 1485285.5 | ET12: =ES12 -> 1485285.5
B13: Capital Reserves | D13: =Summary!F4*Summary!C11 -> 14670.5 | E13: =D13 -> 14670.5 | F13: =E13 -> 14670.5 | G13: =F13 -> 14670.5 | H13: =G13 -> 14670.5 | I13: =H13 -> 14670.5 | J13: =I13 -> 14670.5 | K13: =J13 -> 14670.5 | L13: =K13 -> 14670.5 | M13: =L13 -> 14670.5 | O13: =O12+1 -> 9 | X13: ='Property-Level CF'!L23+'Property-Level CF'!L14 -> 14294901 | Y13: ='Property-Level CF'!L14 -> 452848.5 | AA13: Capital Reserves | AC13: =Summary!F5*Summary!C11 -> 12992 | AD13: =AC13 -> 12992 | AE13: =AD13 -> 12992 | AF13: =AE13 -> 12992 | AG13: =AF13 -> 12992 | AH13: =AG13 -> 12992 | AI13: =AH13 -> 12992 | AJ13: =AI13 -> 12992 | AK13: =AJ13 -> 12992 | AL13: =AK13 -> 12992 | AN13: =AN12+1 -> 9 | AW13: ='Property-Level CF'!AK23+'Property-Level CF'!AK14 -> 14949369 | AX13: ='Property-Level CF'!AK14 -> 668863 | AZ13: Capital Reserves | BB13: =Summary!F6*Summary!C11 -> 15000 | BC13: =BB13 -> 15000 | BD13: =BC13 -> 15000 | BE13: =BD13 -> 15000 | BF13: =BE13 -> 15000 | BG13: =BF13 -> 15000 | BH13: =BG13 -> 15000 | BI13: =BH13 -> 15000 | BJ13: =BI13 -> 15000 | BK13: =BJ13 -> 15000 | BM13: =BM12+1 -> 9 | BV13: ='Property-Level CF'!BJ23+'Property-Level CF'!BJ14 -> 18760332 | BW13: ='Property-Level CF'!BJ14 -> 965870 | BY13: Capital Reserves | CA13: =Summary!F7*Summary!C11 -> 21600.5 | CB13: =CA13 -> 21600.5 | CC13: =CB13 -> 21600.5 | CD13: =CC13 -> 21600.5 | CE13: =CD13 -> 21600.5 | CF13: =CE13 -> 21600.5 | CG13: =CF13 -> 21600.5 | CH13: =CG13 -> 21600.5 | CI13: =CH13 -> 21600.5 | CJ13: =CI13 -> 21600.5 | CL13: =CL12+1 -> 9 | CU13: ='Property-Level CF'!CI23+'Property-Level CF'!CI14 -> 30905763 | CV13: ='Property-Level CF'!CI14 -> 1533943.5 | CX13: Capital Reserves | CZ13: =Summary!F8*Summary!C11 -> 13075 | DA13: =CZ13 -> 13075 | DB13: =DA13 -> 13075 | DC13: =DB13 -> 13075 | DD13: =DC13 -> 13075 | DE13: =DD13 -> 13075 | DF13: =DE13 -> 13075 | DG13: =DF13 -> 13075 | DH13: =DG13 -> 13075 | DI13: =DH13 -> 13075 | DK13: =DK12+1 -> 9 | DT13: ='Property-Level CF'!DH23+'Property-Level CF'!DH14 -> 13352635 | DU13: ='Property-Level CF'!DH14 -> 671325 | DW13: Capital Reserves | DY13: =Summary!F9*Summary!C11 -> 21353.5 | DZ13: =DY13 -> 21353.5 | EA13: =DZ13 -> 21353.5 | EB13: =EA13 -> 21353.5 | EC13: =EB13 -> 21353.5 | ED13: =EC13 -> 21353.5 | EE13: =ED13 -> 21353.5 | EF13: =EE13 -> 21353.5 | EG13: =EF13 -> 21353.5 | EH13: =EG13 -> 21353.5 | EJ13: =EJ12+1 -> 9 | ES13: ='Property-Level CF'!EG23+'Property-Level CF'!EG14 -> 31746889 | ET13: ='Property-Level CF'!EG14 -> 1515263.5
B14: Net Cash Flow before Debt Service | D14: =D10-SUM(D11:D13) -> 761132.5 | E14: =E10-SUM(E11:E13) -> 731468.5 | F14: =F10-SUM(F11:F13) -> 732340.5 | G14: =G10-SUM(G11:G13) -> 476440.5 | H14: =H10-SUM(H11:H13) -> 824705.5 | I14: =I10-SUM(I11:I13) -> 776001.5 | J14: =J10-SUM(J11:J13) -> 343683.5 | K14: =K10-SUM(K11:K13) -> 832629.5 | ... M14: =M10-SUM(M11:M13) -> 638163.5 | O14: =O13+1 -> 10 | Y14: ='Property-Level CF'!M23+'Property-Level CF'!M14 -> 15200745 | AA14: Net Cash Flow before Debt Service | AC14: =AC10-SUM(AC11:AC13) -> 408299 | AD14: =AD10-SUM(AD11:AD13) -> 547987 | AE14: =AE10-SUM(AE11:AE13) -> 713558 | AF14: =AF10-SUM(AF11:AF13) -> 731808 | AG14: =AG10-SUM(AG11:AG13) -> 749249 | AH14: =AH10-SUM(AH11:AH13) -> 757476 | AI14: =AI10-SUM(AI11:AI13) -> 765672 | AJ14: =AJ10-SUM(AJ11:AJ13) -> 773914 | ... AL14: =AL10-SUM(AL11:AL13) -> 563742 | AN14: =AN13+1 -> 10 | AX14: ='Property-Level CF'!AL23+'Property-Level CF'!AL14 -> 14914075 | AZ14: Net Cash Flow before Debt Service | BB14: =BB10-SUM(BB11:BB13) -> 623299 | BC14: =BC10-SUM(BC11:BC13) -> 779615 | BD14: =BD10-SUM(BD11:BD13) -> 862384 | BE14: =BE10-SUM(BE11:BE13) -> 869405 | BF14: =BF10-SUM(BF11:BF13) -> 876356 | BG14: =BG10-SUM(BG11:BG13) -> 883681 | BH14: =BH10-SUM(BH11:BH13) -> 941057 | BI14: =BI10-SUM(BI11:BI13) -> 958687 | ... BK14: =BK10-SUM(BK11:BK13) -> 972095 | BM14: =BM13+1 -> 10 | BW14: ='Property-Level CF'!BK23+'Property-Level CF'!BK14 -> 18879488 | BY14: Net Cash Flow before Debt Service | CA14: =CA10-SUM(CA11:CA13) -> 1332627.5 | CB14: =CB10-SUM(CB11:CB13) -> 1356219.5 | CC14: =CC10-SUM(CC11:CC13) -> 1380140.5 | CD14: =CD10-SUM(CD11:CD13) -> 1404707.5 | CE14: =CE10-SUM(CE11:CE13) -> 1429590.5 | CF14: =CF10-SUM(CF11:CF13) -> 1454974.5 | CG14: =CG10-SUM(CG11:CG13) -> 1480641.5 | CH14: =CH10-SUM(CH11:CH13) -> 1506720.5 | ... CJ14: =CJ10-SUM(CJ11:CJ13) -> 1562997.5 | CL14: =CL13+1 -> 10 | CV14: ='Property-Level CF'!CJ23+'Property-Level CF'!CJ14 -> 31483415 | CX14: Net Cash Flow before Debt Service | CZ14: =CZ10-SUM(CZ11:CZ13) -> 571054 | DA14: =DA10-SUM(DA11:DA13) -> 582737 | DB14: =DB10-SUM(DB11:DB13) -> 594653 | DC14: =DC10-SUM(DC11:DC13) -> 606807 | DD14: =DD10-SUM(DD11:DD13) -> 619205 | DE14: =DE10-SUM(DE11:DE13) -> 631851 | DF14: =DF10-SUM(DF11:DF13) -> 644749 | DG14: =DG10-SUM(DG11:DG13) -> 657906 | ... DI14: =DI10-SUM(DI11:DI13) -> 685013 | DK14: =DK13+1 -> 10 | DU14: ='Property-Level CF'!DI23+'Property-Level CF'!DI14 -> 13619949 | DW14: Net Cash Flow before Debt Service | DY14: =DY10-SUM(DY11:DY13) -> 1290193.5 | DZ14: =DZ10-SUM(DZ11:DZ13) -> 1316526.5 | EA14: =EA10-SUM(EA11:EA13) -> 1343108.5 | EB14: =EB10-SUM(EB11:EB13) -> 1370414.5 | EC14: =EC10-SUM(EC11:EC13) -> 1398269.5 | ED14: =ED10-SUM(ED11:ED13) -> 1426726.5 | EE14: =EE10-SUM(EE11:EE13) -> 1455554.5 | EF14: =EF10-SUM(EF11:EF13) -> 1485285.5 | ... EH14: =EH10-SUM(EH11:EH13) -> 1545966.5 | EJ14: =EJ13+1 -> 10 | ET14: ='Property-Level CF'!EH23+'Property-Level CF'!EH14 -> 32381647
B15: Sale (Unlevered) | M15: =M23 -> 14562582 | O15: =O14+1 -> 11 | AA15: Sale (Unlevered) | AL15: =AL23 -> 14350333 | AN15: =AN14+1 -> 11 | AZ15: Sale (Unlevered) | BK15: =BK23 -> 17907393 | BM15: =BM14+1 -> 11 | BY15: Sale (Unlevered) | CJ15: =CJ23 -> 29920417 | CL15: =CL14+1 -> 11 | CX15: Sale (Unlevered) | DI15: =DI23 -> 12934936 | DK15: =DK14+1 -> 11 | DW15: Sale (Unlevered) | EH15: =EH23 -> 30835681 | EJ15: =EJ14+1 -> 11
B16: Unlevered Cash Flow | C16: =-Summary!J14 -> -13422181 | D16: =D14+D15 -> 761132.5 | E16: =E14+E15 -> 731468.5 | F16: =F14+F15 -> 732340.5 | G16: =G14+G15 -> 476440.5 | H16: =H14+H15 -> 824705.5 | I16: =I14+I15 -> 776001.5 | J16: =J14+J15 -> 343683.5 | K16: =K14+K15 -> 832629.5 | ... M16: =M14+M15 -> 15200745 | O16: Year | P16: =P2 -> Year 1 | Q16: =Q2 -> Year 2 | R16: =R2 -> Year 3 | S16: =S2 -> Year 4 | T16: =T2 -> Year 5 | U16: =U2 -> Year 6 | V16: =V2 -> Year 7 | W16: =W2 -> Year 8 | ... Y16: =Y2 -> Year 10 | AA16: Unlevered Cash Flow | AB16: =-Summary!J15 -> -10961842 | AC16: =AC14+AC15 -> 408299 | AD16: =AD14+AD15 -> 547987 | AE16: =AE14+AE15 -> 713558 | AF16: =AF14+AF15 -> 731808 | AG16: =AG14+AG15 -> 749249 | AH16: =AH14+AH15 -> 757476 | AI16: =AI14+AI15 -> 765672 | AJ16: =AJ14+AJ15 -> 773914 | ... AL16: =AL14+AL15 -> 14914075 | AN16: Year | AO16: =AO2 -> Year 1 | AP16: =AP2 -> Year 2 | AQ16: =AQ2 -> Year 3 | AR16: =AR2 -> Year 4 | AS16: =AS2 -> Year 5 | AT16: =AT2 -> Year 6 | AU16: =AU2 -> Year 7 | AV16: =AV2 -> Year 8 | ... AX16: =AX2 -> Year 10 | AZ16: Unlevered Cash Flow | BA16: =-Summary!J16 -> -14068705 | BB16: =BB14+BB15 -> 623299 | BC16: =BC14+BC15 -> 779615 | BD16: =BD14+BD15 -> 862384 | BE16: =BE14+BE15 -> 869405 | BF16: =BF14+BF15 -> 876356 | BG16: =BG14+BG15 -> 883681 | BH16: =BH14+BH15 -> 941057 | BI16: =BI14+BI15 -> 958687 | ... BK16: =BK14+BK15 -> 18879488 | BM16: Year | BN16: =BN2 -> Year 1 | BO16: =BO2 -> Year 2 | BP16: =BP2 -> Year 3 | BQ16: =BQ2 -> Year 4 | BR16: =BR2 -> Year 5 | BS16: =BS2 -> Year 6 | BT16: =BT2 -> Year 7 | BU16: =BU2 -> Year 8 | ... BW16: =BW2 -> Year 10 | BY16: Unlevered Cash Flow | BZ16: =-Summary!J17 -> -26845115 | CA16: =CA14+CA15 -> 1332627.5 | CB16: =CB14+CB15 -> 1356219.5 | CC16: =CC14+CC15 -> 1380140.5 | CD16: =CD14+CD15 -> 1404707.5 | CE16: =CE14+CE15 -> 1429590.5 | CF16: =CF14+CF15 -> 1454974.5 | CG16: =CG14+CG15 -> 1480641.5 | CH16: =CH14+CH15 -> 1506720.5 | ... CJ16: =CJ14+CJ15 -> 31483415 | CL16: Year | CM16: =CM2 -> Year 1 | CN16: =CN2 -> Year 2 | CO16: =CO2 -> Year 3 | CP16: =CP2 -> Year 4 | CQ16: =CQ2 -> Year 5 | CR16: =CR2 -> Year 6 | CS16: =CS2 -> Year 7 | CT16: =CT2 -> Year 8 | ... CV16: =CV2 -> Year 10 | CX16: Unlevered Cash Flow | CY16: =-Summary!J18 -> -11362865 | CZ16: =CZ14+CZ15 -> 571054 | DA16: =DA14+DA15 -> 582737 | DB16: =DB14+DB15 -> 594653 | DC16: =DC14+DC15 -> 606807 | DD16: =DD14+DD15 -> 619205 | DE16: =DE14+DE15 -> 631851 | DF16: =DF14+DF15 -> 644749 | DG16: =DG14+DG15 -> 657906 | ... DI16: =DI14+DI15 -> 13619949 | DK16: Year | DL16: =DL2 -> Year 1 | DM16: =DM2 -> Year 2 | DN16: =DN2 -> Year 3 | DO16: =DO2 -> Year 4 | DP16: =DP2 -> Year 5 | DQ16: =DQ2 -> Year 6 | DR16: =DR2 -> Year 7 | DS16: =DS2 -> Year 8 | ... DU16: =DU2 -> Year 10 | DW16: Unlevered Cash Flow | DX16: =-Summary!J19 -> -27089729 | DY16: =DY14+DY15 -> 1290193.5 | DZ16: =DZ14+DZ15 -> 1316526.5 | EA16: =EA14+EA15 -> 1343108.5 | EB16: =EB14+EB15 -> 1370414.5 | EC16: =EC14+EC15 -> 1398269.5 | ED16: =ED14+ED15 -> 1426726.5 | EE16: =EE14+EE15 -> 1455554.5 | EF16: =EF14+EF15 -> 1485285.5 | ... EH16: =EH14+EH15 -> 32381647 | EJ16: Year | EK16: =EK2 -> Year 1 | EL16: =EL2 -> Year 2 | EM16: =EM2 -> Year 3 | EN16: =EN2 -> Year 4 | EO16: =EO2 -> Year 5 | EP16: =EP2 -> Year 6 | EQ16: =EQ2 -> Year 7 | ER16: =ER2 -> Year 8 | ... ET16: =ET2 -> Year 10
O17: Levered IRR | P17: =IRR(P18:P29) -> -0.02684335 | Q17: =IRR(Q18:Q29) -> 0.040831845 | R17: =IRR(R18:R29) -> 0.063933131 | S17: =IRR(S18:S29) -> 0.051863851 | T17: =IRR(T18:T29) -> 0.0858378 | U17: =IRR(U18:U29) -> 0.061263801 | V17: =IRR(V18:V29) -> 0.060346328 | W17: =IRR(W18:W29) -> 0.078471231 | ... Y17: =IRR(Y18:Y29) -> 0.080202328 | AN17: Levered IRR | AO17: =IRR(AO18:AO29) -> -0.082442683 | AP17: =IRR(AP18:AP29) -> -0.05907901 | AQ17: =IRR(AQ18:AQ29) -> 0.21737887 | AR17: =IRR(AR18:AR29) -> 0.19556345 | AS17: =IRR(AS18:AS29) -> 0.181736 | AT17: =IRR(AT18:AT29) -> 0.16833302 | AU17: =IRR(AU18:AU29) -> 0.15886919 | AV17: =IRR(AV18:AV29) -> 0.15184412 | ... AX17: =IRR(AX18:AX29) -> 0.13599865 | BM17: Levered IRR | BN17: =IRR(BN18:BN29) -> -0.062280864 | BO17: =IRR(BO18:BO29) -> 0.096457277 | BP17: =IRR(BP18:BP29) -> 0.17718996 | BQ17: =IRR(BQ18:BQ29) -> 0.15676107 | BR17: =IRR(BR18:BR29) -> 0.14465338 | BS17: =IRR(BS18:BS29) -> 0.1367845 | BT17: =IRR(BT18:BT29) -> 0.146395 | BU17: =IRR(BU18:BU29) -> 0.14263384 | ... BW17: =IRR(BW18:BW29) -> 0.13334286 | CL17: Levered IRR | CM17: =IRR(CM18:CM29) -> -0.047031136 | CN17: =IRR(CN18:CN29) -> 0.020540037 | CO17: =IRR(CO18:CO29) -> 0.05269709 | CP17: =IRR(CP18:CP29) -> 0.068643754 | CQ17: =IRR(CQ18:CQ29) -> 0.07783123 | CR17: =IRR(CR18:CR29) -> 0.083677511 | CS17: =IRR(CS18:CS29) -> 0.087572639 | CT17: =IRR(CT18:CT29) -> 0.090289273 | ... CV17: =IRR(CV18:CV29) -> 0.094007475 | DK17: Levered IRR | DL17: =IRR(DL18:DL29) -> -0.045274492 | DM17: =IRR(DM18:DM29) -> 0.02608864 | DN17: =IRR(DN18:DN29) -> 0.059491168 | DO17: =IRR(DO18:DO29) -> 0.075822836 | DP17: =IRR(DP18:DP29) -> 0.085187853 | DQ17: =IRR(DQ18:DQ29) -> 0.091062564 | DR17: =IRR(DR18:DR29) -> 0.094960294 | DS17: =IRR(DS18:DS29) -> 0.097644186 | ... DU17: =IRR(DU18:DU29) -> 0.10089337 | EJ17: Levered IRR | EK17: =IRR(EK18:EK29) -> -0.052787347 | EL17: =IRR(EL18:EL29) -> 0.018454177 | EM17: =IRR(EM18:EM29) -> 0.05171858 | EN17: =IRR(EN18:EN29) -> 0.068143753 | EO17: =IRR(EO18:EO29) -> 0.077607943 | EP17: =IRR(EP18:EP29) -> 0.08359148 | EQ17: =IRR(EQ18:EQ29) -> 0.087544775 | ER17: =IRR(ER18:ER29) -> 0.090347187 | ... ET17: =IRR(ET18:ET29) -> 0.093715507
B18: Cap Rate at Sale | D18: =Summary!L14 -> 0.057876063 | E18: =Summary!L4 -> 0.058421568 | F18: =E18 -> 0.058421568 | G18: =F18 -> 0.058421568 | H18: =G18 -> 0.058421568 | I18: =H18 -> 0.058421568 | J18: =I18 -> 0.058421568 | K18: =J18 -> 0.058421568 | L18: =K18 -> 0.058421568 | M18: =L18 -> 0.058421568 | O18: 0 | P18: =P4+Summary!I24 -> -4697763.4 | Q18: =P18 -> -4697763.4 | R18: =Q18 -> -4697763.4 | S18: =R18 -> -4697763.4 | T18: =S18 -> -4697763.4 | U18: =T18 -> -4697763.4 | V18: =U18 -> -4697763.4 | W18: =V18 -> -4697763.4 | X18: =W18 -> -4697763.4 | Y18: =X18 -> -4697763.4 | AA18: Cap Rate at Sale | AC18: =Summary!L15 -> 0.038432501 | AD18: 0.053 | AE18: =AD18 -> 0.053 | AF18: =AE18 -> 0.053 | AG18: =AF18 -> 0.053 | AH18: =AG18 -> 0.053 | AI18: =AH18 -> 0.053 | AJ18: =AI18 -> 0.053 | AK18: =AJ18 -> 0.053 | AL18: =AK18 -> 0.053 | AN18: 0 | AO18: =AO4+Summary!I25 -> -3836644.7 | AP18: =AO18 -> -3836644.7 | AQ18: =AP18 -> -3836644.7 | AR18: =AQ18 -> -3836644.7 | AS18: =AR18 -> -3836644.7 | AT18: =AS18 -> -3836644.7 | AU18: =AT18 -> -3836644.7 | AV18: =AU18 -> -3836644.7 | AW18: =AV18 -> -3836644.7 | AX18: =AW18 -> -3836644.7 | AZ18: Cap Rate at Sale | BB18: =Summary!L16 -> 0.045370132 | BC18: 0.053 | BD18: =BC18 -> 0.053 | BE18: =BD18 -> 0.053 | BF18: =BE18 -> 0.053 | BG18: =BF18 -> 0.053 | BH18: =BG18 -> 0.053 | BI18: =BH18 -> 0.053 | BJ18: =BI18 -> 0.053 | BK18: =BJ18 -> 0.053 | BM18: 0 | BN18: =BN4+Summary!I26 -> -4924046.8 | BO18: =BN18 -> -4924046.8 | BP18: =BO18 -> -4924046.8 | BQ18: =BP18 -> -4924046.8 | BR18: =BQ18 -> -4924046.8 | BS18: =BR18 -> -4924046.8 | BT18: =BS18 -> -4924046.8 | BU18: =BT18 -> -4924046.8 | BV18: =BU18 -> -4924046.8 | BW18: =BV18 -> -4924046.8 | BY18: Cap Rate at Sale | CA18: =Summary!L17 -> 0.050445974 | CB18: =Summary!L7 -> 0.050921448 | CC18: =CB18 -> 0.050921448 | CD18: =CC18 -> 0.050921448 | CE18: =CD18 -> 0.050921448 | CF18: =CE18 -> 0.050921448 | CG18: =CF18 -> 0.050921448 | CH18: =CG18 -> 0.050921448 | CI18: =CH18 -> 0.050921448 | CJ18: =CI18 -> 0.050921448 | CL18: 0 | CM18: =CM4+Summary!I27 -> -9395790.4 | CN18: =CM18 -> -9395790.4 | CO18: =CN18 -> -9395790.4 | CP18: =CO18 -> -9395790.4 | CQ18: =CP18 -> -9395790.4 | CR18: =CQ18 -> -9395790.4 | CS18: =CR18 -> -9395790.4 | CT18: =CS18 -> -9395790.4 | CU18: =CT18 -> -9395790.4 | CV18: =CU18 -> -9395790.4 | CX18: Cap Rate at Sale | CZ18: =Summary!L18 -> 0.051406844 | DA18: =Summary!L8 -> 0.051891374 | DB18: =DA18 -> 0.051891374 | DC18: =DB18 -> 0.051891374 | DD18: =DC18 -> 0.051891374 | DE18: =DD18 -> 0.051891374 | DF18: =DE18 -> 0.051891374 | DG18: =DF18 -> 0.051891374 | DH18: =DG18 -> 0.051891374 | DI18: =DH18 -> 0.051891374 | DK18: 0 | DL18: =DL4+Summary!I28 -> -3977002.6 | DM18: =DL18 -> -3977002.6 | DN18: =DM18 -> -3977002.6 | DO18: =DN18 -> -3977002.6 | DP18: =DO18 -> -3977002.6 | DQ18: =DP18 -> -3977002.6 | DR18: =DQ18 -> -3977002.6 | DS18: =DR18 -> -3977002.6 | DT18: =DS18 -> -3977002.6 | DU18: =DT18 -> -3977002.6 | DW18: Cap Rate at Sale | DY18: =Summary!L19 -> 0.048414917 | DZ18: =Summary!L9 -> 0.048871247 | EA18: =DZ18 -> 0.048871247 | EB18: =EA18 -> 0.048871247 | EC18: =EB18 -> 0.048871247 | ED18: =EC18 -> 0.048871247 | EE18: =ED18 -> 0.048871247 | EF18: =EE18 -> 0.048871247 | EG18: =EF18 -> 0.048871247 | EH18: =EG18 -> 0.048871247 | EJ18: 0 | EK18: =EK4+Summary!I29 -> -9481405.3 | EL18: =EK18 -> -9481405.3 | EM18: =EL18 -> -9481405.3 | EN18: =EM18 -> -9481405.3 | EO18: =EN18 -> -9481405.3 | EP18: =EO18 -> -9481405.3 | EQ18: =EP18 -> -9481405.3 | ER18: =EQ18 -> -9481405.3 | ES18: =ER18 -> -9481405.3 | ET18: =ES18 -> -9481405.3
B19: Implied Exit Cap Rate | D19: =(D10/$D$23)*(1-'Portfolio-Level CF'!$AC$52) -> 0.057876063 | E19: =(E10/$D$23)*(1-'Portfolio-Level CF'!$AC$52) -> 0.05905821 | F19: =(F10/$D$23)*(1-'Portfolio-Level CF'!$AC$52) -> 0.05972755 | G19: =(G10/$D$23)*(1-'Portfolio-Level CF'!$AC$52) -> 0.059459039 | H19: =(H10/$D$23)*(1-'Portfolio-Level CF'!$AC$52) -> 0.062536483 | I19: =(I10/$D$23)*(1-'Portfolio-Level CF'!$AC$52) -> 0.058907862 | J19: =(J10/$D$23)*(1-'Portfolio-Level CF'!$AC$52) -> 0.060060805 | K19: =(K10/$D$23)*(1-'Portfolio-Level CF'!$AC$52) -> 0.063126849 | ... M19: =(M10/$D$23)*(1-'Portfolio-Level CF'!$AC$52) -> 0.065923339 | O19: =O18+1 -> 1 | P19: =D33+D39 -> 4571659.7 | Q19: ='Property-Level CF'!D39 -> 390650.27 | R19: =Q19 -> 390650.27 | S19: =R19 -> 390650.27 | T19: =S19 -> 390650.27 | U19: =T19 -> 390650.27 | V19: =U19 -> 390650.27 | W19: =V19 -> 390650.27 | X19: =W19 -> 390650.27 | Y19: =X19 -> 390650.27 | AA19: Implied Exit Cap Rate | AC19: =(AC10/$AC$23)*(1-'Portfolio-Level CF'!$AC$52) -> 0.038432501 | AD19: =(AD10/$AC$23)*(1-'Portfolio-Level CF'!$AC$52) -> 0.051175615 | AE19: =(AE10/$AC$23)*(1-'Portfolio-Level CF'!$AC$52) -> 0.066279919 | AF19: =(AF10/$AC$23)*(1-'Portfolio-Level CF'!$AC$52) -> 0.067944785 | AG19: =(AG10/$AC$23)*(1-'Portfolio-Level CF'!$AC$52) -> 0.06953585 | AH19: =(AH10/$AC$23)*(1-'Portfolio-Level CF'!$AC$52) -> 0.070286363 | AI19: =(AI10/$AC$23)*(1-'Portfolio-Level CF'!$AC$52) -> 0.071034047 | AJ19: =(AJ10/$AC$23)*(1-'Portfolio-Level CF'!$AC$52) -> 0.071785928 | ... AL19: =(AL10/$AC$23)*(1-'Portfolio-Level CF'!$AC$52) -> 0.072161412 | AN19: =AN18+1 -> 1 | AO19: =AC33+AC39 -> 3520341.4 | AP19: ='Property-Level CF'!AC39 -> 105727.63 | AQ19: =AP19 -> 105727.63 | AR19: =AQ19 -> 105727.63 | AS19: =AR19 -> 105727.63 | AT19: =AS19 -> 105727.63 | AU19: =AT19 -> 105727.63 | AV19: =AU19 -> 105727.63 | AW19: =AV19 -> 105727.63 | AX19: =AW19 -> 105727.63 | AZ19: Implied Exit Cap Rate | BB19: =(BB10/$BB$23)*(1-'Portfolio-Level CF'!$AC$52) -> 0.045370132 | BC19: =(BC10/$BB$23)*(1-'Portfolio-Level CF'!$AC$52) -> 0.056481033 | BD19: =(BD10/$BB$23)*(1-'Portfolio-Level CF'!$AC$52) -> 0.062364233 | BE19: =(BE10/$BB$23)*(1-'Portfolio-Level CF'!$AC$52) -> 0.062863284 | BF19: =(BF10/$BB$23)*(1-'Portfolio-Level CF'!$AC$52) -> 0.063357359 | BG19: =(BG10/$BB$23)*(1-'Portfolio-Level CF'!$AC$52) -> 0.063878018 | BH19: =(BH10/$BB$23)*(1-'Portfolio-Level CF'!$AC$52) -> 0.06795629 | BI19: =(BI10/$BB$23)*(1-'Portfolio-Level CF'!$AC$52) -> 0.069209426 | ... BK19: =(BK10/$BB$23)*(1-'Portfolio-Level CF'!$AC$52) -> 0.070162463 | BM19: =BM18+1 -> 1 | BN19: =BB33+BB39 -> 4617372.9 | BO19: ='Property-Level CF'!BB39 -> 234971.26 | BP19: =BO19 -> 234971.26 | BQ19: =BP19 -> 234971.26 | BR19: =BQ19 -> 234971.26 | BS19: =BR19 -> 234971.26 | BT19: =BS19 -> 234971.26 | BU19: =BT19 -> 234971.26 | BV19: =BU19 -> 234971.26 | BW19: =BV19 -> 234971.26 | BY19: Implied Exit Cap Rate | CA19: =(CA10/$CA$23)*(1-'Portfolio-Level CF'!$AC$52) -> 0.050445974 | CB19: =(CB10/$CA$23)*(1-'Portfolio-Level CF'!$AC$52) -> 0.051324793 | CC19: =(CC10/$CA$23)*(1-'Portfolio-Level CF'!$AC$52) -> 0.052215868 | CD19: =(CD10/$CA$23)*(1-'Portfolio-Level CF'!$AC$52) -> 0.053131007 | CE19: =(CE10/$CA$23)*(1-'Portfolio-Level CF'!$AC$52) -> 0.054057916 | CF19: =(CF10/$CA$23)*(1-'Portfolio-Level CF'!$AC$52) -> 0.055003489 | CG19: =(CG10/$CA$23)*(1-'Portfolio-Level CF'!$AC$52) -> 0.055959603 | CH19: =(CH10/$CA$23)*(1-'Portfolio-Level CF'!$AC$52) -> 0.056931065 | ... CJ19: =(CJ10/$CA$23)*(1-'Portfolio-Level CF'!$AC$52) -> 0.059027424 | CL19: =CL18+1 -> 1 | CM19: =CA33+CA39 -> 8953895.7 | CN19: ='Property-Level CF'!CA39 -> 591642.25 | CO19: =CN19 -> 591642.25 | CP19: =CO19 -> 591642.25 | CQ19: =CP19 -> 591642.25 | CR19: =CQ19 -> 591642.25 | CS19: =CR19 -> 591642.25 | CT19: =CS19 -> 591642.25 | CU19: =CT19 -> 591642.25 | CV19: =CU19 -> 591642.25 | CX19: Implied Exit Cap Rate | CZ19: =(CZ10/$CZ$23)*(1-'Portfolio-Level CF'!$AC$52) -> 0.051406844 | DA19: =(DA10/$CZ$23)*(1-'Portfolio-Level CF'!$AC$52) -> 0.052435018 | DB19: =(DB10/$CZ$23)*(1-'Portfolio-Level CF'!$AC$52) -> 0.053483697 | DC19: =(DC10/$CZ$23)*(1-'Portfolio-Level CF'!$AC$52) -> 0.054553321 | DD19: =(DD10/$CZ$23)*(1-'Portfolio-Level CF'!$AC$52) -> 0.05564442 | DE19: =(DE10/$CZ$23)*(1-'Portfolio-Level CF'!$AC$52) -> 0.056757343 | DF19: =(DF10/$CZ$23)*(1-'Portfolio-Level CF'!$AC$52) -> 0.057892444 | DG19: =(DG10/$CZ$23)*(1-'Portfolio-Level CF'!$AC$52) -> 0.059050339 | ... DI19: =(DI10/$CZ$23)*(1-'Portfolio-Level CF'!$AC$52) -> 0.061435917 | DK19: =DK18+1 -> 1 | DL19: =CZ33+CZ39 -> 3796945.8 | DM19: ='Property-Level CF'!CZ39 -> 257413.51 | DN19: =DM19 -> 257413.51 | DO19: =DN19 -> 257413.51 | DP19: =DO19 -> 257413.51 | DQ19: =DP19 -> 257413.51 | DR19: =DQ19 -> 257413.51 | DS19: =DR19 -> 257413.51 | DT19: =DS19 -> 257413.51 | DU19: =DT19 -> 257413.51 | DW19: Implied Exit Cap Rate | DY19: =(DY10/$DY$23)*(1-'Portfolio-Level CF'!$AC$52) -> 0.048414917 | DZ19: =(DZ10/$DY$23)*(1-'Portfolio-Level CF'!$AC$52) -> 0.049386983 | EA19: =(EA10/$DY$23)*(1-'Portfolio-Level CF'!$AC$52) -> 0.05036824 | EB19: =(EB10/$DY$23)*(1-'Portfolio-Level CF'!$AC$52) -> 0.051376224 | EC19: =(EC10/$DY$23)*(1-'Portfolio-Level CF'!$AC$52) -> 0.052404473 | ED19: =(ED10/$DY$23)*(1-'Portfolio-Level CF'!$AC$52) -> 0.053454945 | EE19: =(EE10/$DY$23)*(1-'Portfolio-Level CF'!$AC$52) -> 0.054519112 | EF19: =(EF10/$DY$23)*(1-'Portfolio-Level CF'!$AC$52) -> 0.055616613 | ... EH19: =(EH10/$DY$23)*(1-'Portfolio-Level CF'!$AC$52) -> 0.057856613 | EJ19: =EJ18+1 -> 1 | EK19: =DY33+DY39 -> 8980907.1 | EL19: ='Property-Level CF'!DY39 -> 542456.35 | EM19: =EL19 -> 542456.35 | EN19: =EM19 -> 542456.35 | EO19: =EN19 -> 542456.35 | EP19: =EO19 -> 542456.35 | EQ19: =EP19 -> 542456.35 | ER19: =EQ19 -> 542456.35 | ES19: =ER19 -> 542456.35 | ET19: =ES19 -> 542456.35
B20: Accretive (Dilutive) Cap Spread | D20: =D19-D18 -> 0 | E20: =E19-E18 -> 0.00063664258 | F20: =F19-F18 -> 0.0013059824 | G20: =G19-G18 -> 0.0010374716 | H20: =H19-H18 -> 0.0041149148 | I20: =I19-I18 -> 0.00048629444 | J20: =J19-J18 -> 0.0016392367 | K20: =K19-K18 -> 0.0047052809 | ... M20: =M19-M18 -> 0.0075017712 | O20: =O19+1 -> 2 | Q20: =E33+E39 -> 4682631.2 | R20: ='Property-Level CF'!E39 -> 360986.27 | S20: =R20 -> 360986.27 | T20: =S20 -> 360986.27 | U20: =T20 -> 360986.27 | V20: =U20 -> 360986.27 | W20: =V20 -> 360986.27 | X20: =W20 -> 360986.27 | Y20: =X20 -> 360986.27 | AA20: Accretive (Dilutive) Cap Spread | AC20: =AC19-AC18 -> 0 | AD20: =AD19-AD18 -> -0.0018243855 | AE20: =AE19-AE18 -> 0.013279919 | AF20: =AF19-AF18 -> 0.014944785 | AG20: =AG19-AG18 -> 0.01653585 | AH20: =AH19-AH18 -> 0.017286363 | AI20: =AI19-AI18 -> 0.018034047 | AJ20: =AJ19-AJ18 -> 0.018785928 | ... AL20: =AL19-AL18 -> 0.019161412 | AN20: =AN19+1 -> 2 | AP20: =AD33+AD39 -> 3297224.2 | AQ20: ='Property-Level CF'!AD39 -> 245415.63 | AR20: =AQ20 -> 245415.63 | AS20: =AR20 -> 245415.63 | AT20: =AS20 -> 245415.63 | AU20: =AT20 -> 245415.63 | AV20: =AU20 -> 245415.63 | AW20: =AV20 -> 245415.63 | AX20: =AW20 -> 245415.63 | AZ20: Accretive (Dilutive) Cap Spread | BB20: =BB19-BB18 -> 0 | BC20: =BC19-BC18 -> 0.0034810333 | BD20: =BD19-BD18 -> 0.0093642329 | BE20: =BE19-BE18 -> 0.0098632838 | BF20: =BF19-BF18 -> 0.010357359 | BG20: =BG19-BG18 -> 0.010878018 | BH20: =BH19-BH18 -> 0.01495629 | BI20: =BI19-BI18 -> 0.016209426 | ... BK20: =BK19-BK18 -> 0.017162463 | BM20: =BM19+1 -> 2 | BO20: =BC33+BC39 -> 5662144.5 | BP20: ='Property-Level CF'!BC39 -> 391287.26 | BQ20: =BP20 -> 391287.26 | BR20: =BQ20 -> 391287.26 | BS20: =BR20 -> 391287.26 | BT20: =BS20 -> 391287.26 | BU20: =BT20 -> 391287.26 | BV20: =BU20 -> 391287.26 | BW20: =BV20 -> 391287.26 | BY20: Accretive (Dilutive) Cap Spread | CA20: =CA19-CA18 -> 0 | CB20: =CB19-CB18 -> 0.00040334558 | CC20: =CC19-CC18 -> 0.0012944202 | CD20: =CD19-CD18 -> 0.0022095587 | CE20: =CE19-CE18 -> 0.0031364685 | CF20: =CF19-CF18 -> 0.0040820409 | CG20: =CG19-CG18 -> 0.0050381552 | CH20: =CH19-CH18 -> 0.0060096169 | ... CJ20: =CJ19-CJ18 -> 0.0081059759 | CL20: =CL19+1 -> 2 | CN20: =CB33+CB39 -> 9181939.6 | CO20: ='Property-Level CF'!CB39 -> 615234.25 | CP20: =CO20 -> 615234.25 | CQ20: =CP20 -> 615234.25 | CR20: =CQ20 -> 615234.25 | CS20: =CR20 -> 615234.25 | CT20: =CS20 -> 615234.25 | CU20: =CT20 -> 615234.25 | CV20: =CU20 -> 615234.25 | CX20: Accretive (Dilutive) Cap Spread | CZ20: =CZ19-CZ18 -> 0 | DA20: =DA19-DA18 -> 0.00054364375 | DB20: =DB19-DB18 -> 0.001592323 | DC20: =DC19-DC18 -> 0.0026619476 | DD20: =DD19-DD18 -> 0.0037530457 | DE20: =DE19-DE18 -> 0.0048659693 | DF20: =DF19-DF18 -> 0.0060010704 | DG20: =DG19-DG18 -> 0.0071589651 | ... DI20: =DI19-DI18 -> 0.0095445431 | DK20: =DK19+1 -> 2 | DM20: =DA33+DA39 -> 3923089.5 | DN20: ='Property-Level CF'!DA39 -> 269096.51 | DO20: =DN20 -> 269096.51 | DP20: =DO20 -> 269096.51 | DQ20: =DP20 -> 269096.51 | DR20: =DQ20 -> 269096.51 | DS20: =DR20 -> 269096.51 | DT20: =DS20 -> 269096.51 | DU20: =DT20 -> 269096.51 | DW20: Accretive (Dilutive) Cap Spread | DY20: =DY19-DY18 -> 0 | DZ20: =DZ19-DZ18 -> 0.00051573584 | EA20: =EA19-EA18 -> 0.0014969933 | EB20: =EB19-EB18 -> 0.0025049768 | EC20: =EC19-EC18 -> 0.0035332263 | ED20: =ED19-ED18 -> 0.0045836982 | EE20: =EE19-EE18 -> 0.0056478654 | EF20: =EF19-EF18 -> 0.0067453662 | ... EH20: =EH19-EH18 -> 0.0089853664 | EJ20: =EJ19+1 -> 2 | EL20: =DZ33+DZ39 -> 9282110.4 | EM20: ='Property-Level CF'!DZ39 -> 568789.35 | EN20: =EM20 -> 568789.35 | EO20: =EN20 -> 568789.35 | EP20: =EO20 -> 568789.35 | EQ20: =EP20 -> 568789.35 | ER20: =EQ20 -> 568789.35 | ES20: =ER20 -> 568789.35 | ET20: =ES20 -> 568789.35
B21: REIT GAAP Accounting Cap Rate Average | D21: =AVERAGE($D$19:D19) -> 0.057876063 | E21: =AVERAGE($D$19:E19) -> 0.058467137 | F21: =AVERAGE($D$19:F19) -> 0.058887275 | G21: =AVERAGE($D$19:G19) -> 0.059030216 | H21: =AVERAGE($D$19:H19) -> 0.059731469 | I21: =AVERAGE($D$19:I19) -> 0.059594201 | J21: =AVERAGE($D$19:J19) -> 0.059660859 | K21: =AVERAGE($D$19:K19) -> 0.060094108 | ... M21: =AVERAGE($D$19:M19) -> 0.060933777 | O21: =O20+1 -> 3 | R21: =F33+F39 -> 4831361.5 | S21: ='Property-Level CF'!F39 -> 361858.27 | T21: =S21 -> 361858.27 | U21: =T21 -> 361858.27 | V21: =U21 -> 361858.27 | W21: =V21 -> 361858.27 | X21: =W21 -> 361858.27 | Y21: =X21 -> 361858.27 | AA21: REIT GAAP Accounting Cap Rate Average | AC21: =AVERAGE($AC$19:AC19) -> 0.038432501 | AD21: =AVERAGE($AC$19:AD19) -> 0.044804058 | AE21: =AVERAGE($AC$19:AE19) -> 0.051962678 | AF21: =AVERAGE($AC$19:AF19) -> 0.055958205 | AG21: =AVERAGE($AC$19:AG19) -> 0.058673734 | AH21: =AVERAGE($AC$19:AH19) -> 0.060609172 | AI21: =AVERAGE($AC$19:AI19) -> 0.06209844 | AJ21: =AVERAGE($AC$19:AJ19) -> 0.063309376 | ... AL21: =AVERAGE($AC$19:AL19) -> 0.06504467 | AN21: =AN20+1 -> 3 | AQ21: =AE33+AE39 -> 6466503 | AR21: ='Property-Level CF'!AE39 -> 410986.63 | AS21: =AR21 -> 410986.63 | AT21: =AS21 -> 410986.63 | AU21: =AT21 -> 410986.63 | AV21: =AU21 -> 410986.63 | AW21: =AV21 -> 410986.63 | AX21: =AW21 -> 410986.63 | AZ21: REIT GAAP Accounting Cap Rate Average | BB21: =AVERAGE($BB$19:BB19) -> 0.045370132 | BC21: =AVERAGE($BB$19:BC19) -> 0.050925582 | BD21: =AVERAGE($BB$19:BD19) -> 0.054738466 | BE21: =AVERAGE($BB$19:BE19) -> 0.05676967 | BF21: =AVERAGE($BB$19:BF19) -> 0.058087208 | BG21: =AVERAGE($BB$19:BG19) -> 0.059052343 | BH21: =AVERAGE($BB$19:BH19) -> 0.060324336 | BI21: =AVERAGE($BB$19:BI19) -> 0.061434972 | ... BK21: =AVERAGE($BB$19:BK19) -> 0.063136223 | BM21: =BM20+1 -> 3 | BP21: =BD33+BD39 -> 7246468.1 | BQ21: ='Property-Level CF'!BD39 -> 474056.26 | BR21: =BQ21 -> 474056.26 | BS21: =BR21 -> 474056.26 | BT21: =BS21 -> 474056.26 | BU21: =BT21 -> 474056.26 | BV21: =BU21 -> 474056.26 | BW21: =BV21 -> 474056.26 | BY21: REIT GAAP Accounting Cap Rate Average | CA21: =AVERAGE($CA$19:CA19) -> 0.050445974 | CB21: =AVERAGE($CA$19:CB19) -> 0.050885384 | CC21: =AVERAGE($CA$19:CC19) -> 0.051328879 | CD21: =AVERAGE($CA$19:CD19) -> 0.051779411 | CE21: =AVERAGE($CA$19:CE19) -> 0.052235112 | CF21: =AVERAGE($CA$19:CF19) -> 0.052696508 | CG21: =AVERAGE($CA$19:CG19) -> 0.053162664 | CH21: =AVERAGE($CA$19:CH19) -> 0.053633714 | ... CJ21: =AVERAGE($CA$19:CJ19) -> 0.054604228 | CL21: =CL20+1 -> 3 | CO21: =CC33+CC39 -> 9657537.5 | CP21: ='Property-Level CF'!CC39 -> 639155.25 | CQ21: =CP21 -> 639155.25 | CR21: =CQ21 -> 639155.25 | CS21: =CR21 -> 639155.25 | CT21: =CS21 -> 639155.25 | CU21: =CT21 -> 639155.25 | CV21: =CU21 -> 639155.25 | CX21: REIT GAAP Accounting Cap Rate Average | CZ21: =AVERAGE($CZ$19:CZ19) -> 0.051406844 | DA21: =AVERAGE($CZ$19:DA19) -> 0.051920931 | DB21: =AVERAGE($CZ$19:DB19) -> 0.052441853 | DC21: =AVERAGE($CZ$19:DC19) -> 0.05296972 | DD21: =AVERAGE($CZ$19:DD19) -> 0.05350466 | DE21: =AVERAGE($CZ$19:DE19) -> 0.054046774 | DF21: =AVERAGE($CZ$19:DF19) -> 0.054596155 | DG21: =AVERAGE($CZ$19:DG19) -> 0.055152928 | ... DI21: =AVERAGE($CZ$19:DI19) -> 0.056289063 | DK21: =DK20+1 -> 3 | DN21: =DB33+DB39 -> 4155798.1 | DO21: ='Property-Level CF'!DB39 -> 281012.51 | DP21: =DO21 -> 281012.51 | DQ21: =DP21 -> 281012.51 | DR21: =DQ21 -> 281012.51 | DS21: =DR21 -> 281012.51 | DT21: =DS21 -> 281012.51 | DU21: =DT21 -> 281012.51 | DW21: REIT GAAP Accounting Cap Rate Average | DY21: =AVERAGE($DY$19:DY19) -> 0.048414917 | DZ21: =AVERAGE($DY$19:DZ19) -> 0.04890095 | EA21: =AVERAGE($DY$19:EA19) -> 0.049390047 | EB21: =AVERAGE($DY$19:EB19) -> 0.049886591 | EC21: =AVERAGE($DY$19:EC19) -> 0.050390167 | ED21: =AVERAGE($DY$19:ED19) -> 0.050900964 | EE21: =AVERAGE($DY$19:EE19) -> 0.051417842 | EF21: =AVERAGE($DY$19:EF19) -> 0.051942688 | ... EH21: =AVERAGE($DY$19:EH19) -> 0.053012135 | EJ21: =EJ20+1 -> 3 | EM21: =EA33+EA39 -> 9831670.5 | EN21: ='Property-Level CF'!EA39 -> 595371.35 | EO21: =EN21 -> 595371.35 | EP21: =EO21 -> 595371.35 | EQ21: =EP21 -> 595371.35 | ER21: =EQ21 -> 595371.35 | ES21: =ER21 -> 595371.35 | ET21: =ES21 -> 595371.35
O22: =O21+1 -> 4 | S22: =G33+G39 -> 4516147 | T22: ='Property-Level CF'!G39 -> 105958.27 | U22: =T22 -> 105958.27 | V22: =U22 -> 105958.27 | W22: =V22 -> 105958.27 | X22: =W22 -> 105958.27 | Y22: =X22 -> 105958.27 | AN22: =AN21+1 -> 4 | AR22: =AF33+AF39 -> 6815835.6 | AS22: ='Property-Level CF'!AF39 -> 429236.63 | AT22: =AS22 -> 429236.63 | AU22: =AT22 -> 429236.63 | AV22: =AU22 -> 429236.63 | AW22: =AV22 -> 429236.63 | AX22: =AW22 -> 429236.63 | BM22: =BM21+1 -> 4 | BQ22: =BE33+BE39 -> 7380860.6 | BR22: ='Property-Level CF'!BE39 -> 481077.26 | BS22: =BR22 -> 481077.26 | BT22: =BS22 -> 481077.26 | BU22: =BT22 -> 481077.26 | BV22: =BU22 -> 481077.26 | BW22: =BV22 -> 481077.26 | CL22: =CL21+1 -> 4 | CP22: =CD33+CD39 -> 10145979 | CQ22: ='Property-Level CF'!CD39 -> 663722.25 | CR22: =CQ22 -> 663722.25 | CS22: =CR22 -> 663722.25 | CT22: =CS22 -> 663722.25 | CU22: =CT22 -> 663722.25 | CV22: =CU22 -> 663722.25 | DK22: =DK21+1 -> 4 | DO22: =DC33+DC39 -> 4393154.7 | DP22: ='Property-Level CF'!DC39 -> 293166.51 | DQ22: =DP22 -> 293166.51 | DR22: =DQ22 -> 293166.51 | DS22: =DR22 -> 293166.51 | DT22: =DS22 -> 293166.51 | DU22: =DT22 -> 293166.51 | EJ22: =EJ21+1 -> 4 | EN22: =EB33+EB39 -> 10396199 | EO22: ='Property-Level CF'!EB39 -> 622677.35 | EP22: =EO22 -> 622677.35 | EQ22: =EP22 -> 622677.35 | ER22: =EQ22 -> 622677.35 | ES22: =ER22 -> 622677.35 | ET22: =ES22 -> 622677.35
B23: Net Sale Price | D23: =(D10/D18)*(1-'Portfolio-Level CF'!$AC$52) -> 12905427 | E23: =(E10/E18)*(1-'Portfolio-Level CF'!$AC$52) -> 13046063 | F23: =(F10/F18)*(1-'Portfolio-Level CF'!$AC$52) -> 13193921 | G23: =(G10/G18)*(1-'Portfolio-Level CF'!$AC$52) -> 13134606 | H23: =(H10/H18)*(1-'Portfolio-Level CF'!$AC$52) -> 13814419 | I23: =(I10/I18)*(1-'Portfolio-Level CF'!$AC$52) -> 13012850 | J23: =(J10/J18)*(1-'Portfolio-Level CF'!$AC$52) -> 13267537 | K23: =(K10/K18)*(1-'Portfolio-Level CF'!$AC$52) -> 13944832 | ... M23: =(M10/M18)*(1-'Portfolio-Level CF'!$AC$52) -> 14562582 | O23: =O22+1 -> 5 | T23: =H33+H39 -> 5544224.6 | U23: ='Property-Level CF'!H39 -> 454223.27 | V23: =U23 -> 454223.27 | W23: =V23 -> 454223.27 | X23: =W23 -> 454223.27 | Y23: =X23 -> 454223.27 | AA23: Net Sale Price | AC23: =(AC10/AC18)*(1-'Portfolio-Level CF'!$AC$52) -> 10539811 | AD23: =(AD10/AD18)*(1-'Portfolio-Level CF'!$AC$52) -> 10177006 | AE23: =(AE10/AE18)*(1-'Portfolio-Level CF'!$AC$52) -> 13180714 | AF23: =(AF10/AF18)*(1-'Portfolio-Level CF'!$AC$52) -> 13511796 | AG23: =(AG10/AG18)*(1-'Portfolio-Level CF'!$AC$52) -> 13828202 | AH23: =(AH10/AH18)*(1-'Portfolio-Level CF'!$AC$52) -> 13977452 | AI23: =(AI10/AI18)*(1-'Portfolio-Level CF'!$AC$52) -> 14126140 | AJ23: =(AJ10/AJ18)*(1-'Portfolio-Level CF'!$AC$52) -> 14275663 | ... AL23: =(AL10/AL18)*(1-'Portfolio-Level CF'!$AC$52) -> 14350333 | AN23: =AN22+1 -> 5 | AS23: =AG33+AG39 -> 7149682.6 | AT23: ='Property-Level CF'!AG39 -> 446677.63 | AU23: =AT23 -> 446677.63 | AV23: =AU23 -> 446677.63 | AW23: =AV23 -> 446677.63 | AX23: =AW23 -> 446677.63 | AZ23: Net Sale Price | BB23: =(BB10/BB18)*(1-'Portfolio-Level CF'!$AC$52) -> 13527060 | BC23: =(BC10/BC18)*(1-'Portfolio-Level CF'!$AC$52) -> 14415516 | BD23: =(BD10/BD18)*(1-'Portfolio-Level CF'!$AC$52) -> 15917070 | BE23: =(BE10/BE18)*(1-'Portfolio-Level CF'!$AC$52) -> 16044442 | BF23: =(BF10/BF18)*(1-'Portfolio-Level CF'!$AC$52) -> 16170543 | BG23: =(BG10/BG18)*(1-'Portfolio-Level CF'!$AC$52) -> 16303430 | BH23: =(BH10/BH18)*(1-'Portfolio-Level CF'!$AC$52) -> 17344317 | BI23: =(BI10/BI18)*(1-'Portfolio-Level CF'!$AC$52) -> 17664152 | ... BK23: =(BK10/BK18)*(1-'Portfolio-Level CF'!$AC$52) -> 17907393 | BM23: =BM22+1 -> 5 | BR23: =BF33+BF39 -> 7513913.2 | BS23: ='Property-Level CF'!BF39 -> 488028.26 | BT23: =BS23 -> 488028.26 | BU23: =BT23 -> 488028.26 | BV23: =BU23 -> 488028.26 | BW23: =BV23 -> 488028.26 | BY23: Net Sale Price | CA23: =(CA10/CA18)*(1-'Portfolio-Level CF'!$AC$52) -> 25811578 | CB23: =(CB10/CB18)*(1-'Portfolio-Level CF'!$AC$52) -> 26016030 | CC23: =(CC10/CC18)*(1-'Portfolio-Level CF'!$AC$52) -> 26467707 | CD23: =(CD10/CD18)*(1-'Portfolio-Level CF'!$AC$52) -> 26931582 | CE23: =(CE10/CE18)*(1-'Portfolio-Level CF'!$AC$52) -> 27401423 | CF23: =(CF10/CF18)*(1-'Portfolio-Level CF'!$AC$52) -> 27880725 | CG23: =(CG10/CG18)*(1-'Portfolio-Level CF'!$AC$52) -> 28365369 | CH23: =(CH10/CH18)*(1-'Portfolio-Level CF'!$AC$52) -> 28857794 | ... CJ23: =(CJ10/CJ18)*(1-'Portfolio-Level CF'!$AC$52) -> 29920417 | CL23: =CL22+1 -> 5 | CQ23: =CE33+CE39 -> 10640704 | CR23: ='Property-Level CF'!CE39 -> 688605.25 | CS23: =CR23 -> 688605.25 | CT23: =CS23 -> 688605.25 | CU23: =CT23 -> 688605.25 | CV23: =CU23 -> 688605.25 | CX23: Net Sale Price | CZ23: =(CZ10/CZ18)*(1-'Portfolio-Level CF'!$AC$52) -> 10925394 | DA23: =(DA10/DA18)*(1-'Portfolio-Level CF'!$AC$52) -> 11039855 | DB23: =(DB10/DB18)*(1-'Portfolio-Level CF'!$AC$52) -> 11260648 | DC23: =(DC10/DC18)*(1-'Portfolio-Level CF'!$AC$52) -> 11485850 | DD23: =(DD10/DD18)*(1-'Portfolio-Level CF'!$AC$52) -> 11715574 | DE23: =(DE10/DE18)*(1-'Portfolio-Level CF'!$AC$52) -> 11949893 | DF23: =(DF10/DF18)*(1-'Portfolio-Level CF'!$AC$52) -> 12188881 | DG23: =(DG10/DG18)*(1-'Portfolio-Level CF'!$AC$52) -> 12432668 | ... DI23: =(DI10/DI18)*(1-'Portfolio-Level CF'!$AC$52) -> 12934936 | DK23: =DK22+1 -> 5 | DP23: =DD33+DD39 -> 4635276.4 | DQ23: ='Property-Level CF'!DD39 -> 305564.51 | DR23: =DQ23 -> 305564.51 | DS23: =DR23 -> 305564.51 | DT23: =DS23 -> 305564.51 | DU23: =DT23 -> 305564.51 | DW23: Net Sale Price | DY23: =(DY10/DY18)*(1-'Portfolio-Level CF'!$AC$52) -> 26046775 | DZ23: =(DZ10/DZ18)*(1-'Portfolio-Level CF'!$AC$52) -> 26321645 | EA23: =(EA10/EA18)*(1-'Portfolio-Level CF'!$AC$52) -> 26844623 | EB23: =(EB10/EB18)*(1-'Portfolio-Level CF'!$AC$52) -> 27381845 | EC23: =(EC10/EC18)*(1-'Portfolio-Level CF'!$AC$52) -> 27929869 | ED23: =(ED10/ED18)*(1-'Portfolio-Level CF'!$AC$52) -> 28489736 | EE23: =(EE10/EE18)*(1-'Portfolio-Level CF'!$AC$52) -> 29056902 | EF23: =(EF10/EF18)*(1-'Portfolio-Level CF'!$AC$52) -> 29641834 | ... EH23: =(EH10/EH18)*(1-'Portfolio-Level CF'!$AC$52) -> 30835681 | EJ23: =EJ22+1 -> 5 | EO23: =EC33+EC39 -> 10972077 | EP23: ='Property-Level CF'!EC39 -> 650532.35 | EQ23: =EP23 -> 650532.35 | ER23: =EQ23 -> 650532.35 | ES23: =ER23 -> 650532.35 | ET23: =ES23 -> 650532.35
B24: Net Sale Price PSF | D24: =D23/Summary!$F$4 -> 439.84279 | E24: =E23/Summary!$F$4 -> 444.63592 | F24: =F23/Summary!$F$4 -> 449.67523 | G24: =G23/Summary!$F$4 -> 447.65368 | H24: =H23/Summary!$F$4 -> 470.82305 | I24: =I23/Summary!$F$4 -> 443.50399 | J24: =J23/Summary!$F$4 -> 452.18423 | K24: =K23/Summary!$F$4 -> 475.26778 | ... M24: =M23/Summary!$F$4 -> 496.32193 | O24: =O23+1 -> 6 | U24: =I33+I39 -> 4693952 | V24: ='Property-Level CF'!I39 -> 405519.27 | W24: =V24 -> 405519.27 | X24: =W24 -> 405519.27 | Y24: =X24 -> 405519.27 | AA24: Net Sale Price PSF | AC24: =AC23/Summary!$F$5 -> 405.62697 | AD24: =AD23/Summary!$F$5 -> 391.66432 | AE24: =AE23/Summary!$F$5 -> 507.26269 | AF24: =AF23/Summary!$F$5 -> 520.00447 | AG24: =AG23/Summary!$F$5 -> 532.18143 | AH24: =AH23/Summary!$F$5 -> 537.92536 | AI24: =AI23/Summary!$F$5 -> 543.64764 | AJ24: =AJ23/Summary!$F$5 -> 549.40204 | ... AL24: =AL23/Summary!$F$5 -> 552.27575 | AN24: =AN23+1 -> 6 | AT24: =AH33+AH39 -> 7307159.8 | AU24: ='Property-Level CF'!AH39 -> 454904.63 | AV24: =AU24 -> 454904.63 | AW24: =AV24 -> 454904.63 | AX24: =AW24 -> 454904.63 | AZ24: Net Sale Price PSF | BB24: =BB23/Summary!$F$6 -> 450.902 | BC24: =BC23/Summary!$F$6 -> 480.51718 | BD24: =BD23/Summary!$F$6 -> 530.569 | BE24: =BE23/Summary!$F$6 -> 534.81472 | BF24: =BF23/Summary!$F$6 -> 539.01811 | BG24: =BG23/Summary!$F$6 -> 543.44766 | BH24: =BH23/Summary!$F$6 -> 578.1439 | BI24: =BI23/Summary!$F$6 -> 588.80506 | ... BK24: =BK23/Summary!$F$6 -> 596.91311 | BM24: =BM23+1 -> 6 | BS24: =BG33+BG39 -> 7654124.8 | BT24: ='Property-Level CF'!BG39 -> 495353.26 | BU24: =BT24 -> 495353.26 | BV24: =BU24 -> 495353.26 | BW24: =BV24 -> 495353.26 | BY24: Net Sale Price PSF | CA24: =CA23/Summary!$F$7 -> 597.47641 | CB24: =CB23/Summary!$F$7 -> 602.20898 | CC24: =CC23/Summary!$F$7 -> 612.66423 | CD24: =CD23/Summary!$F$7 -> 623.40182 | CE24: =CE23/Summary!$F$7 -> 634.27752 | CF24: =CF23/Summary!$F$7 -> 645.3722 | CG24: =CG23/Summary!$F$7 -> 656.59058 | CH24: =CH23/Summary!$F$7 -> 667.98902 | ... CJ24: =CJ23/Summary!$F$7 -> 692.58622 | CL24: =CL23+1 -> 6 | CR24: =CF33+CF39 -> 11145389 | CS24: ='Property-Level CF'!CF39 -> 713989.25 | CT24: =CS24 -> 713989.25 | CU24: =CT24 -> 713989.25 | CV24: =CU24 -> 713989.25 | CX24: Net Sale Price PSF | CZ24: =CZ23/Summary!$F$8 -> 417.7971 | DA24: =DA23/Summary!$F$8 -> 422.17418 | DB24: =DB23/Summary!$F$8 -> 430.6175 | DC24: =DC23/Summary!$F$8 -> 439.22945 | DD24: =DD23/Summary!$F$8 -> 448.0143 | DE24: =DE23/Summary!$F$8 -> 456.97486 | DF24: =DF23/Summary!$F$8 -> 466.11399 | DG24: =DG23/Summary!$F$8 -> 475.43664 | ... DI24: =DI23/Summary!$F$8 -> 494.64383 | DK24: =DK23+1 -> 6 | DQ24: =DE33+DE39 -> 4882241.3 | DR24: ='Property-Level CF'!DE39 -> 318210.51 | DS24: =DR24 -> 318210.51 | DT24: =DS24 -> 318210.51 | DU24: =DT24 -> 318210.51 | DW24: Net Sale Price PSF | DY24: =DY23/Summary!$F$9 -> 609.89474 | DZ24: =DZ23/Summary!$F$9 -> 616.33093 | EA24: =EA23/Summary!$F$9 -> 628.57666 | EB24: =EB23/Summary!$F$9 -> 641.15591 | EC24: =EC23/Summary!$F$9 -> 653.98808 | ED24: =ED23/Summary!$F$9 -> 667.09757 | EE24: =EE23/Summary!$F$9 -> 680.37798 | EF24: =EF23/Summary!$F$9 -> 694.07437 | ... EH24: =EH23/Summary!$F$9 -> 722.02873 | EJ24: =EJ23+1 -> 6 | EP24: =ED33+ED39 -> 11560401 | EQ24: ='Property-Level CF'!ED39 -> 678989.35 | ER24: =EQ24 -> 678989.35 | ES24: =ER24 -> 678989.35 | ET24: =ES24 -> 678989.35
O25: =O24+1 -> 7 | V25: =J33+J39 -> 4516321 | W25: ='Property-Level CF'!J39 -> -26798.734 | X25: =W25 -> -26798.734 | Y25: =X25 -> -26798.734 | AN25: =AN24+1 -> 7 | AU25: =AI33+AI39 -> 7464043.6 | AV25: ='Property-Level CF'!AI39 -> 463100.63 | AW25: =AV25 -> 463100.63 | AX25: =AW25 -> 463100.63 | BM25: =BM24+1 -> 7 | BT25: =BH33+BH39 -> 8752388 | BU25: ='Property-Level CF'!BH39 -> 552729.26 | BV25: =BU25 -> 552729.26 | BW25: =BV25 -> 552729.26 | CL25: =CL24+1 -> 7 | CS25: =CG33+CG39 -> 11655701 | CT25: ='Property-Level CF'!CG39 -> 739656.25 | CU25: =CT25 -> 739656.25 | CV25: =CU25 -> 739656.25 | DK25: =DK24+1 -> 7 | DR25: =DF33+DF39 -> 5134127.5 | DS25: ='Property-Level CF'!DF39 -> 331108.51 | DT25: =DS25 -> 331108.51 | DU25: =DT25 -> 331108.51 | EJ25: =EJ24+1 -> 7 | EQ25: =EE33+EE39 -> 12156395 | ER25: ='Property-Level CF'!EE39 -> 707817.35 | ES25: =ER25 -> 707817.35 | ET25: =ES25 -> 707817.35
B26: Unlevered IRR | D26: ='Property-Level CF'!P3 -> 0.018207065 | E26: ='Property-Level CF'!Q3 -> 0.041901141 | F26: ='Property-Level CF'!R3 -> 0.049895376 | G26: ='Property-Level CF'!S3 -> 0.045662949 | H26: ='Property-Level CF'!T3 -> 0.057865901 | I26: ='Property-Level CF'!U3 -> 0.048907337 | J26: ='Property-Level CF'!V3 -> 0.048552772 | K26: ='Property-Level CF'!W3 -> 0.055276831 | ... M26: ='Property-Level CF'!Y3 -> 0.056123945 | O26: =O25+1 -> 8 | W26: =K33+K39 -> 5682561.5 | X26: ='Property-Level CF'!K39 -> 462147.27 | Y26: =X26 -> 462147.27 | AA26: Unlevered IRR | AC26: ='Property-Level CF'!AO3 -> -0.0012527016 | AD26: ='Property-Level CF'!AP3 -> 0.0079366159 | AE26: ='Property-Level CF'!AQ3 -> 0.11035437 | AF26: ='Property-Level CF'!AR3 -> 0.10336455 | AG26: ='Property-Level CF'!AS3 -> 0.098897827 | AH26: ='Property-Level CF'!AT3 -> 0.093966435 | AI26: ='Property-Level CF'!AU3 -> 0.090460677 | AJ26: ='Property-Level CF'!AV3 -> 0.087849783 | ... AL26: ='Property-Level CF'!AX3 -> 0.081037425 | AN26: =AN25+1 -> 8 | AV26: =AJ33+AJ39 -> 7621808 | AW26: ='Property-Level CF'!AJ39 -> 471342.63 | AX26: =AW26 -> 471342.63 | AZ26: Unlevered IRR | BB26: ='Property-Level CF'!BN3 -> 0.0058039353 | BC26: ='Property-Level CF'!BO3 -> 0.061650282 | BD26: ='Property-Level CF'!BP3 -> 0.09312356 | BE26: ='Property-Level CF'!BQ3 -> 0.085985009 | BF26: ='Property-Level CF'!BR3 -> 0.081719594 | BG26: ='Property-Level CF'!BS3 -> 0.078954769 | BH26: ='Property-Level CF'!BT3 -> 0.084043199 | BI26: ='Property-Level CF'!BU3 -> 0.08297021 | ... BK26: ='Property-Level CF'!BW3 -> 0.079510418 | BM26: =BM25+1 -> 8 | BU26: =BI33+BI39 -> 9089852.9 | BV26: ='Property-Level CF'!BI39 -> 570359.26 | BW26: =BV26 -> 570359.26 | BY26: Unlevered IRR | CA26: ='Property-Level CF'!CM3 -> 0.01114134 | CB26: ='Property-Level CF'!CN3 -> 0.034896017 | CC26: ='Property-Level CF'!CO3 -> 0.046020665 | CD26: ='Property-Level CF'!CP3 -> 0.051663947 | CE26: ='Property-Level CF'!CQ3 -> 0.055046562 | CF26: ='Property-Level CF'!CR3 -> 0.057312169 | CG26: ='Property-Level CF'!CS3 -> 0.058917249 | CH26: ='Property-Level CF'!CT3 -> 0.060118142 | ... CJ26: ='Property-Level CF'!CV3 -> 0.061945 | CL26: =CL25+1 -> 8 | CT26: =CH33+CH39 -> 12174204 | CU26: ='Property-Level CF'!CH39 -> 765735.25 | CV26: =CU26 -> 765735.25 | CX26: Unlevered IRR | CZ26: ='Property-Level CF'!DL3 -> 0.011756166 | DA26: ='Property-Level CF'!DM3 -> 0.036804407 | DB26: ='Property-Level CF'!DN3 -> 0.048400461 | DC26: ='Property-Level CF'!DO3 -> 0.054245238 | DD26: ='Property-Level CF'!DP3 -> 0.057766297 | DE26: ='Property-Level CF'!DQ3 -> 0.060118578 | DF26: ='Property-Level CF'!DR3 -> 0.061800261 | DG26: ='Property-Level CF'!DS3 -> 0.063061998 | ... DI26: ='Property-Level CF'!DU3 -> 0.064826948 | DK26: =DK25+1 -> 8 | DS26: =DG33+DG39 -> 5391071.8 | DT26: ='Property-Level CF'!DG39 -> 344265.51 | DU26: =DT26 -> 344265.51 | DW26: Unlevered IRR | DY26: ='Property-Level CF'!EK3 -> 0.0091266662 | DZ26: ='Property-Level CF'!EL3 -> 0.034165979 | EA26: ='Property-Level CF'!EM3 -> 0.045690436 | EB26: ='Property-Level CF'!EN3 -> 0.051532587 | EC26: ='Property-Level CF'!EO3 -> 0.055051513 | ED26: ='Property-Level CF'!EP3 -> 0.057406682 | EE26: ='Property-Level CF'!EQ3 -> 0.059072596 | EF26: ='Property-Level CF'!ER3 -> 0.060346407 | ... EH26: ='Property-Level CF'!ET3 -> 0.062094976 | EJ26: =EJ25+1 -> 8 | ER26: =EF33+EF39 -> 12771058 | ES26: ='Property-Level CF'!EF39 -> 737548.35 | ET26: =ES26 -> 737548.35
B27: Unlevered Equity Multiple | D27: =(SUM($D$14:D14)+D23)/-'Property-Level CF'!P4 -> 1.0182071 | E27: =(SUM($D$14:E14)+E23)/-'Property-Level CF'!Q4 -> 1.0831819 | F27: =(SUM($D$14:F14)+F23)/-'Property-Level CF'!R4 -> 1.1487598 | G27: =(SUM($D$14:G14)+G23)/-'Property-Level CF'!S4 -> 1.1798372 | H27: =(SUM($D$14:H14)+H23)/-'Property-Level CF'!T4 -> 1.2919291 | I27: =(SUM($D$14:I14)+I23)/-'Property-Level CF'!U4 -> 1.2900243 | J27: =(SUM($D$14:J14)+J23)/-'Property-Level CF'!V4 -> 1.334605 | K27: =(SUM($D$14:K14)+K23)/-'Property-Level CF'!W4 -> 1.4470997 | ... M27: =(SUM($D$14:M14)+M23)/-'Property-Level CF'!Y4 -> 1.5744085 | O27: =O26+1 -> 9 | X27: =L33+L39 -> 5200000.5 | Y27: ='Property-Level CF'!L39 -> 82366.266 | AA27: Unlevered Equity Multiple | AC27: =(SUM($AC$14:AC14)+AC23)/-'Property-Level CF'!AO4 -> 0.9987473 | AD27: =(SUM($AC$14:AD14)+AD23)/-'Property-Level CF'!AP4 -> 1.0156406 | AE27: =(SUM($AC$14:AE14)+AE23)/-'Property-Level CF'!AQ4 -> 1.3547502 | AF27: =(SUM($AC$14:AF14)+AF23)/-'Property-Level CF'!AR4 -> 1.451713 | AG27: =(SUM($AC$14:AG14)+AG23)/-'Property-Level CF'!AS4 -> 1.5489279 | AH27: =(SUM($AC$14:AH14)+AH23)/-'Property-Level CF'!AT4 -> 1.6316445 | AI27: =(SUM($AC$14:AI14)+AI23)/-'Property-Level CF'!AU4 -> 1.7150575 | AJ27: =(SUM($AC$14:AJ14)+AJ23)/-'Property-Level CF'!AV4 -> 1.7992985 | ... AL27: =(SUM($AC$14:AL14)+AL23)/-'Property-Level CF'!AX4 -> 1.9185554 | AN27: =AN26+1 -> 9 | AW27: =AK33+AK39 -> 7521600.7 | AX27: ='Property-Level CF'!AK39 -> 366291.63 | AZ27: Unlevered Equity Multiple | BB27: =(SUM($BB$14:BB14)+BB23)/-'Property-Level CF'!BN4 -> 1.0058039 | BC27: =(SUM($BB$14:BC14)+BC23)/-'Property-Level CF'!BO4 -> 1.12437 | BD27: =(SUM($BB$14:BD14)+BD23)/-'Property-Level CF'!BP4 -> 1.2923981 | BE27: =(SUM($BB$14:BE14)+BE23)/-'Property-Level CF'!BQ4 -> 1.3632488 | BF27: =(SUM($BB$14:BF14)+BF23)/-'Property-Level CF'!BR4 -> 1.4345032 | BG27: =(SUM($BB$14:BG14)+BG23)/-'Property-Level CF'!BS4 -> 1.5067606 | BH27: =(SUM($BB$14:BH14)+BH23)/-'Property-Level CF'!BT4 -> 1.6476366 | BI27: =(SUM($BB$14:BI14)+BI23)/-'Property-Level CF'!BU4 -> 1.7385137 | ... BK27: =(SUM($BB$14:BK14)+BK23)/-'Property-Level CF'!BW4 -> 1.8935533 | BM27: =BM26+1 -> 9 | BV27: =BJ33+BJ39 -> 9227346.3 | BW27: ='Property-Level CF'!BJ39 -> 577542.26 | BY27: Unlevered Equity Multiple | CA27: =(SUM($CA$14:CA14)+CA23)/-'Property-Level CF'!CM4 -> 1.0111413 | CB27: =(SUM($CA$14:CB14)+CB23)/-'Property-Level CF'!CN4 -> 1.0692775 | CC27: =(SUM($CA$14:CC14)+CC23)/-'Property-Level CF'!CO4 -> 1.137514 | CD27: =(SUM($CA$14:CD14)+CD23)/-'Property-Level CF'!CP4 -> 1.20712 | CE27: =(SUM($CA$14:CE14)+CE23)/-'Property-Level CF'!CQ4 -> 1.2778753 | CF27: =(SUM($CA$14:CF14)+CF23)/-'Property-Level CF'!CR4 -> 1.3499284 | CG27: =(SUM($CA$14:CG14)+CG23)/-'Property-Level CF'!CS4 -> 1.4231368 | CH27: =(SUM($CA$14:CH14)+CH23)/-'Property-Level CF'!CT4 -> 1.4976064 | ... CJ27: =(SUM($CA$14:CJ14)+CJ23)/-'Property-Level CF'!CV4 -> 1.6525532 | CL27: =CL26+1 -> 9 | CU27: =CI33+CI39 -> 12715452 | CV27: ='Property-Level CF'!CI39 -> 792958.25 | CX27: Unlevered Equity Multiple | CZ27: =(SUM($CZ$14:CZ14)+CZ23)/-'Property-Level CF'!DL4 -> 1.0117562 | DA27: =(SUM($CZ$14:DA14)+DA23)/-'Property-Level CF'!DM4 -> 1.0731137 | DB27: =(SUM($CZ$14:DB14)+DB23)/-'Property-Level CF'!DN4 -> 1.1448778 | DC27: =(SUM($CZ$14:DC14)+DC23)/-'Property-Level CF'!DO4 -> 1.2180996 | DD27: =(SUM($CZ$14:DD14)+DD23)/-'Property-Level CF'!DP4 -> 1.2928104 | DE27: =(SUM($CZ$14:DE14)+DE23)/-'Property-Level CF'!DQ4 -> 1.3690386 | DF27: =(SUM($CZ$14:DF14)+DF23)/-'Property-Level CF'!DR4 -> 1.4468127 | DG27: =(SUM($CZ$14:DG14)+DG23)/-'Property-Level CF'!DS4 -> 1.5261671 | ... DI27: =(SUM($CZ$14:DI14)+DI23)/-'Property-Level CF'!DU4 -> 1.6897356 | DK27: =DK26+1 -> 9 | DT27: =DH33+DH39 -> 5653132.6 | DU27: ='Property-Level CF'!DH39 -> 357684.51 | DW27: Unlevered Equity Multiple | DY27: =(SUM($DY$14:DY14)+DY23)/-'Property-Level CF'!EK4 -> 1.0091267 | DZ27: =(SUM($DY$14:DZ14)+DZ23)/-'Property-Level CF'!EL4 -> 1.0678721 | EA27: =(SUM($DY$14:EA14)+EA23)/-'Property-Level CF'!EM4 -> 1.1367575 | EB27: =(SUM($DY$14:EB14)+EB23)/-'Property-Level CF'!EN4 -> 1.2071766 | EC27: =(SUM($DY$14:EC14)+EC23)/-'Property-Level CF'!EO4 -> 1.2790228 | ED27: =(SUM($DY$14:ED14)+ED23)/-'Property-Level CF'!EP4 -> 1.3523566 | EE27: =(SUM($DY$14:EE14)+EE23)/-'Property-Level CF'!EQ4 -> 1.4270241 | EF27: =(SUM($DY$14:EF14)+EF23)/-'Property-Level CF'!ER4 -> 1.5034448 | ... EH27: =(SUM($DY$14:EH14)+EH23)/-'Property-Level CF'!ET4 -> 1.6605182 | EJ27: =EJ26+1 -> 9 | ES27: =EG33+EG39 -> 13390828 | ET27: ='Property-Level CF'!EG39 -> 767526.35
O28: =O27+1 -> 10 | Y28: =M33+M36+M38 -> 6105845.2 | AN28: =AN27+1 -> 10 | AX28: =AL33+AL36+AL38 -> 7486306.4 | BM28: =BM27+1 -> 10 | BW28: =BK33+BK36+BK38 -> 9346502.2 | CL28: =CL27+1 -> 10 | CV28: =CJ33+CJ36+CJ38 -> 13293105 | DK28: =DK27+1 -> 10 | DU28: =DI33+DI36+DI38 -> 5920446.8 | EJ28: =EJ27+1 -> 10 | ET28: =EH33+EH36+EH38 -> 14025586
B29: Loan Balance | D29: =Summary!I24 -> 8724417.8 | E29: =D29 -> 8724417.8 | F29: =E29 -> 8724417.8 | G29: =F29 -> 8724417.8 | H29: =G29 -> 8724417.8 | I29: =H29 -> 8724417.8 | J29: =I29 -> 8724417.8 | K29: =J29 -> 8724417.8 | L29: =K29 -> 8724417.8 | M29: =L29 -> 8724417.8 | O29: =O28+1 -> 11 | AA29: Loan Balance | AC29: =Summary!I25 -> 7125197.3 | AD29: =AC29 -> 7125197.3 | AE29: =AD29 -> 7125197.3 | AF29: =AE29 -> 7125197.3 | AG29: =AF29 -> 7125197.3 | AH29: =AG29 -> 7125197.3 | AI29: =AH29 -> 7125197.3 | AJ29: =AI29 -> 7125197.3 | AK29: =AJ29 -> 7125197.3 | AL29: =AK29 -> 7125197.3 | AN29: =AN28+1 -> 11 | AZ29: Loan Balance | BB29: =Summary!I26 -> 9144658.3 | BC29: =BB29 -> 9144658.3 | BD29: =BC29 -> 9144658.3 | BE29: =BD29 -> 9144658.3 | BF29: =BE29 -> 9144658.3 | BG29: =BF29 -> 9144658.3 | BH29: =BG29 -> 9144658.3 | BI29: =BH29 -> 9144658.3 | BJ29: =BI29 -> 9144658.3 | BK29: =BJ29 -> 9144658.3 | BM29: =BM28+1 -> 11 | BY29: Loan Balance | CA29: =Summary!$I$27 -> 17449325 | CB29: =Summary!$I$27 -> 17449325 | CC29: =Summary!$I$27 -> 17449325 | CD29: =Summary!$I$27 -> 17449325 | CE29: =Summary!$I$27 -> 17449325 | CF29: =Summary!$I$27 -> 17449325 | CG29: =Summary!$I$27 -> 17449325 | CH29: =Summary!$I$27 -> 17449325 | ... CJ29: =Summary!$I$27 -> 17449325 | CL29: =CL28+1 -> 11 | CX29: Loan Balance | CZ29: =Summary!I28 -> 7385861.9 | DA29: =CZ29 -> 7385861.9 | DB29: =DA29 -> 7385861.9 | DC29: =DB29 -> 7385861.9 | DD29: =DC29 -> 7385861.9 | DE29: =DD29 -> 7385861.9 | DF29: =DE29 -> 7385861.9 | DG29: =DF29 -> 7385861.9 | DH29: =DG29 -> 7385861.9 | DI29: =DH29 -> 7385861.9 | DK29: =DK28+1 -> 11 | DW29: Loan Balance | DY29: =Summary!I29 -> 17608324 | DZ29: =DY29 -> 17608324 | EA29: =DZ29 -> 17608324 | EB29: =EA29 -> 17608324 | EC29: =EB29 -> 17608324 | ED29: =EC29 -> 17608324 | EE29: =ED29 -> 17608324 | EF29: =EE29 -> 17608324 | EG29: =EF29 -> 17608324 | EH29: =EG29 -> 17608324 | EJ29: =EJ28+1 -> 11
B30: Debt Service | D30: =Summary!I24*((Summary!C16/360)*365) -> 358737.83 | E30: =D30 -> 358737.83 | F30: =E30 -> 358737.83 | G30: =F30 -> 358737.83 | H30: =G30 -> 358737.83 | I30: =H30 -> 358737.83 | J30: =I30 -> 358737.83 | K30: =J30 -> 358737.83 | L30: =K30 -> 358737.83 | M30: =L30 -> 358737.83 | AA30: Debt Service | AC30: =Summary!I25*((Summary!C16/360)*365) -> 292979.76 | AD30: =AC30 -> 292979.76 | AE30: =AD30 -> 292979.76 | AF30: =AE30 -> 292979.76 | AG30: =AF30 -> 292979.76 | AH30: =AG30 -> 292979.76 | AI30: =AH30 -> 292979.76 | AJ30: =AI30 -> 292979.76 | AK30: =AJ30 -> 292979.76 | AL30: =AK30 -> 292979.76 | AZ30: Debt Service | BB30: =Summary!I26*((Summary!C16/360)*365) -> 376017.62 | BC30: =BB30 -> 376017.62 | BD30: =BC30 -> 376017.62 | BE30: =BD30 -> 376017.62 | BF30: =BE30 -> 376017.62 | BG30: =BF30 -> 376017.62 | BH30: =BG30 -> 376017.62 | BI30: =BH30 -> 376017.62 | BJ30: =BI30 -> 376017.62 | BK30: =BJ30 -> 376017.62 | BY30: Debt Service | CA30: =Summary!I27*((Summary!C16/360)*365) -> 717495.78 | CB30: =CA30 -> 717495.78 | CC30: =CB30 -> 717495.78 | CD30: =CC30 -> 717495.78 | CE30: =CD30 -> 717495.78 | CF30: =CE30 -> 717495.78 | CG30: =CF30 -> 717495.78 | CH30: =CG30 -> 717495.78 | CI30: =CH30 -> 717495.78 | CJ30: =CI30 -> 717495.78 | CX30: Debt Service | CZ30: =Summary!I28*((Summary!C16/360)*365) -> 303697.98 | DA30: =CZ30 -> 303697.98 | DB30: =DA30 -> 303697.98 | DC30: =DB30 -> 303697.98 | DD30: =DC30 -> 303697.98 | DE30: =DD30 -> 303697.98 | DF30: =DE30 -> 303697.98 | DG30: =DF30 -> 303697.98 | DH30: =DG30 -> 303697.98 | DI30: =DH30 -> 303697.98 | DW30: Debt Service | DY30: =Summary!I29*((Summary!C16/360)*365) -> 724033.64 | DZ30: =DY30 -> 724033.64 | EA30: =DZ30 -> 724033.64 | EB30: =EA30 -> 724033.64 | EC30: =EB30 -> 724033.64 | ED30: =EC30 -> 724033.64 | EE30: =ED30 -> 724033.64 | EF30: =EE30 -> 724033.64 | EG30: =EF30 -> 724033.64 | EH30: =EG30 -> 724033.64
B31: Debt Coverage Ratio | D31: =D14/D30 -> 2.1216957 | E31: =E14/E30 -> 2.0390058 | F31: =F14/F30 -> 2.0414365 | G31: =G14/G30 -> 1.3281022 | H31: =H14/H30 -> 2.2989087 | I31: =I14/I30 -> 2.1631438 | J31: =J14/J30 -> 0.9580353 | K31: =K14/K30 -> 2.3209972 | ... M31: =M14/M30 -> 1.7789133 | O31: Portfolio Sale Price by Cap Rate by Exit Year | AA31: Debt Coverage Ratio | AC31: =AC14/AC30 -> 1.3936082 | AD31: =AD14/AD30 -> 1.870392 | AE31: =AE14/AE30 -> 2.4355198 | AF31: =AF14/AF30 -> 2.4978108 | AG31: =AG14/AG30 -> 2.5573405 | AH31: =AH14/AH30 -> 2.585421 | AI31: =AI14/AI30 -> 2.6133956 | AJ31: =AJ14/AJ30 -> 2.6415272 | ... AL31: =AL14/AL30 -> 1.9241671 | AN31: Portfolio Sale Price by Cap Rate by Exit Year | AZ31: Debt Coverage Ratio | BB31: =BB14/BB30 -> 1.6576324 | BC31: =BC14/BC30 -> 2.073347 | BD31: =BD14/BD30 -> 2.293467 | BE31: =BE14/BE30 -> 2.312139 | BF31: =BF14/BF30 -> 2.3306248 | BG31: =BG14/BG30 -> 2.3501053 | BH31: =BH14/BH30 -> 2.5026939 | BI31: =BI14/BI30 -> 2.54958 | ... BK31: =BK14/BK30 -> 2.5852379 | BM31: Portfolio Sale Price by Cap Rate by Exit Year | BY31: Debt Coverage Ratio | CA31: =CA14/CA30 -> 1.8573315 | CB31: =CB14/CB30 -> 1.8902125 | CC31: =CC14/CC30 -> 1.9235521 | CD31: =CD14/CD30 -> 1.957792 | CE31: =CE14/CE30 -> 1.9924724 | CF31: =CF14/CF30 -> 2.027851 | CG31: =CG14/CG30 -> 2.063624 | CH31: =CH14/CH30 -> 2.0999712 | ... CJ31: =CJ14/CJ30 -> 2.1784065 | CL31: Portfolio Sale Price by Cap Rate by Exit Year | CX31: Debt Coverage Ratio | CZ31: =CZ14/CZ30 -> 1.8803352 | DA31: =DA14/DA30 -> 1.9188043 | DB31: =DB14/DB30 -> 1.9580407 | DC31: =DC14/DC30 -> 1.9980607 | DD31: =DD14/DD30 -> 2.0388842 | DE31: =DE14/DE30 -> 2.0805242 | DF31: =DF14/DF30 -> 2.122994 | DG31: =DG14/DG30 -> 2.1663167 | ... DI31: =DI14/DI30 -> 2.2555731 | DK31: Portfolio Sale Price by Cap Rate by Exit Year | DW31: Debt Coverage Ratio | DY31: =DY14/DY30 -> 1.7819524 | DZ31: =DZ14/DZ30 -> 1.8183223 | EA31: =EA14/EA30 -> 1.8550361 | EB31: =EB14/EB30 -> 1.8927498 | EC31: =EC14/EC30 -> 1.9312217 | ED31: =ED14/ED30 -> 1.9705252 | EE31: =EE14/EE30 -> 2.010341 | EF31: =EF14/EF30 -> 2.051404 | ... EH31: =EH14/EH30 -> 2.1352136 | EJ31: Portfolio Sale Price by Cap Rate by Exit Year
O32: Cap Rate | P32: =P16 -> Year 1 | Q32: =Q16 -> Year 2 | R32: =R16 -> Year 3 | S32: =S16 -> Year 4 | T32: =T16 -> Year 5 | U32: =U16 -> Year 6 | V32: =V16 -> Year 7 | W32: =W16 -> Year 8 | ... Y32: =Y16 -> Year 10 | AN32: Cap Rate | AO32: Year 1 | AP32: Year 2 | AQ32: Year 3 | AR32: Year 4 | AS32: Year 5 | AT32: Year 6 | AU32: Year 7 | AV32: Year 8 | AW32: Year 9 | AX32: Year 10 | BM32: Cap Rate | BN32: Year 1 | BO32: Year 2 | BP32: Year 3 | BQ32: Year 4 | BR32: Year 5 | BS32: Year 6 | BT32: Year 7 | BU32: Year 8 | BV32: Year 9 | BW32: Year 10 | CL32: Cap Rate | CM32: Year 1 | CN32: Year 2 | CO32: Year 3 | CP32: Year 4 | CQ32: Year 5 | CR32: Year 6 | CS32: Year 7 | CT32: Year 8 | CU32: Year 9 | CV32: Year 10 | DK32: Cap Rate | DL32: Year 1 | DM32: Year 2 | DN32: Year 3 | DO32: Year 4 | DP32: Year 5 | DQ32: Year 6 | DR32: Year 7 | DS32: Year 8 | DT32: Year 9 | DU32: Year 10 | EJ32: Cap Rate | EK32: Year 1 | EL32: Year 2 | EM32: Year 3 | EN32: Year 4 | EO32: Year 5 | EP32: Year 6 | EQ32: Year 7 | ER32: Year 8 | ES32: Year 9 | ET32: Year 10
B33: Net Cash on Sale | D33: =D23-D29 -> 4181009.4 | E33: =E23-E29 -> 4321644.9 | F33: =F23-F29 -> 4469503.2 | G33: =G23-G29 -> 4410188.7 | H33: =H23-H29 -> 5090001.4 | I33: =I23-I29 -> 4288432.7 | J33: =J23-J29 -> 4543119.7 | K33: =K23-K29 -> 5220414.3 | ... M33: =M23-M29 -> 5838163.9 | O33: 0.057 | P33: =(D10/$O33)*(1-'Portfolio-Level CF'!$AC$52) -> 13103777 | Q33: =(E10/$O33)*(1-'Portfolio-Level CF'!$AC$52) -> 13371429 | R33: =(F10/$O33)*(1-'Portfolio-Level CF'!$AC$52) -> 13522975 | S33: =(G10/$O33)*(1-'Portfolio-Level CF'!$AC$52) -> 13462181 | T33: =(H10/$O33)*(1-'Portfolio-Level CF'!$AC$52) -> 14158948 | U33: =(I10/$O33)*(1-'Portfolio-Level CF'!$AC$52) -> 13337388 | V33: =(J10/$O33)*(1-'Portfolio-Level CF'!$AC$52) -> 13598427 | W33: =(K10/$O33)*(1-'Portfolio-Level CF'!$AC$52) -> 14292613 | ... Y33: =(M10/$O33)*(1-'Portfolio-Level CF'!$AC$52) -> 14925769 | AA33: Net Cash on Sale | AC33: =AC23-AC29 -> 3414613.8 | AD33: =AD23-AD29 -> 3051808.5 | AE33: =AE23-AE29 -> 6055516.4 | AF33: =AF23-AF29 -> 6386598.9 | AG33: =AG23-AG29 -> 6703005 | AH33: =AH23-AH29 -> 6852255.2 | AI33: =AI23-AI29 -> 7000943 | AJ33: =AJ23-AJ29 -> 7150465.3 | ... AL33: =AL23-AL29 -> 7225135.8 | AN33: 0.052 | AO33: =(AC10/$AN33)*(1-'Portfolio-Level CF'!$AC$52) -> 7789832.6 | AP33: =(AD10/$AN33)*(1-'Portfolio-Level CF'!$AC$52) -> 10372717 | AQ33: =(AE10/$AN33)*(1-'Portfolio-Level CF'!$AC$52) -> 13434189 | AR33: =(AF10/$AN33)*(1-'Portfolio-Level CF'!$AC$52) -> 13771638 | AS33: =(AG10/$AN33)*(1-'Portfolio-Level CF'!$AC$52) -> 14094129 | AT33: =(AH10/$AN33)*(1-'Portfolio-Level CF'!$AC$52) -> 14246250 | AU33: =(AI10/$AN33)*(1-'Portfolio-Level CF'!$AC$52) -> 14397797 | AV33: =(AJ10/$AN33)*(1-'Portfolio-Level CF'!$AC$52) -> 14550195 | ... AX33: =(AL10/$AN33)*(1-'Portfolio-Level CF'!$AC$52) -> 14626301 | AZ33: Net Cash on Sale | BB33: =BB23-BB29 -> 4382401.6 | BC33: =BC23-BC29 -> 5270857.2 | BD33: =BD23-BD29 -> 6772411.8 | BE33: =BE23-BE29 -> 6899783.4 | BF33: =BF23-BF29 -> 7025885 | BG33: =BG23-BG29 -> 7158771.5 | BH33: =BH23-BH29 -> 8199658.8 | BI33: =BI23-BI29 -> 8519493.6 | ... BK33: =BK23-BK29 -> 8762735 | BM33: 0.044 | BN33: =(BB10/$BM33)*(1-'Portfolio-Level CF'!$AC$52) -> 13948284 | BO33: =(BC10/$BM33)*(1-'Portfolio-Level CF'!$AC$52) -> 17364144 | BP33: =(BD10/$BM33)*(1-'Portfolio-Level CF'!$AC$52) -> 19172834 | BQ33: =(BE10/$BM33)*(1-'Portfolio-Level CF'!$AC$52) -> 19326259 | BR33: =(BF10/$BM33)*(1-'Portfolio-Level CF'!$AC$52) -> 19478154 | BS33: =(BG10/$BM33)*(1-'Portfolio-Level CF'!$AC$52) -> 19638222 | BT33: =(BH10/$BM33)*(1-'Portfolio-Level CF'!$AC$52) -> 20892018 | BU33: =(BI10/$BM33)*(1-'Portfolio-Level CF'!$AC$52) -> 21277274 | ... BW33: =(BK10/$BM33)*(1-'Portfolio-Level CF'!$AC$52) -> 21570269 | BY33: Net Cash on Sale | CA33: =CA23-CA29 -> 8362253.4 | CB33: =CB23-CB29 -> 8566705.3 | CC33: =CC23-CC29 -> 9018382.2 | CD33: =CD23-CD29 -> 9482256.9 | CE33: =CE23-CE29 -> 9952098.3 | CF33: =CF23-CF29 -> 10431400 | CG33: =CG23-CG29 -> 10916045 | CH33: =CH23-CH29 -> 11408469 | ... CJ33: =CJ23-CJ29 -> 12471092 | CL33: 0.05 | CM33: =(CA10/$CL33)*(1-'Portfolio-Level CF'!$AC$52) -> 26041804 | CN33: =(CB10/$CL33)*(1-'Portfolio-Level CF'!$AC$52) -> 26495479 | CO33: =(CC10/$CL33)*(1-'Portfolio-Level CF'!$AC$52) -> 26955479 | CP33: =(CD10/$CL33)*(1-'Portfolio-Level CF'!$AC$52) -> 27427903 | CQ33: =(CE10/$CL33)*(1-'Portfolio-Level CF'!$AC$52) -> 27906403 | CR33: =(CF10/$CL33)*(1-'Portfolio-Level CF'!$AC$52) -> 28394537 | CS33: =(CG10/$CL33)*(1-'Portfolio-Level CF'!$AC$52) -> 28888114 | CT33: =(CH10/$CL33)*(1-'Portfolio-Level CF'!$AC$52) -> 29389613 | ... CV33: =(CJ10/$CL33)*(1-'Portfolio-Level CF'!$AC$52) -> 30471820 | CX33: Net Cash on Sale | CZ33: =CZ23-CZ29 -> 3539532.3 | DA33: =DA23-DA29 -> 3653993 | DB33: =DB23-DB29 -> 3874785.6 | DC33: =DC23-DC29 -> 4099988.2 | DD33: =DD23-DD29 -> 4329711.9 | DE33: =DE23-DE29 -> 4564030.8 | DF33: =DF23-DF29 -> 4803019 | DG33: =DG23-DG29 -> 5046806.2 | ... DI33: =DI23-DI29 -> 5549074.3 | DK33: 0.051 | DL33: =(CZ10/$DK33)*(1-'Portfolio-Level CF'!$AC$52) -> 11012550 | DM33: =(DA10/$DK33)*(1-'Portfolio-Level CF'!$AC$52) -> 11232809 | DN33: =(DB10/$DK33)*(1-'Portfolio-Level CF'!$AC$52) -> 11457460 | DO33: =(DC10/$DK33)*(1-'Portfolio-Level CF'!$AC$52) -> 11686599 | DP33: =(DD10/$DK33)*(1-'Portfolio-Level CF'!$AC$52) -> 11920338 | DQ33: =(DE10/$DK33)*(1-'Portfolio-Level CF'!$AC$52) -> 12158752 | DR33: =(DF10/$DK33)*(1-'Portfolio-Level CF'!$AC$52) -> 12401917 | DS33: =(DG10/$DK33)*(1-'Portfolio-Level CF'!$AC$52) -> 12649965 | ... DU33: =(DI10/$DK33)*(1-'Portfolio-Level CF'!$AC$52) -> 13161012 | DW33: Net Cash on Sale | DY33: =DY23-DY29 -> 8438450.7 | DZ33: =DZ23-DZ29 -> 8713321 | EA33: =EA23-EA29 -> 9236299.2 | EB33: =EB23-EB29 -> 9773521.4 | EC33: =EC23-EC29 -> 10321545 | ED33: =ED23-ED29 -> 10881412 | EE33: =EE23-EE29 -> 11448578 | EF33: =EF23-EF29 -> 12033510 | ... EH33: =EH23-EH29 -> 13227357 | EJ33: 0.048 | EK33: =(DY10/$EJ33)*(1-'Portfolio-Level CF'!$AC$52) -> 26271926 | EL33: =(DZ10/$EJ33)*(1-'Portfolio-Level CF'!$AC$52) -> 26799409 | EM33: =(EA10/$EJ33)*(1-'Portfolio-Level CF'!$AC$52) -> 27331879 | EN33: =(EB10/$EJ33)*(1-'Portfolio-Level CF'!$AC$52) -> 27878853 | EO33: =(EC10/$EJ33)*(1-'Portfolio-Level CF'!$AC$52) -> 28436823 | EP33: =(ED10/$EJ33)*(1-'Portfolio-Level CF'!$AC$52) -> 29006852 | EQ33: =(EE10/$EJ33)*(1-'Portfolio-Level CF'!$AC$52) -> 29584313 | ER33: =(EF10/$EJ33)*(1-'Portfolio-Level CF'!$AC$52) -> 30179862 | ... ET33: =(EH10/$EJ33)*(1-'Portfolio-Level CF'!$AC$52) -> 31395379
B34: Net Gain | D34: =D33+$C$39 -> -516753.97 | E34: =E33+$C$39 -> -376118.51 | F34: =F33+$C$39 -> -228260.17 | G34: =G33+$C$39 -> -287574.67 | H34: =H33+$C$39 -> 392237.95 | I34: =I33+$C$39 -> -409330.68 | J34: =J33+$C$39 -> -154643.7 | K34: =K33+$C$39 -> 522650.85 | ... M34: =M33+$C$39 -> 1140400.5 | O34: 0.058 | P34: =(D10/$O34)*(1-'Portfolio-Level CF'!$AC$52) -> 12877850 | Q34: =(E10/$O34)*(1-'Portfolio-Level CF'!$AC$52) -> 13140887 | R34: =(F10/$O34)*(1-'Portfolio-Level CF'!$AC$52) -> 13289820 | S34: =(G10/$O34)*(1-'Portfolio-Level CF'!$AC$52) -> 13230074 | T34: =(H10/$O34)*(1-'Portfolio-Level CF'!$AC$52) -> 13914828 | U34: =(I10/$O34)*(1-'Portfolio-Level CF'!$AC$52) -> 13107433 | V34: =(J10/$O34)*(1-'Portfolio-Level CF'!$AC$52) -> 13363971 | W34: =(K10/$O34)*(1-'Portfolio-Level CF'!$AC$52) -> 14046189 | ... Y34: =(M10/$O34)*(1-'Portfolio-Level CF'!$AC$52) -> 14668428 | AA34: Net Gain | AC34: =AC33+$AB$39 -> -422030.92 | AD34: =AD33+$AB$39 -> -784836.17 | AE34: =AE33+$AB$39 -> 2218871.7 | AF34: =AF33+$AB$39 -> 2549954.2 | AG34: =AG33+$AB$39 -> 2866360.3 | AH34: =AH33+$AB$39 -> 3015610.5 | AI34: =AI33+$AB$39 -> 3164298.3 | AJ34: =AJ33+$AB$39 -> 3313820.6 | ... AL34: =AL33+$AB$39 -> 3388491.1 | AN34: 0.053 | AO34: =(AC10/$AN34)*(1-'Portfolio-Level CF'!$AC$52) -> 7642854.7 | AP34: =(AD10/$AN34)*(1-'Portfolio-Level CF'!$AC$52) -> 10177006 | AQ34: =(AE10/$AN34)*(1-'Portfolio-Level CF'!$AC$52) -> 13180714 | AR34: =(AF10/$AN34)*(1-'Portfolio-Level CF'!$AC$52) -> 13511796 | AS34: =(AG10/$AN34)*(1-'Portfolio-Level CF'!$AC$52) -> 13828202 | AT34: =(AH10/$AN34)*(1-'Portfolio-Level CF'!$AC$52) -> 13977452 | AU34: =(AI10/$AN34)*(1-'Portfolio-Level CF'!$AC$52) -> 14126140 | AV34: =(AJ10/$AN34)*(1-'Portfolio-Level CF'!$AC$52) -> 14275663 | ... AX34: =(AL10/$AN34)*(1-'Portfolio-Level CF'!$AC$52) -> 14350333 | AZ34: Net Gain | BB34: =BB33+$BA$39 -> -541645.15 | BC34: =BC33+$BA$39 -> 346810.44 | BD34: =BD33+$BA$39 -> 1848365 | BE34: =BE33+$BA$39 -> 1975736.6 | BF34: =BF33+$BA$39 -> 2101838.2 | BG34: =BG33+$BA$39 -> 2234724.8 | BH34: =BH33+$BA$39 -> 3275612 | BI34: =BI33+$BA$39 -> 3595446.8 | ... BK34: =BK33+$BA$39 -> 3838688.2 | BM34: 0.047 | BN34: =(BB10/$BM34)*(1-'Portfolio-Level CF'!$AC$52) -> 13057968 | BO34: =(BC10/$BM34)*(1-'Portfolio-Level CF'!$AC$52) -> 16255794 | BP34: =(BD10/$BM34)*(1-'Portfolio-Level CF'!$AC$52) -> 17949037 | BQ34: =(BE10/$BM34)*(1-'Portfolio-Level CF'!$AC$52) -> 18092668 | BR34: =(BF10/$BM34)*(1-'Portfolio-Level CF'!$AC$52) -> 18234868 | BS34: =(BG10/$BM34)*(1-'Portfolio-Level CF'!$AC$52) -> 18384719 | BT34: =(BH10/$BM34)*(1-'Portfolio-Level CF'!$AC$52) -> 19558485 | BU34: =(BI10/$BM34)*(1-'Portfolio-Level CF'!$AC$52) -> 19919150 | ... BW34: =(BK10/$BM34)*(1-'Portfolio-Level CF'!$AC$52) -> 20193443 | BY34: Net Gain | CA34: =CA33+$BZ$39 -> -1033536.9 | CB34: =CB33+$BZ$39 -> -829085.05 | CC34: =CC33+$BZ$39 -> -377408.16 | CD34: =CD33+$BZ$39 -> 86466.527 | CE34: =CE33+$BZ$39 -> 556307.93 | CF34: =CF33+$BZ$39 -> 1035609.2 | CG34: =CG33+$BZ$39 -> 1520254.1 | CH34: =CH33+$BZ$39 -> 2012678.4 | ... CJ34: =CJ33+$BZ$39 -> 3075302.1 | CL34: 0.051 | CM34: =(CA10/$CL34)*(1-'Portfolio-Level CF'!$AC$52) -> 25531181 | CN34: =(CB10/$CL34)*(1-'Portfolio-Level CF'!$AC$52) -> 25975959 | CO34: =(CC10/$CL34)*(1-'Portfolio-Level CF'!$AC$52) -> 26426941 | CP34: =(CD10/$CL34)*(1-'Portfolio-Level CF'!$AC$52) -> 26890101 | CQ34: =(CE10/$CL34)*(1-'Portfolio-Level CF'!$AC$52) -> 27359219 | CR34: =(CF10/$CL34)*(1-'Portfolio-Level CF'!$AC$52) -> 27837782 | CS34: =(CG10/$CL34)*(1-'Portfolio-Level CF'!$AC$52) -> 28321680 | CT34: =(CH10/$CL34)*(1-'Portfolio-Level CF'!$AC$52) -> 28813346 | ... CV34: =(CJ10/$CL34)*(1-'Portfolio-Level CF'!$AC$52) -> 29874333 | CX34: Net Gain | CZ34: =CZ33+$CY$39 -> -437470.28 | DA34: =DA33+$CY$39 -> -323009.6 | DB34: =DB33+$CY$39 -> -102216.95 | DC34: =DC33+$CY$39 -> 122985.63 | DD34: =DD33+$CY$39 -> 352709.3 | DE34: =DE33+$CY$39 -> 587028.19 | DF34: =DF33+$CY$39 -> 826016.41 | DG34: =DG33+$CY$39 -> 1069803.7 | ... DI34: =DI33+$CY$39 -> 1572071.7 | DK34: 0.052 | DL34: =(CZ10/$DK34)*(1-'Portfolio-Level CF'!$AC$52) -> 10800770 | DM34: =(DA10/$DK34)*(1-'Portfolio-Level CF'!$AC$52) -> 11016793 | DN34: =(DB10/$DK34)*(1-'Portfolio-Level CF'!$AC$52) -> 11237124 | DO34: =(DC10/$DK34)*(1-'Portfolio-Level CF'!$AC$52) -> 11461857 | DP34: =(DD10/$DK34)*(1-'Portfolio-Level CF'!$AC$52) -> 11691100 | DQ34: =(DE10/$DK34)*(1-'Portfolio-Level CF'!$AC$52) -> 11924930 | DR34: =(DF10/$DK34)*(1-'Portfolio-Level CF'!$AC$52) -> 12163419 | DS34: =(DG10/$DK34)*(1-'Portfolio-Level CF'!$AC$52) -> 12406697 | ... DU34: =(DI10/$DK34)*(1-'Portfolio-Level CF'!$AC$52) -> 12907916 | DW34: Net Gain | DY34: =DY33+$DX$39 -> -1042954.6 | DZ34: =DZ33+$DX$39 -> -768084.26 | EA34: =EA33+$DX$39 -> -245106.14 | EB34: =EB33+$DX$39 -> 292116.06 | EC34: =EC33+$DX$39 -> 840139.37 | ED34: =ED33+$DX$39 -> 1400006.5 | EE34: =EE33+$DX$39 -> 1967172.8 | EF34: =EF33+$DX$39 -> 2552104.8 | ... EH34: =EH33+$DX$39 -> 3745951.6 | EJ34: 0.049 | EK34: =(DY10/$EJ34)*(1-'Portfolio-Level CF'!$AC$52) -> 25735764 | EL34: =(DZ10/$EJ34)*(1-'Portfolio-Level CF'!$AC$52) -> 26252482 | EM34: =(EA10/$EJ34)*(1-'Portfolio-Level CF'!$AC$52) -> 26774086 | EN34: =(EB10/$EJ34)*(1-'Portfolio-Level CF'!$AC$52) -> 27309897 | EO34: =(EC10/$EJ34)*(1-'Portfolio-Level CF'!$AC$52) -> 27856480 | EP34: =(ED10/$EJ34)*(1-'Portfolio-Level CF'!$AC$52) -> 28414876 | EQ34: =(EE10/$EJ34)*(1-'Portfolio-Level CF'!$AC$52) -> 28980552 | ER34: =(EF10/$EJ34)*(1-'Portfolio-Level CF'!$AC$52) -> 29563947 | ... ET34: =(EH10/$EJ34)*(1-'Portfolio-Level CF'!$AC$52) -> 30754657
O35: 0.059 | P35: =(D10/$O35)*(1-'Portfolio-Level CF'!$AC$52) -> 12659582 | Q35: =(E10/$O35)*(1-'Portfolio-Level CF'!$AC$52) -> 12918160 | R35: =(F10/$O35)*(1-'Portfolio-Level CF'!$AC$52) -> 13064569 | S35: =(G10/$O35)*(1-'Portfolio-Level CF'!$AC$52) -> 13005836 | T35: =(H10/$O35)*(1-'Portfolio-Level CF'!$AC$52) -> 13678983 | U35: =(I10/$O35)*(1-'Portfolio-Level CF'!$AC$52) -> 12885273 | V35: =(J10/$O35)*(1-'Portfolio-Level CF'!$AC$52) -> 13137463 | W35: =(K10/$O35)*(1-'Portfolio-Level CF'!$AC$52) -> 13808118 | ... Y35: =(M10/$O35)*(1-'Portfolio-Level CF'!$AC$52) -> 14419811 | AN35: 0.054 | AO35: =(AC10/$AN35)*(1-'Portfolio-Level CF'!$AC$52) -> 7501320.3 | AP35: =(AD10/$AN35)*(1-'Portfolio-Level CF'!$AC$52) -> 9988542.8 | AQ35: =(AE10/$AN35)*(1-'Portfolio-Level CF'!$AC$52) -> 12936626 | AR35: =(AF10/$AN35)*(1-'Portfolio-Level CF'!$AC$52) -> 13261578 | AS35: =(AG10/$AN35)*(1-'Portfolio-Level CF'!$AC$52) -> 13572124 | AT35: =(AH10/$AN35)*(1-'Portfolio-Level CF'!$AC$52) -> 13718611 | AU35: =(AI10/$AN35)*(1-'Portfolio-Level CF'!$AC$52) -> 13864545 | AV35: =(AJ10/$AN35)*(1-'Portfolio-Level CF'!$AC$52) -> 14011298 | ... AX35: =(AL10/$AN35)*(1-'Portfolio-Level CF'!$AC$52) -> 14084586 | BM35: 0.05 | BN35: =(BB10/$BM35)*(1-'Portfolio-Level CF'!$AC$52) -> 12274490 | BO35: =(BC10/$BM35)*(1-'Portfolio-Level CF'!$AC$52) -> 15280446 | BP35: =(BD10/$BM35)*(1-'Portfolio-Level CF'!$AC$52) -> 16872094 | BQ35: =(BE10/$BM35)*(1-'Portfolio-Level CF'!$AC$52) -> 17007108 | BR35: =(BF10/$BM35)*(1-'Portfolio-Level CF'!$AC$52) -> 17140776 | BS35: =(BG10/$BM35)*(1-'Portfolio-Level CF'!$AC$52) -> 17281636 | BT35: =(BH10/$BM35)*(1-'Portfolio-Level CF'!$AC$52) -> 18384976 | BU35: =(BI10/$BM35)*(1-'Portfolio-Level CF'!$AC$52) -> 18724001 | ... BW35: =(BK10/$BM35)*(1-'Portfolio-Level CF'!$AC$52) -> 18981837 | CL35: 0.052 | CM35: =(CA10/$CL35)*(1-'Portfolio-Level CF'!$AC$52) -> 25040197 | CN35: =(CB10/$CL35)*(1-'Portfolio-Level CF'!$AC$52) -> 25476422 | CO35: =(CC10/$CL35)*(1-'Portfolio-Level CF'!$AC$52) -> 25918730 | CP35: =(CD10/$CL35)*(1-'Portfolio-Level CF'!$AC$52) -> 26372984 | CQ35: =(CE10/$CL35)*(1-'Portfolio-Level CF'!$AC$52) -> 26833080 | CR35: =(CF10/$CL35)*(1-'Portfolio-Level CF'!$AC$52) -> 27302440 | CS35: =(CG10/$CL35)*(1-'Portfolio-Level CF'!$AC$52) -> 27777032 | CT35: =(CH10/$CL35)*(1-'Portfolio-Level CF'!$AC$52) -> 28259243 | ... CV35: =(CJ10/$CL35)*(1-'Portfolio-Level CF'!$AC$52) -> 29299826 | DK35: 0.053 | DL35: =(CZ10/$DK35)*(1-'Portfolio-Level CF'!$AC$52) -> 10596982 | DM35: =(DA10/$DK35)*(1-'Portfolio-Level CF'!$AC$52) -> 10808929 | DN35: =(DB10/$DK35)*(1-'Portfolio-Level CF'!$AC$52) -> 11025103 | DO35: =(DC10/$DK35)*(1-'Portfolio-Level CF'!$AC$52) -> 11245595 | DP35: =(DD10/$DK35)*(1-'Portfolio-Level CF'!$AC$52) -> 11470514 | DQ35: =(DE10/$DK35)*(1-'Portfolio-Level CF'!$AC$52) -> 11699931 | DR35: =(DF10/$DK35)*(1-'Portfolio-Level CF'!$AC$52) -> 11933920 | DS35: =(DG10/$DK35)*(1-'Portfolio-Level CF'!$AC$52) -> 12172608 | ... DU35: =(DI10/$DK35)*(1-'Portfolio-Level CF'!$AC$52) -> 12664370 | EJ35: 0.05 | EK35: =(DY10/$EJ35)*(1-'Portfolio-Level CF'!$AC$52) -> 25221049 | EL35: =(DZ10/$EJ35)*(1-'Portfolio-Level CF'!$AC$52) -> 25727432 | EM35: =(EA10/$EJ35)*(1-'Portfolio-Level CF'!$AC$52) -> 26238604 | EN35: =(EB10/$EJ35)*(1-'Portfolio-Level CF'!$AC$52) -> 26763699 | EO35: =(EC10/$EJ35)*(1-'Portfolio-Level CF'!$AC$52) -> 27299350 | EP35: =(ED10/$EJ35)*(1-'Portfolio-Level CF'!$AC$52) -> 27846578 | EQ35: =(EE10/$EJ35)*(1-'Portfolio-Level CF'!$AC$52) -> 28400941 | ER35: =(EF10/$EJ35)*(1-'Portfolio-Level CF'!$AC$52) -> 28972668 | ... ET35: =(EH10/$EJ35)*(1-'Portfolio-Level CF'!$AC$52) -> 30139564
B36: Net Cash Flow after Debt Service | D36: =D14-D30 -> 402394.67 | E36: =E14-E30 -> 372730.67 | F36: =F14-F30 -> 373602.67 | G36: =G14-G30 -> 117702.67 | H36: =H14-H30 -> 465967.67 | I36: =I14-I30 -> 417263.67 | J36: =J14-J30 -> -15054.326 | K36: =K14-K30 -> 473891.67 | ... M36: =M14-M30 -> 279425.67 | O36: 0.06 | P36: =(D10/$O36)*(1-'Portfolio-Level CF'!$AC$52) -> 12448589 | Q36: =(E10/$O36)*(1-'Portfolio-Level CF'!$AC$52) -> 12702857 | R36: =(F10/$O36)*(1-'Portfolio-Level CF'!$AC$52) -> 12846826 | S36: =(G10/$O36)*(1-'Portfolio-Level CF'!$AC$52) -> 12789072 | T36: =(H10/$O36)*(1-'Portfolio-Level CF'!$AC$52) -> 13451000 | U36: =(I10/$O36)*(1-'Portfolio-Level CF'!$AC$52) -> 12670519 | V36: =(J10/$O36)*(1-'Portfolio-Level CF'!$AC$52) -> 12918506 | W36: =(K10/$O36)*(1-'Portfolio-Level CF'!$AC$52) -> 13577983 | ... Y36: =(M10/$O36)*(1-'Portfolio-Level CF'!$AC$52) -> 14179481 | AA36: Net Cash Flow after Debt Service | AC36: =AC14-AC30 -> 115319.24 | AD36: =AD14-AD30 -> 255007.24 | AE36: =AE14-AE30 -> 420578.24 | AF36: =AF14-AF30 -> 438828.24 | AG36: =AG14-AG30 -> 456269.24 | AH36: =AH14-AH30 -> 464496.24 | AI36: =AI14-AI30 -> 472692.24 | AJ36: =AJ14-AJ30 -> 480934.24 | ... AL36: =AL14-AL30 -> 270762.24 | AN36: 0.055 | AO36: =(AC10/$AN36)*(1-'Portfolio-Level CF'!$AC$52) -> 7364932.7 | AP36: =(AD10/$AN36)*(1-'Portfolio-Level CF'!$AC$52) -> 9806932.9 | AQ36: =(AE10/$AN36)*(1-'Portfolio-Level CF'!$AC$52) -> 12701415 | AR36: =(AF10/$AN36)*(1-'Portfolio-Level CF'!$AC$52) -> 13020458 | AS36: =(AG10/$AN36)*(1-'Portfolio-Level CF'!$AC$52) -> 13325359 | AT36: =(AH10/$AN36)*(1-'Portfolio-Level CF'!$AC$52) -> 13469181 | AU36: =(AI10/$AN36)*(1-'Portfolio-Level CF'!$AC$52) -> 13612462 | AV36: =(AJ10/$AN36)*(1-'Portfolio-Level CF'!$AC$52) -> 13756548 | ... AX36: =(AL10/$AN36)*(1-'Portfolio-Level CF'!$AC$52) -> 13828503 | AZ36: Net Cash Flow after Debt Service | BB36: =BB14-BB30 -> 247281.38 | BC36: =BC14-BC30 -> 403597.38 | BD36: =BD14-BD30 -> 486366.38 | BE36: =BE14-BE30 -> 493387.38 | BF36: =BF14-BF30 -> 500338.38 | BG36: =BG14-BG30 -> 507663.38 | BH36: =BH14-BH30 -> 565039.38 | BI36: =BI14-BI30 -> 582669.38 | ... BK36: =BK14-BK30 -> 596077.38 | BM36: 0.053 | BN36: =(BB10/$BM36)*(1-'Portfolio-Level CF'!$AC$52) -> 11579707 | BO36: =(BC10/$BM36)*(1-'Portfolio-Level CF'!$AC$52) -> 14415516 | BP36: =(BD10/$BM36)*(1-'Portfolio-Level CF'!$AC$52) -> 15917070 | BQ36: =(BE10/$BM36)*(1-'Portfolio-Level CF'!$AC$52) -> 16044442 | BR36: =(BF10/$BM36)*(1-'Portfolio-Level CF'!$AC$52) -> 16170543 | BS36: =(BG10/$BM36)*(1-'Portfolio-Level CF'!$AC$52) -> 16303430 | BT36: =(BH10/$BM36)*(1-'Portfolio-Level CF'!$AC$52) -> 17344317 | BU36: =(BI10/$BM36)*(1-'Portfolio-Level CF'!$AC$52) -> 17664152 | ... BW36: =(BK10/$BM36)*(1-'Portfolio-Level CF'!$AC$52) -> 17907393 | BY36: Net Cash Flow after Debt Service | CA36: =CA14-CA30 -> 615131.72 | CB36: =CB14-CB30 -> 638723.72 | CC36: =CC14-CC30 -> 662644.72 | CD36: =CD14-CD30 -> 687211.72 | CE36: =CE14-CE30 -> 712094.72 | CF36: =CF14-CF30 -> 737478.72 | CG36: =CG14-CG30 -> 763145.72 | CH36: =CH14-CH30 -> 789224.72 | ... CJ36: =CJ14-CJ30 -> 845501.72 | CL36: 0.053 | CM36: =(CA10/$CL36)*(1-'Portfolio-Level CF'!$AC$52) -> 24567740 | CN36: =(CB10/$CL36)*(1-'Portfolio-Level CF'!$AC$52) -> 24995735 | CO36: =(CC10/$CL36)*(1-'Portfolio-Level CF'!$AC$52) -> 25429698 | CP36: =(CD10/$CL36)*(1-'Portfolio-Level CF'!$AC$52) -> 25875380 | CQ36: =(CE10/$CL36)*(1-'Portfolio-Level CF'!$AC$52) -> 26326795 | CR36: =(CF10/$CL36)*(1-'Portfolio-Level CF'!$AC$52) -> 26787299 | CS36: =(CG10/$CL36)*(1-'Portfolio-Level CF'!$AC$52) -> 27252937 | CT36: =(CH10/$CL36)*(1-'Portfolio-Level CF'!$AC$52) -> 27726050 | ... CV36: =(CJ10/$CL36)*(1-'Portfolio-Level CF'!$AC$52) -> 28747000 | CX36: Net Cash Flow after Debt Service | CZ36: =CZ14-CZ30 -> 267356.02 | DA36: =DA14-DA30 -> 279039.02 | DB36: =DB14-DB30 -> 290955.02 | DC36: =DC14-DC30 -> 303109.02 | DD36: =DD14-DD30 -> 315507.02 | DE36: =DE14-DE30 -> 328153.02 | DF36: =DF14-DF30 -> 341051.02 | DG36: =DG14-DG30 -> 354208.02 | ... DI36: =DI14-DI30 -> 381315.02 | DK36: 0.054 | DL36: =(CZ10/$DK36)*(1-'Portfolio-Level CF'!$AC$52) -> 10400741 | DM36: =(DA10/$DK36)*(1-'Portfolio-Level CF'!$AC$52) -> 10608764 | DN36: =(DB10/$DK36)*(1-'Portfolio-Level CF'!$AC$52) -> 10820935 | DO36: =(DC10/$DK36)*(1-'Portfolio-Level CF'!$AC$52) -> 11037343 | DP36: =(DD10/$DK36)*(1-'Portfolio-Level CF'!$AC$52) -> 11258097 | DQ36: =(DE10/$DK36)*(1-'Portfolio-Level CF'!$AC$52) -> 11483266 | DR36: =(DF10/$DK36)*(1-'Portfolio-Level CF'!$AC$52) -> 11712922 | DS36: =(DG10/$DK36)*(1-'Portfolio-Level CF'!$AC$52) -> 11947189 | ... DU36: =(DI10/$DK36)*(1-'Portfolio-Level CF'!$AC$52) -> 12429845 | DW36: Net Cash Flow after Debt Service | DY36: =DY14-DY30 -> 566159.86 | DZ36: =DZ14-DZ30 -> 592492.86 | EA36: =EA14-EA30 -> 619074.86 | EB36: =EB14-EB30 -> 646380.86 | EC36: =EC14-EC30 -> 674235.86 | ED36: =ED14-ED30 -> 702692.86 | EE36: =EE14-EE30 -> 731520.86 | EF36: =EF14-EF30 -> 761251.86 | ... EH36: =EH14-EH30 -> 821932.86 | EJ36: 0.051 | EK36: =(DY10/$EJ36)*(1-'Portfolio-Level CF'!$AC$52) -> 24726518 | EL36: =(DZ10/$EJ36)*(1-'Portfolio-Level CF'!$AC$52) -> 25222973 | EM36: =(EA10/$EJ36)*(1-'Portfolio-Level CF'!$AC$52) -> 25724122 | EN36: =(EB10/$EJ36)*(1-'Portfolio-Level CF'!$AC$52) -> 26238920 | EO36: =(EC10/$EJ36)*(1-'Portfolio-Level CF'!$AC$52) -> 26764069 | EP36: =(ED10/$EJ36)*(1-'Portfolio-Level CF'!$AC$52) -> 27300567 | EQ36: =(EE10/$EJ36)*(1-'Portfolio-Level CF'!$AC$52) -> 27844060 | ER36: =(EF10/$EJ36)*(1-'Portfolio-Level CF'!$AC$52) -> 28404576 | ... ET36: =(EH10/$EJ36)*(1-'Portfolio-Level CF'!$AC$52) -> 29548592
B37: Sale (Levered) | M37: =M15-M29 -> 5838163.9 | O37: 0.061 | P37: =(D10/$O37)*(1-'Portfolio-Level CF'!$AC$52) -> 12244513 | Q37: =(E10/$O37)*(1-'Portfolio-Level CF'!$AC$52) -> 12494614 | R37: =(F10/$O37)*(1-'Portfolio-Level CF'!$AC$52) -> 12636222 | S37: =(G10/$O37)*(1-'Portfolio-Level CF'!$AC$52) -> 12579415 | T37: =(H10/$O37)*(1-'Portfolio-Level CF'!$AC$52) -> 13230492 | U37: =(I10/$O37)*(1-'Portfolio-Level CF'!$AC$52) -> 12462805 | V37: =(J10/$O37)*(1-'Portfolio-Level CF'!$AC$52) -> 12706727 | W37: =(K10/$O37)*(1-'Portfolio-Level CF'!$AC$52) -> 13355393 | ... Y37: =(M10/$O37)*(1-'Portfolio-Level CF'!$AC$52) -> 13947030 | AA37: Sale (Levered) | AL37: =AL15-AL29 -> 7225135.8 | AN37: 0.056 | AO37: =(AC10/$AN37)*(1-'Portfolio-Level CF'!$AC$52) -> 7233416 | AP37: =(AD10/$AN37)*(1-'Portfolio-Level CF'!$AC$52) -> 9631809.1 | AQ37: =(AE10/$AN37)*(1-'Portfolio-Level CF'!$AC$52) -> 12474604 | AR37: =(AF10/$AN37)*(1-'Portfolio-Level CF'!$AC$52) -> 12787950 | AS37: =(AG10/$AN37)*(1-'Portfolio-Level CF'!$AC$52) -> 13087406 | AT37: =(AH10/$AN37)*(1-'Portfolio-Level CF'!$AC$52) -> 13228660 | AU37: =(AI10/$AN37)*(1-'Portfolio-Level CF'!$AC$52) -> 13369383 | AV37: =(AJ10/$AN37)*(1-'Portfolio-Level CF'!$AC$52) -> 13510895 | ... AX37: =(AL10/$AN37)*(1-'Portfolio-Level CF'!$AC$52) -> 13581565 | AZ37: Sale (Levered) | BK37: =BK15-BK29 -> 8762735 | BM37: 0.056 | BN37: =(BB10/$BM37)*(1-'Portfolio-Level CF'!$AC$52) -> 10959366 | BO37: =(BC10/$BM37)*(1-'Portfolio-Level CF'!$AC$52) -> 13643256 | BP37: =(BD10/$BM37)*(1-'Portfolio-Level CF'!$AC$52) -> 15064370 | BQ37: =(BE10/$BM37)*(1-'Portfolio-Level CF'!$AC$52) -> 15184918 | BR37: =(BF10/$BM37)*(1-'Portfolio-Level CF'!$AC$52) -> 15304264 | BS37: =(BG10/$BM37)*(1-'Portfolio-Level CF'!$AC$52) -> 15430032 | BT37: =(BH10/$BM37)*(1-'Portfolio-Level CF'!$AC$52) -> 16415157 | BU37: =(BI10/$BM37)*(1-'Portfolio-Level CF'!$AC$52) -> 16717858 | ... BW37: =(BK10/$BM37)*(1-'Portfolio-Level CF'!$AC$52) -> 16948069 | BY37: Sale (Levered) | CJ37: =CJ15-CJ29 -> 12471092 | CL37: 0.054 | CM37: =(CA10/$CL37)*(1-'Portfolio-Level CF'!$AC$52) -> 24112782 | CN37: =(CB10/$CL37)*(1-'Portfolio-Level CF'!$AC$52) -> 24532851 | CO37: =(CC10/$CL37)*(1-'Portfolio-Level CF'!$AC$52) -> 24958777 | CP37: =(CD10/$CL37)*(1-'Portfolio-Level CF'!$AC$52) -> 25396206 | CQ37: =(CE10/$CL37)*(1-'Portfolio-Level CF'!$AC$52) -> 25839262 | CR37: =(CF10/$CL37)*(1-'Portfolio-Level CF'!$AC$52) -> 26291238 | CS37: =(CG10/$CL37)*(1-'Portfolio-Level CF'!$AC$52) -> 26748253 | CT37: =(CH10/$CL37)*(1-'Portfolio-Level CF'!$AC$52) -> 27212604 | ... CV37: =(CJ10/$CL37)*(1-'Portfolio-Level CF'!$AC$52) -> 28214648 | CX37: Sale (Levered) | DI37: =DI15-DI29 -> 5549074.3 | DK37: 0.055 | DL37: =(CZ10/$DK37)*(1-'Portfolio-Level CF'!$AC$52) -> 10211637 | DM37: =(DA10/$DK37)*(1-'Portfolio-Level CF'!$AC$52) -> 10415877 | DN37: =(DB10/$DK37)*(1-'Portfolio-Level CF'!$AC$52) -> 10624190 | DO37: =(DC10/$DK37)*(1-'Portfolio-Level CF'!$AC$52) -> 10836664 | DP37: =(DD10/$DK37)*(1-'Portfolio-Level CF'!$AC$52) -> 11053404 | DQ37: =(DE10/$DK37)*(1-'Portfolio-Level CF'!$AC$52) -> 11274479 | DR37: =(DF10/$DK37)*(1-'Portfolio-Level CF'!$AC$52) -> 11499960 | DS37: =(DG10/$DK37)*(1-'Portfolio-Level CF'!$AC$52) -> 11729968 | ... DU37: =(DI10/$DK37)*(1-'Portfolio-Level CF'!$AC$52) -> 12203847 | DW37: Sale (Levered) | EH37: =EH15-EH29 -> 13227357 | EJ37: 0.052 | EK37: =(DY10/$EJ37)*(1-'Portfolio-Level CF'!$AC$52) -> 24251008 | EL37: =(DZ10/$EJ37)*(1-'Portfolio-Level CF'!$AC$52) -> 24737916 | EM37: =(EA10/$EJ37)*(1-'Portfolio-Level CF'!$AC$52) -> 25229427 | EN37: =(EB10/$EJ37)*(1-'Portfolio-Level CF'!$AC$52) -> 25734326 | EO37: =(EC10/$EJ37)*(1-'Portfolio-Level CF'!$AC$52) -> 26249375 | EP37: =(ED10/$EJ37)*(1-'Portfolio-Level CF'!$AC$52) -> 26775556 | EQ37: =(EE10/$EJ37)*(1-'Portfolio-Level CF'!$AC$52) -> 27308597 | ER37: =(EF10/$EJ37)*(1-'Portfolio-Level CF'!$AC$52) -> 27858335 | ... ET37: =(EH10/$EJ37)*(1-'Portfolio-Level CF'!$AC$52) -> 28980350
B38: Asset Management Fees | D38: =C39*Summary!C10 -> -11744.409 | E38: =D38 -> -11744.409 | F38: =E38 -> -11744.409 | G38: =F38 -> -11744.409 | H38: =G38 -> -11744.409 | I38: =H38 -> -11744.409 | J38: =I38 -> -11744.409 | K38: =J38 -> -11744.409 | L38: =K38 -> -11744.409 | M38: =L38 -> -11744.409 | AA38: Asset Management Fees | AC38: =AB39*Summary!C10 -> -9591.6117 | AD38: =AC38 -> -9591.6117 | AE38: =AD38 -> -9591.6117 | AF38: =AE38 -> -9591.6117 | AG38: =AF38 -> -9591.6117 | AH38: =AG38 -> -9591.6117 | AI38: =AH38 -> -9591.6117 | AJ38: =AI38 -> -9591.6117 | AK38: =AJ38 -> -9591.6117 | AL38: =AK38 -> -9591.6117 | AZ38: Asset Management Fees | BB38: =BA39*Summary!C10 -> -12310.117 | BC38: =BB38 -> -12310.117 | BD38: =BC38 -> -12310.117 | BE38: =BD38 -> -12310.117 | BF38: =BE38 -> -12310.117 | BG38: =BF38 -> -12310.117 | BH38: =BG38 -> -12310.117 | BI38: =BH38 -> -12310.117 | BJ38: =BI38 -> -12310.117 | BK38: =BJ38 -> -12310.117 | BY38: Asset Management Fees | CA38: =BZ39*Summary!C10 -> -23489.476 | CB38: =CA38 -> -23489.476 | CC38: =CB38 -> -23489.476 | CD38: =CC38 -> -23489.476 | CE38: =CD38 -> -23489.476 | CF38: =CE38 -> -23489.476 | CG38: =CF38 -> -23489.476 | CH38: =CG38 -> -23489.476 | CI38: =CH38 -> -23489.476 | CJ38: =CI38 -> -23489.476 | CX38: Asset Management Fees | CZ38: =CY39*Summary!C10 -> -9942.5065 | DA38: =CZ38 -> -9942.5065 | DB38: =DA38 -> -9942.5065 | DC38: =DB38 -> -9942.5065 | DD38: =DC38 -> -9942.5065 | DE38: =DD38 -> -9942.5065 | DF38: =DE38 -> -9942.5065 | DG38: =DF38 -> -9942.5065 | DH38: =DG38 -> -9942.5065 | DI38: =DH38 -> -9942.5065 | DW38: Asset Management Fees | DY38: =DX39*Summary!C10 -> -23703.513 | DZ38: =DY38 -> -23703.513 | EA38: =DZ38 -> -23703.513 | EB38: =EA38 -> -23703.513 | EC38: =EB38 -> -23703.513 | ED38: =EC38 -> -23703.513 | EE38: =ED38 -> -23703.513 | EF38: =EE38 -> -23703.513 | EG38: =EF38 -> -23703.513 | EH38: =EG38 -> -23703.513
B39: Levered Cash Flow | C39: =(C16*(1-Summary!C15)) -> -4697763.4 | D39: =SUM(D36:D38) -> 390650.27 | E39: =SUM(E36:E38) -> 360986.27 | F39: =SUM(F36:F38) -> 361858.27 | G39: =SUM(G36:G38) -> 105958.27 | H39: =SUM(H36:H38) -> 454223.27 | I39: =SUM(I36:I38) -> 405519.27 | J39: =SUM(J36:J38) -> -26798.734 | K39: =SUM(K36:K38) -> 462147.27 | ... M39: =SUM(M36:M38) -> 6105845.2 | O39: Property Final Year Cash Flow by Cap Rate by Exit Year | AA39: Levered Cash Flow | AB39: =(AB16*(1-Summary!C15)) -> -3836644.7 | AC39: =AC36+SUM(AC37:AC38) -> 105727.63 | AD39: =AD36+SUM(AD37:AD38) -> 245415.63 | AE39: =AE36+SUM(AE37:AE38) -> 410986.63 | AF39: =AF36+SUM(AF37:AF38) -> 429236.63 | AG39: =AG36+SUM(AG37:AG38) -> 446677.63 | AH39: =AH36+SUM(AH37:AH38) -> 454904.63 | AI39: =AI36+SUM(AI37:AI38) -> 463100.63 | AJ39: =AJ36+SUM(AJ37:AJ38) -> 471342.63 | ... AL39: =AL36+SUM(AL37:AL38) -> 7486306.4 | AN39: Property Final Year Cash Flow by Cap Rate by Exit Year | AZ39: Levered Cash Flow | BA39: =(BA16*(1-Summary!C15)) -> -4924046.8 | BB39: =BB36+SUM(BB37:BB38) -> 234971.26 | BC39: =BC36+SUM(BC37:BC38) -> 391287.26 | BD39: =BD36+SUM(BD37:BD38) -> 474056.26 | BE39: =BE36+SUM(BE37:BE38) -> 481077.26 | BF39: =BF36+SUM(BF37:BF38) -> 488028.26 | BG39: =BG36+SUM(BG37:BG38) -> 495353.26 | BH39: =BH36+SUM(BH37:BH38) -> 552729.26 | BI39: =BI36+SUM(BI37:BI38) -> 570359.26 | ... BK39: =BK36+SUM(BK37:BK38) -> 9346502.2 | BM39: Property Final Year Cash Flow by Cap Rate by Exit Year | BY39: Levered Cash Flow | BZ39: =(BZ16*(1-Summary!C15)) -> -9395790.4 | CA39: =CA36+SUM(CA37:CA38) -> 591642.25 | CB39: =CB36+SUM(CB37:CB38) -> 615234.25 | CC39: =CC36+SUM(CC37:CC38) -> 639155.25 | CD39: =CD36+SUM(CD37:CD38) -> 663722.25 | CE39: =CE36+SUM(CE37:CE38) -> 688605.25 | CF39: =CF36+SUM(CF37:CF38) -> 713989.25 | CG39: =CG36+SUM(CG37:CG38) -> 739656.25 | CH39: =CH36+SUM(CH37:CH38) -> 765735.25 | ... CJ39: =CJ36+SUM(CJ37:CJ38) -> 13293105 | CL39: Property Final Year Cash Flow by Cap Rate by Exit Year | CX39: Levered Cash Flow | CY39: =(CY16*(1-Summary!C15)) -> -3977002.6 | CZ39: =CZ36+SUM(CZ37:CZ38) -> 257413.51 | DA39: =DA36+SUM(DA37:DA38) -> 269096.51 | DB39: =DB36+SUM(DB37:DB38) -> 281012.51 | DC39: =DC36+SUM(DC37:DC38) -> 293166.51 | DD39: =DD36+SUM(DD37:DD38) -> 305564.51 | DE39: =DE36+SUM(DE37:DE38) -> 318210.51 | DF39: =DF36+SUM(DF37:DF38) -> 331108.51 | DG39: =DG36+SUM(DG37:DG38) -> 344265.51 | ... DI39: =DI36+SUM(DI37:DI38) -> 5920446.8 | DK39: Property Final Year Cash Flow by Cap Rate by Exit Year | DW39: Levered Cash Flow | DX39: =(DX16*(1-Summary!C15)) -> -9481405.3 | DY39: =DY36+SUM(DY37:DY38) -> 542456.35 | DZ39: =DZ36+SUM(DZ37:DZ38) -> 568789.35 | EA39: =EA36+SUM(EA37:EA38) -> 595371.35 | EB39: =EB36+SUM(EB37:EB38) -> 622677.35 | EC39: =EC36+SUM(EC37:EC38) -> 650532.35 | ED39: =ED36+SUM(ED37:ED38) -> 678989.35 | EE39: =EE36+SUM(EE37:EE38) -> 707817.35 | EF39: =EF36+SUM(EF37:EF38) -> 737548.35 | ... EH39: =EH36+SUM(EH37:EH38) -> 14025586 | EJ39: Property Final Year Cash Flow by Cap Rate by Exit Year
O40: Cap Rate | P40: =P32 -> Year 1 | Q40: =Q32 -> Year 2 | R40: =R32 -> Year 3 | S40: =S32 -> Year 4 | T40: =T32 -> Year 5 | U40: =U32 -> Year 6 | V40: =V32 -> Year 7 | W40: =W32 -> Year 8 | ... Y40: =Y32 -> Year 10 | AN40: Cap Rate | AO40: Year 1 | AP40: Year 2 | AQ40: Year 3 | AR40: Year 4 | AS40: Year 5 | AT40: Year 6 | AU40: Year 7 | AV40: Year 8 | AW40: Year 9 | AX40: Year 10 | BM40: Cap Rate | BN40: Year 1 | BO40: Year 2 | BP40: Year 3 | BQ40: Year 4 | BR40: Year 5 | BS40: Year 6 | BT40: Year 7 | BU40: Year 8 | BV40: Year 9 | BW40: Year 10 | CL40: Cap Rate | CM40: Year 1 | CN40: Year 2 | CO40: Year 3 | CP40: Year 4 | CQ40: Year 5 | CR40: Year 6 | CS40: Year 7 | CT40: Year 8 | CU40: Year 9 | CV40: Year 10 | DK40: Cap Rate | DL40: Year 1 | DM40: Year 2 | DN40: Year 3 | DO40: Year 4 | DP40: Year 5 | DQ40: Year 6 | DR40: Year 7 | DS40: Year 8 | DT40: Year 9 | DU40: Year 10 | EJ40: Cap Rate | EK40: Year 1 | EL40: Year 2 | EM40: Year 3 | EN40: Year 4 | EO40: Year 5 | EP40: Year 6 | EQ40: Year 7 | ER40: Year 8 | ES40: Year 9 | ET40: Year 10
